Workbook

Sheet extrato-stone-literarius
A1: Tipo | B1: Número | C1: Data | D1: Documento | E1: Descrição | F1: Valor | G1: Origem | H1: Plano de Contas | I1: Centro Resultados | J1: Conta Contábil
A2: C | B2: 2424 | C2: 01/01/2026 | D2: 2424 | E2: Recebimento vendas - AntecipaÃ | F2: 77 | G2: BANCÁRIO | H2: VENDA DE LIVROS | I2: Receita de vendas | J2: =VLOOKUP(H2,Planilha2!B:C,2,0) -> 132 a 134
A3: C | B3: 2425 | C3: 01/01/2026 | D3: 2425 | E3: Recebimento vendas - AntecipaÃ | F3: 32.38 | G3: BANCÁRIO | H3: VENDA DE LIVROS | I3: Receita de vendas | J3: =VLOOKUP(H3,Planilha2!B:C,2,0) -> 132 a 134
A4: C | B4: 2423 | C4: 02/01/2026 | D4: 2423 | E4: Recebimento vendas - AntecipaÃ | F4: 206.64 | G4: BANCÁRIO | H4: VENDA DE LIVROS | I4: Receita de vendas | J4: =VLOOKUP(H4,Planilha2!B:C,2,0) -> 132 a 134
A5: C | B5: 2370 | C5: 04/01/2026 | D5: 2370 | E5: Recebimento vendas - AntecipaÃ | F5: 51.11 | G5: BANCÁRIO | H5: VENDA DE LIVROS | I5: Receita de vendas | J5: =VLOOKUP(H5,Planilha2!B:C,2,0) -> 132 a 134
A6: C | B6: 2371 | C6: 04/01/2026 | D6: 2371 | E6: Recebimento vendas - AntecipaÃ | F6: 1004.37 | G6: BANCÁRIO | H6: VENDA DE LIVROS | I6: Receita de vendas | J6: =VLOOKUP(H6,Planilha2!B:C,2,0) -> 132 a 134
A7: C | B7: 2372 | C7: 04/01/2026 | D7: 2372 | E7: Recebimento vendas - AntecipaÃ | F7: 198.49 | G7: BANCÁRIO | H7: VENDA DE LIVROS | I7: Receita de vendas | J7: =VLOOKUP(H7,Planilha2!B:C,2,0) -> 132 a 134
A8: C | B8: 2373 | C8: 04/01/2026 | D8: 2373 | E8: Recebimento vendas - AntecipaÃ | F8: 340.36 | G8: BANCÁRIO | H8: VENDA DE LIVROS | I8: Receita de vendas | J8: =VLOOKUP(H8,Planilha2!B:C,2,0) -> 132 a 134
A9: C | B9: 2374 | C9: 04/01/2026 | D9: 2374 | E9: Recebimento vendas - AntecipaÃ | F9: 711.3 | G9: BANCÁRIO | H9: VENDA DE LIVROS | I9: Receita de vendas | J9: =VLOOKUP(H9,Planilha2!B:C,2,0) -> 132 a 134
A10: C | B10: 2375 | C10: 04/01/2026 | D10: 2375 | E10: Recebimento vendas - AntecipaÃ | F10: 86.51 | G10: BANCÁRIO | H10: VENDA DE LIVROS | I10: Receita de vendas | J10: =VLOOKUP(H10,Planilha2!B:C,2,0) -> 132 a 134
A11: C | B11: 2376 | C11: 04/01/2026 | D11: 2376 | E11: Recebimento vendas - AntecipaÃ | F11: 237.77 | G11: BANCÁRIO | H11: VENDA DE LIVROS | I11: Receita de vendas | J11: =VLOOKUP(H11,Planilha2!B:C,2,0) -> 132 a 134
A12: C | B12: 2377 | C12: 04/01/2026 | D12: 2377 | E12: Recebimento vendas - AntecipaÃ | F12: 355.46 | G12: BANCÁRIO | H12: VENDA DE LIVROS | I12: Receita de vendas | J12: =VLOOKUP(H12,Planilha2!B:C,2,0) -> 132 a 134
A13: C | B13: 2378 | C13: 04/01/2026 | D13: 2378 | E13: Recebimento vendas - AntecipaÃ | F13: 561.7 | G13: BANCÁRIO | H13: VENDA DE LIVROS | I13: Receita de vendas | J13: =VLOOKUP(H13,Planilha2!B:C,2,0) -> 132 a 134
... A399: C | B399: 2611 | C399: 31/01/2026 | D399: 2611 | E399: PEDRO ARTHUR FREITAS DIAS - Tr | F399: 1500 | G399: BANCÁRIO | H399: VENDA DE LIVROS | I399: Receita de vendas | J399: =VLOOKUP(H399,Planilha2!B:C,2,0) -> 132 a 134

Sheet Planilha2
A1: Codigo | B1: Descrição | C1: Contas contábeis
A2: 0 | B2: Cod 0561 | Cod 1082 | Cod 1138 | Cod 1170 | Cod 1176 | Cod 1191 | Cod 1196 | Cod 1200 | Cod 1646 | Cod 8301 | C2: 62
A3: 2 | B3: VENDA DE LIVROS | C3: 132 a 134
A4: 3 | B4: AQUISIÇÃO DE LIVROS | C4: 28
A5: 4 | B5: VENDA DE EBOOK | C5: 134
A6: 10 | B6: 13º Salário | C6: 180 a 192
A7: 11 | B7: Despesas Editorial - Capa | C7: 752
A8: 12 | B8: Despesas Editorial - Conferência de Emendas | Despesas Editorial - Revisão de Prova | C8: 752
A9: 13 | B9: Despesas Editorial - Diagramação | C9: 185
A10: 14 | B10: Despesas Editorial - Edição | C10: 185
A11: 15 | B11: Despesas Editorial - Ilustração | C11: 752
A12: 16 | B12: Despesas Editorial - Preparação | C12: 752
A13: 17 | B13: Despesas Editorial - Produção Editorial | C13: 752
A14: 18 | B14: Despesas Editorial - Revisão de Prova | C14: 752
A15: 19 | B15: Despesas Editorial - Tradução | C15: 752
A16: 20 | B16: Materiais Para Revenda | C16: 80
A17: 21 | B17: Producao Material Proprio | C17: 80
A18: 21 | B18: Produção Material Próprio | C18: 80
... A75: 77 | B75: Impostos E Taxas | C75: 225
A76: 78 | B76: Estorno e Reembolso | C76: 231 LANÇAR NA NATUREZA DA DESPESA
A77: 79 | B77: Internet | C77: 233
A78: 80 | B78: Monitoramento Sede | C78: 67
A79: 81 | B79: Royalties | C79: 165
A80: 82 | B80: PIS 8301 | C80: 197
A81: 83 | B81: Terreno e Dependências - Sede | C81: 255
A82: 84 | B82: Sistemas e Softwares -Adm Marketing | C82: 244
A83: 85 | B83: Sistemas e Softwares Comerciais | C83: 710
A84: 86 | B84: Devolução de Venda | C84: 166
A85: 87 | B85: Exames médicos | C85: 193
A86: 88 | B86: Juros pagos/passivos | C86: 251
A87: 89 | B87: Lanches e Refeições Equipe | C87: 215
A88: 90 | B88: Lanches e Refeições Comercial | C88: 212
... A99: 101 | B99: Condomínio | C99: 237
A100: 102 | B100: DESPESAS OPERACIONAIS | C100: 4.3.1
A101: 103 | B101: DESPESAS ADMINISTRATIVAS | C101: 4.3.1.01
A102: 104 | B102: Materiais Impressos | C102: 224
A103: 105 | B103: Cod 0561 | C103: 67
A104: 106 | B104: TRANSFERENCIA ENTRE CONTAS | C104: 0
A105: 107 | B105: Despesas Bancárias | C105: 252
A106: 108 | B106: Rescisões | C106: 188 A 192
A107: 109 | B107: Cod 5952 | C107: 73
A108: 110 | B108: Móveis, Máquinas e Utensílios | C108: 41
A109: 111 | B109: Outras despesas | C109: 76
A110: 112 | B110: Receitas financeiras | C110: 135
A111: 113 | B111: Condominio | C111: 237
A112: 114 | B112: Cod 1162 | C112: 62

Sheet extrato stone
A1: Movimentação | B1: Tipo | C1: Valor | D1: Tarifa | F1: Saldo antes | G1: Saldo depois | H1: Data | J1: Nosso Número | K1: Situação | L1: Destino | M1: Destino Documento | N1: Destino Instituição | O1: Destino Agência | P1: Destino Conta | Q1: Origem | R1: Origem Documento | S1: Origem Instituição | T1: Origem Agência | U1: Origem Conta
A2: Crédito | B2: Transferência entre contas Stone | C2: 77,00 | D2: R$ 0,00 | E2: =C2-D2 -> 77 | F2: R$ 10.054,83 | G2: R$ 10.131,83 | H2: 01/01/2026 03:13 | I2: 46023 | K2: Recebida | L2: Editora Heziom | M2: 40.804.477/0001-44 | N2: Stone Instituição de Pagamento S.A. | O2: 0001 | P2: 890291-8 | Q2: Stone Principal | R2: 16.501.555/0001-57 | S2: STONE INSTITUIÇÃO DE PAGAMENTO S.A. | T2: 0001 | U2: 30772-8
A3: Crédito | B3: Transferência entre contas Stone | C3: 32,38 | D3: R$ 0,00 | E3: =C3-D3 -> 32.38 | F3: R$ 10.022,45 | G3: R$ 10.054,83 | H3: 01/01/2026 03:13 | I3: 46023 | K3: Recebida | L3: Editora Heziom | M3: 40.804.477/0001-44 | N3: Stone Instituição de Pagamento S.A. | O3: 0001 | P3: 890291-8 | Q3: Stone Principal | R3: 16.501.555/0001-57 | S3: STONE INSTITUIÇÃO DE PAGAMENTO S.A. | T3: 0001 | U3: 30772-8
A4: Crédito | B4: Transferência entre contas Stone | C4: 206,64 | D4: R$ 0,00 | E4: =C4-D4 -> 206.64 | F4: R$ 10.131,83 | G4: R$ 10.338,47 | H4: 02/01/2026 13:29 | I4: 46024 | K4: Recebida | L4: Editora Heziom | M4: 40.804.477/0001-44 | N4: Stone Instituição de Pagamento S.A. | O4: 0001 | P4: 890291-8 | Q4: Stone Principal | R4: 16.501.555/0001-57 | S4: STONE INSTITUIÇÃO DE PAGAMENTO S.A. | T4: 0001 | U4: 30772-8
A5: Crédito | B5: Transação | C5: 30,00 | D5: R$ 0,15 | E5: =C5-D5 -> 29.85 | F5: R$ 10.338,47 | G5: R$ 10.368,32 | H5: 04/01/2026 07:43 | I5: 46026 | K5: FINISHED | L5: Editora Heziom | M5: 40.804.477/0001-44 | N5: Stone Instituição de Pagamento S.A. | O5: 0001 | P5: 890291-8 | Q5: GLEYCE ROSA SILVA SANTOS | R5: ***.897.771-** | S5: Banco do Brasil S.A. | T5: Desconhecido | U5: Desconhecido
A6: Crédito | B6: Transferência entre contas Stone | C6: 76,54 | D6: R$ 0,00 | E6: =C6-D6 -> 76.54 | F6: R$ 10.550,90 | G6: R$ 10.627,44 | H6: 04/01/2026 09:12 | I6: 46026 | K6: Recebida | L6: Editora Heziom | M6: 40.804.477/0001-44 | N6: Stone Instituição de Pagamento S.A. | O6: 0001 | P6: 890291-8 | Q6: Stone Principal | R6: 16.501.555/0001-57 | S6: STONE INSTITUIÇÃO DE PAGAMENTO S.A. | T6: 0001 | U6: 30772-8
A7: Crédito | B7: Transferência entre contas Stone | C7: 182,58 | D7: R$ 0,00 | E7: =C7-D7 -> 182.58 | F7: R$ 10.368,32 | G7: R$ 10.550,90 | H7: 04/01/2026 09:12 | I7: 46026 | K7: Recebida | L7: Editora Heziom | M7: 40.804.477/0001-44 | N7: Stone Instituição de Pagamento S.A. | O7: 0001 | P7: 890291-8 | Q7: Stone Principal | R7: 16.501.555/0001-57 | S7: STONE INSTITUIÇÃO DE PAGAMENTO S.A. | T7: 0001 | U7: 30772-8
A8: Crédito | B8: Transação | C8: 215,80 | D8: R$ 1,07 | E8: =C8-D8 -> 214.73 | F8: R$ 10.627,44 | G8: R$ 10.842,17 | H8: 04/01/2026 09:25 | I8: 46026 | K8: FINISHED | L8: Editora Heziom | M8: 40.804.477/0001-44 | N8: Stone Instituição de Pagamento S.A. | O8: 0001 | P8: 890291-8 | Q8: RAQUEL MARCHIORI LESSA DE AZEVEDO | R8: ***.507.724-** | S8: 99PAY INSTITUICAO DE PAGAMENTO S.A. | T8: Desconhecido | U8: Desconhecido
A9: Crédito | B9: Transação | C9: 159,80 | D9: R$ 0,79 | E9: =C9-D9 -> 159.01 | F9: R$ 10.842,17 | G9: R$ 11.001,18 | H9: 04/01/2026 09:43 | I9: 46026 | K9: FINISHED | L9: Editora Heziom | M9: 40.804.477/0001-44 | N9: Stone Instituição de Pagamento S.A. | O9: 0001 | P9: 890291-8 | Q9: JULIANA DA ROCHA MIRANDA | R9: ***.256.282-** | S9: ITAÚ UNIBANCO S.A. | T9: Desconhecido | U9: Desconhecido
A10: Crédito | B10: Transação | C10: 222,02 | D10: R$ 1,11 | E10: =C10-D10 -> 220.91 | F10: R$ 11.001,18 | G10: R$ 11.222,09 | H10: 04/01/2026 10:31 | I10: 46026 | K10: FINISHED | L10: Editora Heziom | M10: 40.804.477/0001-44 | N10: Stone Instituição de Pagamento S.A. | O10: 0001 | P10: 890291-8 | Q10: JEFERSON APARECIDO PEREIRA DE ANDRADE | R10: ***.358.698-** | S10: COOPERATIVA DE CRÉDITO COOPACREDI LTDA. - SICOOB COOPACREDI | T10: Desconhecido | U10: Desconhecido
A11: Crédito | B11: Transação | C11: 129,36 | D11: R$ 0,64 | E11: =C11-D11 -> 128.72 | F11: R$ 11.222,09 | G11: R$ 11.350,81 | H11: 04/01/2026 10:34 | I11: 46026 | K11: FINISHED | L11: Editora Heziom | M11: 40.804.477/0001-44 | N11: Stone Instituição de Pagamento S.A. | O11: 0001 | P11: 890291-8 | Q11: PRISCYLA K PROENCA DE ARAUJO | R11: ***.243.608-** | S11: ITAÚ UNIBANCO S.A. | T11: Desconhecido | U11: Desconhecido
A12: Crédito | B12: Transação | C12: 149,90 | D12: R$ 0,74 | E12: =C12-D12 -> 149.16 | F12: R$ 11.350,81 | G12: R$ 11.499,97 | H12: 04/01/2026 10:36 | I12: 46026 | K12: FINISHED | L12: Editora Heziom | M12: 40.804.477/0001-44 | N12: Stone Instituição de Pagamento S.A. | O12: 0001 | P12: 890291-8 | Q12: Luciane da Silva | R12: ***.904.738-** | S12: MERCADO PAGO INSTITUIÇÃO DE PAGAMENTO LTDA. | T12: Desconhecido | U12: Desconhecido
A13: Crédito | B13: Transação | C13: 84,90 | D13: R$ 0,42 | E13: =C13-D13 -> 84.48 | F13: R$ 11.499,97 | G13: R$ 11.584,45 | H13: 04/01/2026 10:50 | I13: 46026 | K13: FINISHED | L13: Editora Heziom | M13: 40.804.477/0001-44 | N13: Stone Instituição de Pagamento S.A. | O13: 0001 | P13: 890291-8 | Q13: CAMILA PRADO SANTOS | R13: ***.094.681-** | S13: Banco Inter S.A. | T13: Desconhecido | U13: Desconhecido
... A57: Crédito | B57: Transferência entre contas Stone | C57: 711,30 | D57: R$ 0,00 | E57: =C57-D57 -> 711.3 | F57: R$ 23.999,68 | G57: R$ 24.710,98 | H57: 04/01/2026 23:11 | I57: 46026 | K57: Recebida | L57: Editora Heziom | M57: 40.804.477/0001-44 | N57: Stone Instituição de Pagamento S.A. | O57: 0001 | P57: 890291-8 | Q57: Stone Principal | R57: 16.501.555/0001-57 | S57: STONE INSTITUIÇÃO DE PAGAMENTO S.A. | T57: 0001 | U57: 30772-8
A58: Crédito | B58: Pix | C58: 1.018,30 | D58: 0 | E58: =C58-D58 -> 1018.3 | F58: R$ 26.305,31 | G58: R$ 27.323,61 | H58: 05/01/2026 12:13 | I58: 46027 | K58: Recebido | L58: Editora Heziom | M58: 40.804.477/0001-44 | N58: Stone Instituição de Pagamento S.A. | O58: 0001 | P58: 890291-8 | Q58: Débora Vanessa Mariano | R58: ***.978.996-** | S58: Banco BTG Pactual S.A. | T58: Desconhecido | U58: Desconhecido
A59: Crédito | B59: Pix | C59: 1.497,50 | D59: 0 | E59: =C59-D59 -> 1497.5 | F59: R$ 27.323,61 | G59: R$ 28.821,11 | H59: 05/01/2026 13:00 | I59: 46027 | K59: Recebido | L59: Editora Heziom | M59: 40.804.477/0001-44 | N59: Stone Instituição de Pagamento S.A. | O59: 0001 | P59: 890291-8 | Q59: IANNA ROSA LUCAS TORRES | R59: ***.299.321-** | S59: Banco XP S.A. | T59: Desconhecido | U59: Desconhecido
A60: Crédito | B60: Pix | C60: 419,30 | D60: 0 | E60: =C60-D60 -> 419.3 | F60: R$ 28.821,11 | G60: R$ 29.240,41 | H60: 05/01/2026 13:09 | I60: 46027 | K60: Recebido | L60: Editora Heziom | M60: 40.804.477/0001-44 | N60: Stone Instituição de Pagamento S.A. | O60: 0001 | P60: 890291-8 | Q60: Glaucilene Campos Figueredo | R60: ***.406.691-** | S60: NU PAGAMENTOS S.A. - INSTITUIÇÃO DE PAGAMENTO | T60: Desconhecido | U60: Desconhecido
A61: Crédito | B61: Pix | C61: 1.500,00 | D61: 0 | E61: =C61-D61 -> 1500 | F61: R$ 29.240,41 | G61: R$ 30.740,41 | H61: 05/01/2026 13:53 | I61: 46027 | K61: Recebido | L61: Editora Heziom | M61: 40.804.477/0001-44 | N61: Stone Instituição de Pagamento S.A. | O61: 0001 | P61: 890291-8 | Q61: IGREJA P NACIONAL | R61: 00.096.388/0001-76 | S61: Banco do Brasil S.A. | T61: Desconhecido | U61: Desconhecido
A62: Crédito | B62: Pix | C62: 61,05 | D62: 0 | E62: =C62-D62 -> 61.05 | F62: R$ 30.740,41 | G62: R$ 30.801,46 | H62: 05/01/2026 14:44 | I62: 46027 | K62: Recebido | L62: Editora Heziom | M62: 40.804.477/0001-44 | N62: Stone Instituição de Pagamento S.A. | O62: 0001 | P62: 890291-8 | Q62: JOCELI CARVALHO A FERREIRA | R62: ***.341.778-** | S62: ITAÚ UNIBANCO S.A. | T62: Desconhecido | U62: Desconhecido
A63: Crédito | B63: Transferência entre contas Stone | C63: 49,38 | D63: R$ 0,00 | E63: =C63-D63 -> 49.38 | F63: R$ 30.801,46 | G63: R$ 30.850,84 | H63: 05/01/2026 15:18 | I63: 46027 | K63: Recebida | L63: Editora Heziom | M63: 40.804.477/0001-44 | N63: Stone Instituição de Pagamento S.A. | O63: 0001 | P63: 890291-8 | Q63: Stone Principal | R63: 16.501.555/0001-57 | S63: STONE INSTITUIÇÃO DE PAGAMENTO S.A. | T63: 0001 | U63: 30772-8
A64: Crédito | B64: Pix | C64: 718,80 | D64: 0 | E64: =C64-D64 -> 718.8 | F64: R$ 30.850,84 | G64: R$ 31.569,64 | H64: 05/01/2026 15:26 | I64: 46027 | K64: Recebido | L64: Editora Heziom | M64: 40.804.477/0001-44 | N64: Stone Instituição de Pagamento S.A. | O64: 0001 | P64: 890291-8 | Q64: HERMELINDA COSTA SARAIVA | R64: ***.814.391-** | S64: CAIXA ECONOMICA FEDERAL | T64: Desconhecido | U64: Desconhecido
A65: Débito | B65: Pix | C65: -104,40 | D65: 0 | E65: =C65-D65 -> -104.4 | F65: R$ 31.569,64 | G65: R$ 31.465,24 | H65: 05/01/2026 15:42 | I65: 46027 | K65: Enviado | L65: ANA MARIA NEVES SAC ZECHMANN | M65: ***.943.138-** | N65: Banco C6 S.A. | O65: Desconhecido | P65: Desconhecido | Q65: Editora Heziom | R65: 40.804.477/0001-44 | S65: Stone Instituição de Pagamento S.A. | T65: 0001 | U65: 890291-8
A66: Débito | B66: Pix | C66: -50,00 | D66: 0 | E66: =C66-D66 -> -50 | F66: R$ 32.004,34 | G66: R$ 31.954,34 | H66: 05/01/2026 15:43 | I66: 46027 | K66: Enviado | L66: Rafael Pereira Barbosa | M66: ***.248.848-** | N66: NU PAGAMENTOS S.A. - INSTITUIÇÃO DE PAGAMENTO | O66: Desconhecido | P66: Desconhecido | Q66: Editora Heziom | R66: 40.804.477/0001-44 | S66: Stone Instituição de Pagamento S.A. | T66: 0001 | U66: 890291-8
A67: Crédito | B67: Pix | C67: 539,10 | D67: 0 | E67: =C67-D67 -> 539.1 | F67: R$ 31.465,24 | G67: R$ 32.004,34 | H67: 05/01/2026 15:43 | I67: 46027 | K67: Recebido | L67: Editora Heziom | M67: 40.804.477/0001-44 | N67: Stone Instituição de Pagamento S.A. | O67: 0001 | P67: 890291-8 | Q67: Maria Cristina Soares Dias Ribeiro | R67: ***.651.541-** | S67: NU PAGAMENTOS S.A. - INSTITUIÇÃO DE PAGAMENTO | T67: Desconhecido | U67: Desconhecido
A68: Débito | B68: Pix | C68: -28.000,00 | D68: 0 | E68: =C68-D68 -> -28000 | F68: R$ 31.954,34 | G68: R$ 3.954,34 | H68: 05/01/2026 15:44 | I68: 46027 | K68: Enviado | L68: ASSOCIACAO EDITORA PRESBITERIANA DE PINHEIROS | M68: 40.804.477/0001-44 | N68: BANCO SANTANDER (BRASIL) S.A. | O68: Desconhecido | P68: Desconhecido | Q68: Editora Heziom | R68: 40.804.477/0001-44 | S68: Stone Instituição de Pagamento S.A. | T68: 0001 | U68: 890291-8
A69: Crédito | B69: Pix | C69: 958,40 | D69: 0 | E69: =C69-D69 -> 958.4 | F69: R$ 3.954,34 | G69: R$ 4.912,74 | H69: 05/01/2026 15:49 | I69: 46027 | K69: Recebido | L69: Editora Heziom | M69: 40.804.477/0001-44 | N69: Stone Instituição de Pagamento S.A. | O69: 0001 | P69: 890291-8 | Q69: GLAUCIA STELA DE CASTRO ROCHA | R69: ***.560.561-** | S69: PICPAY INSTITUIçãO DE PAGAMENTO S.A. | T69: Desconhecido | U69: Desconhecido
A70: Crédito | B70: Pix | C70: 86,42 | D70: 0 | E70: =C70-D70 -> 86.42 | F70: R$ 4.912,74 | G70: R$ 4.999,16 | H70: 05/01/2026 15:56 | I70: 46027 | K70: Recebido | L70: Editora Heziom | M70: 40.804.477/0001-44 | N70: Stone Instituição de Pagamento S.A. | O70: 0001 | P70: 890291-8 | Q70: IGREJA P NACIONAL | R70: 00.096.388/0001-76 | S70: Banco do Brasil S.A. | T70: Desconhecido | U70: Desconhecido
A71: Crédito | B71: Transação | C71: 41,93 | D71: R$ 0,20 | E71: =C71-D71 -> 41.73 | F71: R$ 4.999,16 | G71: R$ 5.040,89 | H71: 05/01/2026 16:35 | I71: 46027 | K71: FINISHED | L71: Editora Heziom | M71: 40.804.477/0001-44 | N71: Stone Instituição de Pagamento S.A. | O71: 0001 | P71: 890291-8 | Q71: DIEGO M GALHARDO | R71: ***.818.118-** | S71: Banco Bradesco S.A. | T71: Desconhecido | U71: Desconhecido
A72: Crédito | B72: Transferência entre contas Stone | C72: 80,20 | D72: R$ 0,00 | E72: =C72-D72 -> 80.2 | F72: R$ 5.040,89 | G72: R$ 5.121,09 | H72: 05/01/2026 17:09 | I72: 46027 | K72: Recebida | L72: Editora Heziom | M72: 40.804.477/0001-44 | N72: Stone Instituição de Pagamento S.A. | O72: 0001 | P72: 890291-8 | Q72: Stone Principal | R72: 16.501.555/0001-57 | S72: STONE INSTITUIÇÃO DE PAGAMENTO S.A. | T72: 0001 | U72: 30772-8
A73: Crédito | B73: Transferência entre contas Stone | C73: 234,97 | D73: R$ 0,00 | E73: =C73-D73 -> 234.97 | F73: R$ 5.148,60 | G73: R$ 5.383,57 | H73: 05/01/2026 19:23 | I73: 46027 | K73: Recebida | L73: Editora Heziom | M73: 40.804.477/0001-44 | N73: Stone Instituição de Pagamento S.A. | O73: 0001 | P73: 890291-8 | Q73: Stone Principal | R73: 16.501.555/0001-57 | S73: STONE INSTITUIÇÃO DE PAGAMENTO S.A. | T73: 0001 | U73: 30772-8
A74: Crédito | B74: Transferência entre contas Stone | C74: 27,51 | D74: R$ 0,00 | E74: =C74-D74 -> 27.51 | F74: R$ 5.121,09 | G74: R$ 5.148,60 | H74: 05/01/2026 19:23 | I74: 46027 | K74: Recebida | L74: Editora Heziom | M74: 40.804.477/0001-44 | N74: Stone Instituição de Pagamento S.A. | O74: 0001 | P74: 890291-8 | Q74: Stone Principal | R74: 16.501.555/0001-57 | S74: STONE INSTITUIÇÃO DE PAGAMENTO S.A. | T74: 0001 | U74: 30772-8
A75: Crédito | B75: Pix | C75: 172,53 | D75: 0 | E75: =C75-D75 -> 172.53 | F75: R$ 5.383,57 | G75: R$ 5.556,10 | H75: 06/01/2026 11:49 | I75: 46028 | K75: Recebido | L75: Editora Heziom | M75: 40.804.477/0001-44 | N75: Stone Instituição de Pagamento S.A. | O75: 0001 | P75: 890291-8 | Q75: PATRICIA REGINA BARRETO LEITE | R75: ***.822.733-** | S75: CAIXA ECONOMICA FEDERAL | T75: Desconhecido | U75: Desconhecido
A76: Crédito | B76: Pix | C76: 9.887,92 | D76: 0 | E76: =C76-D76 -> 9887.92 | F76: R$ 5.556,10 | G76: R$ 15.444,02 | H76: 06/01/2026 11:56 | I76: 46028 | K76: Recebido | L76: Editora Heziom | M76: 40.804.477/0001-44 | N76: Stone Instituição de Pagamento S.A. | O76: 0001 | P76: 890291-8 | Q76: NEUSA FERNANDA BERNARDO ROSA | R76: ***.386.349-** | S76: CAIXA ECONOMICA FEDERAL | T76: Desconhecido | U76: Desconhecido
A77: Crédito | B77: Pix | C77: 1.377,70 | D77: 0 | E77: =C77-D77 -> 1377.7 | F77: R$ 15.444,02 | G77: R$ 16.821,72 | H77: 06/01/2026 12:38 | I77: 46028 | K77: Recebido | L77: Editora Heziom | M77: 40.804.477/0001-44 | N77: Stone Instituição de Pagamento S.A. | O77: 0001 | P77: 890291-8 | Q77: ELZA DE FATIMA SILVA | R77: ***.468.856-** | S77: Banco do Brasil S.A. | T77: Desconhecido | U77: Desconhecido
A78: Crédito | B78: Pix | C78: 6.682,54 | D78: 0 | E78: =C78-D78 -> 6682.54 | F78: R$ 16.821,72 | G78: R$ 23.504,26 | H78: 06/01/2026 16:00 | I78: 46028 | K78: Recebido | L78: Editora Heziom | M78: 40.804.477/0001-44 | N78: Stone Instituição de Pagamento S.A. | O78: 0001 | P78: 890291-8 | Q78: JOSE GONCALVES OLIVEIRA | R78: 630..-011 | S78: Banco do Brasil S.A. | T78: Desconhecido | U78: Desconhecido
A79: Crédito | B79: Pix | C79: 3.619,55 | D79: 0 | E79: =C79-D79 -> 3619.55 | F79: R$ 23.504,26 | G79: R$ 27.123,81 | H79: 06/01/2026 18:18 | I79: 46028 | K79: Recebido | L79: Editora Heziom | M79: 40.804.477/0001-44 | N79: Stone Instituição de Pagamento S.A. | O79: 0001 | P79: 890291-8 | Q79: Maria Emília de Almeida | R79: ***.844.101-** | S79: NU PAGAMENTOS S.A. - INSTITUIÇÃO DE PAGAMENTO | T79: Desconhecido | U79: Desconhecido
A80: Crédito | B80: Pix | C80: 2.237,54 | D80: 0 | E80: =C80-D80 -> 2237.54 | F80: R$ 27.123,81 | G80: R$ 29.361,35 | H80: 07/01/2026 10:22 | I80: 46029 | K80: Recebido | L80: Editora Heziom | M80: 40.804.477/0001-44 | N80: Stone Instituição de Pagamento S.A. | O80: 0001 | P80: 890291-8 | Q80: ANA MARIA ARRUDA OLIVEIRA | R80: ***.166.331-** | S80: CAIXA ECONOMICA FEDERAL | T80: Desconhecido | U80: Desconhecido
A81: Débito | B81: Pix | C81: -25.000,00 | D81: 0 | E81: =C81-D81 -> -25000 | F81: R$ 29.361,35 | G81: R$ 4.361,35 | H81: 07/01/2026 10:23 | I81: 46029 | K81: Enviado | L81: ASSOCIACAO EDITORA PRESBITERIANA DE PINHEIROS | M81: 40.804.477/0001-44 | N81: BANCO SANTANDER (BRASIL) S.A. | O81: Desconhecido | P81: Desconhecido | Q81: Editora Heziom | R81: 40.804.477/0001-44 | S81: Stone Instituição de Pagamento S.A. | T81: 0001 | U81: 890291-8
A82: Crédito | B82: Pix | C82: 105,50 | D82: 0 | E82: =C82-D82 -> 105.5 | F82: R$ 4.361,35 | G82: R$ 4.466,85 | H82: 07/01/2026 10:38 | I82: 46029 | K82: Recebido | L82: Editora Heziom | M82: 40.804.477/0001-44 | N82: Stone Instituição de Pagamento S.A. | O82: 0001 | P82: 890291-8 | Q82: IANNA ROSA LUCAS TORRES | R82: ***.299.321-** | S82: Banco XP S.A. | T82: Desconhecido | U82: Desconhecido
A83: Crédito | B83: Pix | C83: 67,52 | D83: 0 | E83: =C83-D83 -> 67.52 | F83: R$ 4.466,85 | G83: R$ 4.534,37 | H83: 07/01/2026 11:53 | I83: 46029 | K83: Recebido | L83: Editora Heziom | M83: 40.804.477/0001-44 | N83: Stone Instituição de Pagamento S.A. | O83: 0001 | P83: 890291-8 | Q83: GLAUCIA STELA DE CASTRO ROCHA | R83: ***.560.561-** | S83: PICPAY INSTITUIçãO DE PAGAMENTO S.A. | T83: Desconhecido | U83: Desconhecido
A84: Crédito | B84: Pix | C84: 37,98 | D84: 0 | E84: =C84-D84 -> 37.98 | F84: R$ 4.534,37 | G84: R$ 4.572,35 | H84: 07/01/2026 12:07 | I84: 46029 | K84: Recebido | L84: Editora Heziom | M84: 40.804.477/0001-44 | N84: Stone Instituição de Pagamento S.A. | O84: 0001 | P84: 890291-8 | Q84: Maria Cristina Soares Dias Ribeiro | R84: ***.651.541-** | S84: NU PAGAMENTOS S.A. - INSTITUIÇÃO DE PAGAMENTO | T84: Desconhecido | U84: Desconhecido
A85: Crédito | B85: Pix | C85: 71,74 | D85: 0 | E85: =C85-D85 -> 71.74 | F85: R$ 4.572,35 | G85: R$ 4.644,09 | H85: 07/01/2026 12:12 | I85: 46029 | K85: Recebido | L85: Editora Heziom | M85: 40.804.477/0001-44 | N85: Stone Instituição de Pagamento S.A. | O85: 0001 | P85: 890291-8 | Q85: Débora Vanessa Mariano | R85: ***.978.996-** | S85: Banco BTG Pactual S.A. | T85: Desconhecido | U85: Desconhecido
A86: Crédito | B86: Pix | C86: 50,64 | D86: 0 | E86: =C86-D86 -> 50.64 | F86: R$ 4.644,09 | G86: R$ 4.694,73 | H86: 07/01/2026 12:50 | I86: 46029 | K86: Recebido | L86: Editora Heziom | M86: 40.804.477/0001-44 | N86: Stone Instituição de Pagamento S.A. | O86: 0001 | P86: 890291-8 | Q86: HERMELINDA COSTA SARAIVA | R86: ***.814.391-** | S86: CAIXA ECONOMICA FEDERAL | T86: Desconhecido | U86: Desconhecido
... A99: Crédito | B99: Pix | C99: 52,00 | D99: 0 | E99: =C99-D99 -> 52 | F99: R$ 11.504,53 | G99: R$ 11.556,53 | H99: 10/01/2026 13:29 | I99: 46032 | K99: Recebido | L99: Editora Heziom | M99: 40.804.477/0001-44 | N99: Stone Instituição de Pagamento S.A. | O99: 0001 | P99: 890291-8 | Q99: ALESSANDRA BORGES GONZ LOPES | R99: ***.874.178-** | S99: ITAÚ UNIBANCO S.A. | T99: Desconhecido | U99: Desconhecido
A100: Crédito | B100: Transação | C100: 249,80 | D100: R$ 1,24 | E100: =C100-D100 -> 248.56 | F100: R$ 11.556,53 | G100: R$ 11.805,09 | H100: 11/01/2026 09:07 | I100: 46033 | K100: FINISHED | L100: Editora Heziom | M100: 40.804.477/0001-44 | N100: Stone Instituição de Pagamento S.A. | O100: 0001 | P100: 890291-8 | Q100: Carmen Maria Vargas Ferreira | R100: ***.088.188-** | S100: Banco BTG Pactual S.A. | T100: Desconhecido | U100: Desconhecido
A101: Crédito | B101: Transação | C101: 84,92 | D101: R$ 0,42 | E101: =C101-D101 -> 84.5 | F101: R$ 11.805,09 | G101: R$ 11.889,59 | H101: 11/01/2026 09:16 | I101: 46033 | K101: FINISHED | L101: Editora Heziom | M101: 40.804.477/0001-44 | N101: Stone Instituição de Pagamento S.A. | O101: 0001 | P101: 890291-8 | Q101: MARILIA MELO DAMASCENO | R101: ***.396.188-** | S101: ITAÚ UNIBANCO S.A. | T101: Desconhecido | U101: Desconhecido
A102: Crédito | B102: Transação | C102: 76,41 | D102: R$ 0,38 | E102: =C102-D102 -> 76.03 | F102: R$ 11.935,19 | G102: R$ 12.011,22 | H102: 11/01/2026 10:35 | I102: 46033 | K102: FINISHED | L102: Editora Heziom | M102: 40.804.477/0001-44 | N102: Stone Instituição de Pagamento S.A. | O102: 0001 | P102: 890291-8 | Q102: PATRICIA OTTAIANO | R102: ***.389.598-** | S102: Banco do Brasil S.A. | T102: Desconhecido | U102: Desconhecido
A103: Crédito | B103: Transação | C103: 45,82 | D103: R$ 0,22 | E103: =C103-D103 -> 45.6 | F103: R$ 11.889,59 | G103: R$ 11.935,19 | H103: 11/01/2026 10:35 | I103: 46033 | K103: FINISHED | L103: Editora Heziom | M103: 40.804.477/0001-44 | N103: Stone Instituição de Pagamento S.A. | O103: 0001 | P103: 890291-8 | Q103: ANA CAROLINA SILVA | R103: ***.009.366-** | S103: Banco do Brasil S.A. | T103: Desconhecido | U103: Desconhecido
A104: Crédito | B104: Transação | C104: 155,90 | D104: R$ 0,77 | E104: =C104-D104 -> 155.13 | F104: R$ 12.011,22 | G104: R$ 12.166,35 | H104: 11/01/2026 10:56 | I104: 46033 | K104: FINISHED | L104: Editora Heziom | M104: 40.804.477/0001-44 | N104: Stone Instituição de Pagamento S.A. | O104: 0001 | P104: 890291-8 | Q104: REBECA NEGRAO C B BOAVENTURA | R104: ***.474.323-** | S104: ITAÚ UNIBANCO S.A. | T104: Desconhecido | U104: Desconhecido
A105: Crédito | B105: Transferência entre contas Stone | C105: 573,49 | D105: R$ 0,00 | E105: =C105-D105 -> 573.49 | F105: R$ 13.110,90 | G105: R$ 13.684,39 | H105: 11/01/2026 11:27 | I105: 46033 | K105: Recebida | L105: Editora Heziom | M105: 40.804.477/0001-44 | N105: Stone Instituição de Pagamento S.A. | O105: 0001 | P105: 890291-8 | Q105: Stone Principal | R105: 16.501.555/0001-57 | S105: STONE INSTITUIÇÃO DE PAGAMENTO S.A. | T105: 0001 | U105: 30772-8
A106: Crédito | B106: Transferência entre contas Stone | C106: 504,05 | D106: R$ 0,00 | E106: =C106-D106 -> 504.05 | F106: R$ 12.606,85 | G106: R$ 13.110,90 | H106: 11/01/2026 11:27 | I106: 46033 | K106: Recebida | L106: Editora Heziom | M106: 40.804.477/0001-44 | N106: Stone Instituição de Pagamento S.A. | O106: 0001 | P106: 890291-8 | Q106: Stone Principal | R106: 16.501.555/0001-57 | S106: STONE INSTITUIÇÃO DE PAGAMENTO S.A. | T106: 0001 | U106: 30772-8
A107: Crédito | B107: Transferência entre contas Stone | C107: 81,49 | D107: R$ 0,00 | E107: =C107-D107 -> 81.49 | F107: R$ 12.525,36 | G107: R$ 12.606,85 | H107: 11/01/2026 11:27 | I107: 46033 | K107: Recebida | L107: Editora Heziom | M107: 40.804.477/0001-44 | N107: Stone Instituição de Pagamento S.A. | O107: 0001 | P107: 890291-8 | Q107: Stone Principal | R107: 16.501.555/0001-57 | S107: STONE INSTITUIÇÃO DE PAGAMENTO S.A. | T107: 0001 | U107: 30772-8
A108: Crédito | B108: Transferência entre contas Stone | C108: 167,85 | D108: R$ 0,00 | E108: =C108-D108 -> 167.85 | F108: R$ 12.357,51 | G108: R$ 12.525,36 | H108: 11/01/2026 11:27 | I108: 46033 | K108: Recebida | L108: Editora Heziom | M108: 40.804.477/0001-44 | N108: Stone Instituição de Pagamento S.A. | O108: 0001 | P108: 890291-8 | Q108: Stone Principal | R108: 16.501.555/0001-57 | S108: STONE INSTITUIÇÃO DE PAGAMENTO S.A. | T108: 0001 | U108: 30772-8
A109: Crédito | B109: Transferência entre contas Stone | C109: 191,16 | D109: R$ 0,00 | E109: =C109-D109 -> 191.16 | F109: R$ 12.166,35 | G109: R$ 12.357,51 | H109: 11/01/2026 11:27 | I109: 46033 | K109: Recebida | L109: Editora Heziom | M109: 40.804.477/0001-44 | N109: Stone Instituição de Pagamento S.A. | O109: 0001 | P109: 890291-8 | Q109: Stone Principal | R109: 16.501.555/0001-57 | S109: STONE INSTITUIÇÃO DE PAGAMENTO S.A. | T109: 0001 | U109: 30772-8
A110: Crédito | B110: Transação | C110: 37,40 | D110: R$ 0,18 | E110: =C110-D110 -> 37.22 | F110: R$ 13.684,39 | G110: R$ 13.721,61 | H110: 11/01/2026 12:14 | I110: 46033 | K110: FINISHED | L110: Editora Heziom | M110: 40.804.477/0001-44 | N110: Stone Instituição de Pagamento S.A. | O110: 0001 | P110: 890291-8 | Q110: MARIANA ARIOZO FALEIROS | R110: ***.127.518-** | S110: Banco do Brasil S.A. | T110: Desconhecido | U110: Desconhecido
A111: Crédito | B111: Transação | C111: 33,90 | D111: R$ 0,16 | E111: =C111-D111 -> 33.74 | F111: R$ 13.721,61 | G111: R$ 13.755,35 | H111: 11/01/2026 12:17 | I111: 46033 | K111: FINISHED | L111: Editora Heziom | M111: 40.804.477/0001-44 | N111: Stone Instituição de Pagamento S.A. | O111: 0001 | P111: 890291-8 | Q111: ELIO OLIVEIRA COSTA | R111: ***.179.705-** | S111: Banco Bradesco S.A. | T111: Desconhecido | U111: Desconhecido
... A119: Crédito | B119: Transferência entre contas Stone | C119: 64,70 | D119: R$ 0,00 | E119: =C119-D119 -> 64.7 | F119: R$ 14.154,78 | G119: R$ 14.219,48 | H119: 11/01/2026 13:32 | I119: 46033 | K119: Recebida | L119: Editora Heziom | M119: 40.804.477/0001-44 | N119: Stone Instituição de Pagamento S.A. | O119: 0001 | P119: 890291-8 | Q119: Stone Principal | R119: 16.501.555/0001-57 | S119: STONE INSTITUIÇÃO DE PAGAMENTO S.A. | T119: 0001 | U119: 30772-8
A120: Crédito | B120: Pix | C120: 2.000,00 | D120: 0 | E120: =C120-D120 -> 2000 | F120: R$ 17.332,56 | G120: R$ 19.332,56 | H120: 11/01/2026 15:12 | I120: 46033 | K120: Recebido | L120: Editora Heziom | M120: 40.804.477/0001-44 | N120: Stone Instituição de Pagamento S.A. | O120: 0001 | P120: 890291-8 | Q120: KERLIANY FIDEL ALMEIDA PEREIRA | R120: ***.943.911-** | S120: ITAÚ UNIBANCO S.A. | T120: Desconhecido | U120: Desconhecido
A121: Crédito | B121: Transferência entre contas Stone | C121: 40,25 | D121: R$ 0,00 | E121: =C121-D121 -> 40.25 | F121: R$ 21.549,96 | G121: R$ 21.590,21 | H121: 11/01/2026 15:36 | I121: 46033 | K121: Recebida | L121: Editora Heziom | M121: 40.804.477/0001-44 | N121: Stone Instituição de Pagamento S.A. | O121: 0001 | P121: 890291-8 | Q121: Stone Principal | R121: 16.501.555/0001-57 | S121: STONE INSTITUIÇÃO DE PAGAMENTO S.A. | T121: 0001 | U121: 30772-8
A122: Crédito | B122: Transferência entre contas Stone | C122: 892,68 | D122: R$ 0,00 | E122: =C122-D122 -> 892.68 | F122: R$ 20.657,28 | G122: R$ 21.549,96 | H122: 11/01/2026 15:36 | I122: 46033 | K122: Recebida | L122: Editora Heziom | M122: 40.804.477/0001-44 | N122: Stone Instituição de Pagamento S.A. | O122: 0001 | P122: 890291-8 | Q122: Stone Principal | R122: 16.501.555/0001-57 | S122: STONE INSTITUIÇÃO DE PAGAMENTO S.A. | T122: 0001 | U122: 30772-8
A123: Crédito | B123: Transferência entre contas Stone | C123: 660,38 | D123: R$ 0,00 | E123: =C123-D123 -> 660.38 | F123: R$ 19.996,90 | G123: R$ 20.657,28 | H123: 11/01/2026 15:36 | I123: 46033 | K123: Recebida | L123: Editora Heziom | M123: 40.804.477/0001-44 | N123: Stone Instituição de Pagamento S.A. | O123: 0001 | P123: 890291-8 | Q123: Stone Principal | R123: 16.501.555/0001-57 | S123: STONE INSTITUIÇÃO DE PAGAMENTO S.A. | T123: 0001 | U123: 30772-8
A124: Crédito | B124: Transferência entre contas Stone | C124: 106,27 | D124: R$ 0,00 | E124: =C124-D124 -> 106.27 | F124: R$ 19.890,63 | G124: R$ 19.996,90 | H124: 11/01/2026 15:36 | I124: 46033 | K124: Recebida | L124: Editora Heziom | M124: 40.804.477/0001-44 | N124: Stone Instituição de Pagamento S.A. | O124: 0001 | P124: 890291-8 | Q124: Stone Principal | R124: 16.501.555/0001-57 | S124: STONE INSTITUIÇÃO DE PAGAMENTO S.A. | T124: 0001 | U124: 30772-8
A125: Crédito | B125: Transferência entre contas Stone | C125: 506,71 | D125: R$ 0,00 | E125: =C125-D125 -> 506.71 | F125: R$ 19.383,92 | G125: R$ 19.890,63 | H125: 11/01/2026 15:36 | I125: 46033 | K125: Recebida | L125: Editora Heziom | M125: 40.804.477/0001-44 | N125: Stone Instituição de Pagamento S.A. | O125: 0001 | P125: 890291-8 | Q125: Stone Principal | R125: 16.501.555/0001-57 | S125: STONE INSTITUIÇÃO DE PAGAMENTO S.A. | T125: 0001 | U125: 30772-8
A126: Crédito | B126: Transferência entre contas Stone | C126: 51,36 | D126: R$ 0,00 | E126: =C126-D126 -> 51.36 | F126: R$ 19.332,56 | G126: R$ 19.383,92 | H126: 11/01/2026 15:36 | I126: 46033 | K126: Recebida | L126: Editora Heziom | M126: 40.804.477/0001-44 | N126: Stone Instituição de Pagamento S.A. | O126: 0001 | P126: 890291-8 | Q126: Stone Principal | R126: 16.501.555/0001-57 | S126: STONE INSTITUIÇÃO DE PAGAMENTO S.A. | T126: 0001 | U126: 30772-8
A127: Crédito | B127: Transação | C127: 271,92 | D127: R$ 1,35 | E127: =C127-D127 -> 270.57 | F127: R$ 21.590,21 | G127: R$ 21.860,78 | H127: 11/01/2026 18:37 | I127: 46033 | K127: FINISHED | L127: Editora Heziom | M127: 40.804.477/0001-44 | N127: Stone Instituição de Pagamento S.A. | O127: 0001 | P127: 890291-8 | Q127: VICTOR AMORA DIAS | R127: ***.309.351-** | S127: Banco Inter S.A. | T127: Desconhecido | U127: Desconhecido
A128: Crédito | B128: Transação | C128: 469,70 | D128: R$ 2,34 | E128: =C128-D128 -> 467.36 | F128: R$ 21.860,78 | G128: R$ 22.328,14 | H128: 11/01/2026 18:55 | I128: 46033 | K128: FINISHED | L128: Editora Heziom | M128: 40.804.477/0001-44 | N128: Stone Instituição de Pagamento S.A. | O128: 0001 | P128: 890291-8 | Q128: FELIPE ZAZIRSKAS DA CRUZ | R128: ***.306.848-** | S128: Banco C6 S.A. | T128: Desconhecido | U128: Desconhecido
A129: Crédito | B129: Transferência entre contas Stone | C129: 49,72 | D129: R$ 0,00 | E129: =C129-D129 -> 49.72 | F129: R$ 23.286,66 | G129: R$ 23.336,38 | H129: 11/01/2026 19:22 | I129: 46033 | K129: Recebida | L129: Editora Heziom | M129: 40.804.477/0001-44 | N129: Stone Instituição de Pagamento S.A. | O129: 0001 | P129: 890291-8 | Q129: Stone Principal | R129: 16.501.555/0001-57 | S129: STONE INSTITUIÇÃO DE PAGAMENTO S.A. | T129: 0001 | U129: 30772-8
A130: Crédito | B130: Transferência entre contas Stone | C130: 958,52 | D130: R$ 0,00 | E130: =C130-D130 -> 958.52 | F130: R$ 22.328,14 | G130: R$ 23.286,66 | H130: 11/01/2026 19:22 | I130: 46033 | K130: Recebida | L130: Editora Heziom | M130: 40.804.477/0001-44 | N130: Stone Instituição de Pagamento S.A. | O130: 0001 | P130: 890291-8 | Q130: Stone Principal | R130: 16.501.555/0001-57 | S130: STONE INSTITUIÇÃO DE PAGAMENTO S.A. | T130: 0001 | U130: 30772-8
A131: Crédito | B131: Transação | C131: 51,90 | D131: R$ 0,25 | E131: =C131-D131 -> 51.65 | F131: R$ 23.336,38 | G131: R$ 23.388,03 | H131: 11/01/2026 20:29 | I131: 46033 | K131: FINISHED | L131: Editora Heziom | M131: 40.804.477/0001-44 | N131: Stone Instituição de Pagamento S.A. | O131: 0001 | P131: 890291-8 | Q131: ELIZABETE DO NASCIMENTO | R131: ***.816.048-** | S131: ITAÚ UNIBANCO S.A. | T131: Desconhecido | U131: Desconhecido
A132: Crédito | B132: Transação | C132: 71,91 | D132: R$ 0,35 | E132: =C132-D132 -> 71.56 | F132: R$ 23.408,25 | G132: R$ 23.479,81 | H132: 11/01/2026 20:40 | I132: 46033 | K132: FINISHED | L132: Editora Heziom | M132: 40.804.477/0001-44 | N132: Stone Instituição de Pagamento S.A. | O132: 0001 | P132: 890291-8 | Q132: WENDEL ANDRE RODRIGUES VALENTIM | R132: ***.884.758-** | S132: PICPAY INSTITUIçãO DE PAGAMENTO S.A. | T132: Desconhecido | U132: Desconhecido
... A145: Crédito | B145: Transferência entre contas Stone | C145: 229,82 | D145: R$ 0,00 | E145: =C145-D145 -> 229.82 | F145: R$ 26.912,22 | G145: R$ 27.142,04 | H145: 12/01/2026 11:01 | I145: 46034 | K145: Recebida | L145: Editora Heziom | M145: 40.804.477/0001-44 | N145: Stone Instituição de Pagamento S.A. | O145: 0001 | P145: 890291-8 | Q145: Stone Principal | R145: 16.501.555/0001-57 | S145: STONE INSTITUIÇÃO DE PAGAMENTO S.A. | T145: 0001 | U145: 30772-8
A146: Crédito | B146: Pix | C146: 4.000,00 | D146: 0 | E146: =C146-D146 -> 4000 | F146: R$ 27.142,04 | G146: R$ 31.142,04 | H146: 12/01/2026 12:48 | I146: 46034 | K146: Recebido | L146: Editora Heziom | M146: 40.804.477/0001-44 | N146: Stone Instituição de Pagamento S.A. | O146: 0001 | P146: 890291-8 | Q146: PEDRO ARTHUR FREITAS DIAS | R146: ***.136.753-** | S146: CAIXA ECONOMICA FEDERAL | T146: Desconhecido | U146: Desconhecido
A147: Crédito | B147: Pix | C147: 3.628,36 | D147: 0 | E147: =C147-D147 -> 3628.36 | F147: R$ 31.142,04 | G147: R$ 34.770,40 | H147: 12/01/2026 14:04 | I147: 46034 | K147: Recebido | L147: Editora Heziom | M147: 40.804.477/0001-44 | N147: Stone Instituição de Pagamento S.A. | O147: 0001 | P147: 890291-8 | Q147: Rosana Moretes Silvestre | R147: ***.356.231-** | S147: PAGSEGURO INTERNET INSTITUIÇÃO DE PAGAMENTO S.A. | T147: Desconhecido | U147: Desconhecido
A148: Crédito | B148: Pix | C148: 2.885,00 | D148: 0 | E148: =C148-D148 -> 2885 | F148: R$ 34.770,40 | G148: R$ 37.655,40 | H148: 12/01/2026 16:51 | I148: 46034 | K148: Recebido | L148: Editora Heziom | M148: 40.804.477/0001-44 | N148: Stone Instituição de Pagamento S.A. | O148: 0001 | P148: 890291-8 | Q148: DEBORA TORRES DE OLIVEIRA KEMPA | R148: ***.366.731-** | S148: PAGSEGURO INTERNET INSTITUIÇÃO DE PAGAMENTO S.A. | T148: Desconhecido | U148: Desconhecido
A149: Crédito | B149: Transferência entre contas Stone | C149: 342,36 | D149: R$ 0,00 | E149: =C149-D149 -> 342.36 | F149: R$ 37.655,40 | G149: R$ 37.997,76 | H149: 12/01/2026 19:24 | I149: 46034 | K149: Recebida | L149: Editora Heziom | M149: 40.804.477/0001-44 | N149: Stone Instituição de Pagamento S.A. | O149: 0001 | P149: 890291-8 | Q149: Stone Principal | R149: 16.501.555/0001-57 | S149: STONE INSTITUIÇÃO DE PAGAMENTO S.A. | T149: 0001 | U149: 30772-8
A150: Crédito | B150: Pix | C150: 5.508,00 | D150: 0 | E150: =C150-D150 -> 5508 | F150: R$ 37.997,76 | G150: R$ 43.505,76 | H150: 13/01/2026 14:01 | I150: 46035 | K150: Recebido | L150: Editora Heziom | M150: 40.804.477/0001-44 | N150: Stone Instituição de Pagamento S.A. | O150: 0001 | P150: 890291-8 | Q150: Maria Esmeralda de Oliveira Souza | R150: ***.824.613-** | S150: NU PAGAMENTOS S.A. - INSTITUIÇÃO DE PAGAMENTO | T150: Desconhecido | U150: Desconhecido
A151: Crédito | B151: Pix | C151: 814,00 | D151: 0 | E151: =C151-D151 -> 814 | F151: R$ 43.505,76 | G151: R$ 44.319,76 | H151: 13/01/2026 15:10 | I151: 46035 | K151: Recebido | L151: Editora Heziom | M151: 40.804.477/0001-44 | N151: Stone Instituição de Pagamento S.A. | O151: 0001 | P151: 890291-8 | Q151: Maria Esmeralda de Oliveira Souza | R151: ***.824.613-** | S151: NU PAGAMENTOS S.A. - INSTITUIÇÃO DE PAGAMENTO | T151: Desconhecido | U151: Desconhecido
A152: Crédito | B152: Transferência entre contas Stone | C152: 29,51 | D152: R$ 0,00 | E152: =C152-D152 -> 29.51 | F152: R$ 44.319,76 | G152: R$ 44.349,27 | H152: 13/01/2026 15:22 | I152: 46035 | K152: Recebida | L152: Editora Heziom | M152: 40.804.477/0001-44 | N152: Stone Instituição de Pagamento S.A. | O152: 0001 | P152: 890291-8 | Q152: Stone Principal | R152: 16.501.555/0001-57 | S152: STONE INSTITUIÇÃO DE PAGAMENTO S.A. | T152: 0001 | U152: 30772-8
A153: Crédito | B153: Pix | C153: 3.000,00 | D153: 0 | E153: =C153-D153 -> 3000 | F153: R$ 44.349,27 | G153: R$ 47.349,27 | H153: 13/01/2026 18:29 | I153: 46035 | K153: Recebido | L153: Editora Heziom | M153: 40.804.477/0001-44 | N153: Stone Instituição de Pagamento S.A. | O153: 0001 | P153: 890291-8 | Q153: QUEILA COSTA VILELA DOURADO SAMPAIO | R153: ***.203.135-** | S153: CAIXA ECONOMICA FEDERAL | T153: Desconhecido | U153: Desconhecido
A154: Crédito | B154: Pix | C154: 3.000,00 | D154: 0 | E154: =C154-D154 -> 3000 | F154: R$ 47.349,27 | G154: R$ 50.349,27 | H154: 14/01/2026 07:09 | I154: 46036 | K154: Recebido | L154: Editora Heziom | M154: 40.804.477/0001-44 | N154: Stone Instituição de Pagamento S.A. | O154: 0001 | P154: 890291-8 | Q154: DAVID NIAN DOURADO SAMPAIO | R154: ***.977.804-** | S154: CAIXA ECONOMICA FEDERAL | T154: Desconhecido | U154: Desconhecido
A155: Crédito | B155: Pix | C155: 1.985,33 | D155: 0 | E155: =C155-D155 -> 1985.33 | F155: R$ 50.349,27 | G155: R$ 52.334,60 | H155: 14/01/2026 07:37 | I155: 46036 | K155: Recebido | L155: Editora Heziom | M155: 40.804.477/0001-44 | N155: Stone Instituição de Pagamento S.A. | O155: 0001 | P155: 890291-8 | Q155: QUEILA COSTA VILELA DOURADO SAMPAIO | R155: ***.203.135-** | S155: CAIXA ECONOMICA FEDERAL | T155: Desconhecido | U155: Desconhecido
A156: Crédito | B156: Pix | C156: 612,00 | D156: 0 | E156: =C156-D156 -> 612 | F156: R$ 52.334,60 | G156: R$ 52.946,60 | H156: 14/01/2026 09:30 | I156: 46036 | K156: Recebido | L156: Editora Heziom | M156: 40.804.477/0001-44 | N156: Stone Instituição de Pagamento S.A. | O156: 0001 | P156: 890291-8 | Q156: Maria Esmeralda de Oliveira Souza | R156: ***.824.613-** | S156: NU PAGAMENTOS S.A. - INSTITUIÇÃO DE PAGAMENTO | T156: Desconhecido | U156: Desconhecido
A157: Crédito | B157: Transferência entre contas Stone | C157: 110,87 | D157: R$ 0,00 | E157: =C157-D157 -> 110.87 | F157: R$ 52.946,60 | G157: R$ 53.057,47 | H157: 14/01/2026 13:10 | I157: 46036 | K157: Recebida | L157: Editora Heziom | M157: 40.804.477/0001-44 | N157: Stone Instituição de Pagamento S.A. | O157: 0001 | P157: 890291-8 | Q157: Stone Principal | R157: 16.501.555/0001-57 | S157: STONE INSTITUIÇÃO DE PAGAMENTO S.A. | T157: 0001 | U157: 30772-8
A158: Débito | B158: Pix | C158: -500,00 | D158: 0 | E158: =C158-D158 -> -500 | F158: R$ 53.057,47 | G158: R$ 52.557,47 | H158: 14/01/2026 13:21 | I158: 46036 | K158: Enviado | L158: LALAMOVE TECNOLOGIA (BRASIL) LTDA. | M158: 34.538.625/0001-23 | N158: MERCADO PAGO INSTITUIÇÃO DE PAGAMENTO LTDA. | O158: Desconhecido | P158: Desconhecido | Q158: Editora Heziom | R158: 40.804.477/0001-44 | S158: Stone Instituição de Pagamento S.A. | T158: 0001 | U158: 890291-8
A159: Débito | B159: Pix | C159: -50.000,00 | D159: 0 | E159: =C159-D159 -> -50000 | F159: R$ 52.557,47 | G159: R$ 2.557,47 | H159: 14/01/2026 13:22 | I159: 46036 | K159: Enviado | L159: ASSOCIACAO EDITORA PRESBITERIANA DE PINHEIROS | M159: 40.804.477/0001-44 | N159: BANCO SANTANDER (BRASIL) S.A. | O159: Desconhecido | P159: Desconhecido | Q159: Editora Heziom | R159: 40.804.477/0001-44 | S159: Stone Instituição de Pagamento S.A. | T159: 0001 | U159: 890291-8
A160: Crédito | B160: Pix | C160: 1.379,22 | D160: 0 | E160: =C160-D160 -> 1379.22 | F160: R$ 2.557,47 | G160: R$ 3.936,69 | H160: 14/01/2026 16:12 | I160: 46036 | K160: Recebido | L160: Editora Heziom | M160: 40.804.477/0001-44 | N160: Stone Instituição de Pagamento S.A. | O160: 0001 | P160: 890291-8 | Q160: FABIANA DE ALMEIDA MUNIZ HENRIQUE | R160: ***.221.608-** | S160: CAIXA ECONOMICA FEDERAL | T160: Desconhecido | U160: Desconhecido
A161: Crédito | B161: Transferência entre contas Stone | C161: 119,30 | D161: R$ 0,00 | E161: =C161-D161 -> 119.3 | F161: R$ 4.129,42 | G161: R$ 4.248,72 | H161: 14/01/2026 17:27 | I161: 46036 | K161: Recebida | L161: Editora Heziom | M161: 40.804.477/0001-44 | N161: Stone Instituição de Pagamento S.A. | O161: 0001 | P161: 890291-8 | Q161: Stone Principal | R161: 16.501.555/0001-57 | S161: STONE INSTITUIÇÃO DE PAGAMENTO S.A. | T161: 0001 | U161: 30772-8
A162: Crédito | B162: Transferência entre contas Stone | C162: 192,73 | D162: R$ 0,00 | E162: =C162-D162 -> 192.73 | F162: R$ 3.936,69 | G162: R$ 4.129,42 | H162: 14/01/2026 17:27 | I162: 46036 | K162: Recebida | L162: Editora Heziom | M162: 40.804.477/0001-44 | N162: Stone Instituição de Pagamento S.A. | O162: 0001 | P162: 890291-8 | Q162: Stone Principal | R162: 16.501.555/0001-57 | S162: STONE INSTITUIÇÃO DE PAGAMENTO S.A. | T162: 0001 | U162: 30772-8
A163: Crédito | B163: Transferência entre contas Stone | C163: 79,73 | D163: R$ 0,00 | E163: =C163-D163 -> 79.73 | F163: R$ 4.248,72 | G163: R$ 4.328,45 | H163: 14/01/2026 19:24 | I163: 46036 | K163: Recebida | L163: Editora Heziom | M163: 40.804.477/0001-44 | N163: Stone Instituição de Pagamento S.A. | O163: 0001 | P163: 890291-8 | Q163: Stone Principal | R163: 16.501.555/0001-57 | S163: STONE INSTITUIÇÃO DE PAGAMENTO S.A. | T163: 0001 | U163: 30772-8
A164: Crédito | B164: Pix | C164: 68,00 | D164: 0 | E164: =C164-D164 -> 68 | F164: R$ 4.328,45 | G164: R$ 4.396,45 | H164: 14/01/2026 21:01 | I164: 46036 | K164: Recebido | L164: Editora Heziom | M164: 40.804.477/0001-44 | N164: Stone Instituição de Pagamento S.A. | O164: 0001 | P164: 890291-8 | Q164: Maria Esmeralda de Oliveira Souza | R164: ***.824.613-** | S164: NU PAGAMENTOS S.A. - INSTITUIÇÃO DE PAGAMENTO | T164: Desconhecido | U164: Desconhecido
A165: Crédito | B165: Transação | C165: 72,90 | D165: R$ 0,36 | E165: =C165-D165 -> 72.54 | F165: R$ 4.396,45 | G165: R$ 4.468,99 | H165: 15/01/2026 10:33 | I165: 46037 | K165: FINISHED | L165: Editora Heziom | M165: 40.804.477/0001-44 | N165: Stone Instituição de Pagamento S.A. | O165: 0001 | P165: 890291-8 | Q165: PATRICIA NEVES COSTA DA SILVA | R165: ***.519.688-** | S165: Banco Bradesco S.A. | T165: Desconhecido | U165: Desconhecido
A166: Crédito | B166: Pix | C166: 99,90 | D166: 0 | E166: =C166-D166 -> 99.9 | F166: R$ 4.468,99 | G166: R$ 4.568,89 | H166: 15/01/2026 12:27 | I166: 46037 | K166: Recebido | L166: Editora Heziom | M166: 40.804.477/0001-44 | N166: Stone Instituição de Pagamento S.A. | O166: 0001 | P166: 890291-8 | Q166: ANA KAROLINA LOPES PAZINI | R166: ***.115.661-** | S166: ITAÚ UNIBANCO S.A. | T166: Desconhecido | U166: Desconhecido
A167: Crédito | B167: Transferência entre contas Stone | C167: 226,50 | D167: R$ 0,00 | E167: =C167-D167 -> 226.5 | F167: R$ 4.784,30 | G167: R$ 5.010,80 | H167: 15/01/2026 13:31 | I167: 46037 | K167: Recebida | L167: Editora Heziom | M167: 40.804.477/0001-44 | N167: Stone Instituição de Pagamento S.A. | O167: 0001 | P167: 890291-8 | Q167: Stone Principal | R167: 16.501.555/0001-57 | S167: STONE INSTITUIÇÃO DE PAGAMENTO S.A. | T167: 0001 | U167: 30772-8
A168: Crédito | B168: Transferência entre contas Stone | C168: 215,41 | D168: R$ 0,00 | E168: =C168-D168 -> 215.41 | F168: R$ 4.568,89 | G168: R$ 4.784,30 | H168: 15/01/2026 13:31 | I168: 46037 | K168: Recebida | L168: Editora Heziom | M168: 40.804.477/0001-44 | N168: Stone Instituição de Pagamento S.A. | O168: 0001 | P168: 890291-8 | Q168: Stone Principal | R168: 16.501.555/0001-57 | S168: STONE INSTITUIÇÃO DE PAGAMENTO S.A. | T168: 0001 | U168: 30772-8
A169: Crédito | B169: Pix | C169: 1.655,47 | D169: 0 | E169: =C169-D169 -> 1655.47 | F169: R$ 5.010,80 | G169: R$ 6.666,27 | H169: 15/01/2026 15:01 | I169: 46037 | K169: Recebido | L169: Editora Heziom | M169: 40.804.477/0001-44 | N169: Stone Instituição de Pagamento S.A. | O169: 0001 | P169: 890291-8 | Q169: PRIMEIRA IGREJA BATISTA DA LAGOINHA EM SANTOS | R169: 38.029.306/0001-43 | S169: PAGSEGURO INTERNET INSTITUIÇÃO DE PAGAMENTO S.A. | T169: Desconhecido | U169: Desconhecido
A170: Crédito | B170: Pix | C170: 49,90 | D170: 0 | E170: =C170-D170 -> 49.9 | F170: R$ 6.666,27 | G170: R$ 6.716,17 | H170: 15/01/2026 17:01 | I170: 46037 | K170: Recebido | L170: Editora Heziom | M170: 40.804.477/0001-44 | N170: Stone Instituição de Pagamento S.A. | O170: 0001 | P170: 890291-8 | Q170: João Vitor de Castro Carneiro | R170: ***.230.251-** | S170: NU PAGAMENTOS S.A. - INSTITUIÇÃO DE PAGAMENTO | T170: Desconhecido | U170: Desconhecido
A171: Crédito | B171: Transferência entre contas Stone | C171: 98,85 | D171: R$ 0,00 | E171: =C171-D171 -> 98.85 | F171: R$ 6.802,29 | G171: R$ 6.901,14 | H171: 15/01/2026 17:24 | I171: 46037 | K171: Recebida | L171: Editora Heziom | M171: 40.804.477/0001-44 | N171: Stone Instituição de Pagamento S.A. | O171: 0001 | P171: 890291-8 | Q171: Stone Principal | R171: 16.501.555/0001-57 | S171: STONE INSTITUIÇÃO DE PAGAMENTO S.A. | T171: 0001 | U171: 30772-8
A172: Crédito | B172: Transferência entre contas Stone | C172: 86,12 | D172: R$ 0,00 | E172: =C172-D172 -> 86.12 | F172: R$ 6.716,17 | G172: R$ 6.802,29 | H172: 15/01/2026 17:24 | I172: 46037 | K172: Recebida | L172: Editora Heziom | M172: 40.804.477/0001-44 | N172: Stone Instituição de Pagamento S.A. | O172: 0001 | P172: 890291-8 | Q172: Stone Principal | R172: 16.501.555/0001-57 | S172: STONE INSTITUIÇÃO DE PAGAMENTO S.A. | T172: 0001 | U172: 30772-8
A173: Crédito | B173: Transferência entre contas Stone | C173: 99,53 | D173: R$ 0,00 | E173: =C173-D173 -> 99.53 | F173: R$ 6.901,14 | G173: R$ 7.000,67 | H173: 16/01/2026 04:24 | I173: 46038 | K173: Recebida | L173: Editora Heziom | M173: 40.804.477/0001-44 | N173: Stone Instituição de Pagamento S.A. | O173: 0001 | P173: 890291-8 | Q173: Stone Principal | R173: 16.501.555/0001-57 | S173: STONE INSTITUIÇÃO DE PAGAMENTO S.A. | T173: 0001 | U173: 30772-8
A174: Crédito | B174: Pix | C174: 245,32 | D174: 0 | E174: =C174-D174 -> 245.32 | F174: R$ 7.000,67 | G174: R$ 7.245,99 | H174: 16/01/2026 11:15 | I174: 46038 | K174: Recebido | L174: Editora Heziom | M174: 40.804.477/0001-44 | N174: Stone Instituição de Pagamento S.A. | O174: 0001 | P174: 890291-8 | Q174: JORGE ALVES DE SOUZA | R174: ***.120.148-** | S174: Banco do Brasil S.A. | T174: Desconhecido | U174: Desconhecido
...

Sheet Planilha1
A1: Data | B1: Literarius | C1: Stone | D1: Diferença
A2: 46023 | B2: =SUMIF('extrato-stone-literarius'!C:C,Planilha1!A2,'extrato-stone-literarius'!F:F) -> 109.38 | C2: =SUMIF('extrato stone'!I:I,Planilha1!A2,'extrato stone'!E:E) -> 109.38 | D2: =B2-C2 -> 0
A3: 46024 | B3: =SUMIF('extrato-stone-literarius'!C:C,Planilha1!A3,'extrato-stone-literarius'!F:F) -> 206.64 | C3: =SUMIF('extrato stone'!I:I,Planilha1!A3,'extrato stone'!E:E) -> 206.64 | D3: =B3-C3 -> 0
A4: 46026 | B4: =SUMIF('extrato-stone-literarius'!C:C,Planilha1!A4,'extrato-stone-literarius'!F:F) -> 15966.84 | C4: =SUMIF('extrato stone'!I:I,Planilha1!A4,'extrato stone'!E:E) -> 15966.84 | D4: =B4-C4 -> 0
A5: 46027 | B5: =SUMIF('extrato-stone-literarius'!C:C,Planilha1!A5,'extrato-stone-literarius'!F:F) -> -20921.74 | C5: =SUMIF('extrato stone'!I:I,Planilha1!A5,'extrato stone'!E:E) -> -20921.74 | D5: =B5-C5 -> 0
A6: 46028 | B6: =SUMIF('extrato-stone-literarius'!C:C,Planilha1!A6,'extrato-stone-literarius'!F:F) -> 21740.24 | C6: =SUMIF('extrato stone'!I:I,Planilha1!A6,'extrato stone'!E:E) -> 21740.24 | D6: =B6-C6 -> 0
A7: 46029 | B7: =SUMIF('extrato-stone-literarius'!C:C,Planilha1!A7,'extrato-stone-literarius'!F:F) -> -22402.57 | C7: =SUMIF('extrato stone'!I:I,Planilha1!A7,'extrato stone'!E:E) -> -22402.57 | D7: =B7-C7 -> 0
A8: 46030 | B8: =SUMIF('extrato-stone-literarius'!C:C,Planilha1!A8,'extrato-stone-literarius'!F:F) -> 1096.37 | C8: =SUMIF('extrato stone'!I:I,Planilha1!A8,'extrato stone'!E:E) -> 1096.37 | D8: =B8-C8 -> 0
A9: 46031 | B9: =SUMIF('extrato-stone-literarius'!C:C,Planilha1!A9,'extrato-stone-literarius'!F:F) -> -1000 | C9: =SUMIF('extrato stone'!I:I,Planilha1!A9,'extrato stone'!E:E) -> -1000 | D9: =B9-C9 -> 0
A10: 46032 | B10: =SUMIF('extrato-stone-literarius'!C:C,Planilha1!A10,'extrato-stone-literarius'!F:F) -> 6738.92 | C10: =SUMIF('extrato stone'!I:I,Planilha1!A10,'extrato stone'!E:E) -> 6738.92 | D10: =B10-C10 -> 0
A11: 46033 | B11: =SUMIF('extrato-stone-literarius'!C:C,Planilha1!A11,'extrato-stone-literarius'!F:F) -> 15355.69 | C11: =SUMIF('extrato stone'!I:I,Planilha1!A11,'extrato stone'!E:E) -> 15355.69 | D11: =B11-C11 -> 0
A12: 46034 | B12: =SUMIF('extrato-stone-literarius'!C:C,Planilha1!A12,'extrato-stone-literarius'!F:F) -> 11085.54 | C12: =SUMIF('extrato stone'!I:I,Planilha1!A12,'extrato stone'!E:E) -> 11085.54 | D12: =B12-C12 -> 0
A13: 46035 | B13: =SUMIF('extrato-stone-literarius'!C:C,Planilha1!A13,'extrato-stone-literarius'!F:F) -> 9351.51 | C13: =SUMIF('extrato stone'!I:I,Planilha1!A13,'extrato stone'!E:E) -> 9351.51 | D13: =B13-C13 -> 0
... A29: 46053 | B29: =SUMIF('extrato-stone-literarius'!C:C,Planilha1!A29,'extrato-stone-literarius'!F:F) -> 2178.5 | C29: =SUMIF('extrato stone'!I:I,Planilha1!A29,'extrato stone'!E:E) -> 2178.5 | D29: =B29-C29 -> 0
