Workbook

Sheet extrato-literarius
A1: Tipo | B1: Número | D1: Documento | E1: Descrição | F1: Valor | G1: Origem | H1: Plano de Contas | I1: Centro Resultados | J1: Conta contábil
A2: D | B2: 20545 | C2: 46024 | D2: 20545 | E2: CONTABIL RIBEIRO | F2: -6505 | G2: BAIXA | H2: Contabilidade | I2: Administrativo | J2: =VLOOKUP(H2,Planilha1!B:C,2,0) -> 214
A3: D | B3: 20581 | C3: 46024 | D3: 20581 | E3: Porto Saúde S.A | F3: -1710.17 | G3: BAIXA | H3: Assistencia Medica | I3: Administrativo | J3: =VLOOKUP(H3,Planilha1!B:C,2,0) -> 200
A4: D | B4: 23083 | C4: 46024 | D4: 23083 | E4: FLEXPACK INDUSTRIA E COMERCIO DE EMBALAGENS LTDA | F4: -3289.16 | G4: BAIXA | H4: Materiais Aplicados Venda Prod | I4: Expedição | J4: =VLOOKUP(H4,Planilha1!B:C,2,0) -> 224
A5: D | B5: 10628 | C5: 46024 | D5: 10628 | E5: EDITORA HAGNOS LTDA | F5: -270.72 | G5: BAIXA | H5: Materiais Para Revenda | I5: CPC Offline | J5: =VLOOKUP(H5,Planilha1!B:C,2,0) -> 80
A6: D | B6: 23161 | C6: 46024 | D6: 23161 | E6: Marcos Roberto Loiola Arrais | F6: -1105 | G6: BAIXA | H6: Despesas Editorial - Edição | I6: Editorial | J6: =VLOOKUP(H6,Planilha1!B:C,2,0) -> 185
A7: D | B7: 23125 | C7: 46024 | D7: 23125 | E7: GUILHERME JUNIOR GUIMARAES | F7: -810 | G7: BAIXA | H7: Despesas Editorial - Revisão de Prova | I7: Editorial | J7: =VLOOKUP(H7,Planilha1!B:C,2,0) -> 752
A8: D | B8: 23154 | C8: 46024 | D8: 23154 | E8: GUILHERME JUNIOR GUIMARAES | F8: -78 | G8: BAIXA | H8: Despesas Editorial - Revisão de Prova | I8: Editorial | J8: =VLOOKUP(H8,Planilha1!B:C,2,0) -> 752
A9: D | B9: 10625 | C9: 46024 | D9: 10625 | E9: VIDA MELHOR EDITORA LTDA | F9: -4796.51 | G9: BAIXA | H9: Materiais Para Revenda | I9: CPC Offline | J9: =VLOOKUP(H9,Planilha1!B:C,2,0) -> 80
A10: C | B10: 1925 | C10: 46024 | D10: 1925 | E10: TED RECEBIDA 4080447700014 | F10: 19598.72 | G10: BANCÁRIO | H10: TRANSFERENCIA ENTRE CONTAS | I10: TRANSFERENCIAS ENTRE CONTAS | J10: =VLOOKUP(H10,Planilha1!B:C,2,0) -> 0
A11: C | B11: 1926 | C11: 46024 | D11: 1926 | E11: PIX RECEBIDO 07290754867 | F11: 160 | G11: BANCÁRIO | H11: VENDA DE LIVROS | I11: Receita de vendas | J11: =VLOOKUP(H11,Planilha1!B:C,2,0) -> 132 a 134
A12: D | B12: 15870 | C12: 46024 | D12: 15870 | E12: Luz Para o Caminho | F12: -725 | G12: BAIXA | H12: Materiais Para Revenda | I12: CPC Offline | J12: =VLOOKUP(H12,Planilha1!B:C,2,0) -> 80
A13: D | B13: 5128 | C13: 46027 | D13: 5128 | E13: EDITORA HAGNOS LTDA | F13: -1586.1 | G13: BAIXA | H13: Materiais Para Revenda | I13: CPC Offline | J13: =VLOOKUP(H13,Planilha1!B:C,2,0) -> 80
... A317: C | B317: 2599 | C317: 46052 | D317: 2599 | E317: RENDIMENTO LIQUIDO DE CONTAMAX | F317: 5.91 | G317: BANCÁRIO | H317: Receitas financeiras | I317: Financeiro | J317: =VLOOKUP(H317,Planilha1!B:C,2,0) -> 135

Sheet Planilha1
A1: Codigo | B1: Descrição | C1: Contas contábeis
A2: 0 | B2: Cod 0561 | Cod 1082 | Cod 1138 | Cod 1170 | Cod 1176 | Cod 1191 | Cod 1196 | Cod 1200 | Cod 1646 | Cod 8301 | C2: 62
A3: 2 | B3: VENDA DE LIVROS | C3: 132 a 134
A4: 3 | B4: AQUISIÇÃO DE LIVROS | C4: 28
A5: 4 | B5: VENDA DE EBOOK | C5: 134
A6: 10 | B6: 13º Salário | C6: 180 a 192
A7: 11 | B7: Despesas Editorial - Capa | C7: 752
A8: 12 | B8: Despesas Editorial - Conferência de Emendas | Despesas Editorial - Revisão de Prova | C8: 752
A9: 13 | B9: Despesas Editorial - Diagramação | C9: 185
A10: 14 | B10: Despesas Editorial - Edição | C10: 185
A11: 15 | B11: Despesas Editorial - Ilustração | C11: 752
A12: 16 | B12: Despesas Editorial - Preparação | C12: 752
A13: 17 | B13: Despesas Editorial - Produção Editorial | C13: 752
A14: 18 | B14: Despesas Editorial - Revisão de Prova | C14: 752
A15: 19 | B15: Despesas Editorial - Tradução | C15: 752
A16: 20 | B16: Materiais Para Revenda | C16: 80
A17: 21 | B17: Producao Material Proprio | C17: 80
A18: 21 | B18: Produção Material Próprio | C18: 80
... A75: 77 | B75: Impostos E Taxas | C75: 225
A76: 78 | B76: Estorno e Reembolso | C76: 231 LANÇAR NA NATUREZA DA DESPESA
A77: 79 | B77: Internet | C77: 233
A78: 80 | B78: Monitoramento Sede | C78: 67
A79: 81 | B79: Royalties | C79: 165
A80: 82 | B80: PIS 8301 | C80: 197
A81: 83 | B81: Terreno e Dependências - Sede | C81: 255
A82: 84 | B82: Sistemas e Softwares -Adm Marketing | C82: 244
A83: 85 | B83: Sistemas e Softwares Comerciais | C83: 710
A84: 86 | B84: Devolução de Venda | C84: 166
A85: 87 | B85: Exames médicos | C85: 193
A86: 88 | B86: Juros pagos/passivos | C86: 251
A87: 89 | B87: Lanches e Refeições Equipe | C87: 215
A88: 90 | B88: Lanches e Refeições Comercial | C88: 212
... A99: 101 | B99: Condomínio | C99: 237
A100: 102 | B100: DESPESAS OPERACIONAIS | C100: 4.3.1
A101: 103 | B101: DESPESAS ADMINISTRATIVAS | C101: 4.3.1.01
A102: 104 | B102: Materiais Impressos | C102: 224
A103: 105 | B103: Cod 0561 | C103: 67
A104: 106 | B104: TRANSFERENCIA ENTRE CONTAS | C104: 0
A105: 107 | B105: Despesas Bancárias | C105: 252
A106: 108 | B106: Rescisões | C106: 188 A 192
A107: 109 | B107: Cod 5952 | C107: 73
A108: 110 | B108: Móveis, Máquinas e Utensílios | C108: 41
A109: 111 | B109: Outras despesas | C109: 76
A110: 112 | B110: Receitas financeiras | C110: 135
A111: 113 | B111: Condominio | C111: 237
A112: 114 | B112: Cod 1162 | C112: 62

Sheet extrato-santander
A1: AGENCIA | B1: 0729 | C1: CONTA | D1: 130020815
A2: 02/01/2026 | B2: PIX RECEBIDO 07290754867 | D2: 160 | E2: 413670.59
A3: 02/01/2026 | B3: TED RECEBIDA 40804477000144 | D3: 19598.72 | E3: 413510.59
A4: 02/01/2026 | B4: PIX ENVIADO 53 321 629 MARCOS ROBERTO | D4: -1105 | E4: 393911.87
A5: 02/01/2026 | B5: PIX ENVIADO 40 284 132 GUILHERME JUNI | D5: -888 | E5: 395016.87
A6: 02/01/2026 | B6: PAGAMENTO DE BOLETO OUTROS BANCOS LUZ PARA O CAMINHO | C6: 0000000000 | D6: -725 | E6: 395904.87
A7: 02/01/2026 | B7: PAGAMENTO DE BOLETO VIDA MELHOR EDI | C7: 0000000000 | D7: -4796.51 | E7: 396629.87
A8: 02/01/2026 | B8: PAGAMENTO DE BOLETO EDITORA HAGNOS | C8: 0000000000 | D8: -270.72 | E8: 401426.38
A9: 02/01/2026 | B9: PAGAMENTO DE BOLETO OUTROS BANCOS FLEXPACK INDUSTRIA E COME | C9: 0000000000 | D9: -3289.16 | E9: 401697.1
A10: 02/01/2026 | B10: PAGAMENTO DE BOLETO PORTO SEGURO - | C10: 0000000000 | D10: -1710.17 | E10: 404986.26
A11: 02/01/2026 | B11: PAGAMENTO DE BOLETO OUTROS BANCOS CONTABIL RIBEIRO LTDA | C11: 0000000000 | D11: -6505 | E11: 406696.43
A12: 05/01/2026 | B12: PIX ENVIADO 21 972 538 ABNER HENRIQUE | D12: -975.69 | E12: 418415.81
A13: 05/01/2026 | B13: PAGAMENTO DE BOLETO OUTROS BANCOS EDITORA HAGNOS LTDA | C13: 0000000000 | D13: -307.72 | E13: 419391.5
A14: 05/01/2026 | B14: PAGAMENTO DE BOLETO OUTROS BANCOS EMPRESA BRASILEIRA DE COR | C14: 0000000000 | D14: -5133.31 | E14: 419699.22
A15: 05/01/2026 | B15: PAGAMENTO DE BOLETO OUTROS BANCOS IPSIS GRAFICA E EDITORA S | C15: 0000000000 | D15: -14318.53 | E15: 424832.53
A16: 05/01/2026 | B16: PAGAMENTO DE BOLETO OUTROS BANCOS FLOWBIZ TECNOLOGIA DA INF | C16: 0000000000 | D16: -2178 | E16: 439151.06
A17: 05/01/2026 | B17: PAGAMENTO DE BOLETO OUTROS BANCOS IPSIS GRAFICA E EDITORA S | C17: 0000000000 | D17: -18475.52 | E17: 441329.06
A18: 05/01/2026 | B18: PAGAMENTO DE BOLETO OUTROS BANCOS EDITORA HAGNOS LTDA | C18: 0000000000 | D18: -1288.99 | E18: 459804.58
A19: 05/01/2026 | B19: PAGAMENTO DE BOLETO OUTROS BANCOS IPSIS GRAFICA E EDITORA S | C19: 0000000000 | D19: -12009.09 | E19: 461093.57
A20: 05/01/2026 | B20: PAGAMENTO DE BOLETO OUTROS BANCOS EDITORA HAGNOS LTDA | C20: 0000000000 | D20: -1586.1 | E20: 473102.66
A21: 05/01/2026 | B21: TED RECEBIDA 40804477000144 | D21: 25101.72 | E21: 474688.76
A22: 05/01/2026 | B22: PIX RECEBIDO 40804477000144 | D22: 28000 | E22: 449587.04
A23: 05/01/2026 | B23: PAGAMENTO CARTAO DE CREDITO AMAZON-VISA | C23: 0000477144 | D23: 4842.54 | E23: 421587.04
A24: 05/01/2026 | B24: PEDAGIO ELETRONICO - SEM PARAR SEM PARAR | D24: -64.74 | E24: 416744.5
A25: 05/01/2026 | B25: TARIFA AVULSA ENVIO PIX | D25: -5.78 | E25: 416809.24
A26: 05/01/2026 | B26: CR COB BLOQ COMP CONF RECEBIMENTO 0729/000028892 | D26: 3144.43 | E26: 416815.02
A27: 06/01/2026 | B27: RENDIMENTO LIQUIDO DE CONTAMAX 7000 RENDIMENTO LIQUIDO DE CONTAMAX | D27: 2.88 | E27: 387003.01
A28: 06/01/2026 | B28: TARIFA MANUTENCAO TIT VENCIDO | C28: 198927 | D28: -3.28 | E28: 387000.13
A29: 06/01/2026 | B29: PIX ENVIADO TO ON LOG | C29: 16593136 | D29: -579.9 | E29: 387003.41
A30: 06/01/2026 | B30: PAGAMENTO DE BOLETO OUTROS BANCOS SOC RELIGIOSA EDIC VIDA N | C30: 0000000000 | D30: -423.91 | E30: 387583.31
A31: 06/01/2026 | B31: PAGAMENTO DE BOLETO OUTROS BANCOS IPSIS GRAFICA E EDITORA S | C31: 0000000000 | D31: -16764.06 | E31: 388007.22
A32: 06/01/2026 | B32: PIX ENVIADO PNH TRAVEL | D32: -1454.62 | E32: 404771.28
A33: 06/01/2026 | B33: PIX ENVIADO EDUARDO MANO DE ANDRADE | D33: -2960 | E33: 406225.9
A34: 06/01/2026 | B34: PIX ENVIADO 21 972 538 ABNER HENRIQUE | D34: -960 | E34: 409185.9
A35: 06/01/2026 | B35: PIX ENVIADO CAMARA BRASILEIRA DO LIVR | D35: -27.4 | E35: 410145.9
A36: 06/01/2026 | B36: PAGAMENTO DE BOLETO QUALICORP ADMINISTRADORA | D36: -8242.51 | E36: 410173.3
A37: 07/01/2026 | B37: TAR BAIXA COB SIMPLES-ELETRONICA | C37: 198927 | D37: -1.84 | E37: 443661.86
A38: 07/01/2026 | B38: TAR LIQ COB COM REG COMPE | C38: 198927 | D38: -4.28 | E38: 443663.7
A39: 07/01/2026 | B39: PAGAMENTO DE BOLETO OUTROS BANCOS J V M I COMERCIO CAFE LTD | C39: 0000000000 | D39: -219.5 | E39: 443667.98
A40: 07/01/2026 | B40: PAGAMENTO DE BOLETO OUTROS BANCOS EDITORA HAGNOS LTDA | C40: 0000000000 | D40: -2891.32 | E40: 443887.48
A41: 07/01/2026 | B41: PAGAMENTO DE BOLETO OUTROS BANCOS G3 SECURITIZADORA DE ATIV | C41: 0000000000 | D41: -4355.4 | E41: 446778.8
A42: 07/01/2026 | B42: PIX ENVIADO VICTORIA CARDOSO ALDAMA P | D42: -134.85 | E42: 451134.2
A43: 07/01/2026 | B43: PIX ENVIADO CAMARA BRASILEIRA DO LIVR | D43: -27.4 | E43: 451269.05
A44: 07/01/2026 | B44: PIX ENVIADO ANA MARIA NEVES SAC ZECHM | D44: -30.96 | E44: 451296.45
A45: 07/01/2026 | B45: TED RECEBIDA 40804477000144 | D45: 34119.37 | E45: 451327.41
A46: 07/01/2026 | B46: PIX RECEBIDO 40804477000144 | D46: 25000 | E46: 417208.04
A47: 07/01/2026 | B47: TED RECEBIDA 15436940000103 | D47: 4294.1 | E47: 392208.04
A48: 07/01/2026 | B48: CR COB BLOQ COMP CONF RECEBIMENTO 0729/000028892 | D48: 910.93 | E48: 387913.94
A49: 08/01/2026 | B49: RENDIMENTO LIQUIDO DE CONTAMAX 7000 RENDIMENTO LIQUIDO DE CONTAMAX | D49: 0.71 | E49: 435400.83
A50: 08/01/2026 | B50: TAR LIQ COB COM REG COMPE | C50: 198927 | D50: -12.84 | E50: 435400.12
A51: 08/01/2026 | B51: TARIFA MANUTENCAO TIT VENCIDO | C51: 198927 | D51: -1.64 | E51: 435412.96
A52: 08/01/2026 | B52: PIX ENVIADO 55 145 400 LUCAS DIAS SIL | D52: -3056.69 | E52: 435414.6
A53: 08/01/2026 | B53: PIX ENVIADO TO ON LOG | C53: 09584510 | D53: -260.1 | E53: 438471.29
A54: 08/01/2026 | B54: PIX ENVIADO ADC MEDIA GROUP | D54: -1511.94 | E54: 438731.39
A55: 08/01/2026 | B55: PIX ENVIADO PAPIRO SOLUCOES TEXTUAIS | D55: -1416 | E55: 440243.33
A56: 08/01/2026 | B56: PIX ENVIADO DANNY MEDEIROS CHARAO 009 | D56: -567.55 | E56: 441659.33
A57: 08/01/2026 | B57: PAGAMENTO DE BOLETO PROMOVE ARTES G | C57: 0000000000 | D57: -1899.27 | E57: 442226.88
A58: 08/01/2026 | B58: PAGAMENTO DE BOLETO OUTROS BANCOS EDITORA HAGNOS LTDA | C58: 0000000000 | D58: -7347.38 | E58: 444126.15
A59: 08/01/2026 | B59: PAGAMENTO CARTAO DE CREDITO AMAZON-AMEX | C59: 0000477144 | D59: 84.91 | E59: 451473.53
A60: 08/01/2026 | B60: PAGAMENTO CARTAO DE CREDITO AMAZON-ELO | C60: 0000477144 | D60: 237.73 | E60: 451388.62
A61: 08/01/2026 | B61: PAGAMENTO CARTAO DE CREDITO AMAZON-MASTER | C61: 0000477144 | D61: 3884.49 | E61: 451150.89
A62: 08/01/2026 | B62: CR COB BLOQ COMP CONF RECEBIMENTO 0729/000028892 | D62: 3607.43 | E62: 447266.4
A63: 08/01/2026 | B63: TARIFA AVULSA ENVIO PIX 07/01/2026 | D63: -2.89 | E63: 443658.97
A64: 09/01/2026 | B64: RENDIMENTO LIQUIDO DE CONTAMAX 7000 RENDIMENTO LIQUIDO DE CONTAMAX | D64: 5.07 | E64: 383006.26
A65: 09/01/2026 | B65: PIX ENVIADO ADC MEDIA GROUP | D65: -55885.19 | E65: 383001.19
A66: 09/01/2026 | B66: PIX ENVIADO BKM ASSESSORIA | D66: -829.07 | E66: 438886.38
A67: 09/01/2026 | B67: PAGAMENTO DE BOLETO PROMOVE ARTES G | C67: 0000000000 | D67: -3502.2 | E67: 439715.45
A68: 09/01/2026 | B68: PAGAMENTO DE BOLETO OUTROS BANCOS SINDICATO DOS EMPREGADOS | C68: 0000000000 | D68: -17.22 | E68: 443217.65
A69: 09/01/2026 | B69: TED RECEBIDA 146.681.655-49 | D69: 7845.6 | E69: 443234.87
A70: 09/01/2026 | B70: TARIFA AVULSA ENVIO PIX | D70: -11.56 | E70: 435389.27
A71: 12/01/2026 | B71: RENDIMENTO LIQUIDO DE CONTAMAX 7000 RENDIMENTO LIQUIDO DE CONTAMAX | D71: 7.51 | E71: 294165.88
A72: 12/01/2026 | B72: PIX ENVIADO PRECEITO EDITORA LTDA | D72: -2064 | E72: 294158.37
A73: 12/01/2026 | B73: PIX ENVIADO RAFAEL PEREIRA BARBOSA | D73: -100 | E73: 296222.37
A74: 12/01/2026 | B74: PIX ENVIADO 24 549 182 ALBERTO MURAKA | D74: -768 | E74: 296322.37
A75: 12/01/2026 | B75: PIX ENVIADO REBECA CHIMINAZZO DE FIGU | D75: -13.43 | E75: 297090.37
A76: 12/01/2026 | B76: PAGAMENTO DE BOLETO OUTROS BANCOS PROMOVE ARTES GRAFICAS LT | C76: 0000000000 | D76: -4386.15 | E76: 297103.8
A77: 12/01/2026 | B77: PAGAMENTO DE BOLETO EDITORA HAGNOS | C77: 0000000000 | D77: -307.72 | E77: 301489.95
A78: 12/01/2026 | B78: PAGAMENTO DE BOLETO OUTROS BANCOS LITERARIUS SISTEMAS E CON | C78: 0000000000 | D78: -3235 | E78: 301797.67
A79: 12/01/2026 | B79: PAGAMENTO DE BOLETO PROMOVE ARTES G | C79: 0000000000 | D79: -4579.8 | E79: 305032.67
A80: 12/01/2026 | B80: PAGAMENTO DE BOLETO OUTROS BANCOS GEO GRAFICA E EDITORA LTD | C80: 0000000000 | D80: -1453.92 | E80: 309612.47
A81: 12/01/2026 | B81: PAGAMENTO DE BOLETO OUTROS BANCOS SOC RELIGIOSA EDIC VIDA N | C81: 0000000000 | D81: -2122.46 | E81: 311066.39
A82: 12/01/2026 | B82: PAGAMENTO DE BOLETO OUTROS BANCOS LILLE SCHOOL INTELIGENCIA | C82: 0000000000 | D82: -3550 | E82: 313188.85
A83: 12/01/2026 | B83: PAGAMENTO DE BOLETO OUTROS BANCOS SOCIEDADE BIBLICA DO BRAS | C83: 0000000000 | D83: -868.85 | E83: 316738.85
A84: 12/01/2026 | B84: PAGAMENTO DE BOLETO OUTROS BANCOS MISSAO EVANGELICA LITERAR | C84: 0000000000 | D84: -356.62 | E84: 317607.7
A85: 12/01/2026 | B85: PAGAMENTO DE BOLETO OUTROS BANCOS MISSAO EVANGELICA LITERAR | C85: 0000000000 | D85: -1576.32 | E85: 317964.32
A86: 12/01/2026 | B86: PAGAMENTO DE BOLETO OUTROS BANCOS MISSAO EVANGELICA LITERAR | C86: 0000000000 | D86: -474.74 | E86: 319540.64
A87: 12/01/2026 | B87: PAGAMENTO DE BOLETO OUTROS BANCOS LUZ PARA O CAMINHO | C87: 0000000000 | D87: -725 | E87: 320015.38
... A93: 12/01/2026 | B93: PAGAMENTO DE BOLETO OUTROS BANCOS ASSOCIACAO IGREJA PRESBIT | C93: 0000000000 | D93: -4140 | E93: 336898.85
A94: 12/01/2026 | B94: DEBITO AUT. FAT.CARTAO MASTER CARD FINAL 7369 | D94: -17209.73 | E94: 341038.85
A95: 12/01/2026 | B95: DEBITO AUT. FAT.CARTAO MASTER CARD FINAL 6277 | D95: -24639.9 | E95: 358248.58
A96: 12/01/2026 | B96: TARIFA AVULSA ENVIO PIX | D96: -5.78 | E96: 382888.48
A97: 12/01/2026 | B97: TARIFA MENSALIDADE PACOTE SERVICOS DEZEMBRO / 2025 | D97: -112 | E97: 382894.26
A98: 13/01/2026 | B98: RENDIMENTO LIQUIDO DE CONTAMAX 7000 RENDIMENTO LIQUIDO DE CONTAMAX | D98: 0.7 | E98: 285297.75
A99: 13/01/2026 | B99: TAR LIQ COB COM REG COMPE | C99: 198927 | D99: -8.56 | E99: 285297.05
A100: 13/01/2026 | B100: TARIFA MANUTENCAO TIT VENCIDO | C100: 198927 | D100: -1.64 | E100: 285305.61
A101: 13/01/2026 | B101: PIX ENVIADO JOSE ALFREDO MAMMINI | D101: -490 | E101: 285307.25
A102: 13/01/2026 | B102: PIX ENVIADO BIANCA DE ASSIS FARIAS | D102: -375.19 | E102: 285797.25
A103: 13/01/2026 | B103: PIX ENVIADO LUIZ FERNANDO MARTINS DE | D103: -4000 | E103: 286172.44
A104: 13/01/2026 | B104: PAGAMENTO DE BOLETO PROMOVE ARTES G | C104: 0000000000 | D104: -4849.2 | E104: 290172.44
A105: 13/01/2026 | B105: PAGAMENTO DE BOLETO OUTROS BANCOS EDITORA HAGNOS LTDA | C105: 0000000000 | D105: -461.55 | E105: 295021.64
...

Sheet literarius-santander
B1: Literárius | C1: Santander | D1: Diferença
A2: 46024 | B2: =SUMIF('extrato-literarius'!C:C,'literarius-santander'!A2,'extrato-literarius'!F:F) -> 469.16 | C2: =SUMIF('extrato-santander'!A:A,'literarius-santander'!A2,'extrato-santander'!D:D) -> 469.16 | D2: =B2-C2 -> 1.8189894e-12
A3: 46027 | B3: =SUMIF('extrato-literarius'!C:C,'literarius-santander'!A3,'extrato-literarius'!F:F) -> 4745.22 | C3: =SUMIF('extrato-santander'!A:A,'literarius-santander'!A3,'extrato-santander'!D:D) -> 4745.22 | D3: =B3-C3 -> 1.1823431e-11
A4: 46028 | B4: =SUMIF('extrato-literarius'!C:C,'literarius-santander'!A4,'extrato-literarius'!F:F) -> -31412.8 | C4: =SUMIF('extrato-santander'!A:A,'literarius-santander'!A4,'extrato-santander'!D:D) -> -31412.8 | D4: =B4-C4 -> 0
A5: 46029 | B5: =SUMIF('extrato-literarius'!C:C,'literarius-santander'!A5,'extrato-literarius'!F:F) -> 56658.85 | C5: =SUMIF('extrato-santander'!A:A,'literarius-santander'!A5,'extrato-santander'!D:D) -> 56658.85 | D5: =B5-C5 -> 0
A6: 46030 | B6: =SUMIF('extrato-literarius'!C:C,'literarius-santander'!A6,'extrato-literarius'!F:F) -> -8261.03 | C6: =SUMIF('extrato-santander'!A:A,'literarius-santander'!A6,'extrato-santander'!D:D) -> -8261.03 | D6: =B6-C6 -> 0
A7: 46031 | B7: =SUMIF('extrato-literarius'!C:C,'literarius-santander'!A7,'extrato-literarius'!F:F) -> -52394.57 | C7: =SUMIF('extrato-santander'!A:A,'literarius-santander'!A7,'extrato-santander'!D:D) -> -52394.57 | D7: =B7-C7 -> 0
A8: 46034 | B8: =SUMIF('extrato-literarius'!C:C,'literarius-santander'!A8,'extrato-literarius'!F:F) -> -88840.38 | C8: =SUMIF('extrato-santander'!A:A,'literarius-santander'!A8,'extrato-santander'!D:D) -> -88840.38 | D8: =B8-C8 -> 0
A9: 46035 | B9: =SUMIF('extrato-literarius'!C:C,'literarius-santander'!A9,'extrato-literarius'!F:F) -> -8868.13 | C9: =SUMIF('extrato-santander'!A:A,'literarius-santander'!A9,'extrato-santander'!D:D) -> -8868.13 | D9: =B9-C9 -> 0
A10: 46036 | B10: =SUMIF('extrato-literarius'!C:C,'literarius-santander'!A10,'extrato-literarius'!F:F) -> 17633.36 | C10: =SUMIF('extrato-santander'!A:A,'literarius-santander'!A10,'extrato-santander'!D:D) -> 17633.36 | D10: =B10-C10 -> 0
A11: 46037 | B11: =SUMIF('extrato-literarius'!C:C,'literarius-santander'!A11,'extrato-literarius'!F:F) -> -29225.33 | C11: =SUMIF('extrato-santander'!A:A,'literarius-santander'!A11,'extrato-santander'!D:D) -> -29225.33 | D11: =B11-C11 -> 0
A12: 46038 | B12: =SUMIF('extrato-literarius'!C:C,'literarius-santander'!A12,'extrato-literarius'!F:F) -> -25042.79 | C12: =SUMIF('extrato-santander'!A:A,'literarius-santander'!A12,'extrato-santander'!D:D) -> -25042.79 | D12: =B12-C12 -> 0
A13: 46041 | B13: =SUMIF('extrato-literarius'!C:C,'literarius-santander'!A13,'extrato-literarius'!F:F) -> 68431.13 | C13: =SUMIF('extrato-santander'!A:A,'literarius-santander'!A13,'extrato-santander'!D:D) -> 68431.13 | D13: =B13-C13 -> 0
... A22: 46052 | B22: =SUMIF('extrato-literarius'!C:C,'literarius-santander'!A22,'extrato-literarius'!F:F) -> -118921.51 | C22: =SUMIF('extrato-santander'!A:A,'literarius-santander'!A22,'extrato-santander'!D:D) -> -118921.51 | D22: =B22-C22 -> 0
