Workbook

Sheet Planilha1
A1: Código | D1: Classificação | H1: Descrição | R1: Saldo Atual
H2: RECEITA COM VENDAS | R2: 495905.57
A3: 860 | D3: 3.1.1.03.0860 | I3: ATACADO | R3: 254042.11
A4: 861 | D4: 3.1.1.03.0861 | I4: ECOMMERCE | R4: 163266.31
A5: 865 | D5: 3.1.1.03.0865 | I5: LIVRARIA | R5: 78597.15
H6: MARKETPLACES | R6: 13298.19
A7: 863 | D7: 3.1.1.03.0863 | I7: AMAZON | R7: 11612.4
A8: 864 | D8: 3.1.1.03.0864 | I8: MERCADO LIVRE | R8: 1685.79
H9: TOTAL RECEITA BRUTA COM VENDAS | R9: 509203.76
H11: DEVOLUÇÃO E DESCONTO DE VENDAS | R11: -318.25
A12: 166 | D12: 3.6.1.01.0166 | I12: DEVOLUCAO DE VENDAS | R12: -296.45
A13: 168 | D13: 3.6.1.01.0168 | I13: DESCONTO SOBRE VENDAS | R13: -21.8
H14: RECEITA LÍQUIDA DE VENDAS | R14: 508885.51
H16: FRETE COBRADO DOS CLIENTES | R16: 35417.32
A17: 749 | D17: 3.1.1.04.0749 | I17: FRETES COBRADOS DOS CLIENTES | R17: 35417.32
H18: RECEITA OPERACIONAL TOTAL | R18: 544302.83
H20: CUSTO DOS PRODUTOS VENDIDOS (CPV/CMV) | R20: -229501.55
A21: 162 | D21: 3.7.1.01.0162 | I21: CUSTO DAS MERCADORIAS VENDIDAS | R21: -118537
A22: 165 | D22: 3.7.1.01.0165 | I22: DIREITOS AUTORAIS | R22: -39097.27
A23: 167 | D23: 3.7.1.01.0167 | I23: MATERIAIS APLICADOS NA VENDA DE PRODUTOS | R23: -2271.61
A24: 170 | D24: 3.7.1.01.0170 | I24: ROYALTIES EDITORIAIS E OUTROS | R24: -69595.67
H25: TOTAL CUSTO DOS PRODUTOS VENDIDOS | R25: -229501.55
H27: LUCRO BRUTO | R27: 314801.28
H29: DESPESAS VARIÁVEIS COMERCIAIS | R29: -45438.63
A30: 164 | D30: 3.7.1.01.0164 | I30: FRETES SOBRE MERCADORIAS | R30: -38368.67
A31: 206 | D31: 4.1.1.05.0206 | I31: COMISSOES POR VENDA | R31: -5380.07
A32: 212 | D32: 4.3.1.01.0212 | I32: DESPESAS REPRESENTACAO COMERCIAL | R32: -690.89
A33: 224 | D33: 4.3.1.01.0224 | I33: EMBALAGENS E MATERIAS GRAFICOS | R33: -999
H34: TAXA DE CARTAO / GATEWAY | R34: -7467.97
A35: 250 | D35: 4.3.1.03.0250 | I35: DESPESAS PAGAR ME | R35: -14.41
A36: 253 | D36: 4.3.1.03.0253 | I36: DESPESAS MERCADO PAGO.COM | R36: -127.84
A37: 651 | D37: 4.3.1.03.0651 | I37: DESPESAS AMAZON | R37: -192.64
A38: 653 | D38: 4.3.1.03.0653 | I38: DESPESAS STONE | R38: -39.71
A39: 654 | D39: 4.3.1.03.0654 | I39: DESPESAS VINDI | R39: -7093.37
H40: TOTAL DESPESAS VARIÁVEIS COMERCIAIS | R40: -52906.6
H42: MARGEM DE CONTRIBUIÇÃO | R42: 261894.68
H44: DESPESAS FIXAS OPERACIONAIS | R44: -73305.91
H46: DESPESA FIXA COMERCIAL | R46: -73305.91
H48: SALARIO FIXO DOS VENDEDORES | R48: -3214.9
A49: 182 | D49: 4.1.1.01.0182 | I49: COMERCIAL - PJ | R49: -3214.9
H50: EQUIPE DE MARKETING | R50: -20385.71
A51: 181 | D51: 4.1.1.01.0181 | I51: MARKETING - PJ | R51: -9430
A52: 188 | D52: 4.1.1.02.0188 | I52: MARKETING - CLT | R52: -10955.71
H53: LIVRARIA | R53: -6985
A54: 184 | D54: 4.1.1.01.0184 | I54: LIVRARIA - PJ | R54: -6985
H55: ENCARGOS PREVIDENCIARIOS E SOCIAIS | R55: -5776.55
A56: 502 | D56: 4.1.1.03.0502 | I56: INSS - COMERCIAL | R56: -3487.17
A57: 503 | D57: 4.1.1.03.0503 | I57: FGTS - COMERCIAL | R57: -963.01
A58: 504 | D58: 4.1.1.03.0504 | I58: PIS - COMERCIAL | R58: -120.37
A59: 511 | D59: 4.1.1.04.0511 | I59: VALE TRANSPORTE - COMERCIAL | R59: -1206
H60: SISTEMAS E FERRAMENTAS ADMINISTRATIVAS - COMERCIAL | R60: -3522.01
A61: 710 | D61: 4.3.1.06.0710 | I61: DESPESAS COM INFORMATICA / SISTEMAS / SOFTWARES - COMERCIAL | R61: -3522.01
H62: OUTROS - COMERCIAL | R62: -6307.63
A63: 711 | D63: 4.3.1.06.0711 | I63: VIAGEM, ESTADIA E PEDAGIO | R63: -6307.63
H64: PUBLICIDADE | R64: -27114.11
A65: 171 | D65: 4.3.1.02.0171 | I65: PUBLICIDADE - TRAFEGO PAGO | R65: -25724.11
A66: 245 | D66: 4.3.1.02.0245 | I66: DESPESAS COM MARKETING E PUBLICIDADE - | R66: -1390
H67: DESPESA FIXA ADMINITRATIVA | R67: -96068.02
H69: SALÁRIOS E ENCARGOS | R69: -57629.3
A70: 180 | D70: 4.1.1.01.0180 | I70: ADMINISTRACAO - PJ | R70: -17401.46
A71: 187 | D71: 4.1.1.01.0187 | I71: DIRETORIA - PJ | R71: -9224.77
A72: 189 | D72: 4.1.1.02.0189 | I72: ADMINISTRACAO - CLT | R72: -3750.54
A73: 190 | D73: 4.1.1.02.0190 | I73: EXPEDICAO - CLT | R73: -8968.18
A74: 192 | D74: 4.1.1.02.0192 | I74: FINANCEIRO - CLT | R74: -3038.9
A75: 193 | D75: 4.1.1.02.0193 | I75: DIVERSOS | R75: -100
A76: 195 | D76: 4.1.1.03.0195 | I76: INSS - ADMINISTRATIVO | R76: -2151.87
A77: 196 | D77: 4.1.1.03.0196 | I77: FGTS - ADMINISTRATIVO | R77: -894.02
A78: 197 | D78: 4.1.1.03.0197 | I78: PIS - ADMINISTRATIVO | R78: -90.04
A79: 200 | D79: 4.1.1.04.0200 | I79: ASSISTENCIA MEDICA | R79: -2640.6
A80: 201 | D80: 4.1.1.04.0201 | I80: VALE TRANSPORTE - ADMINISTRATIVO | R80: -1279.24
A81: 202 | D81: 4.1.1.04.0202 | I81: VALE REFEICAO | R81: -6003.48
... A83: 210 | D83: 4.2.1.02.0210 | I83: CAPACITACAO PROFISSIONAL | R83: -459
H84: ALUGUEL E CONDOMÍNIO | R84: -7119.08
A85: 229 | D85: 4.3.1.01.0229 | I85: ALUGUEIS | R85: -7089.41
A86: 237 | D86: 4.3.1.01.0237 | I86: DESPESAS COM CONDOMINIO | R86: -29.67
H87: CONTABILIDADE | R87: -6054
A88: 214 | D88: 4.3.1.01.0214 | I88: SERVICOS CONTABEIS E AFINS | R88: -6054
H89: OUTRAS PRESTACAO DE SERVIÇO | R89: -42.64
A90: 217 | D90: 4.3.1.01.0217 | I90: DESPESAS C/PRESTACAO DE SERVICOS - PJ | R90: -42.64
H91: ENERGIA ELÉTRICA, ÁGUA E ESGOTO E INTERNET | R91: -3891.03
A92: 219 | D92: 4.3.1.01.0219 | I92: ENERGIA ELETRICA | R92: -3788.33
A93: 220 | D93: 4.3.1.01.0220 | I93: AGUA E ESGOTO | R93: -102.7
H94: SISTEMAS E FERRAMENTAS ADMINISTRATIVAS | R94: -8504.58
A95: 244 | D95: 4.3.1.01.0244 | I95: DESPESAS COM INFORMATICA / SISTEMAS / SOFTWARES | R95: -8504.58
H96: TARIFAS BANCÁRIAS | R96: -329.12
A97: 252 | D97: 4.3.1.03.0252 | I97: DESPESAS BANCARIAS | R97: -329.12
H98: OUTROS | R98: -12498.27
A99: 213 | D99: 4.3.1.01.0213 | I99: DESPESAS COM LANCHES E REFEICOES | R99: -1005.26
A100: 216 | D100: 4.3.1.01.0216 | I100: DESPESAS COM ESTACIONAMENTO DE VEICULOS | R100: -40
A101: 225 | D101: 4.3.1.01.0225 | I101: IMPOSTOS E TAXAS | R101: -35.01
A102: 227 | D102: 4.3.1.01.0227 | I102: MATERIAL DE EXPEDIENTE | R102: -425.3
A103: 231 | D103: 4.3.1.01.0231 | I103: DIVERSAS | R103: -93.26
A104: 236 | D104: 4.3.1.01.0236 | I104: DESPESAS COM BRINDES E PRESENTES | R104: -5938.43
A105: 238 | D105: 4.3.1.01.0238 | I105: DESPESAS COM CONDUCAO E COMBUSTIVEL | R105: -330.18
A106: 243 | D106: 4.3.1.01.0243 | I106: ENCARGOS DE DEPRECIACAO | R106: -453.02
A107: 251 | D107: 4.3.1.03.0251 | I107: DESPESAS FINANCEIRAS | R107: -0.41
A108: 255 | D108: 4.3.1.04.0255 | I108: TERRENO E DEPENDENCIAS - SEDE | R108: -4145
A109: 263 | D109: 4.3.1.04.0263 | I109: MOVEIS, MAQUINAS E UTENSILIOS | R109: -32.4
H110: SUPERÁVIT APURADO NO EXERCÍCIO DE | R110: 92520.75

Sheet Planilha2
A1: Código | D1: Classificação | H1: Descrição | R1: Saldo Atual
H2: RECEITA COM VENDAS | R2: 418702.3
A3: 860 | D3: 3.1.1.03.0860 | I3: ATACADO | R3: 164622.6
A4: 861 | D4: 3.1.1.03.0861 | I4: ECOMMERCE | R4: 128055.93
A5: 862 | D5: 3.1.1.03.0862 | I5: EVENTO | R5: 47047.21
A6: 865 | D6: 3.1.1.03.0865 | I6: LIVRARIA | R6: 78976.56
H7: MARKETPLACES | R7: 4630.01
A8: 863 | D8: 3.1.1.03.0863 | I8: AMAZON | R8: 1393.5
A9: 864 | D9: 3.1.1.03.0864 | I9: MERCADO LIVRE | R9: 3236.51
H10: TOTAL RECEITA BRUTA COM VENDAS | R10: 423332.31
H12: DEVOLUÇÃO E DESCONTO DE VENDAS | R12: -743.82
A13: 166 | D13: 3.6.1.01.0166 | I13: DEVOLUCAO DE VENDAS | R13: -743.82
H14: RECEITA LÍQUIDA DE VENDAS | R14: 422588.49
H16: FRETE COBRADO DOS CLIENTES | R16: 25291.83
A17: 749 | D17: 3.1.1.04.0749 | I17: FRETES COBRADOS DOS CLIENTES | R17: 25291.83
H18: RECEITA OPERACIONAL TOTAL | R18: 447880.32
H20: CUSTO DOS PRODUTOS VENDIDOS (CPV/CMV) | R20: -205378.48
A21: 162 | D21: 3.7.1.01.0162 | I21: CUSTO DAS MERCADORIAS VENDIDAS | R21: -142495.37
A22: 165 | D22: 3.7.1.01.0165 | I22: DIREITOS AUTORAIS | R22: -22144.59
A23: 167 | D23: 3.7.1.01.0167 | I23: MATERIAIS APLICADOS NA VENDA DE PRODUTOS | R23: -1716.78
A24: 170 | D24: 3.7.1.01.0170 | I24: ROYALTIES EDITORIAIS E OUTROS | R24: -39021.74
H25: TOTAL CUSTO DOS PRODUTOS VENDIDOS | R25: -205378.48
H27: LUCRO BRUTO | R27: 242501.84
H29: DESPESAS VARIÁVEIS COMERCIAIS | R29: -37315.23
A30: 164 | D30: 3.7.1.01.0164 | I30: FRETES SOBRE MERCADORIAS | R30: -32396.03
A31: 206 | D31: 4.1.1.05.0206 | I31: COMISSOES POR VENDA | R31: -4301.18
A32: 212 | D32: 4.3.1.01.0212 | I32: DESPESAS REPRESENTACAO COMERCIAL | R32: -165.05
A33: 224 | D33: 4.3.1.01.0224 | I33: EMBALAGENS E MATERIAS GRAFICOS | R33: -452.97
H34: TAXA DE CARTAO / GATEWAY | R34: -6388.04
A35: 250 | D35: 4.3.1.03.0250 | I35: DESPESAS PAGAR ME | R35: -22.99
A36: 253 | D36: 4.3.1.03.0253 | I36: DESPESAS MERCADO PAGO.COM | R36: -106.44
A37: 651 | D37: 4.3.1.03.0651 | I37: DESPESAS AMAZON | R37: -85.23
A38: 653 | D38: 4.3.1.03.0653 | I38: DESPESAS STONE | R38: -70.31
A39: 654 | D39: 4.3.1.03.0654 | I39: DESPESAS VINDI | R39: -6103.07
H40: TOTAL DESPESAS VARIÁVEIS COMERCIAIS | R40: -43703.27
H42: MARGEM DE CONTRIBUIÇÃO | R42: 198798.57
H44: DESPESAS FIXAS OPERACIONAIS | R44: -90837.05
H46: DESPESA FIXA COMERCIAL | R46: -90837.05
H48: SALARIO FIXO DOS VENDEDORES | R48: -3214.9
A49: 182 | D49: 4.1.1.01.0182 | I49: COMERCIAL - PJ | R49: -3214.9
H50: EQUIPE DE MARKETING | R50: -23903.13
A51: 181 | D51: 4.1.1.01.0181 | I51: MARKETING - PJ | R51: -15915.33
A52: 188 | D52: 4.1.1.02.0188 | I52: MARKETING - CLT | R52: -7987.8
H53: LIVRARIA | R53: -9700
A54: 184 | D54: 4.1.1.01.0184 | I54: LIVRARIA - PJ | R54: -9700
H55: ENCARGOS PREVIDENCIARIOS E SOCIAIS | R55: -3306.17
A56: 502 | D56: 4.1.1.03.0502 | I56: INSS - COMERCIAL | R56: -1808.76
A57: 503 | D57: 4.1.1.03.0503 | I57: FGTS - COMERCIAL | R57: -539.92
A58: 504 | D58: 4.1.1.03.0504 | I58: PIS - COMERCIAL | R58: -67.49
A59: 511 | D59: 4.1.1.04.0511 | I59: VALE TRANSPORTE - COMERCIAL | R59: -890
H60: SISTEMAS E FERRAMENTAS ADMINISTRATIVAS - COMERCIAL | R60: -7548.4
A61: 710 | D61: 4.3.1.06.0710 | I61: DESPESAS COM INFORMATICA / SISTEMAS / SOFTWARES - COMERCIAL | R61: -7548.4
H62: OUTROS - COMERCIAL | R62: -37.18
A63: 711 | D63: 4.3.1.06.0711 | I63: VIAGEM, ESTADIA E PEDAGIO | R63: -37.18
H64: PUBLICIDADE | R64: -43127.27
A65: 171 | D65: 4.3.1.02.0171 | I65: PUBLICIDADE - TRAFEGO PAGO | R65: -41763.77
A66: 245 | D66: 4.3.1.02.0245 | I66: DESPESAS COM MARKETING E PUBLICIDADE - | R66: -155
A67: 709 | D67: 4.3.1.06.0709 | I67: MARKETING E PUBLICIDADE - COMERCIAL | R67: -1208.5
H68: DESPESA FIXA ADMINITRATIVA | R68: -92790.32
H70: SALÁRIOS E ENCARGOS | R70: -58442.18
A71: 180 | D71: 4.1.1.01.0180 | I71: ADMINISTRACAO - PJ | R71: -17401.46
A72: 186 | D72: 4.1.1.01.0186 | I72: LOGISTICA / EXPEDICAO - PJ | R72: -6300
A73: 187 | D73: 4.1.1.01.0187 | I73: DIRETORIA - PJ | R73: -7262.12
A74: 189 | D74: 4.1.1.02.0189 | I74: ADMINISTRACAO - CLT | R74: -6043.8
A75: 190 | D75: 4.1.1.02.0190 | I75: EXPEDICAO - CLT | R75: -1890
A76: 192 | D76: 4.1.1.02.0192 | I76: FINANCEIRO - CLT | R76: -3675
A77: 193 | D77: 4.1.1.02.0193 | I77: DIVERSOS | R77: -117.34
A78: 195 | D78: 4.1.1.03.0195 | I78: INSS - ADMINISTRATIVO | R78: -3010.96
A79: 196 | D79: 4.1.1.03.0196 | I79: FGTS - ADMINISTRATIVO | R79: -898.8
A80: 197 | D80: 4.1.1.03.0197 | I80: PIS - ADMINISTRATIVO | R80: -112.35
A81: 200 | D81: 4.1.1.04.0200 | I81: ASSISTENCIA MEDICA | R81: -4071
A82: 201 | D82: 4.1.1.04.0201 | I82: VALE TRANSPORTE - ADMINISTRATIVO | R82: -275.97
... A85: 210 | D85: 4.2.1.02.0210 | I85: CAPACITACAO PROFISSIONAL | R85: -59
H86: ALUGUEL E CONDOMÍNIO | R86: -13996.98
A87: 229 | D87: 4.3.1.01.0229 | I87: ALUGUEIS | R87: -13996.98
H88: CONTABILIDADE | R88: -4519
A89: 214 | D89: 4.3.1.01.0214 | I89: SERVICOS CONTABEIS E AFINS | R89: -4519
H90: OUTRAS PRESTACAO DE SERVIÇO | R90: -2112.03
A91: 217 | D91: 4.3.1.01.0217 | I91: DESPESAS C/PRESTACAO DE SERVICOS - PJ | R91: -1962.03
A92: 218 | D92: 4.3.1.01.0218 | I92: DESPESAS C/PRESTACAO DE SERVICOS - PF | R92: -150
H93: ENERGIA ELÉTRICA, ÁGUA E ESGOTO E INTERNET | R93: -3994.4
A94: 219 | D94: 4.3.1.01.0219 | I94: ENERGIA ELETRICA | R94: -3840.44
A95: 220 | D95: 4.3.1.01.0220 | I95: AGUA E ESGOTO | R95: -153.96
H96: SISTEMAS E FERRAMENTAS ADMINISTRATIVAS | R96: -5478.23
A97: 244 | D97: 4.3.1.01.0244 | I97: DESPESAS COM INFORMATICA / SISTEMAS / SOFTWARES | R97: -5478.23
H98: TARIFAS BANCÁRIAS | R98: -279.47
A99: 252 | D99: 4.3.1.03.0252 | I99: DESPESAS BANCARIAS | R99: -279.47
H100: OUTROS | R100: -3968.03
A101: 213 | D101: 4.3.1.01.0213 | I101: DESPESAS COM LANCHES E REFEICOES | R101: -893.47
A102: 216 | D102: 4.3.1.01.0216 | I102: DESPESAS COM ESTACIONAMENTO DE VEICULOS | R102: -83
A103: 222 | D103: 4.3.1.01.0222 | I103: DESPESAS POSTAIS E FRETES | R103: -150
A104: 228 | D104: 4.3.1.01.0228 | I104: MATERIAL DE LIMPEZA | R104: -101.57
A105: 243 | D105: 4.3.1.01.0243 | I105: ENCARGOS DE DEPRECIACAO | R105: -2477.88
A106: 251 | D106: 4.3.1.03.0251 | I106: DESPESAS FINANCEIRAS | R106: -37.39
A107: 255 | D107: 4.3.1.04.0255 | I107: TERRENO E DEPENDENCIAS - SEDE | R107: -224.72
H108: SUPERÁVIT APURADO NO EXERCÍCIO DE | R108: 15171.2
S109: 0 | T109: =+R109-S109 -> 0

Sheet Planilha3
A1: Código | D1: Classificação | H1: Descrição | R1: Saldo Atual
H2: RECEITA COM VENDAS | R2: 467954.66
A3: 860 | D3: 3.1.1.03.0860 | I3: ATACADO | R3: 193567.41
A4: 861 | D4: 3.1.1.03.0861 | I4: ECOMMERCE | R4: 164134.17
A5: 862 | D5: 3.1.1.03.0862 | I5: EVENTO | R5: 20118.81
A6: 865 | D6: 3.1.1.03.0865 | I6: LIVRARIA | R6: 90134.27
H7: MARKETPLACES | R7: 28379.02
A8: 863 | D8: 3.1.1.03.0863 | I8: AMAZON | R8: 22701.73
A9: 864 | D9: 3.1.1.03.0864 | I9: MERCADO LIVRE | R9: 5677.29
H10: TOTAL RECEITA BRUTA COM VENDAS | R10: 496333.68
H12: DEVOLUÇÃO E DESCONTO DE VENDAS | R12: -109.63
A13: 166 | D13: 3.6.1.01.0166 | I13: DEVOLUCAO DE VENDAS | R13: -109.63
H14: RECEITA LÍQUIDA DE VENDAS | R14: 496224.05
H16: FRETE COBRADO DOS CLIENTES | R16: 29999.19
A17: 749 | D17: 3.1.1.04.0749 | I17: FRETES COBRADOS DOS CLIENTES | R17: 29999.19
H18: RECEITA OPERACIONAL TOTAL | R18: 526223.24
H20: CUSTO DOS PRODUTOS VENDIDOS (CPV/CMV) | R20: -262495.89
A21: 162 | D21: 3.7.1.01.0162 | I21: CUSTO DAS MERCADORIAS VENDIDAS | R21: -202408.68
A22: 165 | D22: 3.7.1.01.0165 | I22: DIREITOS AUTORAIS | R22: -21519.93
A23: 167 | D23: 3.7.1.01.0167 | I23: MATERIAIS APLICADOS NA VENDA DE PRODUTOS | R23: -4910.46
A24: 170 | D24: 3.7.1.01.0170 | I24: ROYALTIES EDITORIAIS E OUTROS | R24: -33656.82
H25: TOTAL CUSTO DOS PRODUTOS VENDIDOS | R25: -262495.89
H27: LUCRO BRUTO | R27: 263727.35
H29: DESPESAS VARIÁVEIS COMERCIAIS | R29: -38241.74
A30: 164 | D30: 3.7.1.01.0164 | I30: FRETES SOBRE MERCADORIAS | R30: -30266.43
A31: 206 | D31: 4.1.1.05.0206 | I31: COMISSOES POR VENDA | R31: -4108.25
A32: 207 | D32: 4.1.1.05.0207 | I32: BONUS POR RESULTADO | R32: -3000
A33: 224 | D33: 4.3.1.01.0224 | I33: EMBALAGENS E MATERIAS GRAFICOS | R33: -867.06
H34: TAXA DE CARTAO / GATEWAY | R34: -11904.13
A35: 250 | D35: 4.3.1.03.0250 | I35: DESPESAS PAGAR ME | R35: -36.25
A36: 253 | D36: 4.3.1.03.0253 | I36: DESPESAS MERCADO PAGO.COM | R36: -120.19
A37: 651 | D37: 4.3.1.03.0651 | I37: DESPESAS AMAZON | R37: -3587.81
A38: 653 | D38: 4.3.1.03.0653 | I38: DESPESAS STONE | R38: -49.67
A39: 654 | D39: 4.3.1.03.0654 | I39: DESPESAS VINDI | R39: -8110.21
H40: TOTAL DESPESAS VARIÁVEIS COMERCIAIS | R40: -50145.87
H42: MARGEM DE CONTRIBUIÇÃO | R42: 213581.48
H44: DESPESAS FIXAS OPERACIONAIS | R44: -82984.22
H46: DESPESA FIXA COMERCIAL | R46: -82984.22
H48: SALARIO FIXO DOS VENDEDORES | R48: -3214.9
A49: 182 | D49: 4.1.1.01.0182 | I49: COMERCIAL - PJ | R49: -3214.9
H50: EQUIPE DE MARKETING | R50: -20110
A51: 181 | D51: 4.1.1.01.0181 | I51: MARKETING - PJ | R51: -12910
A52: 188 | D52: 4.1.1.02.0188 | I52: MARKETING - CLT | R52: -7200
H53: LIVRARIA | R53: -10520
A54: 184 | D54: 4.1.1.01.0184 | I54: LIVRARIA - PJ | R54: -10520
H55: ENCARGOS PREVIDENCIARIOS E SOCIAIS | R55: -3347.08
A56: 502 | D56: 4.1.1.03.0502 | I56: INSS - COMERCIAL | R56: -1929.6
A57: 503 | D57: 4.1.1.03.0503 | I57: FGTS - COMERCIAL | R57: -576
A58: 504 | D58: 4.1.1.03.0504 | I58: PIS - COMERCIAL | R58: -72
A59: 511 | D59: 4.1.1.04.0511 | I59: VALE TRANSPORTE - COMERCIAL | R59: -769.48
H60: SISTEMAS E FERRAMENTAS ADMINISTRATIVAS - COMERCIAL | R60: -7155.32
A61: 710 | D61: 4.3.1.06.0710 | I61: DESPESAS COM INFORMATICA / SISTEMAS / SOFTWARES - COMERCIAL | R61: -7155.32
H62: OUTROS - COMERCIAL | R62: -3830.11
A63: 247 | D63: 4.3.1.02.0247 | I63: DESPESAS DE CUSTOS COM EVENTOS | R63: -2672.69
A64: 711 | D64: 4.3.1.06.0711 | I64: VIAGEM, ESTADIA E PEDAGIO | R64: -1157.42
H65: PUBLICIDADE | R65: -34806.81
A66: 171 | D66: 4.3.1.02.0171 | I66: PUBLICIDADE - TRAFEGO PAGO | R66: -32928.85
A67: 245 | D67: 4.3.1.02.0245 | I67: DESPESAS COM MARKETING E PUBLICIDADE - | R67: -664
A68: 709 | D68: 4.3.1.06.0709 | I68: MARKETING E PUBLICIDADE - COMERCIAL | R68: -1213.96
H69: DESPESA FIXA ADMINITRATIVA | R69: -93267.69
H71: SALÁRIOS E ENCARGOS | R71: -59805.29
A72: 180 | D72: 4.1.1.01.0180 | I72: ADMINISTRACAO - PJ | R72: -18271.54
A73: 186 | D73: 4.1.1.01.0186 | I73: LOGISTICA / EXPEDICAO - PJ | R73: -6695.87
A74: 187 | D74: 4.1.1.01.0187 | I74: DIRETORIA - PJ | R74: -11244.29
A75: 189 | D75: 4.1.1.02.0189 | I75: ADMINISTRACAO - CLT | R75: -4834
A76: 190 | D76: 4.1.1.02.0190 | I76: EXPEDICAO - CLT | R76: -1855.25
A77: 192 | D77: 4.1.1.02.0192 | I77: FINANCEIRO - CLT | R77: -3675
A78: 193 | D78: 4.1.1.02.0193 | I78: DIVERSOS | R78: -117.34
A79: 195 | D79: 4.1.1.03.0195 | I79: INSS - ADMINISTRATIVO | R79: -2783.01
A80: 196 | D80: 4.1.1.03.0196 | I80: FGTS - ADMINISTRATIVO | R80: -830.76
A81: 197 | D81: 4.1.1.03.0197 | I81: PIS - ADMINISTRATIVO | R81: -103.84
A82: 200 | D82: 4.1.1.04.0200 | I82: ASSISTENCIA MEDICA | R82: -2805.57
A83: 201 | D83: 4.1.1.04.0201 | I83: VALE TRANSPORTE - ADMINISTRATIVO | R83: -762.28
... A86: 210 | D86: 4.2.1.02.0210 | I86: CAPACITACAO PROFISSIONAL | R86: -49
H87: ALUGUEL E CONDOMÍNIO | R87: -13818.23
A88: 229 | D88: 4.3.1.01.0229 | I88: ALUGUEIS | R88: -13757.47
A89: 237 | D89: 4.3.1.01.0237 | I89: DESPESAS COM CONDOMINIO | R89: -60.76
H90: CONTABILIDADE | R90: -4519
A91: 214 | D91: 4.3.1.01.0214 | I91: SERVICOS CONTABEIS E AFINS | R91: -4519
H92: OUTRAS PRESTACAO DE SERVIÇO | R92: -1209.98
A93: 217 | D93: 4.3.1.01.0217 | I93: DESPESAS C/PRESTACAO DE SERVICOS - PJ | R93: -1209.98
H94: ENERGIA ELÉTRICA, ÁGUA E ESGOTO E INTERNET | R94: -4273.55
A95: 219 | D95: 4.3.1.01.0219 | I95: ENERGIA ELETRICA | R95: -3970.57
A96: 220 | D96: 4.3.1.01.0220 | I96: AGUA E ESGOTO | R96: -153.96
A97: 233 | D97: 4.3.1.01.0233 | I97: INTERNET | R97: -149.02
H98: SISTEMAS E FERRAMENTAS ADMINISTRATIVAS | R98: -3440.82
A99: 244 | D99: 4.3.1.01.0244 | I99: DESPESAS COM INFORMATICA / SISTEMAS / SOFTWARES | R99: -3440.82
H100: TARIFAS BANCÁRIAS | R100: -188.55
A101: 252 | D101: 4.3.1.03.0252 | I101: DESPESAS BANCARIAS | R101: -188.55
H102: OUTROS | R102: -6012.27
A103: 213 | D103: 4.3.1.01.0213 | I103: DESPESAS COM LANCHES E REFEICOES | R103: -984.83
A104: 216 | D104: 4.3.1.01.0216 | I104: DESPESAS COM ESTACIONAMENTO DE VEICULOS | R104: -12
A105: 222 | D105: 4.3.1.01.0222 | I105: DESPESAS POSTAIS E FRETES | R105: 150
A106: 225 | D106: 4.3.1.01.0225 | I106: IMPOSTOS E TAXAS | R106: -104.13
A107: 227 | D107: 4.3.1.01.0227 | I107: MATERIAL DE EXPEDIENTE | R107: -535
A108: 228 | D108: 4.3.1.01.0228 | I108: MATERIAL DE LIMPEZA | R108: -34.67
A109: 231 | D109: 4.3.1.01.0231 | I109: DIVERSAS | R109: -29.88
A110: 238 | D110: 4.3.1.01.0238 | I110: DESPESAS COM CONDUCAO E COMBUSTIVEL | R110: -740.87
A111: 243 | D111: 4.3.1.01.0243 | I111: ENCARGOS DE DEPRECIACAO | R111: -2722.23
A112: 251 | D112: 4.3.1.03.0251 | I112: DESPESAS FINANCEIRAS | R112: -118.21
...

Sheet Planilha4
A1: Código | D1: Classificação | H1: Descrição | R1: Saldo Atual
H2: RECEITA COM VENDAS | R2: 388073.88
A3: 860 | D3: 3.1.1.03.0860 | I3: ATACADO | R3: 132575.25
A4: 861 | D4: 3.1.1.03.0861 | I4: ECOMMERCE | R4: 161518.87
A5: 862 | D5: 3.1.1.03.0862 | I5: EVENTO | R5: 1613.05
A6: 865 | D6: 3.1.1.03.0865 | I6: LIVRARIA | R6: 92366.71
H7: MARKETPLACES | R7: 22410.2
A8: 863 | D8: 3.1.1.03.0863 | I8: AMAZON | R8: 19863
A9: 864 | D9: 3.1.1.03.0864 | I9: MERCADO LIVRE | R9: 2547.2
H10: TOTAL RECEITA BRUTA COM VENDAS | R10: 410484.08
H12: DEVOLUÇÃO E DESCONTO DE VENDAS | R12: -967.46
A13: 166 | D13: 3.6.1.01.0166 | I13: DEVOLUCAO DE VENDAS | R13: -967.46
H14: RECEITA LÍQUIDA DE VENDAS | R14: 409516.62
H16: FRETE COBRADO DOS CLIENTES | R16: 29685.64
A17: 749 | D17: 3.1.1.04.0749 | I17: FRETES COBRADOS DOS CLIENTES | R17: 29685.64
H18: RECEITA OPERACIONAL TOTAL | R18: 439202.26
H20: CUSTO DOS PRODUTOS VENDIDOS (CPV/CMV) | R20: -216442.65
A21: 162 | D21: 3.7.1.01.0162 | I21: CUSTO DAS MERCADORIAS VENDIDAS | R21: -171775.47
A22: 165 | D22: 3.7.1.01.0165 | I22: DIREITOS AUTORAIS | R22: -15091.45
A23: 167 | D23: 3.7.1.01.0167 | I23: MATERIAIS APLICADOS NA VENDA DE PRODUTOS | R23: -2405.33
A24: 170 | D24: 3.7.1.01.0170 | I24: ROYALTIES EDITORIAIS E OUTROS | R24: -27170.4
H25: TOTAL CUSTO DOS PRODUTOS VENDIDOS | R25: -216442.65
H27: RECEITAS FINANCEIRAS | R27: 10.49
A28: 135 | D28: 3.2.1.01.0135 | I28: FUNDOS DIVERSOS | R28: 10.49
H29: LUCRO BRUTO | R29: 222770.1
H31: DESPESAS VARIÁVEIS COMERCIAIS | R31: -36743.93
A32: 164 | D32: 3.7.1.01.0164 | I32: FRETES SOBRE MERCADORIAS | R32: -31117.68
A33: 206 | D33: 4.1.1.05.0206 | I33: COMISSOES POR VENDA | R33: -2657.31
A34: 212 | D34: 4.3.1.01.0212 | I34: DESPESAS REPRESENTACAO COMERCIAL | R34: -969
A35: 224 | D35: 4.3.1.01.0224 | I35: EMBALAGENS E MATERIAS GRAFICOS | R35: -1999.94
H36: TAXA DE CARTAO / GATEWAY | R36: -12710.26
A37: 250 | D37: 4.3.1.03.0250 | I37: DESPESAS PAGAR ME | R37: -62.91
A38: 253 | D38: 4.3.1.03.0253 | I38: DESPESAS MERCADO PAGO.COM | R38: -719.07
A39: 651 | D39: 4.3.1.03.0651 | I39: DESPESAS AMAZON | R39: -1874.88
A40: 653 | D40: 4.3.1.03.0653 | I40: DESPESAS STONE | R40: -70.3
A41: 654 | D41: 4.3.1.03.0654 | I41: DESPESAS VINDI | R41: -9983.1
H42: TOTAL DESPESAS VARIÁVEIS COMERCIAIS | R42: -49454.19
H44: MARGEM DE CONTRIBUIÇÃO | R44: 173315.91
H46: DESPESAS FIXAS OPERACIONAIS | R46: -97464.56
H48: DESPESA FIXA COMERCIAL | R48: -97464.56
H50: SALARIO FIXO DOS VENDEDORES | R50: -3214.9
A51: 182 | D51: 4.1.1.01.0182 | I51: COMERCIAL - PJ | R51: -3214.9
H52: EQUIPE DE MARKETING | R52: -28544.13
A53: 181 | D53: 4.1.1.01.0181 | I53: MARKETING - PJ | R53: -13250
A54: 188 | D54: 4.1.1.02.0188 | I54: MARKETING - CLT | R54: -8961.13
A55: 535 | D55: 4.1.1.02.0535 | I55: SALARIO DE FERIAS - MARKETING | R55: -4983
A56: 536 | D56: 4.1.1.02.0536 | I56: 13 SALARIO - COMERCIAL | R56: -1350
H57: LIVRARIA | R57: -6320
A58: 184 | D58: 4.1.1.01.0184 | I58: LIVRARIA - PJ | R58: -6320
H59: ENCARGOS PREVIDENCIARIOS E SOCIAIS | R59: -6934.5
A60: 502 | D60: 4.1.1.03.0502 | I60: INSS - COMERCIAL | R60: -2891.56
A61: 503 | D61: 4.1.1.03.0503 | I61: FGTS - COMERCIAL | R61: -644.91
A62: 504 | D62: 4.1.1.03.0504 | I62: PIS - COMERCIAL | R62: -80.61
A63: 505 | D63: 4.1.1.03.0505 | I63: INSS FERIAS - COMERCIAL | R63: -1335.46
A64: 506 | D64: 4.1.1.03.0506 | I64: FGTS FERIAS - COMERCIAL | R64: -398.63
A65: 508 | D65: 4.1.1.03.0508 | I65: PIS FERIAS - COMERCIAL | R65: -49.83
A66: 527 | D66: 4.1.1.03.0527 | I66: INSS SOBRE 13 SALARIO - COMERCIAL | R66: -361.8
A67: 528 | D67: 4.1.1.03.0528 | I67: FGTS SOBRE 13 SALARIO - COMERCIAL | R67: -108
A68: 529 | D68: 4.1.1.03.0529 | I68: PIS SOBRE 13 SALARIO - COMERCIAL | R68: -13.5
A69: 511 | D69: 4.1.1.04.0511 | I69: VALE TRANSPORTE - COMERCIAL | R69: -1050.2
H70: SISTEMAS E FERRAMENTAS ADMINISTRATIVAS - COMERCIAL | R70: -10740.87
A71: 710 | D71: 4.3.1.06.0710 | I71: DESPESAS COM INFORMATICA / SISTEMAS / SOFTWARES - COMERCIAL | R71: -10740.87
H72: PUBLICIDADE | R72: -41710.16
A73: 171 | D73: 4.3.1.02.0171 | I73: PUBLICIDADE - TRAFEGO PAGO | R73: -39630.35
A74: 245 | D74: 4.3.1.02.0245 | I74: DESPESAS COM MARKETING E PUBLICIDADE - | R74: -874.81
A75: 709 | D75: 4.3.1.06.0709 | I75: MARKETING E PUBLICIDADE - COMERCIAL | R75: -1205
H76: DESPESA FIXA ADMINITRATIVA | R76: -117707.2
H78: SALÁRIOS E ENCARGOS | R78: -78398.39
A79: 180 | D79: 4.1.1.01.0180 | I79: ADMINISTRACAO - PJ | R79: -19141.62
A80: 186 | D80: 4.1.1.01.0186 | I80: LOGISTICA / EXPEDICAO - PJ | R80: -7500
A81: 187 | D81: 4.1.1.01.0187 | I81: DIRETORIA - PJ | R81: -9224.77
A82: 189 | D82: 4.1.1.02.0189 | I82: ADMINISTRACAO - CLT | R82: -6248.03
A83: 190 | D83: 4.1.1.02.0190 | I83: EXPEDICAO - CLT | R83: -3727.12
A84: 192 | D84: 4.1.1.02.0192 | I84: FINANCEIRO - CLT | R84: -3675
A85: 193 | D85: 4.1.1.02.0193 | I85: DIVERSOS | R85: -104.77
A86: 530 | D86: 4.1.1.02.0530 | I86: SALARIO DE FERIAS - ADMINISTRACAO | R86: -9075.03
A87: 531 | D87: 4.1.1.02.0531 | I87: 13 SALARIO - ADMINISTRACAO | R87: -2495.93
A88: 195 | D88: 4.1.1.03.0195 | I88: INSS - ADMINISTRATIVO | R88: -1915.68
A89: 196 | D89: 4.1.1.03.0196 | I89: FGTS - ADMINISTRATIVO | R89: -790.09
A90: 197 | D90: 4.1.1.03.0197 | I90: PIS - ADMINISTRATIVO | R90: -98.76
... A101: 210 | D101: 4.2.1.02.0210 | I101: CAPACITACAO PROFISSIONAL | R101: -929
H102: ALUGUEL E CONDOMÍNIO | R102: -13526.65
A103: 229 | D103: 4.3.1.01.0229 | I103: ALUGUEIS | R103: -13496.98
A104: 237 | D104: 4.3.1.01.0237 | I104: DESPESAS COM CONDOMINIO | R104: -29.67
H105: CONTABILIDADE | R105: -4915
A106: 214 | D106: 4.3.1.01.0214 | I106: SERVICOS CONTABEIS E AFINS | R106: -4915
H107: OUTRAS PRESTACAO DE SERVIÇO | R107: -5483.69
A108: 217 | D108: 4.3.1.01.0217 | I108: DESPESAS C/PRESTACAO DE SERVICOS - PJ | R108: -5483.69
H109: ENERGIA ELÉTRICA, ÁGUA E ESGOTO E INTERNET | R109: -666.66
A110: 219 | D110: 4.3.1.01.0219 | I110: ENERGIA ELETRICA | R110: -133.92
A111: 220 | D111: 4.3.1.01.0220 | I111: AGUA E ESGOTO | R111: -184.07
A112: 233 | D112: 4.3.1.01.0233 | I112: INTERNET | R112: -348.67
H113: SISTEMAS E FERRAMENTAS ADMINISTRATIVAS | R113: -5542.39
A114: 244 | D114: 4.3.1.01.0244 | I114: DESPESAS COM INFORMATICA / SISTEMAS / SOFTWARES | R114: -5542.39
H115: TARIFAS BANCÁRIAS | R115: -859.85
A116: 252 | D116: 4.3.1.03.0252 | I116: DESPESAS BANCARIAS | R116: -859.85
H117: OUTROS | R117: -8314.57
A118: 213 | D118: 4.3.1.01.0213 | I118: DESPESAS COM LANCHES E REFEICOES | R118: -667.92
A119: 215 | D119: 4.3.1.01.0215 | I119: DESPESAS COM COPA E COZINHA | R119: -65.97
A120: 225 | D120: 4.3.1.01.0225 | I120: IMPOSTOS E TAXAS | R120: -47.74
...

Sheet Planilha5
A1: Código | D1: Classificação | H1: Descrição | R1: Saldo Atual
H2: RECEITA COM VENDAS | R2: 503039.55
A3: 860 | D3: 3.1.1.03.0860 | I3: ATACADO | R3: 219556.41
A4: 861 | D4: 3.1.1.03.0861 | I4: ECOMMERCE | R4: 167517.93
A5: 862 | D5: 3.1.1.03.0862 | I5: EVENTO | R5: 2953.61
A6: 865 | D6: 3.1.1.03.0865 | I6: LIVRARIA | R6: 113011.6
H7: MARKETPLACES | R7: 14548.79
A8: 863 | D8: 3.1.1.03.0863 | I8: AMAZON | R8: 11019.65
A9: 864 | D9: 3.1.1.03.0864 | I9: MERCADO LIVRE | R9: 3529.14
H10: TOTAL RECEITA BRUTA COM VENDAS | R10: 517588.34
H12: DEVOLUÇÃO E DESCONTO DE VENDAS | R12: -569.8
A13: 166 | D13: 3.6.1.01.0166 | I13: DEVOLUCAO DE VENDAS | R13: -569.8
H14: RECEITA LÍQUIDA DE VENDAS | R14: 517018.54
H16: FRETE COBRADO DOS CLIENTES | R16: 34698.87
A17: 749 | D17: 3.1.1.04.0749 | I17: FRETES COBRADOS DOS CLIENTES | R17: 34698.87
H18: RECEITA OPERACIONAL TOTAL | R18: 551717.41
H20: CUSTO DOS PRODUTOS VENDIDOS (CPV/CMV) | R20: -316722.03
A21: 162 | D21: 3.7.1.01.0162 | I21: CUSTO DAS MERCADORIAS VENDIDAS | R21: -216281.18
A22: 165 | D22: 3.7.1.01.0165 | I22: DIREITOS AUTORAIS | R22: -20504.68
A23: 167 | D23: 3.7.1.01.0167 | I23: MATERIAIS APLICADOS NA VENDA DE PRODUTOS | R23: -281.7
A24: 170 | D24: 3.7.1.01.0170 | I24: ROYALTIES EDITORIAIS E OUTROS | R24: -79654.47
H25: TOTAL CUSTO DOS PRODUTOS VENDIDOS | R25: -316722.03
H27: LUCRO BRUTO | R27: 234995.38
H29: DESPESAS VARIÁVEIS COMERCIAIS | R29: -46248.31
A30: 164 | D30: 3.7.1.01.0164 | I30: FRETES SOBRE MERCADORIAS | R30: -39597.87
A31: 206 | D31: 4.1.1.05.0206 | I31: COMISSOES POR VENDA | R31: -3650.44
A32: 207 | D32: 4.1.1.05.0207 | I32: BONUS POR RESULTADO | R32: -3000
H33: TAXA DE CARTAO / GATEWAY | R33: -10745.85
A34: 250 | D34: 4.3.1.03.0250 | I34: DESPESAS PAGAR ME | R34: -114.26
A35: 253 | D35: 4.3.1.03.0253 | I35: DESPESAS MERCADO PAGO.COM | R35: -1200.21
A36: 651 | D36: 4.3.1.03.0651 | I36: DESPESAS AMAZON | R36: -104.59
A37: 653 | D37: 4.3.1.03.0653 | I37: DESPESAS STONE | R37: -61.8
A38: 654 | D38: 4.3.1.03.0654 | I38: DESPESAS VINDI | R38: -9264.99
H39: TOTAL DESPESAS VARIÁVEIS COMERCIAIS | R39: -56994.16
H41: MARGEM DE CONTRIBUIÇÃO | R41: 178001.22
H43: DESPESAS FIXAS OPERACIONAIS | R43: -83740.92
H45: DESPESA FIXA COMERCIAL | R45: -83740.92
H47: SALARIO FIXO DOS VENDEDORES | R47: -3214.9
A48: 182 | D48: 4.1.1.01.0182 | I48: COMERCIAL - PJ | R48: -3214.9
H49: EQUIPE DE MARKETING | R49: -25711.19
A50: 181 | D50: 4.1.1.01.0181 | I50: MARKETING - PJ | R50: -14410
A51: 188 | D51: 4.1.1.02.0188 | I51: MARKETING - CLT | R51: -9698.29
A52: 535 | D52: 4.1.1.02.0535 | I52: SALARIO DE FERIAS - MARKETING | R52: -1089.15
A53: 536 | D53: 4.1.1.02.0536 | I53: 13 SALARIO - COMERCIAL | R53: -513.75
H54: LIVRARIA | R54: -6830
A55: 184 | D55: 4.1.1.01.0184 | I55: LIVRARIA - PJ | R55: -6830
H56: ENCARGOS PREVIDENCIARIOS E SOCIAIS | R56: -2673.5
A57: 502 | D57: 4.1.1.03.0502 | I57: INSS - COMERCIAL | R57: -1571.82
A58: 503 | D58: 4.1.1.03.0503 | I58: FGTS - COMERCIAL | R58: -469.2
A59: 504 | D59: 4.1.1.03.0504 | I59: PIS - COMERCIAL | R59: -58.65
A60: 505 | D60: 4.1.1.03.0505 | I60: INSS FERIAS - COMERCIAL | R60: -291.86
A61: 506 | D61: 4.1.1.03.0506 | I61: FGTS FERIAS - COMERCIAL | R61: -87.14
A62: 508 | D62: 4.1.1.03.0508 | I62: PIS FERIAS - COMERCIAL | R62: -10.89
A63: 527 | D63: 4.1.1.03.0527 | I63: INSS SOBRE 13 SALARIO - COMERCIAL | R63: -137.7
A64: 528 | D64: 4.1.1.03.0528 | I64: FGTS SOBRE 13 SALARIO - COMERCIAL | R64: -41.1
A65: 529 | D65: 4.1.1.03.0529 | I65: PIS SOBRE 13 SALARIO - COMERCIAL | R65: -5.14
H66: SISTEMAS E FERRAMENTAS ADMINISTRATIVAS - COMERCIAL | R66: -4464.73
A67: 710 | D67: 4.3.1.06.0710 | I67: DESPESAS COM INFORMATICA / SISTEMAS / SOFTWARES - COMERCIAL | R67: -4464.73
H68: PUBLICIDADE | R68: -40846.6
A69: 171 | D69: 4.3.1.02.0171 | I69: PUBLICIDADE - TRAFEGO PAGO | R69: -38181.25
A70: 245 | D70: 4.3.1.02.0245 | I70: DESPESAS COM MARKETING E PUBLICIDADE - | R70: -2611.45
A71: 709 | D71: 4.3.1.06.0709 | I71: MARKETING E PUBLICIDADE - COMERCIAL | R71: -53.9
H72: DESPESA FIXA ADMINITRATIVA | R72: -114758.28
H74: SALÁRIOS E ENCARGOS | R74: -77333.49
A75: 179 | D75: 4.1.1.01.0179 | I75: FINANCEIRO - PJ | R75: -3509.67
A76: 180 | D76: 4.1.1.01.0180 | I76: ADMINISTRACAO - PJ | R76: -19141.62
A77: 186 | D77: 4.1.1.01.0186 | I77: LOGISTICA / EXPEDICAO - PJ | R77: -9450
A78: 187 | D78: 4.1.1.01.0187 | I78: DIRETORIA - PJ | R78: -9278.67
A79: 189 | D79: 4.1.1.02.0189 | I79: ADMINISTRACAO - CLT | R79: -1102.18
A80: 190 | D80: 4.1.1.02.0190 | I80: EXPEDICAO - CLT | R80: -291.84
A81: 192 | D81: 4.1.1.02.0192 | I81: FINANCEIRO - CLT | R81: -2981.04
A82: 193 | D82: 4.1.1.02.0193 | I82: DIVERSOS | R82: -104.77
A83: 530 | D83: 4.1.1.02.0530 | I83: SALARIO DE FERIAS - ADMINISTRACAO | R83: -1356.59
A84: 531 | D84: 4.1.1.02.0531 | I84: 13 SALARIO - ADMINISTRACAO | R84: -394.31
A85: 195 | D85: 4.1.1.03.0195 | I85: INSS - ADMINISTRATIVO | R85: -2563.71
A86: 196 | D86: 4.1.1.03.0196 | I86: FGTS - ADMINISTRATIVO | R86: -765.26
... A99: 210 | D99: 4.2.1.02.0210 | I99: CAPACITACAO PROFISSIONAL | R99: -20478.6
H100: ALUGUEL E CONDOMÍNIO | R100: -10029.67
A101: 229 | D101: 4.3.1.01.0229 | I101: ALUGUEIS | R101: -10000
A102: 237 | D102: 4.3.1.01.0237 | I102: DESPESAS COM CONDOMINIO | R102: -29.67
H103: CONTABILIDADE | R103: -4519
A104: 214 | D104: 4.3.1.01.0214 | I104: SERVICOS CONTABEIS E AFINS | R104: -4519
H105: OUTRAS PRESTACAO DE SERVIÇO | R105: -2954.27
A106: 217 | D106: 4.3.1.01.0217 | I106: DESPESAS C/PRESTACAO DE SERVICOS - PJ | R106: -2954.27
H107: ENERGIA ELÉTRICA, ÁGUA E ESGOTO E INTERNET | R107: -2435.47
A108: 233 | D108: 4.3.1.01.0233 | I108: INTERNET | R108: -2435.47
H109: SISTEMAS E FERRAMENTAS ADMINISTRATIVAS | R109: -8517.58
A110: 244 | D110: 4.3.1.01.0244 | I110: DESPESAS COM INFORMATICA / SISTEMAS / SOFTWARES | R110: -8517.58
H111: TARIFAS BANCÁRIAS | R111: -434.36
A112: 252 | D112: 4.3.1.03.0252 | I112: DESPESAS BANCARIAS | R112: -434.36
H113: OUTROS | R113: -8534.44
A114: 213 | D114: 4.3.1.01.0213 | I114: DESPESAS COM LANCHES E REFEICOES | R114: -886.08
A115: 225 | D115: 4.3.1.01.0225 | I115: IMPOSTOS E TAXAS | R115: -194.63
A116: 227 | D116: 4.3.1.01.0227 | I116: MATERIAL DE EXPEDIENTE | R116: -483.78
A117: 228 | D117: 4.3.1.01.0228 | I117: MATERIAL DE LIMPEZA | R117: -65.09
A118: 231 | D118: 4.3.1.01.0231 | I118: DIVERSAS | R118: -1341.41
A119: 236 | D119: 4.3.1.01.0236 | I119: DESPESAS COM BRINDES E PRESENTES | R119: -63.04
A120: 238 | D120: 4.3.1.01.0238 | I120: DESPESAS COM CONDUCAO E COMBUSTIVEL | R120: -375
A121: 243 | D121: 4.3.1.01.0243 | I121: ENCARGOS DE DEPRECIACAO | R121: -2813.87
A122: 251 | D122: 4.3.1.03.0251 | I122: DESPESAS FINANCEIRAS | R122: -4.38
...

Sheet Planilha6
A1: Código | D1: Classificação | H1: Descrição | R1: Saldo Atual
H2: RECEITA COM VENDAS | R2: 347333.52
A3: 860 | D3: 3.1.1.03.0860 | I3: ATACADO | R3: 60852.57
A4: 861 | D4: 3.1.1.03.0861 | I4: ECOMMERCE | R4: 173821.57
A5: 862 | D5: 3.1.1.03.0862 | I5: EVENTO | R5: 4466.5
A6: 865 | D6: 3.1.1.03.0865 | I6: LIVRARIA | R6: 108192.88
H7: MARKETPLACES | R7: 32617.49
A8: 863 | D8: 3.1.1.03.0863 | I8: AMAZON | R8: 11271.66
A9: 864 | D9: 3.1.1.03.0864 | I9: MERCADO LIVRE | R9: 18965.25
A10: 866 | D10: 3.1.1.03.0866 | I10: FULL ML | R10: 2281.66
A11: 867 | D11: 3.1.1.03.0867 | I11: TIKTOK | R11: 98.92
H12: TOTAL RECEITA BRUTA COM VENDAS | R12: 379951.01
H14: DEVOLUÇÃO E DESCONTO DE VENDAS | R14: -1607.93
A15: 166 | D15: 3.6.1.01.0166 | I15: DEVOLUCAO DE VENDAS | R15: -1607.93
H16: RECEITA LÍQUIDA DE VENDAS | R16: 378343.08
H18: FRETE COBRADO DOS CLIENTES | R18: 26661.5
A19: 749 | D19: 3.1.1.04.0749 | I19: FRETES COBRADOS DOS CLIENTES | R19: 26661.5
H20: RECEITA OPERACIONAL TOTAL | R20: 405004.58
H22: CUSTO DOS PRODUTOS VENDIDOS (CPV/CMV) | R22: -128709.05
A23: 162 | D23: 3.7.1.01.0162 | I23: CUSTO DAS MERCADORIAS VENDIDAS | R23: -126681.55
A24: 165 | D24: 3.7.1.01.0165 | I24: DIREITOS AUTORAIS | R24: -1895.08
A25: 170 | D25: 3.7.1.01.0170 | I25: ROYALTIES EDITORIAIS E OUTROS | R25: -132.42
H26: TOTAL CUSTO DOS PRODUTOS VENDIDOS | R26: -128709.05
H28: RECEITAS FINANCEIRAS | R28: 4.16
A29: 135 | D29: 3.2.1.01.0135 | I29: FUNDOS DIVERSOS | R29: 4.16
H30: OUTRAS RECEITAS | R30: 8.9
A31: 159 | D31: 3.3.1.01.0159 | I31: OUTRAS RECEITAS | R31: 8.9
H32: LUCRO BRUTO | R32: 276308.59
H34: DESPESAS VARIÁVEIS COMERCIAIS | R34: -33737.16
A35: 164 | D35: 3.7.1.01.0164 | I35: FRETES SOBRE MERCADORIAS | R35: -27086.72
A36: 206 | D36: 4.1.1.05.0206 | I36: COMISSOES POR VENDA | R36: -3650.44
A37: 207 | D37: 4.1.1.05.0207 | I37: BONUS POR RESULTADO | R37: -3000
H38: TAXA DE CARTAO / GATEWAY | R38: -17952.99
A39: 250 | D39: 4.3.1.03.0250 | I39: DESPESAS PAGAR ME | R39: -23.94
A40: 253 | D40: 4.3.1.03.0253 | I40: DESPESAS MERCADO PAGO.COM | R40: -9031.48
A41: 651 | D41: 4.3.1.03.0651 | I41: DESPESAS AMAZON | R41: -822.32
A42: 653 | D42: 4.3.1.03.0653 | I42: DESPESAS STONE | R42: -53.09
A43: 654 | D43: 4.3.1.03.0654 | I43: DESPESAS VINDI | R43: -8022.16
H44: TOTAL DESPESAS VARIÁVEIS COMERCIAIS | R44: -51690.15
H46: MARGEM DE CONTRIBUIÇÃO | R46: 224618.44
H48: DESPESAS FIXAS OPERACIONAIS | R48: -88444.47
H50: DESPESA FIXA COMERCIAL | R50: -88444.47
H52: SALARIO FIXO DOS VENDEDORES | R52: -3214.9
A53: 182 | D53: 4.1.1.01.0182 | I53: COMERCIAL - PJ | R53: -3214.9
H54: EQUIPE DE MARKETING | R54: -17126.06
A55: 181 | D55: 4.1.1.01.0181 | I55: MARKETING - PJ | R55: -12626.8
A56: 188 | D56: 4.1.1.02.0188 | I56: MARKETING - CLT | R56: -8095.16
A57: 535 | D57: 4.1.1.02.0535 | I57: SALARIO DE FERIAS - MARKETING | R57: 4042.15
A58: 536 | D58: 4.1.1.02.0536 | I58: 13 SALARIO - COMERCIAL | R58: -446.25
H59: LIVRARIA | R59: -9887.76
A60: 184 | D60: 4.1.1.01.0184 | I60: LIVRARIA - PJ | R60: -9887.76
H61: ENCARGOS PREVIDENCIARIOS E SOCIAIS | R61: -852.12
A62: 502 | D62: 4.1.1.03.0502 | I62: INSS - COMERCIAL | R62: -1601.59
A63: 503 | D63: 4.1.1.03.0503 | I63: FGTS - COMERCIAL | R63: -478.08
A64: 504 | D64: 4.1.1.03.0504 | I64: PIS - COMERCIAL | R64: -59.76
A65: 505 | D65: 4.1.1.03.0505 | I65: INSS FERIAS - COMERCIAL | R65: 1083.28
A66: 506 | D66: 4.1.1.03.0506 | I66: FGTS FERIAS - COMERCIAL | R66: 323.37
A67: 508 | D67: 4.1.1.03.0508 | I67: PIS FERIAS - COMERCIAL | R67: 40.42
A68: 527 | D68: 4.1.1.03.0527 | I68: INSS SOBRE 13 SALARIO - COMERCIAL | R68: -119.6
A69: 528 | D69: 4.1.1.03.0528 | I69: FGTS SOBRE 13 SALARIO - COMERCIAL | R69: -35.7
A70: 529 | D70: 4.1.1.03.0529 | I70: PIS SOBRE 13 SALARIO - COMERCIAL | R70: -4.46
H71: SISTEMAS E FERRAMENTAS ADMINISTRATIVAS - COMERCIAL | R71: -7709.03
A72: 710 | D72: 4.3.1.06.0710 | I72: DESPESAS COM INFORMATICA / SISTEMAS / SOFTWARES - COMERCIAL | R72: -7709.03
H73: OUTROS - COMERCIAL | R73: -26.8
A74: 711 | D74: 4.3.1.06.0711 | I74: VIAGEM, ESTADIA E PEDAGIO | R74: -26.8
H75: PUBLICIDADE | R75: -49627.8
A76: 171 | D76: 4.3.1.02.0171 | I76: PUBLICIDADE - TRAFEGO PAGO | R76: -49627.8
H77: DESPESA FIXA ADMINITRATIVA | R77: -99594.14
H79: SALÁRIOS E ENCARGOS | R79: -63887.87
A80: 179 | D80: 4.1.1.01.0179 | I80: FINANCEIRO - PJ | R80: -6750
A81: 180 | D81: 4.1.1.01.0180 | I81: ADMINISTRACAO - PJ | R81: -19141.62
A82: 186 | D82: 4.1.1.01.0186 | I82: LOGISTICA / EXPEDICAO - PJ | R82: -9900
A83: 187 | D83: 4.1.1.01.0187 | I83: DIRETORIA - PJ | R83: -9224.77
A84: 189 | D84: 4.1.1.02.0189 | I84: ADMINISTRACAO - CLT | R84: -3822.34
A85: 190 | D85: 4.1.1.02.0190 | I85: EXPEDICAO - CLT | R85: -1984.5
A86: 193 | D86: 4.1.1.02.0193 | I86: DIVERSOS | R86: -104.77
A87: 530 | D87: 4.1.1.02.0530 | I87: SALARIO DE FERIAS - ADMINISTRACAO | R87: -674.34
A88: 531 | D88: 4.1.1.02.0531 | I88: 13 SALARIO - ADMINISTRACAO | R88: -505.74
A89: 195 | D89: 4.1.1.03.0195 | I89: INSS - ADMINISTRATIVO | R89: -1674.48
A90: 196 | D90: 4.1.1.03.0196 | I90: FGTS - ADMINISTRATIVO | R90: -499.85
A91: 197 | D91: 4.1.1.03.0197 | I91: PIS - ADMINISTRATIVO | R91: -62.49
... A101: 203 | D101: 4.1.1.04.0203 | I101: VALE CESTA BASICA | R101: -430
H102: ALUGUEL E CONDOMÍNIO | R102: -10029.67
A103: 229 | D103: 4.3.1.01.0229 | I103: ALUGUEIS | R103: -10000
A104: 237 | D104: 4.3.1.01.0237 | I104: DESPESAS COM CONDOMINIO | R104: -29.67
H105: CONTABILIDADE | R105: -4519
A106: 214 | D106: 4.3.1.01.0214 | I106: SERVICOS CONTABEIS E AFINS | R106: -4519
H107: OUTRAS PRESTACAO DE SERVIÇO | R107: -360.59
A108: 217 | D108: 4.3.1.01.0217 | I108: DESPESAS C/PRESTACAO DE SERVICOS - PJ | R108: -360.59
H109: ENERGIA ELÉTRICA, ÁGUA E ESGOTO E INTERNET | R109: -3427.01
A110: 219 | D110: 4.3.1.01.0219 | I110: ENERGIA ELETRICA | R110: -3133.06
A111: 220 | D111: 4.3.1.01.0220 | I111: AGUA E ESGOTO | R111: -153.96
A112: 233 | D112: 4.3.1.01.0233 | I112: INTERNET | R112: -139.99
H113: SISTEMAS E FERRAMENTAS ADMINISTRATIVAS | R113: -10535.89
A114: 244 | D114: 4.3.1.01.0244 | I114: DESPESAS COM INFORMATICA / SISTEMAS / SOFTWARES | R114: -10535.89
H115: TARIFAS BANCÁRIAS | R115: -406.88
A116: 252 | D116: 4.3.1.03.0252 | I116: DESPESAS BANCARIAS | R116: -406.88
H117: OUTROS | R117: -6427.23
A118: 225 | D118: 4.3.1.01.0225 | I118: IMPOSTOS E TAXAS | R118: -76.69
A119: 226 | D119: 4.3.1.01.0226 | I119: SEGUROS | R119: -133
...

Sheet Planilha7
A1: Código | D1: Classificação | H1: Descrição | R1: Saldo Atual
H2: RECEITA COM VENDAS | R2: 316622.52
A3: 860 | D3: 3.1.1.03.0860 | I3: ATACADO | R3: 60934.28
A4: 861 | D4: 3.1.1.03.0861 | I4: ECOMMERCE | R4: 158614.03
A5: 862 | D5: 3.1.1.03.0862 | I5: EVENTO | R5: 193.79
A6: 865 | D6: 3.1.1.03.0865 | I6: LIVRARIA | R6: 96573.67
A7: 868 | D7: 3.1.1.03.0868 | I7: SHOWROOM | R7: 306.75
H8: MARKETPLACES | R8: 52521.49
A9: 863 | D9: 3.1.1.03.0863 | I9: AMAZON | R9: 5295.83
A10: 864 | D10: 3.1.1.03.0864 | I10: MERCADO LIVRE | R10: 26286.41
A11: 866 | D11: 3.1.1.03.0866 | I11: FULL ML | R11: 20939.25
H12: TOTAL RECEITA BRUTA COM VENDAS | R12: 369144.01
H14: DEVOLUÇÃO E DESCONTO DE VENDAS | R14: -3996.41
A15: 166 | D15: 3.6.1.01.0166 | I15: DEVOLUCAO DE VENDAS | R15: -3996.41
H16: RECEITA LÍQUIDA DE VENDAS | R16: 365147.6
H18: FRETE COBRADO DOS CLIENTES | R18: 25319.27
A19: 749 | D19: 3.1.1.04.0749 | I19: FRETES COBRADOS DOS CLIENTES | R19: 25319.27
H20: RECEITA OPERACIONAL TOTAL | R20: 390466.87
H22: CUSTO DOS PRODUTOS VENDIDOS (CPV/CMV) | R22: -119343.78
A23: 162 | D23: 3.7.1.01.0162 | I23: CUSTO DAS MERCADORIAS VENDIDAS | R23: -116012.28
A24: 165 | D24: 3.7.1.01.0165 | I24: DIREITOS AUTORAIS | R24: -2867.37
A25: 170 | D25: 3.7.1.01.0170 | I25: ROYALTIES EDITORIAIS E OUTROS | R25: -464.13
H26: TOTAL CUSTO DOS PRODUTOS VENDIDOS | R26: -119343.78
H28: RECEITAS FINANCEIRAS | R28: 0.76
A29: 135 | D29: 3.2.1.01.0135 | I29: FUNDOS DIVERSOS | R29: 0.76
H30: OUTRAS RECEITAS | R30: 78.94
A31: 159 | D31: 3.3.1.01.0159 | I31: OUTRAS RECEITAS | R31: 78.94
H32: LUCRO BRUTO | R32: 271202.79
H34: DESPESAS VARIÁVEIS COMERCIAIS | R34: -29155.49
A35: 164 | D35: 3.7.1.01.0164 | I35: FRETES SOBRE MERCADORIAS | R35: -25733.24
A36: 206 | D36: 4.1.1.05.0206 | I36: COMISSOES POR VENDA | R36: -104.79
A37: 207 | D37: 4.1.1.05.0207 | I37: BONUS POR RESULTADO | R37: -750
A38: 224 | D38: 4.3.1.01.0224 | I38: EMBALAGENS E MATERIAS GRAFICOS | R38: -2567.46
H39: TAXA DE CARTAO / GATEWAY | R39: -26613.38
A40: 250 | D40: 4.3.1.03.0250 | I40: DESPESAS PAGAR ME | R40: -8.06
A41: 253 | D41: 4.3.1.03.0253 | I41: DESPESAS MERCADO PAGO.COM | R41: -19449.37
A42: 651 | D42: 4.3.1.03.0651 | I42: DESPESAS AMAZON | R42: -359.72
A43: 653 | D43: 4.3.1.03.0653 | I43: DESPESAS STONE | R43: -60.02
A44: 654 | D44: 4.3.1.03.0654 | I44: DESPESAS VINDI | R44: -6736.21
H45: TOTAL DESPESAS VARIÁVEIS COMERCIAIS | R45: -55768.87
H47: MARGEM DE CONTRIBUIÇÃO | R47: 215433.92
H49: DESPESAS FIXAS OPERACIONAIS | R49: -82166.97
H51: DESPESA FIXA COMERCIAL | R51: -82166.97
H53: SALARIO FIXO DOS VENDEDORES | R53: -1951.3
A54: 182 | D54: 4.1.1.01.0182 | I54: COMERCIAL - PJ | R54: -1951.3
H55: EQUIPE DE MARKETING | R55: -18460.04
A56: 181 | D56: 4.1.1.01.0181 | I56: MARKETING - PJ | R56: -12266.8
A57: 188 | D57: 4.1.1.02.0188 | I57: MARKETING - CLT | R57: -4906.99
A58: 535 | D58: 4.1.1.02.0535 | I58: SALARIO DE FERIAS - MARKETING | R58: -840
A59: 536 | D59: 4.1.1.02.0536 | I59: 13 SALARIO - COMERCIAL | R59: -446.25
H60: LIVRARIA | R60: -6270
A61: 184 | D61: 4.1.1.01.0184 | I61: LIVRARIA - PJ | R61: -6270
H62: ENCARGOS PREVIDENCIARIOS E SOCIAIS | R62: -2451.69
A63: 502 | D63: 4.1.1.03.0502 | I63: INSS - COMERCIAL | R63: -1490.62
A64: 503 | D64: 4.1.1.03.0503 | I64: FGTS - COMERCIAL | R64: -444.96
A65: 504 | D65: 4.1.1.03.0504 | I65: PIS - COMERCIAL | R65: -55.62
A66: 505 | D66: 4.1.1.03.0505 | I66: INSS FERIAS - COMERCIAL | R66: -225.12
A67: 506 | D67: 4.1.1.03.0506 | I67: FGTS FERIAS - COMERCIAL | R67: -67.2
A68: 508 | D68: 4.1.1.03.0508 | I68: PIS FERIAS - COMERCIAL | R68: -8.4
A69: 527 | D69: 4.1.1.03.0527 | I69: INSS SOBRE 13 SALARIO - COMERCIAL | R69: -119.6
A70: 528 | D70: 4.1.1.03.0528 | I70: FGTS SOBRE 13 SALARIO - COMERCIAL | R70: -35.7
A71: 529 | D71: 4.1.1.03.0529 | I71: PIS SOBRE 13 SALARIO - COMERCIAL | R71: -4.47
H72: SISTEMAS E FERRAMENTAS ADMINISTRATIVAS - COMERCIAL | R72: -3094.37
A73: 710 | D73: 4.3.1.06.0710 | I73: DESPESAS COM INFORMATICA / SISTEMAS / SOFTWARES - COMERCIAL | R73: -3094.37
H74: OUTROS - COMERCIAL | R74: -1218.93
A75: 247 | D75: 4.3.1.02.0247 | I75: DESPESAS DE CUSTOS COM EVENTOS | R75: -1000
A76: 711 | D76: 4.3.1.06.0711 | I76: VIAGEM, ESTADIA E PEDAGIO | R76: -218.93
H77: PUBLICIDADE | R77: -48720.64
A78: 171 | D78: 4.3.1.02.0171 | I78: PUBLICIDADE - TRAFEGO PAGO | R78: -47548.8
A79: 245 | D79: 4.3.1.02.0245 | I79: DESPESAS COM MARKETING E PUBLICIDADE - | R79: -1064.04
A80: 709 | D80: 4.3.1.06.0709 | I80: MARKETING E PUBLICIDADE - COMERCIAL | R80: -107.8
H81: DESPESA FIXA ADMINITRATIVA | R81: -114685.31
H83: SALÁRIOS E ENCARGOS | R83: -68959.91
A84: 179 | D84: 4.1.1.01.0179 | I84: FINANCEIRO - PJ | R84: -6750
A85: 180 | D85: 4.1.1.01.0180 | I85: ADMINISTRACAO - PJ | R85: -19141.62
A86: 186 | D86: 4.1.1.01.0186 | I86: LOGISTICA / EXPEDICAO - PJ | R86: -9300
A87: 187 | D87: 4.1.1.01.0187 | I87: DIRETORIA - PJ | R87: -9224.77
A88: 189 | D88: 4.1.1.02.0189 | I88: ADMINISTRACAO - CLT | R88: -6069
A89: 190 | D89: 4.1.1.02.0190 | I89: EXPEDICAO - CLT | R89: -1984.5
A90: 193 | D90: 4.1.1.02.0193 | I90: DIVERSOS | R90: -104.77
A91: 530 | D91: 4.1.1.02.0530 | I91: SALARIO DE FERIAS - ADMINISTRACAO | R91: -894.84
A92: 531 | D92: 4.1.1.02.0531 | I92: 13 SALARIO - ADMINISTRACAO | R92: -671.13
A93: 195 | D93: 4.1.1.03.0195 | I93: INSS - ADMINISTRATIVO | R93: -2158.31
A94: 196 | D94: 4.1.1.03.0196 | I94: FGTS - ADMINISTRATIVO | R94: -644.28
A95: 197 | D95: 4.1.1.03.0197 | I95: PIS - ADMINISTRATIVO | R95: -80.53
... A106: 210 | D106: 4.2.1.02.0210 | I106: CAPACITACAO PROFISSIONAL | R106: -1817.37
H107: ALUGUEL E CONDOMÍNIO | R107: -10042.27
A108: 229 | D108: 4.3.1.01.0229 | I108: ALUGUEIS | R108: -10000
A109: 237 | D109: 4.3.1.01.0237 | I109: DESPESAS COM CONDOMINIO | R109: -42.27
H110: CONTABILIDADE | R110: -4519
A111: 214 | D111: 4.3.1.01.0214 | I111: SERVICOS CONTABEIS E AFINS | R111: -4519
H112: OUTRAS PRESTACAO DE SERVIÇO | R112: -2837.89
A113: 217 | D113: 4.3.1.01.0217 | I113: DESPESAS C/PRESTACAO DE SERVICOS - PJ | R113: -2837.89
H114: ENERGIA ELÉTRICA, ÁGUA E ESGOTO E INTERNET | R114: -3736.53
A115: 219 | D115: 4.3.1.01.0219 | I115: ENERGIA ELETRICA | R115: -3230.75
A116: 220 | D116: 4.3.1.01.0220 | I116: AGUA E ESGOTO | R116: -153.96
A117: 233 | D117: 4.3.1.01.0233 | I117: INTERNET | R117: -351.82
H118: SISTEMAS E FERRAMENTAS ADMINISTRATIVAS | R118: -13672.22
A119: 244 | D119: 4.3.1.01.0244 | I119: DESPESAS COM INFORMATICA / SISTEMAS / SOFTWARES | R119: -13672.22
H120: TARIFAS BANCÁRIAS | R120: -312.43
...

Sheet Planilha8
A1: Código | D1: Classificação | H1: Descrição | R1: Saldo Atual
H2: RECEITA COM VENDAS | R2: 393480.25
A3: 860 | D3: 3.1.1.03.0860 | I3: ATACADO | R3: 67772.31
A4: 861 | D4: 3.1.1.03.0861 | I4: ECOMMERCE | R4: 183185.27
A5: 862 | D5: 3.1.1.03.0862 | I5: EVENTO | R5: 5920.9
A6: 865 | D6: 3.1.1.03.0865 | I6: LIVRARIA | R6: 132362.67
A7: 868 | D7: 3.1.1.03.0868 | I7: SHOWROOM | R7: 4239.1
H8: MARKETPLACES | R8: 102348.89
A9: 863 | D9: 3.1.1.03.0863 | I9: AMAZON | R9: 12708.58
A10: 864 | D10: 3.1.1.03.0864 | I10: MERCADO LIVRE | R10: 56458.35
A11: 866 | D11: 3.1.1.03.0866 | I11: FULL ML | R11: 27487.96
A12: 869 | D12: 3.1.1.03.0869 | I12: AMAZON FULL | R12: 5694
H13: TOTAL RECEITA BRUTA COM VENDAS | R13: 495829.14
H15: DEVOLUÇÃO E DESCONTO DE VENDAS | R15: -4964.76
A16: 166 | D16: 3.6.1.01.0166 | I16: DEVOLUCAO DE VENDAS | R16: -4964.76
H17: RECEITA LÍQUIDA DE VENDAS | R17: 490864.38
H19: FRETE COBRADO DOS CLIENTES | R19: 27185.91
A20: 749 | D20: 3.1.1.04.0749 | I20: FRETES COBRADOS DOS CLIENTES | R20: 27185.91
H21: RECEITA OPERACIONAL TOTAL | R21: 518050.29
H23: CUSTO DOS PRODUTOS VENDIDOS (CPV/CMV) | R23: -197655.91
A24: 162 | D24: 3.7.1.01.0162 | I24: CUSTO DAS MERCADORIAS VENDIDAS | R24: -187451.29
A25: 165 | D25: 3.7.1.01.0165 | I25: DIREITOS AUTORAIS | R25: -8035.08
A26: 167 | D26: 3.7.1.01.0167 | I26: MATERIAIS APLICADOS NA VENDA DE PRODUTOS | R26: -2169.54
H27: TOTAL CUSTO DOS PRODUTOS VENDIDOS | R27: -197655.91
H29: RECEITAS FINANCEIRAS | R29: 3.2
A30: 135 | D30: 3.2.1.01.0135 | I30: FUNDOS DIVERSOS | R30: 3.2
H31: OUTRAS RECEITAS | R31: 352.76
A32: 159 | D32: 3.3.1.01.0159 | I32: OUTRAS RECEITAS | R32: 352.76
H33: LUCRO BRUTO | R33: 320750.34
H35: DESPESAS VARIÁVEIS COMERCIAIS | R35: -23752.08
A36: 164 | D36: 3.7.1.01.0164 | I36: FRETES SOBRE MERCADORIAS | R36: -22182.95
A37: 206 | D37: 4.1.1.05.0206 | I37: COMISSOES POR VENDA | R37: -219.13
A38: 207 | D38: 4.1.1.05.0207 | I38: BONUS POR RESULTADO | R38: -1350
H39: TAXA DE CARTAO / GATEWAY | R39: -32006.59
A40: 250 | D40: 4.3.1.03.0250 | I40: DESPESAS PAGAR ME | R40: -18.34
A41: 253 | D41: 4.3.1.03.0253 | I41: DESPESAS MERCADO PAGO.COM | R41: -24004
A42: 651 | D42: 4.3.1.03.0651 | I42: DESPESAS AMAZON | R42: -331.66
A43: 653 | D43: 4.3.1.03.0653 | I43: DESPESAS STONE | R43: -86.19
A44: 654 | D44: 4.3.1.03.0654 | I44: DESPESAS VINDI | R44: -7566.4
H45: TOTAL DESPESAS VARIÁVEIS COMERCIAIS | R45: -55758.67
H47: MARGEM DE CONTRIBUIÇÃO | R47: 264991.67
H49: DESPESAS FIXAS OPERACIONAIS | R49: -110080.21
H51: DESPESA FIXA COMERCIAL | R51: -110080.21
H53: SALARIO FIXO DOS VENDEDORES | R53: -3000
A54: 182 | D54: 4.1.1.01.0182 | I54: COMERCIAL - PJ | R54: -3000
H55: EQUIPE DE MARKETING | R55: -19363.05
A56: 181 | D56: 4.1.1.01.0181 | I56: MARKETING - PJ | R56: -12966.8
A57: 188 | D57: 4.1.1.02.0188 | I57: MARKETING - CLT | R57: -5355
A58: 535 | D58: 4.1.1.02.0535 | I58: SALARIO DE FERIAS - MARKETING | R58: -595
A59: 536 | D59: 4.1.1.02.0536 | I59: 13 SALARIO - COMERCIAL | R59: -446.25
H60: LIVRARIA | R60: -10570
A61: 184 | D61: 4.1.1.01.0184 | I61: LIVRARIA - PJ | R61: -10570
H62: ENCARGOS PREVIDENCIARIOS E SOCIAIS | R62: -2256.52
A63: 502 | D63: 4.1.1.03.0502 | I63: INSS - COMERCIAL | R63: -1435.14
A64: 503 | D64: 4.1.1.03.0503 | I64: FGTS - COMERCIAL | R64: -428.4
A65: 504 | D65: 4.1.1.03.0504 | I65: PIS - COMERCIAL | R65: -53.55
A66: 505 | D66: 4.1.1.03.0505 | I66: INSS FERIAS - COMERCIAL | R66: -142.15
A67: 506 | D67: 4.1.1.03.0506 | I67: FGTS FERIAS - COMERCIAL | R67: -47.6
A68: 508 | D68: 4.1.1.03.0508 | I68: PIS FERIAS - COMERCIAL | R68: -5.95
A69: 527 | D69: 4.1.1.03.0527 | I69: INSS SOBRE 13 SALARIO - COMERCIAL | R69: -103.57
A70: 528 | D70: 4.1.1.03.0528 | I70: FGTS SOBRE 13 SALARIO - COMERCIAL | R70: -35.7
A71: 529 | D71: 4.1.1.03.0529 | I71: PIS SOBRE 13 SALARIO - COMERCIAL | R71: -4.46
H72: SISTEMAS E FERRAMENTAS ADMINISTRATIVAS - COMERCIAL | R72: -6855.96
A73: 710 | D73: 4.3.1.06.0710 | I73: DESPESAS COM INFORMATICA / SISTEMAS / SOFTWARES - COMERCIAL | R73: -6855.96
H74: OUTROS - COMERCIAL | R74: -510.76
A75: 247 | D75: 4.3.1.02.0247 | I75: DESPESAS DE CUSTOS COM EVENTOS | R75: -295.35
A76: 711 | D76: 4.3.1.06.0711 | I76: VIAGEM, ESTADIA E PEDAGIO | R76: -215.41
H77: PUBLICIDADE | R77: -67523.92
A78: 171 | D78: 4.3.1.02.0171 | I78: PUBLICIDADE - TRAFEGO PAGO | R78: -58078.98
A79: 245 | D79: 4.3.1.02.0245 | I79: DESPESAS COM MARKETING E PUBLICIDADE - | R79: -9444.94
H80: DESPESA FIXA ADMINITRATIVA | R80: -119785.41
H82: SALÁRIOS E ENCARGOS | R82: -68593.98
A83: 179 | D83: 4.1.1.01.0179 | I83: FINANCEIRO - PJ | R83: -6750
A84: 180 | D84: 4.1.1.01.0180 | I84: ADMINISTRACAO - PJ | R84: -19141.62
A85: 186 | D85: 4.1.1.01.0186 | I85: LOGISTICA / EXPEDICAO - PJ | R85: -9750
A86: 187 | D86: 4.1.1.01.0187 | I86: DIRETORIA - PJ | R86: -9462.63
A87: 189 | D87: 4.1.1.02.0189 | I87: ADMINISTRACAO - CLT | R87: -7000.92
A88: 190 | D88: 4.1.1.02.0190 | I88: EXPEDICAO - CLT | R88: -4629.09
A89: 193 | D89: 4.1.1.02.0193 | I89: DIVERSOS | R89: -104.77
A90: 530 | D90: 4.1.1.02.0530 | I90: SALARIO DE FERIAS - ADMINISTRACAO | R90: -194.83
A91: 531 | D91: 4.1.1.02.0531 | I91: 13 SALARIO - ADMINISTRACAO | R91: -671.12
A92: 195 | D92: 4.1.1.03.0195 | I92: INSS - ADMINISTRATIVO | R92: -2032.6
A93: 196 | D93: 4.1.1.03.0196 | I93: FGTS - ADMINISTRATIVO | R93: -476.28
A94: 197 | D94: 4.1.1.03.0197 | I94: PIS - ADMINISTRATIVO | R94: -78.3
... A104: 203 | D104: 4.1.1.04.0203 | I104: VALE CESTA BASICA | R104: -1075
H105: ALUGUEL E CONDOMÍNIO | R105: -10030.27
A106: 229 | D106: 4.3.1.01.0229 | I106: ALUGUEIS | R106: -10000
A107: 237 | D107: 4.3.1.01.0237 | I107: DESPESAS COM CONDOMINIO | R107: -30.27
H108: CONTABILIDADE | R108: -4519
A109: 214 | D109: 4.3.1.01.0214 | I109: SERVICOS CONTABEIS E AFINS | R109: -4519
H110: OUTRAS PRESTACAO DE SERVIÇO | R110: -326.8
A111: 217 | D111: 4.3.1.01.0217 | I111: DESPESAS C/PRESTACAO DE SERVICOS - PJ | R111: -326.8
H112: ENERGIA ELÉTRICA, ÁGUA E ESGOTO E INTERNET | R112: -5049.27
A113: 219 | D113: 4.3.1.01.0219 | I113: ENERGIA ELETRICA | R113: -3736.75
A114: 220 | D114: 4.3.1.01.0220 | I114: AGUA E ESGOTO | R114: -1172.53
A115: 233 | D115: 4.3.1.01.0233 | I115: INTERNET | R115: -139.99
H116: SISTEMAS E FERRAMENTAS ADMINISTRATIVAS | R116: -23729.93
A117: 244 | D117: 4.3.1.01.0244 | I117: DESPESAS COM INFORMATICA / SISTEMAS / SOFTWARES | R117: -23729.93
H118: TARIFAS BANCÁRIAS | R118: -294.46
A119: 252 | D119: 4.3.1.03.0252 | I119: DESPESAS BANCARIAS | R119: -294.46
...

Sheet Planilha9
A1: Código | D1: Classificação | H1: Descrição | R1: Saldo Atual
H2: RECEITA COM VENDAS | R2: 365887.99
A3: 860 | D3: 3.1.1.03.0860 | I3: ATACADO | R3: 119355.57
A4: 861 | D4: 3.1.1.03.0861 | I4: ECOMMERCE | R4: 128905.32
A5: 862 | D5: 3.1.1.03.0862 | I5: EVENTO | R5: 2022.62
A6: 865 | D6: 3.1.1.03.0865 | I6: LIVRARIA | R6: 108371.46
A7: 868 | D7: 3.1.1.03.0868 | I7: SHOWROOM | R7: 7233.02
H8: MARKETPLACES | R8: 76825.93
A9: 863 | D9: 3.1.1.03.0863 | I9: AMAZON | R9: 14195.45
A10: 864 | D10: 3.1.1.03.0864 | I10: MERCADO LIVRE | R10: 36501
A11: 866 | D11: 3.1.1.03.0866 | I11: FULL ML | R11: 22983.78
A12: 869 | D12: 3.1.1.03.0869 | I12: AMAZON FULL | R12: 3145.7
H13: TOTAL RECEITA BRUTA COM VENDAS | R13: 442713.92
H15: DEVOLUÇÃO E DESCONTO DE VENDAS | R15: -5299.1
A16: 166 | D16: 3.6.1.01.0166 | I16: DEVOLUCAO DE VENDAS | R16: -5299.1
H17: RECEITA LÍQUIDA DE VENDAS | R17: 437414.82
H19: FRETE COBRADO DOS CLIENTES | R19: 20968.57
A20: 749 | D20: 3.1.1.04.0749 | I20: FRETES COBRADOS DOS CLIENTES | R20: 20968.57
H21: RECEITA OPERACIONAL TOTAL | R21: 458383.39
H23: CUSTO DOS PRODUTOS VENDIDOS (CPV/CMV) | R23: -116814.82
A24: 162 | D24: 3.7.1.01.0162 | I24: CUSTO DAS MERCADORIAS VENDIDAS | R24: -103605.83
A25: 165 | D25: 3.7.1.01.0165 | I25: DIREITOS AUTORAIS | R25: -13208.99
H26: TOTAL CUSTO DOS PRODUTOS VENDIDOS | R26: -116814.82
H28: RECEITAS FINANCEIRAS | R28: 3.21
A29: 135 | D29: 3.2.1.01.0135 | I29: FUNDOS DIVERSOS | R29: 3.21
H30: OUTRAS RECEITAS | R30: 3834.2
A31: 159 | D31: 3.3.1.01.0159 | I31: OUTRAS RECEITAS | R31: 3834.2
H32: LUCRO BRUTO | R32: 345405.98
H34: DESPESAS VARIÁVEIS COMERCIAIS | R34: -32588.96
A35: 164 | D35: 3.7.1.01.0164 | I35: FRETES SOBRE MERCADORIAS | R35: -20189.25
A36: 206 | D36: 4.1.1.05.0206 | I36: COMISSOES POR VENDA | R36: -569.13
A37: 207 | D37: 4.1.1.05.0207 | I37: BONUS POR RESULTADO | R37: -7509.27
A38: 224 | D38: 4.3.1.01.0224 | I38: EMBALAGENS E MATERIAS GRAFICOS | R38: -4321.31
H39: TAXA DE CARTAO / GATEWAY | R39: -23346.11
A40: 250 | D40: 4.3.1.03.0250 | I40: DESPESAS PAGAR ME | R40: -18.54
A41: 253 | D41: 4.3.1.03.0253 | I41: DESPESAS MERCADO PAGO.COM | R41: -14867.44
A42: 651 | D42: 4.3.1.03.0651 | I42: DESPESAS AMAZON | R42: -331.66
A43: 653 | D43: 4.3.1.03.0653 | I43: DESPESAS STONE | R43: -59.23
A44: 654 | D44: 4.3.1.03.0654 | I44: DESPESAS VINDI | R44: -8069.24
H45: TOTAL DESPESAS VARIÁVEIS COMERCIAIS | R45: -55935.07
H47: MARGEM DE CONTRIBUIÇÃO | R47: 289470.91
H49: DESPESAS FIXAS OPERACIONAIS | R49: -102457.77
H51: DESPESA FIXA COMERCIAL | R51: -102457.77
H53: SALARIO FIXO DOS VENDEDORES | R53: -3000
A54: 182 | D54: 4.1.1.01.0182 | I54: COMERCIAL - PJ | R54: -3000
H55: EQUIPE DE MARKETING | R55: -19513.05
A56: 181 | D56: 4.1.1.01.0181 | I56: MARKETING - PJ | R56: -12806.8
A57: 188 | D57: 4.1.1.02.0188 | I57: MARKETING - CLT | R57: -5910
A58: 535 | D58: 4.1.1.02.0535 | I58: SALARIO DE FERIAS - MARKETING | R58: -350
A59: 536 | D59: 4.1.1.02.0536 | I59: 13 SALARIO - COMERCIAL | R59: -446.25
H60: LIVRARIA | R60: -7580
A61: 184 | D61: 4.1.1.01.0184 | I61: LIVRARIA - PJ | R61: -7580
H62: ENCARGOS PREVIDENCIARIOS E SOCIAIS | R62: -2198.16
A63: 502 | D63: 4.1.1.03.0502 | I63: INSS - COMERCIAL | R63: -1435.14
A64: 503 | D64: 4.1.1.03.0503 | I64: FGTS - COMERCIAL | R64: -428.4
A65: 504 | D65: 4.1.1.03.0504 | I65: PIS - COMERCIAL | R65: -53.55
A66: 505 | D66: 4.1.1.03.0505 | I66: INSS FERIAS - COMERCIAL | R66: -92.05
A67: 506 | D67: 4.1.1.03.0506 | I67: FGTS FERIAS - COMERCIAL | R67: -28
A68: 508 | D68: 4.1.1.03.0508 | I68: PIS FERIAS - COMERCIAL | R68: -3.5
A69: 527 | D69: 4.1.1.03.0527 | I69: INSS SOBRE 13 SALARIO - COMERCIAL | R69: -117.36
A70: 528 | D70: 4.1.1.03.0528 | I70: FGTS SOBRE 13 SALARIO - COMERCIAL | R70: -35.7
A71: 529 | D71: 4.1.1.03.0529 | I71: PIS SOBRE 13 SALARIO - COMERCIAL | R71: -4.46
H72: SISTEMAS E FERRAMENTAS ADMINISTRATIVAS - COMERCIAL | R72: -11826.89
A73: 710 | D73: 4.3.1.06.0710 | I73: DESPESAS COM INFORMATICA / SISTEMAS / SOFTWARES - COMERCIAL | R73: -11826.89
H74: OUTROS - COMERCIAL | R74: -105.6
A75: 247 | D75: 4.3.1.02.0247 | I75: DESPESAS DE CUSTOS COM EVENTOS | R75: -50
A76: 711 | D76: 4.3.1.06.0711 | I76: VIAGEM, ESTADIA E PEDAGIO | R76: -55.6
H77: PUBLICIDADE | R77: -58234.07
A78: 171 | D78: 4.3.1.02.0171 | I78: PUBLICIDADE - TRAFEGO PAGO | R78: -52310.07
A79: 245 | D79: 4.3.1.02.0245 | I79: DESPESAS COM MARKETING E PUBLICIDADE - | R79: -5924
H80: DESPESA FIXA ADMINITRATIVA | R80: -100692.94
H82: SALÁRIOS E ENCARGOS | R82: -58966.48
A83: 179 | D83: 4.1.1.01.0179 | I83: FINANCEIRO - PJ | R83: -6750
A84: 180 | D84: 4.1.1.01.0180 | I84: ADMINISTRACAO - PJ | R84: -19141.62
A85: 186 | D85: 4.1.1.01.0186 | I85: LOGISTICA / EXPEDICAO - PJ | R85: -11850
A86: 187 | D86: 4.1.1.01.0187 | I86: DIRETORIA - PJ | R86: -9343.7
A87: 189 | D87: 4.1.1.02.0189 | I87: ADMINISTRACAO - CLT | R87: -5035.28
A88: 190 | D88: 4.1.1.02.0190 | I88: EXPEDICAO - CLT | R88: 2440.71
A89: 193 | D89: 4.1.1.02.0193 | I89: DIVERSOS | R89: -104.77
A90: 530 | D90: 4.1.1.02.0530 | I90: SALARIO DE FERIAS - ADMINISTRACAO | R90: 477.21
A91: 531 | D91: 4.1.1.02.0531 | I91: 13 SALARIO - ADMINISTRACAO | R91: 18.19
A92: 195 | D92: 4.1.1.03.0195 | I92: INSS - ADMINISTRATIVO | R92: -1920.95
A93: 196 | D93: 4.1.1.03.0196 | I93: FGTS - ADMINISTRATIVO | R93: -577.36
A94: 197 | D94: 4.1.1.03.0197 | I94: PIS - ADMINISTRATIVO | R94: -72.17
... A104: 203 | D104: 4.1.1.04.0203 | I104: VALE CESTA BASICA | R104: -860
H105: ALUGUEL E CONDOMÍNIO | R105: -10000
A106: 229 | D106: 4.3.1.01.0229 | I106: ALUGUEIS | R106: -10000
H107: CONTABILIDADE | R107: -4519
A108: 214 | D108: 4.3.1.01.0214 | I108: SERVICOS CONTABEIS E AFINS | R108: -4519
H109: OUTRAS PRESTACAO DE SERVIÇO | R109: -1174.48
A110: 217 | D110: 4.3.1.01.0217 | I110: DESPESAS C/PRESTACAO DE SERVICOS - PJ | R110: -1174.48
H111: ENERGIA ELÉTRICA, ÁGUA E ESGOTO E INTERNET | R111: -4848.39
A112: 219 | D112: 4.3.1.01.0219 | I112: ENERGIA ELETRICA | R112: -3810.84
A113: 220 | D113: 4.3.1.01.0220 | I113: AGUA E ESGOTO | R113: -897.56
A114: 233 | D114: 4.3.1.01.0233 | I114: INTERNET | R114: -139.99
H115: SISTEMAS E FERRAMENTAS ADMINISTRATIVAS | R115: -14131.61
A116: 244 | D116: 4.3.1.01.0244 | I116: DESPESAS COM INFORMATICA / SISTEMAS / SOFTWARES | R116: -14131.61
H117: TARIFAS BANCÁRIAS | R117: -270.38
A118: 252 | D118: 4.3.1.03.0252 | I118: DESPESAS BANCARIAS | R118: -270.38
H119: OUTROS | R119: -6782.6
...

Sheet Planilha10
A1: Código | D1: Classificação | H1: Descrição | R1: Saldo Atual
H2: RECEITA COM VENDAS | R2: 581307.37
A3: 860 | D3: 3.1.1.03.0860 | I3: ATACADO | R3: 103628.97
A4: 861 | D4: 3.1.1.03.0861 | I4: ECOMMERCE | R4: 362077.95
A5: 865 | D5: 3.1.1.03.0865 | I5: LIVRARIA | R5: 114754.37
A6: 868 | D6: 3.1.1.03.0868 | I6: SHOWROOM | R6: 846.08
H7: MARKETPLACES | R7: 66278.9
A8: 863 | D8: 3.1.1.03.0863 | I8: AMAZON | R8: 23873.87
A9: 864 | D9: 3.1.1.03.0864 | I9: MERCADO LIVRE | R9: 17237.34
A10: 866 | D10: 3.1.1.03.0866 | I10: FULL ML | R10: 22021.99
A11: 869 | D11: 3.1.1.03.0869 | I11: AMAZON FULL | R11: 3145.7
H12: TOTAL RECEITA BRUTA COM VENDAS | R12: 647586.27
H14: DEVOLUÇÃO E DESCONTO DE VENDAS | R14: -1467.16
A15: 166 | D15: 3.6.1.01.0166 | I15: DEVOLUCAO DE VENDAS | R15: -1467.16
H16: RECEITA LÍQUIDA DE VENDAS | R16: 646119.11
H18: FRETE COBRADO DOS CLIENTES | R18: 34011.27
A19: 749 | D19: 3.1.1.04.0749 | I19: FRETES COBRADOS DOS CLIENTES | R19: 34011.27
H20: RECEITA OPERACIONAL TOTAL | R20: 680130.38
H22: CUSTO DOS PRODUTOS VENDIDOS (CPV/CMV) | R22: -149255.1
A23: 162 | D23: 3.7.1.01.0162 | I23: CUSTO DAS MERCADORIAS VENDIDAS | R23: -137158.93
A24: 165 | D24: 3.7.1.01.0165 | I24: DIREITOS AUTORAIS | R24: -9114.17
A25: 167 | D25: 3.7.1.01.0167 | I25: MATERIAIS APLICADOS NA VENDA DE PRODUTOS | R25: -2982
H26: TOTAL CUSTO DOS PRODUTOS VENDIDOS | R26: -149255.1
H28: OUTRAS RECEITAS | R28: 1552.28
A29: 159 | D29: 3.3.1.01.0159 | I29: OUTRAS RECEITAS | R29: 1552.28
H30: LUCRO BRUTO | R30: 532427.56
H32: DESPESAS VARIÁVEIS COMERCIAIS | R32: -43020.04
A33: 164 | D33: 3.7.1.01.0164 | I33: FRETES SOBRE MERCADORIAS | R33: -29566.35
A34: 206 | D34: 4.1.1.05.0206 | I34: COMISSOES POR VENDA | R34: -2093.42
A35: 207 | D35: 4.1.1.05.0207 | I35: BONUS POR RESULTADO | R35: -7284.27
A36: 224 | D36: 4.3.1.01.0224 | I36: EMBALAGENS E MATERIAS GRAFICOS | R36: -4076
H37: TAXA DE CARTAO / GATEWAY | R37: -20628.88
A38: 250 | D38: 4.3.1.03.0250 | I38: DESPESAS PAGAR ME | R38: -9485.26
A39: 253 | D39: 4.3.1.03.0253 | I39: DESPESAS MERCADO PAGO.COM | R39: -10888.27
A40: 651 | D40: 4.3.1.03.0651 | I40: DESPESAS AMAZON | R40: -187.73
A41: 653 | D41: 4.3.1.03.0653 | I41: DESPESAS STONE | R41: -67.62
H42: TOTAL DESPESAS VARIÁVEIS COMERCIAIS | R42: -63648.92
H44: MARGEM DE CONTRIBUIÇÃO | R44: 468778.64
H46: DESPESAS FIXAS OPERACIONAIS | R46: -136596.67
H48: DESPESA FIXA COMERCIAL | R48: -136596.67
H50: SALARIO FIXO DOS VENDEDORES | R50: -3000
A51: 182 | D51: 4.1.1.01.0182 | I51: COMERCIAL - PJ | R51: -3000
H52: EQUIPE DE MARKETING | R52: -22554.72
A53: 181 | D53: 4.1.1.01.0181 | I53: MARKETING - PJ | R53: -15913.47
A54: 188 | D54: 4.1.1.02.0188 | I54: MARKETING - CLT | R54: -5355
A55: 535 | D55: 4.1.1.02.0535 | I55: SALARIO DE FERIAS - MARKETING | R55: -840
A56: 536 | D56: 4.1.1.02.0536 | I56: 13 SALARIO - COMERCIAL | R56: -446.25
H57: LIVRARIA | R57: -6320
A58: 184 | D58: 4.1.1.01.0184 | I58: LIVRARIA - PJ | R58: -6320
H59: ENCARGOS PREVIDENCIARIOS E SOCIAIS | R59: -3369.82
A60: 502 | D60: 4.1.1.03.0502 | I60: INSS - COMERCIAL | R60: -2182.76
A61: 503 | D61: 4.1.1.03.0503 | I61: FGTS - COMERCIAL | R61: -651.56
A62: 504 | D62: 4.1.1.03.0504 | I62: PIS - COMERCIAL | R62: -81.45
A63: 505 | D63: 4.1.1.03.0505 | I63: INSS FERIAS - COMERCIAL | R63: -220.92
A64: 506 | D64: 4.1.1.03.0506 | I64: FGTS FERIAS - COMERCIAL | R64: -67.2
A65: 508 | D65: 4.1.1.03.0508 | I65: PIS FERIAS - COMERCIAL | R65: -8.4
A66: 527 | D66: 4.1.1.03.0527 | I66: INSS SOBRE 13 SALARIO - COMERCIAL | R66: -117.37
A67: 528 | D67: 4.1.1.03.0528 | I67: FGTS SOBRE 13 SALARIO - COMERCIAL | R67: -35.7
A68: 529 | D68: 4.1.1.03.0529 | I68: PIS SOBRE 13 SALARIO - COMERCIAL | R68: -4.46
H69: SISTEMAS E FERRAMENTAS ADMINISTRATIVAS - COMERCIAL | R69: -26498.07
A70: 710 | D70: 4.3.1.06.0710 | I70: DESPESAS COM INFORMATICA / SISTEMAS / SOFTWARES - COMERCIAL | R70: -26498.07
H71: OUTROS - COMERCIAL | R71: -15832.55
A72: 247 | D72: 4.3.1.02.0247 | I72: DESPESAS DE CUSTOS COM EVENTOS | R72: -15783.51
A73: 711 | D73: 4.3.1.06.0711 | I73: VIAGEM, ESTADIA E PEDAGIO | R73: -49.04
H74: PUBLICIDADE | R74: -59021.51
A75: 171 | D75: 4.3.1.02.0171 | I75: PUBLICIDADE - TRAFEGO PAGO | R75: -55789.51
A76: 245 | D76: 4.3.1.02.0245 | I76: DESPESAS COM MARKETING E PUBLICIDADE - | R76: -3232
H77: DESPESA FIXA ADMINITRATIVA | R77: -113586.09
H79: SALÁRIOS E ENCARGOS | R79: -60162.76
A80: 179 | D80: 4.1.1.01.0179 | I80: FINANCEIRO - PJ | R80: -6750
A81: 180 | D81: 4.1.1.01.0180 | I81: ADMINISTRACAO - PJ | R81: -19141.62
A82: 186 | D82: 4.1.1.01.0186 | I82: LOGISTICA / EXPEDICAO - PJ | R82: -9022.8
A83: 187 | D83: 4.1.1.01.0187 | I83: DIRETORIA - PJ | R83: -9343.7
A84: 189 | D84: 4.1.1.02.0189 | I84: ADMINISTRACAO - CLT | R84: -3901.17
A85: 190 | D85: 4.1.1.02.0190 | I85: EXPEDICAO - CLT | R85: -1984.5
A86: 193 | D86: 4.1.1.02.0193 | I86: DIVERSOS | R86: -104.77
A87: 530 | D87: 4.1.1.02.0530 | I87: SALARIO DE FERIAS - ADMINISTRACAO | R87: -696.56
A88: 531 | D88: 4.1.1.02.0531 | I88: 13 SALARIO - ADMINISTRACAO | R88: 984.69
A89: 195 | D89: 4.1.1.03.0195 | I89: INSS - ADMINISTRATIVO | R89: -1711.67
A90: 196 | D90: 4.1.1.03.0196 | I90: FGTS - ADMINISTRATIVO | R90: -533.05
A91: 197 | D91: 4.1.1.03.0197 | I91: PIS - ADMINISTRATIVO | R91: -66.62
... A102: 210 | D102: 4.2.1.02.0210 | I102: CAPACITACAO PROFISSIONAL | R102: -49
H103: ALUGUEL E CONDOMÍNIO | R103: -10029.67
A104: 229 | D104: 4.3.1.01.0229 | I104: ALUGUEIS | R104: -10000
A105: 237 | D105: 4.3.1.01.0237 | I105: DESPESAS COM CONDOMINIO | R105: -29.67
H106: CONTABILIDADE | R106: -4560.14
A107: 214 | D107: 4.3.1.01.0214 | I107: SERVICOS CONTABEIS E AFINS | R107: -4560.14
H108: OUTRAS PRESTACAO DE SERVIÇO | R108: -6730.92
A109: 217 | D109: 4.3.1.01.0217 | I109: DESPESAS C/PRESTACAO DE SERVICOS - PJ | R109: -6730.92
H110: ENERGIA ELÉTRICA, ÁGUA E ESGOTO E INTERNET | R110: -4525.66
A111: 219 | D111: 4.3.1.01.0219 | I111: ENERGIA ELETRICA | R111: -3813.83
A112: 220 | D112: 4.3.1.01.0220 | I112: AGUA E ESGOTO | R112: -570.48
A113: 233 | D113: 4.3.1.01.0233 | I113: INTERNET | R113: -141.35
H114: SISTEMAS E FERRAMENTAS ADMINISTRATIVAS | R114: -13670.84
A115: 244 | D115: 4.3.1.01.0244 | I115: DESPESAS COM INFORMATICA / SISTEMAS / SOFTWARES | R115: -13670.84
H116: TARIFAS BANCÁRIAS | R116: -256.61
A117: 252 | D117: 4.3.1.03.0252 | I117: DESPESAS BANCARIAS | R117: -256.61
H118: OUTROS | R118: -13649.49
A119: 215 | D119: 4.3.1.01.0215 | I119: DESPESAS COM COPA E COZINHA | R119: -1763.89
A120: 216 | D120: 4.3.1.01.0216 | I120: DESPESAS COM ESTACIONAMENTO DE VEICULOS | R120: -52
...

Sheet Planilha11
A1: Código | D1: Classificação | H1: Descrição | R1: Saldo Atual
H2: RECEITA COM VENDAS | R2: 721066.96
A3: 860 | D3: 3.1.1.03.0860 | I3: ATACADO | R3: 81748.93
A4: 861 | D4: 3.1.1.03.0861 | I4: ECOMMERCE | R4: 337371.61
A5: 862 | D5: 3.1.1.03.0862 | I5: EVENTO | R5: 139352.76
A6: 865 | D6: 3.1.1.03.0865 | I6: LIVRARIA | R6: 159575.85
A7: 868 | D7: 3.1.1.03.0868 | I7: SHOWROOM | R7: 3017.81
H8: MARKETPLACES | R8: 97895.65
A9: 863 | D9: 3.1.1.03.0863 | I9: AMAZON | R9: 43014.56
A10: 864 | D10: 3.1.1.03.0864 | I10: MERCADO LIVRE | R10: 34575.46
A11: 866 | D11: 3.1.1.03.0866 | I11: FULL ML | R11: 19076.53
A12: 869 | D12: 3.1.1.03.0869 | I12: AMAZON FULL | R12: 1229.1
H13: TOTAL RECEITA BRUTA COM VENDAS | R13: 818962.61
H15: DEVOLUÇÃO E DESCONTO DE VENDAS | R15: -2839.49
A16: 166 | D16: 3.6.1.01.0166 | I16: DEVOLUCAO DE VENDAS | R16: -2839.49
H17: RECEITA LÍQUIDA DE VENDAS | R17: 816123.12
H19: FRETE COBRADO DOS CLIENTES | R19: 41078.72
A20: 749 | D20: 3.1.1.04.0749 | I20: FRETES COBRADOS DOS CLIENTES | R20: 41078.72
H21: RECEITA OPERACIONAL TOTAL | R21: 857201.84
H23: CUSTO DOS PRODUTOS VENDIDOS (CPV/CMV) | R23: -295912.48
A24: 162 | D24: 3.7.1.01.0162 | I24: CUSTO DAS MERCADORIAS VENDIDAS | R24: -252632.58
A25: 165 | D25: 3.7.1.01.0165 | I25: DIREITOS AUTORAIS | R25: -43279.9
H26: TOTAL CUSTO DOS PRODUTOS VENDIDOS | R26: -295912.48
H28: RECEITAS FINANCEIRAS | R28: 1.69
A29: 135 | D29: 3.2.1.01.0135 | I29: FUNDOS DIVERSOS | R29: 1.69
H30: OUTRAS RECEITAS | R30: 260.45
A31: 159 | D31: 3.3.1.01.0159 | I31: OUTRAS RECEITAS | R31: 260.45
H32: LUCRO BRUTO | R32: 561551.5
H34: DESPESAS VARIÁVEIS COMERCIAIS | R34: -69590.53
A35: 164 | D35: 3.7.1.01.0164 | I35: FRETES SOBRE MERCADORIAS | R35: -42892.46
A36: 206 | D36: 4.1.1.05.0206 | I36: COMISSOES POR VENDA | R36: -2570.34
A37: 207 | D37: 4.1.1.05.0207 | I37: BONUS POR RESULTADO | R37: -16501.75
A38: 224 | D38: 4.3.1.01.0224 | I38: EMBALAGENS E MATERIAS GRAFICOS | R38: -7625.98
H39: TAXA DE CARTAO / GATEWAY | R39: -37959.16
A40: 250 | D40: 4.3.1.03.0250 | I40: DESPESAS PAGAR ME | R40: -13576.69
A41: 253 | D41: 4.3.1.03.0253 | I41: DESPESAS MERCADO PAGO.COM | R41: -22440.42
A42: 651 | D42: 4.3.1.03.0651 | I42: DESPESAS AMAZON | R42: -149.29
A43: 653 | D43: 4.3.1.03.0653 | I43: DESPESAS STONE | R43: -146.22
A44: 654 | D44: 4.3.1.03.0654 | I44: DESPESAS VINDI | R44: -1646.54
H45: TOTAL DESPESAS VARIÁVEIS COMERCIAIS | R45: -107549.69
H47: MARGEM DE CONTRIBUIÇÃO | R47: 454001.81
H49: DESPESAS FIXAS OPERACIONAIS | R49: -164181.19
H51: DESPESA FIXA COMERCIAL | R51: -164181.19
H53: SALARIO FIXO DOS VENDEDORES | R53: -3300
A54: 182 | D54: 4.1.1.01.0182 | I54: COMERCIAL - PJ | R54: -3300
H55: EQUIPE DE MARKETING | R55: -23907.55
A56: 181 | D56: 4.1.1.01.0181 | I56: MARKETING - PJ | R56: -17756.8
A57: 188 | D57: 4.1.1.02.0188 | I57: MARKETING - CLT | R57: -5355
A58: 535 | D58: 4.1.1.02.0535 | I58: SALARIO DE FERIAS - MARKETING | R58: -350
A59: 536 | D59: 4.1.1.02.0536 | I59: 13 SALARIO - COMERCIAL | R59: -445.75
H60: LIVRARIA | R60: -11550
A61: 184 | D61: 4.1.1.01.0184 | I61: LIVRARIA - PJ | R61: -11550
H62: ENCARGOS PREVIDENCIARIOS E SOCIAIS | R62: -3446.21
A63: 502 | D63: 4.1.1.03.0502 | I63: INSS - COMERCIAL | R63: -2369.43
A64: 503 | D64: 4.1.1.03.0503 | I64: FGTS - COMERCIAL | R64: -707.28
A65: 504 | D65: 4.1.1.03.0504 | I65: PIS - COMERCIAL | R65: -88.41
A66: 505 | D66: 4.1.1.03.0505 | I66: INSS FERIAS - COMERCIAL | R66: -92.05
A67: 506 | D67: 4.1.1.03.0506 | I67: FGTS FERIAS - COMERCIAL | R67: -28
A68: 508 | D68: 4.1.1.03.0508 | I68: PIS FERIAS - COMERCIAL | R68: -3.5
A69: 527 | D69: 4.1.1.03.0527 | I69: INSS SOBRE 13 SALARIO - COMERCIAL | R69: -117.37
A70: 528 | D70: 4.1.1.03.0528 | I70: FGTS SOBRE 13 SALARIO - COMERCIAL | R70: -35.7
A71: 529 | D71: 4.1.1.03.0529 | I71: PIS SOBRE 13 SALARIO - COMERCIAL | R71: -4.47
H72: SISTEMAS E FERRAMENTAS ADMINISTRATIVAS - COMERCIAL | R72: -4963.09
A73: 710 | D73: 4.3.1.06.0710 | I73: DESPESAS COM INFORMATICA / SISTEMAS / SOFTWARES - COMERCIAL | R73: -4963.09
H74: OUTROS - COMERCIAL | R74: -44387.5
A75: 247 | D75: 4.3.1.02.0247 | I75: DESPESAS DE CUSTOS COM EVENTOS | R75: -44341.96
A76: 711 | D76: 4.3.1.06.0711 | I76: VIAGEM, ESTADIA E PEDAGIO | R76: -45.54
H77: PUBLICIDADE | R77: -72626.84
A78: 171 | D78: 4.3.1.02.0171 | I78: PUBLICIDADE - TRAFEGO PAGO | R78: -68841.86
A79: 245 | D79: 4.3.1.02.0245 | I79: DESPESAS COM MARKETING E PUBLICIDADE - | R79: -3784.98
H80: DESPESA FIXA ADMINITRATIVA | R80: -115548.11
H82: SALÁRIOS E ENCARGOS | R82: -65289.27
A83: 179 | D83: 4.1.1.01.0179 | I83: FINANCEIRO - PJ | R83: -7000
A84: 180 | D84: 4.1.1.01.0180 | I84: ADMINISTRACAO - PJ | R84: -19141.62
A85: 186 | D85: 4.1.1.01.0186 | I85: LOGISTICA / EXPEDICAO - PJ | R85: -9945
A86: 187 | D86: 4.1.1.01.0187 | I86: DIRETORIA - PJ | R86: -8594.85
A87: 189 | D87: 4.1.1.02.0189 | I87: ADMINISTRACAO - CLT | R87: -4284.5
A88: 190 | D88: 4.1.1.02.0190 | I88: EXPEDICAO - CLT | R88: -2487.8
A89: 193 | D89: 4.1.1.02.0193 | I89: DIVERSOS | R89: -104.77
A90: 530 | D90: 4.1.1.02.0530 | I90: SALARIO DE FERIAS - ADMINISTRACAO | R90: -696.55
A91: 531 | D91: 4.1.1.02.0531 | I91: 13 SALARIO - ADMINISTRACAO | R91: -522.92
A92: 195 | D92: 4.1.1.03.0195 | I92: INSS - ADMINISTRATIVO | R92: -2445.34
A93: 196 | D93: 4.1.1.03.0196 | I93: FGTS - ADMINISTRATIVO | R93: -1941.88
A94: 197 | D94: 4.1.1.03.0197 | I94: PIS - ADMINISTRATIVO | R94: -94.66
... A105: 203 | D105: 4.1.1.04.0203 | I105: VALE CESTA BASICA | R105: -1290
H106: ALUGUEL E CONDOMÍNIO | R106: -10279.67
A107: 229 | D107: 4.3.1.01.0229 | I107: ALUGUEIS | R107: -10279.67
H108: CONTABILIDADE | R108: -6505
A109: 214 | D109: 4.3.1.01.0214 | I109: SERVICOS CONTABEIS E AFINS | R109: -6505
H110: OUTRAS PRESTACAO DE SERVIÇO | R110: -4485.54
A111: 217 | D111: 4.3.1.01.0217 | I111: DESPESAS C/PRESTACAO DE SERVICOS - PJ | R111: -4485.54
H112: ENERGIA ELÉTRICA, ÁGUA E ESGOTO E INTERNET | R112: -4443.6
A113: 219 | D113: 4.3.1.01.0219 | I113: ENERGIA ELETRICA | R113: -3675.66
A114: 220 | D114: 4.3.1.01.0220 | I114: AGUA E ESGOTO | R114: -623.85
A115: 233 | D115: 4.3.1.01.0233 | I115: INTERNET | R115: -144.09
H116: SISTEMAS E FERRAMENTAS ADMINISTRATIVAS | R116: -17911.5
A117: 244 | D117: 4.3.1.01.0244 | I117: DESPESAS COM INFORMATICA / SISTEMAS / SOFTWARES | R117: -17911.5
H118: TARIFAS BANCÁRIAS | R118: -425.99
A119: 252 | D119: 4.3.1.03.0252 | I119: DESPESAS BANCARIAS | R119: -425.99
H120: OUTROS | R120: -6207.54
...

Sheet Planilha12
A1: Código | D1: Classificação | H1: Descrição | R1: Saldo Atual
H2: RECEITA COM VENDAS | R2: 891397.91
A3: 860 | D3: 3.1.1.03.0860 | I3: ATACADO | R3: 302775.76
A4: 861 | D4: 3.1.1.03.0861 | I4: ECOMMERCE | R4: 451807.46
A5: 865 | D5: 3.1.1.03.0865 | I5: LIVRARIA | R5: 135979.09
A6: 868 | D6: 3.1.1.03.0868 | I6: SHOWROOM | R6: 835.6
H7: MARKETPLACES | R7: 217313.13
A8: 863 | D8: 3.1.1.03.0863 | I8: AMAZON | R8: 62324.86
A9: 864 | D9: 3.1.1.03.0864 | I9: MERCADO LIVRE | R9: 143877.78
A10: 866 | D10: 3.1.1.03.0866 | I10: FULL ML | R10: 9019.49
A11: 869 | D11: 3.1.1.03.0869 | I11: AMAZON FULL | R11: 2091
H12: TOTAL RECEITA BRUTA COM VENDAS | R12: 1108711
H14: DEVOLUÇÃO E DESCONTO DE VENDAS | R14: -4693.04
A15: 166 | D15: 3.6.1.01.0166 | I15: DEVOLUCAO DE VENDAS | R15: -4693.04
H16: RECEITA LÍQUIDA DE VENDAS | R16: 1104018
H18: FRETE COBRADO DOS CLIENTES | R18: 70994.15
A19: 749 | D19: 3.1.1.04.0749 | I19: FRETES COBRADOS DOS CLIENTES | R19: 70994.15
H20: RECEITA OPERACIONAL TOTAL | R20: 1175012.1
H22: CUSTO DOS PRODUTOS VENDIDOS (CPV/CMV) | R22: -418644.32
A23: 162 | D23: 3.7.1.01.0162 | I23: CUSTO DAS MERCADORIAS VENDIDAS | R23: -315364.95
A24: 165 | D24: 3.7.1.01.0165 | I24: DIREITOS AUTORAIS | R24: -73809.99
A25: 170 | D25: 3.7.1.01.0170 | I25: ROYALTIES EDITORIAIS E OUTROS | R25: -29469.38
H26: TOTAL CUSTO DOS PRODUTOS VENDIDOS | R26: -418644.32
H28: RECEITAS FINANCEIRAS | R28: 5.05
A29: 135 | D29: 3.2.1.01.0135 | I29: FUNDOS DIVERSOS | R29: 5.05
H30: OUTRAS RECEITAS | R30: 646.12
A31: 159 | D31: 3.3.1.01.0159 | I31: OUTRAS RECEITAS | R31: 646.12
H32: LUCRO BRUTO | R32: 757019
H34: DESPESAS VARIÁVEIS COMERCIAIS | R34: -99850.61
A35: 164 | D35: 3.7.1.01.0164 | I35: FRETES SOBRE MERCADORIAS | R35: -57419.4
A36: 206 | D36: 4.1.1.05.0206 | I36: COMISSOES POR VENDA | R36: -3885.76
A37: 207 | D37: 4.1.1.05.0207 | I37: BONUS POR RESULTADO | R37: -5430.92
A38: 224 | D38: 4.3.1.01.0224 | I38: EMBALAGENS E MATERIAS GRAFICOS | R38: -33114.53
H39: TAXA DE CARTAO / GATEWAY | R39: -82349.2
A40: 250 | D40: 4.3.1.03.0250 | I40: DESPESAS PAGAR ME | R40: -18860.63
A41: 253 | D41: 4.3.1.03.0253 | I41: DESPESAS MERCADO PAGO.COM | R41: -53682.39
A42: 651 | D42: 4.3.1.03.0651 | I42: DESPESAS AMAZON | R42: -9742.64
A43: 653 | D43: 4.3.1.03.0653 | I43: DESPESAS STONE | R43: -63.54
H44: TOTAL DESPESAS VARIÁVEIS COMERCIAIS | R44: -182199.81
H46: MARGEM DE CONTRIBUIÇÃO | R46: 574819.19
H48: DESPESAS FIXAS OPERACIONAIS | R48: -232783.36
H50: DESPESA FIXA COMERCIAL | R50: -232783.36
H52: SALARIO FIXO DOS VENDEDORES | R52: -3000
A53: 182 | D53: 4.1.1.01.0182 | I53: COMERCIAL - PJ | R53: -3000
H54: EQUIPE DE MARKETING | R54: -22308.05
A55: 181 | D55: 4.1.1.01.0181 | I55: MARKETING - PJ | R55: -15666.8
A56: 188 | D56: 4.1.1.02.0188 | I56: MARKETING - CLT | R56: -5355
A57: 535 | D57: 4.1.1.02.0535 | I57: SALARIO DE FERIAS - MARKETING | R57: -840
A58: 536 | D58: 4.1.1.02.0536 | I58: 13 SALARIO - COMERCIAL | R58: -446.25
H59: LIVRARIA | R59: -7110
A60: 184 | D60: 4.1.1.01.0184 | I60: LIVRARIA - PJ | R60: -7110
H61: ENCARGOS PREVIDENCIARIOS E SOCIAIS | R61: -2371.13
A62: 502 | D62: 4.1.1.03.0502 | I62: INSS - COMERCIAL | R62: -1435.14
A63: 503 | D63: 4.1.1.03.0503 | I63: FGTS - COMERCIAL | R63: -428.4
A64: 504 | D64: 4.1.1.03.0504 | I64: PIS - COMERCIAL | R64: -53.55
A65: 505 | D65: 4.1.1.03.0505 | I65: INSS FERIAS - COMERCIAL | R65: -220.92
A66: 506 | D66: 4.1.1.03.0506 | I66: FGTS FERIAS - COMERCIAL | R66: -67.2
A67: 508 | D67: 4.1.1.03.0508 | I67: PIS FERIAS - COMERCIAL | R67: -8.4
A68: 527 | D68: 4.1.1.03.0527 | I68: INSS SOBRE 13 SALARIO - COMERCIAL | R68: -117.36
A69: 528 | D69: 4.1.1.03.0528 | I69: FGTS SOBRE 13 SALARIO - COMERCIAL | R69: -35.7
A70: 529 | D70: 4.1.1.03.0529 | I70: PIS SOBRE 13 SALARIO - COMERCIAL | R70: -4.46
H71: SISTEMAS E FERRAMENTAS ADMINISTRATIVAS - COMERCIAL | R71: -3250.79
A72: 710 | D72: 4.3.1.06.0710 | I72: DESPESAS COM INFORMATICA / SISTEMAS / SOFTWARES - COMERCIAL | R72: -3250.79
H73: OUTROS - COMERCIAL | R73: -65647.03
A74: 247 | D74: 4.3.1.02.0247 | I74: DESPESAS DE CUSTOS COM EVENTOS | R74: -65592.29
A75: 711 | D75: 4.3.1.06.0711 | I75: VIAGEM, ESTADIA E PEDAGIO | R75: -54.74
H76: PUBLICIDADE | R76: -129096.36
A77: 171 | D77: 4.3.1.02.0171 | I77: PUBLICIDADE - TRAFEGO PAGO | R77: -126306.5
A78: 245 | D78: 4.3.1.02.0245 | I78: DESPESAS COM MARKETING E PUBLICIDADE - | R78: -2789.86
H79: DESPESA FIXA ADMINITRATIVA | R79: -172565.83
H81: SALÁRIOS E ENCARGOS | R81: -124354.32
A82: 179 | D82: 4.1.1.01.0179 | I82: FINANCEIRO - PJ | R82: -6750
A83: 180 | D83: 4.1.1.01.0180 | I83: ADMINISTRACAO - PJ | R83: -19141.62
A84: 185 | D84: 4.1.1.01.0185 | I84: EDITORIAL - PJ | R84: -4743
A85: 186 | D85: 4.1.1.01.0186 | I85: LOGISTICA / EXPEDICAO - PJ | R85: -9930
A86: 187 | D86: 4.1.1.01.0187 | I86: DIRETORIA - PJ | R86: -13521.59
A87: 189 | D87: 4.1.1.02.0189 | I87: ADMINISTRACAO - CLT | R87: -4284.5
A88: 190 | D88: 4.1.1.02.0190 | I88: EXPEDICAO - CLT | R88: -3358.87
A89: 193 | D89: 4.1.1.02.0193 | I89: DIVERSOS | R89: -104.77
A90: 530 | D90: 4.1.1.02.0530 | I90: SALARIO DE FERIAS - ADMINISTRACAO | R90: -764.09
A91: 531 | D91: 4.1.1.02.0531 | I91: 13 SALARIO - ADMINISTRACAO | R91: -573.05
A92: 195 | D92: 4.1.1.03.0195 | I92: INSS - ADMINISTRATIVO | R92: -1863.38
A93: 196 | D93: 4.1.1.03.0196 | I93: FGTS - ADMINISTRATIVO | R93: -563.5
... A105: 541 | D105: 4.1.1.05.0541 | I105: BONUS POR META - SETOR ATACADO | R105: -4667.24
H106: ALUGUEL E CONDOMÍNIO | R106: -11887.43
A107: 229 | D107: 4.3.1.01.0229 | I107: ALUGUEIS | R107: -11857.16
A108: 237 | D108: 4.3.1.01.0237 | I108: DESPESAS COM CONDOMINIO | R108: -30.27
H109: CONTABILIDADE | R109: -6505
A110: 214 | D110: 4.3.1.01.0214 | I110: SERVICOS CONTABEIS E AFINS | R110: -6505
H111: OUTRAS PRESTACAO DE SERVIÇO | R111: -544.29
A112: 217 | D112: 4.3.1.01.0217 | I112: DESPESAS C/PRESTACAO DE SERVICOS - PJ | R112: -544.29
H113: ENERGIA ELÉTRICA, ÁGUA E ESGOTO E INTERNET | R113: -4496.53
A114: 219 | D114: 4.3.1.01.0219 | I114: ENERGIA ELETRICA | R114: -3657.06
A115: 220 | D115: 4.3.1.01.0220 | I115: AGUA E ESGOTO | R115: -695.38
A116: 233 | D116: 4.3.1.01.0233 | I116: INTERNET | R116: -144.09
H117: SISTEMAS E FERRAMENTAS ADMINISTRATIVAS | R117: -15566.98
A118: 244 | D118: 4.3.1.01.0244 | I118: DESPESAS COM INFORMATICA / SISTEMAS / SOFTWARES | R118: -15566.98
H119: TARIFAS BANCÁRIAS | R119: -495.76
A120: 252 | D120: 4.3.1.03.0252 | I120: DESPESAS BANCARIAS | R120: -495.76
H121: OUTROS | R121: -8715.52
...

Sheet 2025
A1: Código | D1: Classificação | H1: Descrição | R1: Saldo Atual
H2: RECEITA COM VENDAS | R2: 5890772.5
A3: 860 | D3: 3.1.1.03.0860 | I3: ATACADO | R3: 1761432.2
A4: 861 | D4: 3.1.1.03.0861 | I4: ECOMMERCE | R4: 2580276.4
A5: 862 | D5: 3.1.1.03.0862 | I5: EVENTO | R5: 223689.25
A6: 865 | D6: 3.1.1.03.0865 | I6: LIVRARIA | R6: 1308896.3
A7: 868 | D7: 3.1.1.03.0868 | I7: SHOWROOM | R7: 16478.36
H8: MARKETPLACES | R8: 729067.69
A9: 863 | D9: 3.1.1.03.0863 | I9: AMAZON | R9: 239275.09
A10: 864 | D10: 3.1.1.03.0864 | I10: MERCADO LIVRE | R10: 350577.52
A11: 866 | D11: 3.1.1.03.0866 | I11: FULL ML | R11: 123810.66
A12: 867 | D12: 3.1.1.03.0867 | I12: TIKTOK | R12: 98.92
A13: 869 | D13: 3.1.1.03.0869 | I13: AMAZON FULL | R13: 15305.5
H14: TOTAL RECEITA BRUTA COM VENDAS | R14: 6619840.2
H16: DEVOLUÇÃO E DESCONTO DE VENDAS | R16: -27576.85
A17: 166 | D17: 3.6.1.01.0166 | I17: DEVOLUCAO DE VENDAS | R17: -27555.05
A18: 168 | D18: 3.6.1.01.0168 | I18: DESCONTO SOBRE VENDAS | R18: -21.8
H19: RECEITA LÍQUIDA DE VENDAS | R19: 6592263.3
H21: FRETE COBRADO DOS CLIENTES | R21: 401312.24
A22: 749 | D22: 3.1.1.04.0749 | I22: FRETES COBRADOS DOS CLIENTES | R22: 401312.24
H23: RECEITA OPERACIONAL TOTAL | R23: 6993575.6
H25: CUSTO DOS PRODUTOS VENDIDOS (CPV/CMV) | R25: -2656876.1
A26: 162 | D26: 3.7.1.01.0162 | I26: CUSTO DAS MERCADORIAS VENDIDAS | R26: -2090405.1
A27: 165 | D27: 3.7.1.01.0165 | I27: DIREITOS AUTORAIS | R27: -270568.5
A28: 167 | D28: 3.7.1.01.0167 | I28: MATERIAIS APLICADOS NA VENDA DE PRODUTOS | R28: -16737.42
A29: 170 | D29: 3.7.1.01.0170 | I29: ROYALTIES EDITORIAIS E OUTROS | R29: -279165.03
H30: TOTAL CUSTO DOS PRODUTOS VENDIDOS | R30: -2656876.1
H32: RECEITAS FINANCEIRAS | R32: 28.56
A33: 135 | D33: 3.2.1.01.0135 | I33: FUNDOS DIVERSOS | R33: 28.56
H34: OUTRAS RECEITAS | R34: 6733.65
A35: 159 | D35: 3.3.1.01.0159 | I35: OUTRAS RECEITAS | R35: 6733.65
H36: LUCRO BRUTO | R36: 4343461.7
H38: DESPESAS VARIÁVEIS COMERCIAIS | R38: -535682.71
A39: 164 | D39: 3.7.1.01.0164 | I39: FRETES SOBRE MERCADORIAS | R39: -396817.05
A40: 206 | D40: 4.1.1.05.0206 | I40: COMISSOES POR VENDA | R40: -33190.26
A41: 207 | D41: 4.1.1.05.0207 | I41: BONUS POR RESULTADO | R41: -47826.21
A42: 212 | D42: 4.3.1.01.0212 | I42: DESPESAS REPRESENTACAO COMERCIAL | R42: -1824.94
A43: 224 | D43: 4.3.1.01.0224 | I43: EMBALAGENS E MATERIAS GRAFICOS | R43: -56024.25
H44: TAXA DE CARTAO / GATEWAY | R44: -290072.56
A45: 250 | D45: 4.3.1.03.0250 | I45: DESPESAS PAGAR ME | R45: -42242.28
A46: 253 | D46: 4.3.1.03.0253 | I46: DESPESAS MERCADO PAGO.COM | R46: -156637.12
A47: 651 | D47: 4.3.1.03.0651 | I47: DESPESAS AMAZON | R47: -17770.17
A48: 653 | D48: 4.3.1.03.0653 | I48: DESPESAS STONE | R48: -827.7
A49: 654 | D49: 4.3.1.03.0654 | I49: DESPESAS VINDI | R49: -72595.29
H50: TOTAL DESPESAS VARIÁVEIS COMERCIAIS | R50: -825755.27
H52: MARGEM DE CONTRIBUIÇÃO | R52: 3517706.4
H54: DESPESAS FIXAS OPERACIONAIS | R54: -1345043.3
H56: DESPESA FIXA COMERCIAL | R56: -1345043.3
H58: SALARIO FIXO DOS VENDEDORES | R58: -36540.7
A59: 182 | D59: 4.1.1.01.0182 | I59: COMERCIAL - PJ | R59: -36540.7
H60: EQUIPE DE MARKETING | R60: -261886.68
A61: 181 | D61: 4.1.1.01.0181 | I61: MARKETING - PJ | R61: -165919.6
A62: 188 | D62: 4.1.1.02.0188 | I62: MARKETING - CLT | R62: -85135.08
A63: 535 | D63: 4.1.1.02.0535 | I63: SALARIO DE FERIAS - MARKETING | R63: -5845
A64: 536 | D64: 4.1.1.02.0536 | I64: 13 SALARIO - COMERCIAL | R64: -4987
H65: LIVRARIA | R65: -99642.76
A66: 184 | D66: 4.1.1.01.0184 | I66: LIVRARIA - PJ | R66: -99642.76
H67: ENCARGOS PREVIDENCIARIOS E SOCIAIS | R67: -38983.45
A68: 502 | D68: 4.1.1.03.0502 | I68: INSS - COMERCIAL | R68: -23638.73
A69: 503 | D69: 4.1.1.03.0503 | I69: FGTS - COMERCIAL | R69: -6760.12
A70: 504 | D70: 4.1.1.03.0504 | I70: PIS - COMERCIAL | R70: -845.01
A71: 505 | D71: 4.1.1.03.0505 | I71: INSS FERIAS - COMERCIAL | R71: -1537.25
A72: 506 | D72: 4.1.1.03.0506 | I72: FGTS FERIAS - COMERCIAL | R72: -467.6
A73: 508 | D73: 4.1.1.03.0508 | I73: PIS FERIAS - COMERCIAL | R73: -58.45
A74: 527 | D74: 4.1.1.03.0527 | I74: INSS SOBRE 13 SALARIO - COMERCIAL | R74: -1311.73
A75: 528 | D75: 4.1.1.03.0528 | I75: FGTS SOBRE 13 SALARIO - COMERCIAL | R75: -399
A76: 529 | D76: 4.1.1.03.0529 | I76: PIS SOBRE 13 SALARIO - COMERCIAL | R76: -49.88
A77: 511 | D77: 4.1.1.04.0511 | I77: VALE TRANSPORTE - COMERCIAL | R77: -3915.68
H78: SISTEMAS E FERRAMENTAS ADMINISTRATIVAS - COMERCIAL | R78: -97629.53
A79: 710 | D79: 4.3.1.06.0710 | I79: DESPESAS COM INFORMATICA / SISTEMAS / SOFTWARES - COMERCIAL | R79: -97629.53
H80: OUTROS - COMERCIAL | R80: -137904.09
A81: 247 | D81: 4.3.1.02.0247 | I81: DESPESAS DE CUSTOS COM EVENTOS | R81: -129735.8
A82: 711 | D82: 4.3.1.06.0711 | I82: VIAGEM, ESTADIA E PEDAGIO | R82: -8168.29
H83: PUBLICIDADE | R83: -672456.09
A84: 171 | D84: 4.3.1.02.0171 | I84: PUBLICIDADE - TRAFEGO PAGO | R84: -636731.85
A85: 245 | D85: 4.3.1.02.0245 | I85: DESPESAS COM MARKETING E PUBLICIDADE - | R85: -31935.08
A86: 709 | D86: 4.3.1.06.0709 | I86: MARKETING E PUBLICIDADE - COMERCIAL | R86: -3789.16
H87: DESPESA FIXA ADMINITRATIVA | R87: -1351049.3
H89: SALÁRIOS E ENCARGOS | R89: -841823.24
A90: 179 | D90: 4.1.1.01.0179 | I90: FINANCEIRO - PJ | R90: -51009.67
A91: 180 | D91: 4.1.1.01.0180 | I91: ADMINISTRACAO - PJ | R91: -225349.04
A92: 185 | D92: 4.1.1.01.0185 | I92: EDITORIAL - PJ | R92: -4743
A93: 186 | D93: 4.1.1.01.0186 | I93: LOGISTICA / EXPEDICAO - PJ | R93: -99643.67
A94: 187 | D94: 4.1.1.01.0187 | I94: DIRETORIA - PJ | R94: -114950.63
A95: 189 | D95: 4.1.1.02.0189 | I95: ADMINISTRACAO - CLT | R95: -56376.26
A96: 190 | D96: 4.1.1.02.0190 | I96: EXPEDICAO - CLT | R96: -30720.94
A97: 192 | D97: 4.1.1.02.0192 | I97: FINANCEIRO - CLT | R97: -17044.94
A98: 193 | D98: 4.1.1.02.0193 | I98: DIVERSOS | R98: -1277.61
A99: 530 | D99: 4.1.1.02.0530 | I99: SALARIO DE FERIAS - ADMINISTRACAO | R99: -13875.62
A100: 531 | D100: 4.1.1.02.0531 | I100: 13 SALARIO - ADMINISTRACAO | R100: -4831.32
A101: 195 | D101: 4.1.1.03.0195 | I101: INSS - ADMINISTRATIVO | R101: -26231.96
... A117: 210 | D117: 4.2.1.02.0210 | I117: CAPACITACAO PROFISSIONAL | R117: -23840.97
H118: ALUGUEL E CONDOMÍNIO | R118: -130789.59
A119: 229 | D119: 4.3.1.01.0229 | I119: ALUGUEIS | R119: -130477.67
A120: 237 | D120: 4.3.1.01.0237 | I120: DESPESAS COM CONDOMINIO | R120: -311.92
H121: CONTABILIDADE | R121: -60172.14
A122: 214 | D122: 4.3.1.01.0214 | I122: SERVICOS CONTABEIS E AFINS | R122: -60172.14
H123: OUTRAS PRESTACAO DE SERVIÇO | R123: -28263.12
A124: 217 | D124: 4.3.1.01.0217 | I124: DESPESAS C/PRESTACAO DE SERVICOS - PJ | R124: -28113.12
A125: 218 | D125: 4.3.1.01.0218 | I125: DESPESAS C/PRESTACAO DE SERVICOS - PF | R125: -150
...

Sheet Planilha13
A1: Código | D1: Classificação | H1: Descrição | R1: Saldo Atual
H2: RECEITA COM VENDAS | R2: 689636.36
A3: 860 | D3: 3.1.1.03.0860 | I3: ATACADO | R3: 296951.19
A4: 861 | D4: 3.1.1.03.0861 | I4: ECOMMERCE | R4: 301545.85
A5: 865 | D5: 3.1.1.03.0865 | I5: LIVRARIA | R5: 90172.44
A6: 868 | D6: 3.1.1.03.0868 | I6: SHOWROOM | R6: 966.88
H7: MARKETPLACES | R7: 191702.95
A8: 863 | D8: 3.1.1.03.0863 | I8: AMAZON | R8: 74979.08
A9: 864 | D9: 3.1.1.03.0864 | I9: MERCADO LIVRE | R9: 108716.92
A10: 866 | D10: 3.1.1.03.0866 | I10: FULL ML | R10: 2193.35
A11: 869 | D11: 3.1.1.03.0869 | I11: AMAZON FULL | R11: 5813.6
H12: TOTAL RECEITA BRUTA COM VENDAS | R12: 881339.31
H14: DEVOLUÇÃO E DESCONTO DE VENDAS | R14: -5995.25
A15: 166 | D15: 3.6.1.01.0166 | I15: DEVOLUCAO DE VENDAS | R15: -5995.25
H16: RECEITA LÍQUIDA DE VENDAS | R16: 875344.06
H18: FRETE COBRADO DOS CLIENTES | R18: 57972.3
A19: 749 | D19: 3.1.1.04.0749 | I19: FRETES COBRADOS DOS CLIENTES | R19: 57972.3
H20: RECEITA OPERACIONAL TOTAL | R20: 933316.36
H22: CUSTO DOS PRODUTOS VENDIDOS (CPV/CMV) | R22: -323061.98
A23: 162 | D23: 3.7.1.01.0162 | I23: CUSTO DAS MERCADORIAS VENDIDAS | R23: -224504.78
A24: 165 | D24: 3.7.1.01.0165 | I24: DIREITOS AUTORAIS | R24: -55662.56
A25: 170 | D25: 3.7.1.01.0170 | I25: ROYALTIES EDITORIAIS E OUTROS | R25: -42894.64
H26: TOTAL CUSTO DOS PRODUTOS VENDIDOS | R26: -323061.98
H28: RECEITAS FINANCEIRAS | R28: 40.59
A29: 135 | D29: 3.2.1.01.0135 | I29: FUNDOS DIVERSOS | R29: 40.59
H30: OUTRAS RECEITAS | R30: 1231.9
A31: 159 | D31: 3.3.1.01.0159 | I31: OUTRAS RECEITAS | R31: 1231.9
H32: LUCRO BRUTO | R32: 611526.87
H34: DESPESAS VARIÁVEIS COMERCIAIS | R34: -72234.57
A35: 164 | D35: 3.7.1.01.0164 | I35: FRETES SOBRE MERCADORIAS | R35: -55960.11
A36: 206 | D36: 4.1.1.05.0206 | I36: COMISSOES POR VENDA | R36: -7925.23
A37: 207 | D37: 4.1.1.05.0207 | I37: BONUS POR RESULTADO | R37: -450
A38: 224 | D38: 4.3.1.01.0224 | I38: EMBALAGENS E MATERIAS GRAFICOS | R38: -7899.23
H39: TAXA DE CARTAO / GATEWAY | R39: -80047.92
A40: 250 | D40: 4.3.1.03.0250 | I40: DESPESAS PAGAR ME | R40: -9629.75
A41: 253 | D41: 4.3.1.03.0253 | I41: DESPESAS MERCADO PAGO.COM | R41: -45119.27
A42: 651 | D42: 4.3.1.03.0651 | I42: DESPESAS AMAZON | R42: -21745.48
A43: 653 | D43: 4.3.1.03.0653 | I43: DESPESAS STONE | R43: -3553.42
H44: TOTAL DESPESAS VARIÁVEIS COMERCIAIS | R44: -152282.49
H46: MARGEM DE CONTRIBUIÇÃO | R46: 459244.38
H48: DESPESAS FIXAS OPERACIONAIS | R48: -190557.32
H50: DESPESA FIXA COMERCIAL | R50: -190557.32
H52: EQUIPE DE MARKETING | R52: -17289.13
A53: 181 | D53: 4.1.1.01.0181 | I53: MARKETING - PJ | R53: -10666.8
A54: 188 | D54: 4.1.1.02.0188 | I54: MARKETING - CLT | R54: -5568.06
A55: 535 | D55: 4.1.1.02.0535 | I55: SALARIO DE FERIAS - MARKETING | R55: -602.44
A56: 536 | D56: 4.1.1.02.0536 | I56: 13 SALARIO - COMERCIAL | R56: -451.83
H57: LIVRARIA | R57: -8120
A58: 184 | D58: 4.1.1.01.0184 | I58: LIVRARIA - PJ | R58: -8120
H59: ENCARGOS PREVIDENCIARIOS E SOCIAIS | R59: -2290.62
A60: 502 | D60: 4.1.1.03.0502 | I60: INSS - COMERCIAL | R60: -1429.36
A61: 503 | D61: 4.1.1.03.0503 | I61: FGTS - COMERCIAL | R61: -434.78
A62: 504 | D62: 4.1.1.03.0504 | I62: PIS - COMERCIAL | R62: -54.35
A63: 505 | D63: 4.1.1.03.0505 | I63: INSS FERIAS - COMERCIAL | R63: -158.42
A64: 506 | D64: 4.1.1.03.0506 | I64: FGTS FERIAS - COMERCIAL | R64: -48.19
A65: 508 | D65: 4.1.1.03.0508 | I65: PIS FERIAS - COMERCIAL | R65: -6.02
A66: 527 | D66: 4.1.1.03.0527 | I66: INSS SOBRE 13 SALARIO - COMERCIAL | R66: -118.84
A67: 528 | D67: 4.1.1.03.0528 | I67: FGTS SOBRE 13 SALARIO - COMERCIAL | R67: -36.14
A68: 529 | D68: 4.1.1.03.0529 | I68: PIS SOBRE 13 SALARIO - COMERCIAL | R68: -4.52
H69: SISTEMAS E FERRAMENTAS ADMINISTRATIVAS - COMERCIAL | R69: -2765.23
A70: 710 | D70: 4.3.1.06.0710 | I70: DESPESAS COM INFORMATICA / SISTEMAS / SOFTWARES - COMERCIAL | R70: -2765.23
H71: OUTROS - COMERCIAL | R71: -11872.11
A72: 247 | D72: 4.3.1.02.0247 | I72: DESPESAS DE CUSTOS COM EVENTOS | R72: -11807.37
A73: 711 | D73: 4.3.1.06.0711 | I73: VIAGEM, ESTADIA E PEDAGIO | R73: -64.74
H74: PUBLICIDADE | R74: -148220.23
A75: 171 | D75: 4.3.1.02.0171 | I75: PUBLICIDADE - TRAFEGO PAGO | R75: -98813.29
A76: 245 | D76: 4.3.1.02.0245 | I76: DESPESAS COM MARKETING E PUBLICIDADE - | R76: -49406.94
H77: DESPESA FIXA ADMINITRATIVA | R77: -132128.11
H79: SALÁRIOS E ENCARGOS | R79: -80976.13
A80: 179 | D80: 4.1.1.01.0179 | I80: FINANCEIRO - PJ | R80: -6750
A81: 180 | D81: 4.1.1.01.0180 | I81: ADMINISTRACAO - PJ | R81: -18435.91
A82: 185 | D82: 4.1.1.01.0185 | I82: EDITORIAL - PJ | R82: -8852.55
A83: 186 | D83: 4.1.1.01.0186 | I83: LOGISTICA / EXPEDICAO - PJ | R83: -9822.5
A84: 187 | D84: 4.1.1.01.0187 | I84: DIRETORIA - PJ | R84: -12217.82
A85: 189 | D85: 4.1.1.02.0189 | I85: ADMINISTRACAO - CLT | R85: -5308.53
A86: 190 | D86: 4.1.1.02.0190 | I86: EXPEDICAO - CLT | R86: -2056.17
A87: 193 | D87: 4.1.1.02.0193 | I87: DIVERSOS | R87: -104.77
A88: 530 | D88: 4.1.1.02.0530 | I88: SALARIO DE FERIAS - ADMINISTRACAO | R88: -1024.66
A89: 531 | D89: 4.1.1.02.0531 | I89: 13 SALARIO - ADMINISTRACAO | R89: -594.61
A90: 195 | D90: 4.1.1.03.0195 | I90: INSS - ADMINISTRATIVO | R90: -1971.92
A91: 196 | D91: 4.1.1.03.0196 | I91: FGTS - ADMINISTRATIVO | R91: -599.83
... A102: 203 | D102: 4.1.1.04.0203 | I102: VALE CESTA BASICA | R102: -1290
H103: ALUGUEL E CONDOMÍNIO | R103: -11468.66
A104: 229 | D104: 4.3.1.01.0229 | I104: ALUGUEIS | R104: -11468.66
H105: CONTABILIDADE | R105: -6505
A106: 214 | D106: 4.3.1.01.0214 | I106: SERVICOS CONTABEIS E AFINS | R106: -6505
H107: OUTRAS PRESTACAO DE SERVIÇO | R107: -6628.8
A108: 217 | D108: 4.3.1.01.0217 | I108: DESPESAS C/PRESTACAO DE SERVICOS - PJ | R108: -6628.8
H109: ENERGIA ELÉTRICA, ÁGUA E ESGOTO E INTERNET | R109: -4151.91
A110: 219 | D110: 4.3.1.01.0219 | I110: ENERGIA ELETRICA | R110: -3552.75
A111: 220 | D111: 4.3.1.01.0220 | I111: AGUA E ESGOTO | R111: -455.07
A112: 233 | D112: 4.3.1.01.0233 | I112: INTERNET | R112: -144.09
H113: SISTEMAS E FERRAMENTAS ADMINISTRATIVAS | R113: -15649.97
A114: 244 | D114: 4.3.1.01.0244 | I114: DESPESAS COM INFORMATICA / SISTEMAS / SOFTWARES | R114: -15649.97
H115: TARIFAS BANCÁRIAS | R115: -269.07
A116: 252 | D116: 4.3.1.03.0252 | I116: DESPESAS BANCARIAS | R116: -269.07
H117: OUTROS | R117: -6478.57
A118: 215 | D118: 4.3.1.01.0215 | I118: DESPESAS COM COPA E COZINHA | R118: -516.5
A119: 225 | D119: 4.3.1.01.0225 | I119: IMPOSTOS E TAXAS | R119: -126.18
A120: 226 | D120: 4.3.1.01.0226 | I120: SEGUROS | R120: -143.19
...

Sheet Planilha14
A1: Código | D1: Classificação | H1: Descrição | R1: Saldo Atual
H2: RECEITA COM VENDAS | R2: 532921.71
A3: 860 | D3: 3.1.1.03.0860 | I3: ATACADO | R3: 196602.12
A4: 861 | D4: 3.1.1.03.0861 | I4: ECOMMERCE | R4: 211081.53
A5: 862 | D5: 3.1.1.03.0862 | I5: EVENTO | R5: 2312.7
A6: 865 | D6: 3.1.1.03.0865 | I6: LIVRARIA | R6: 121460.56
A7: 868 | D7: 3.1.1.03.0868 | I7: SHOWROOM | R7: 1464.8
H8: MARKETPLACES | R8: 115473.06
A9: 863 | D9: 3.1.1.03.0863 | I9: AMAZON | R9: 26276.33
A10: 864 | D10: 3.1.1.03.0864 | I10: MERCADO LIVRE | R10: 83583.13
A11: 866 | D11: 3.1.1.03.0866 | I11: FULL ML | R11: 1260.7
A12: 869 | D12: 3.1.1.03.0869 | I12: AMAZON FULL | R12: 4352.9
H13: TOTAL RECEITA BRUTA COM VENDAS | R13: 648394.77
H15: DEVOLUÇÃO E DESCONTO DE VENDAS | R15: -1321.6
A16: 166 | D16: 3.6.1.01.0166 | I16: DEVOLUCAO DE VENDAS | R16: -1321.6
H17: RECEITA LÍQUIDA DE VENDAS | R17: 647073.17
H19: FRETE COBRADO DOS CLIENTES | R19: 43241.57
A20: 749 | D20: 3.1.1.04.0749 | I20: FRETES COBRADOS DOS CLIENTES | R20: 43241.57
H21: RECEITA OPERACIONAL TOTAL | R21: 690314.74
H23: CUSTO DOS PRODUTOS VENDIDOS (CPV/CMV) | R23: -268554.6
A24: 162 | D24: 3.7.1.01.0162 | I24: CUSTO DAS MERCADORIAS VENDIDAS | R24: -226388.73
A25: 165 | D25: 3.7.1.01.0165 | I25: DIREITOS AUTORAIS | R25: -24922.51
A26: 170 | D26: 3.7.1.01.0170 | I26: ROYALTIES EDITORIAIS E OUTROS | R26: -17243.36
H27: TOTAL CUSTO DOS PRODUTOS VENDIDOS | R27: -268554.6
H29: RECEITAS FINANCEIRAS | R29: 12.69
A30: 135 | D30: 3.2.1.01.0135 | I30: FUNDOS DIVERSOS | R30: 12.69
H31: OUTRAS RECEITAS | R31: 1831.47
A32: 159 | D32: 3.3.1.01.0159 | I32: OUTRAS RECEITAS | R32: 1831.47
H33: LUCRO BRUTO | R33: 423604.3
H35: DESPESAS VARIÁVEIS COMERCIAIS | R35: -41897.45
A36: 164 | D36: 3.7.1.01.0164 | I36: FRETES SOBRE MERCADORIAS | R36: -37902.87
A37: 206 | D37: 4.1.1.05.0206 | I37: COMISSOES POR VENDA | R37: -1397.61
A38: 207 | D38: 4.1.1.05.0207 | I38: BONUS POR RESULTADO | R38: -450
A39: 224 | D39: 4.3.1.01.0224 | I39: EMBALAGENS E MATERIAS GRAFICOS | R39: -2146.97
H40: TAXA DE CARTAO / GATEWAY | R40: -47957.89
A41: 250 | D41: 4.3.1.03.0250 | I41: DESPESAS PAGAR ME | R41: -7748.07
A42: 253 | D42: 4.3.1.03.0253 | I42: DESPESAS MERCADO PAGO.COM | R42: -24656.73
A43: 651 | D43: 4.3.1.03.0651 | I43: DESPESAS AMAZON | R43: -10705.12
A44: 653 | D44: 4.3.1.03.0653 | I44: DESPESAS STONE | R44: -4847.97
H45: TOTAL DESPESAS VARIÁVEIS COMERCIAIS | R45: -89855.34
H47: MARGEM DE CONTRIBUIÇÃO | R47: 333748.96
H49: DESPESAS FIXAS OPERACIONAIS | R49: -98463.87
H51: DESPESA FIXA COMERCIAL | R51: -98463.87
H53: SALARIO FIXO DOS VENDEDORES | R53: -3000
A54: 182 | D54: 4.1.1.01.0182 | I54: COMERCIAL - PJ | R54: -3000
H55: EQUIPE DE MARKETING | R55: -16818.05
A56: 181 | D56: 4.1.1.01.0181 | I56: MARKETING - PJ | R56: -10666.8
A57: 188 | D57: 4.1.1.02.0188 | I57: MARKETING - CLT | R57: -5355
A58: 535 | D58: 4.1.1.02.0535 | I58: SALARIO DE FERIAS - MARKETING | R58: -350
A59: 536 | D59: 4.1.1.02.0536 | I59: 13 SALARIO - COMERCIAL | R59: -446.25
H60: LIVRARIA | R60: -8810
A61: 184 | D61: 4.1.1.01.0184 | I61: LIVRARIA - PJ | R61: -8810
H62: ENCARGOS PREVIDENCIARIOS E SOCIAIS | R62: -2171.39
A63: 502 | D63: 4.1.1.03.0502 | I63: INSS - COMERCIAL | R63: -1408.37
A64: 503 | D64: 4.1.1.03.0503 | I64: FGTS - COMERCIAL | R64: -428.4
A65: 504 | D65: 4.1.1.03.0504 | I65: PIS - COMERCIAL | R65: -53.55
A66: 505 | D66: 4.1.1.03.0505 | I66: INSS FERIAS - COMERCIAL | R66: -92.05
A67: 506 | D67: 4.1.1.03.0506 | I67: FGTS FERIAS - COMERCIAL | R67: -28
A68: 508 | D68: 4.1.1.03.0508 | I68: PIS FERIAS - COMERCIAL | R68: -3.5
A69: 527 | D69: 4.1.1.03.0527 | I69: INSS SOBRE 13 SALARIO - COMERCIAL | R69: -117.36
A70: 528 | D70: 4.1.1.03.0528 | I70: FGTS SOBRE 13 SALARIO - COMERCIAL | R70: -35.7
A71: 529 | D71: 4.1.1.03.0529 | I71: PIS SOBRE 13 SALARIO - COMERCIAL | R71: -4.46
H72: SISTEMAS E FERRAMENTAS ADMINISTRATIVAS - COMERCIAL | R72: -1625.71
A73: 710 | D73: 4.3.1.06.0710 | I73: DESPESAS COM INFORMATICA / SISTEMAS / SOFTWARES - COMERCIAL | R73: -1625.71
H74: OUTROS - COMERCIAL | R74: -8369.86
A75: 247 | D75: 4.3.1.02.0247 | I75: DESPESAS DE CUSTOS COM EVENTOS | R75: -8335.12
A76: 711 | D76: 4.3.1.06.0711 | I76: VIAGEM, ESTADIA E PEDAGIO | R76: -34.74
H77: PUBLICIDADE | R77: -57668.86
A78: 171 | D78: 4.3.1.02.0171 | I78: PUBLICIDADE - TRAFEGO PAGO | R78: -56239.25
A79: 245 | D79: 4.3.1.02.0245 | I79: DESPESAS COM MARKETING E PUBLICIDADE - | R79: -1429.61
H80: DESPESA FIXA ADMINITRATIVA | R80: -119652.68
H82: SALÁRIOS E ENCARGOS | R82: -73595.59
A83: 179 | D83: 4.1.1.01.0179 | I83: FINANCEIRO - PJ | R83: -6750
A84: 180 | D84: 4.1.1.01.0180 | I84: ADMINISTRACAO - PJ | R84: -18460.98
A85: 185 | D85: 4.1.1.01.0185 | I85: EDITORIAL - PJ | R85: -1672.74
A86: 186 | D86: 4.1.1.01.0186 | I86: LOGISTICA / EXPEDICAO - PJ | R86: -7200
A87: 187 | D87: 4.1.1.01.0187 | I87: DIRETORIA - PJ | R87: -12217.82
A88: 189 | D88: 4.1.1.02.0189 | I88: ADMINISTRACAO - CLT | R88: -6969
A89: 190 | D89: 4.1.1.02.0190 | I89: EXPEDICAO - CLT | R89: -3704.4
A90: 193 | D90: 4.1.1.02.0193 | I90: DIVERSOS | R90: -104.77
A91: 530 | D91: 4.1.1.02.0530 | I91: SALARIO DE FERIAS - ADMINISTRACAO | R91: -1215.52
A92: 531 | D92: 4.1.1.02.0531 | I92: 13 SALARIO - ADMINISTRACAO | R92: -135.84
A93: 195 | D93: 4.1.1.03.0195 | I93: INSS - ADMINISTRATIVO | R93: -2807.08
A94: 196 | D94: 4.1.1.03.0196 | I94: FGTS - ADMINISTRATIVO | R94: -853.87
... A105: 203 | D105: 4.1.1.04.0203 | I105: VALE CESTA BASICA | R105: -215
H106: ALUGUEL E CONDOMÍNIO | R106: -12029.67
A107: 229 | D107: 4.3.1.01.0229 | I107: ALUGUEIS | R107: -12029.67
H108: CONTABILIDADE | R108: -4826
A109: 214 | D109: 4.3.1.01.0214 | I109: SERVICOS CONTABEIS E AFINS | R109: -4826
H110: OUTRAS PRESTACAO DE SERVIÇO | R110: -4379.2
A111: 217 | D111: 4.3.1.01.0217 | I111: DESPESAS C/PRESTACAO DE SERVICOS - PJ | R111: -4379.2
H112: ENERGIA ELÉTRICA, ÁGUA E ESGOTO E INTERNET | R112: -577.4
A113: 220 | D113: 4.3.1.01.0220 | I113: AGUA E ESGOTO | R113: -433.31
A114: 233 | D114: 4.3.1.01.0233 | I114: INTERNET | R114: -144.09
H115: SISTEMAS E FERRAMENTAS ADMINISTRATIVAS | R115: -15915.1
A116: 244 | D116: 4.3.1.01.0244 | I116: DESPESAS COM INFORMATICA / SISTEMAS / SOFTWARES | R116: -15915.1
H117: TARIFAS BANCÁRIAS | R117: -346.4
A118: 252 | D118: 4.3.1.03.0252 | I118: DESPESAS BANCARIAS | R118: -346.4
H119: OUTROS | R119: -7983.32
A120: 215 | D120: 4.3.1.01.0215 | I120: DESPESAS COM COPA E COZINHA | R120: -439.5
...

Sheet 2026
A1: Código | D1: Classificação | H1: Descrição | R1: Saldo Atual
H2: RECEITA COM VENDAS | R2: 1222558.1
A3: 860 | D3: 3.1.1.03.0860 | I3: ATACADO | R3: 493553.31
A4: 861 | D4: 3.1.1.03.0861 | I4: ECOMMERCE | R4: 512627.38
A5: 862 | D5: 3.1.1.03.0862 | I5: EVENTO | R5: 2312.7
A6: 865 | D6: 3.1.1.03.0865 | I6: LIVRARIA | R6: 211633
A7: 868 | D7: 3.1.1.03.0868 | I7: SHOWROOM | R7: 2431.68
H8: MARKETPLACES | R8: 307176.01
A9: 863 | D9: 3.1.1.03.0863 | I9: AMAZON | R9: 101255.41
A10: 864 | D10: 3.1.1.03.0864 | I10: MERCADO LIVRE | R10: 192300.05
A11: 866 | D11: 3.1.1.03.0866 | I11: FULL ML | R11: 3454.05
A12: 869 | D12: 3.1.1.03.0869 | I12: AMAZON FULL | R12: 10166.5
H13: TOTAL RECEITA BRUTA COM VENDAS | R13: 1529734.1
H15: DEVOLUÇÃO E DESCONTO DE VENDAS | R15: -7316.85
A16: 166 | D16: 3.6.1.01.0166 | I16: DEVOLUCAO DE VENDAS | R16: -7316.85
H17: RECEITA LÍQUIDA DE VENDAS | R17: 1522417.2
H19: FRETE COBRADO DOS CLIENTES | R19: 101213.87
A20: 749 | D20: 3.1.1.04.0749 | I20: FRETES COBRADOS DOS CLIENTES | R20: 101213.87
H21: RECEITA OPERACIONAL TOTAL | R21: 1623631.1
H23: CUSTO DOS PRODUTOS VENDIDOS (CPV/CMV) | R23: -591616.58
A24: 162 | D24: 3.7.1.01.0162 | I24: CUSTO DAS MERCADORIAS VENDIDAS | R24: -450893.51
A25: 165 | D25: 3.7.1.01.0165 | I25: DIREITOS AUTORAIS | R25: -80585.07
A26: 170 | D26: 3.7.1.01.0170 | I26: ROYALTIES EDITORIAIS E OUTROS | R26: -60138
H27: TOTAL CUSTO DOS PRODUTOS VENDIDOS | R27: -591616.58
H29: RECEITAS FINANCEIRAS | R29: 53.28
A30: 135 | D30: 3.2.1.01.0135 | I30: FUNDOS DIVERSOS | R30: 53.28
H31: OUTRAS RECEITAS | R31: 3063.37
A32: 159 | D32: 3.3.1.01.0159 | I32: OUTRAS RECEITAS | R32: 3063.37
H33: LUCRO BRUTO | R33: 1035131.2
H35: DESPESAS VARIÁVEIS COMERCIAIS | R35: -114132.02
A36: 164 | D36: 3.7.1.01.0164 | I36: FRETES SOBRE MERCADORIAS | R36: -93862.98
A37: 206 | D37: 4.1.1.05.0206 | I37: COMISSOES POR VENDA | R37: -9322.84
A38: 207 | D38: 4.1.1.05.0207 | I38: BONUS POR RESULTADO | R38: -900
A39: 224 | D39: 4.3.1.01.0224 | I39: EMBALAGENS E MATERIAS GRAFICOS | R39: -10046.2
H40: TAXA DE CARTAO / GATEWAY | R40: -128005.81
A41: 250 | D41: 4.3.1.03.0250 | I41: DESPESAS PAGAR ME | R41: -17377.82
A42: 253 | D42: 4.3.1.03.0253 | I42: DESPESAS MERCADO PAGO.COM | R42: -69776
A43: 651 | D43: 4.3.1.03.0651 | I43: DESPESAS AMAZON | R43: -32450.6
A44: 653 | D44: 4.3.1.03.0653 | I44: DESPESAS STONE | R44: -8401.39
H45: TOTAL DESPESAS VARIÁVEIS COMERCIAIS | R45: -242137.83
H47: MARGEM DE CONTRIBUIÇÃO | R47: 792993.34
H49: DESPESAS FIXAS OPERACIONAIS | R49: -289021.19
H51: DESPESA FIXA COMERCIAL | R51: -289021.19
H53: SALARIO FIXO DOS VENDEDORES | R53: -3000
A54: 182 | D54: 4.1.1.01.0182 | I54: COMERCIAL - PJ | R54: -3000
H55: EQUIPE DE MARKETING | R55: -34107.18
A56: 181 | D56: 4.1.1.01.0181 | I56: MARKETING - PJ | R56: -21333.6
A57: 188 | D57: 4.1.1.02.0188 | I57: MARKETING - CLT | R57: -10923.06
A58: 535 | D58: 4.1.1.02.0535 | I58: SALARIO DE FERIAS - MARKETING | R58: -952.44
A59: 536 | D59: 4.1.1.02.0536 | I59: 13 SALARIO - COMERCIAL | R59: -898.08
H60: LIVRARIA | R60: -16930
A61: 184 | D61: 4.1.1.01.0184 | I61: LIVRARIA - PJ | R61: -16930
H62: ENCARGOS PREVIDENCIARIOS E SOCIAIS | R62: -4462.01
A63: 502 | D63: 4.1.1.03.0502 | I63: INSS - COMERCIAL | R63: -2837.73
A64: 503 | D64: 4.1.1.03.0503 | I64: FGTS - COMERCIAL | R64: -863.18
A65: 504 | D65: 4.1.1.03.0504 | I65: PIS - COMERCIAL | R65: -107.9
A66: 505 | D66: 4.1.1.03.0505 | I66: INSS FERIAS - COMERCIAL | R66: -250.47
A67: 506 | D67: 4.1.1.03.0506 | I67: FGTS FERIAS - COMERCIAL | R67: -76.19
A68: 508 | D68: 4.1.1.03.0508 | I68: PIS FERIAS - COMERCIAL | R68: -9.52
A69: 527 | D69: 4.1.1.03.0527 | I69: INSS SOBRE 13 SALARIO - COMERCIAL | R69: -236.2
A70: 528 | D70: 4.1.1.03.0528 | I70: FGTS SOBRE 13 SALARIO - COMERCIAL | R70: -71.84
A71: 529 | D71: 4.1.1.03.0529 | I71: PIS SOBRE 13 SALARIO - COMERCIAL | R71: -8.98
H72: SISTEMAS E FERRAMENTAS ADMINISTRATIVAS - COMERCIAL | R72: -4390.94
A73: 710 | D73: 4.3.1.06.0710 | I73: DESPESAS COM INFORMATICA / SISTEMAS / SOFTWARES - COMERCIAL | R73: -4390.94
H74: OUTROS - COMERCIAL | R74: -20241.97
A75: 247 | D75: 4.3.1.02.0247 | I75: DESPESAS DE CUSTOS COM EVENTOS | R75: -20142.49
A76: 711 | D76: 4.3.1.06.0711 | I76: VIAGEM, ESTADIA E PEDAGIO | R76: -99.48
H77: PUBLICIDADE | R77: -205889.09
A78: 171 | D78: 4.3.1.02.0171 | I78: PUBLICIDADE - TRAFEGO PAGO | R78: -155052.54
A79: 245 | D79: 4.3.1.02.0245 | I79: DESPESAS COM MARKETING E PUBLICIDADE - | R79: -50836.55
H80: DESPESA FIXA ADMINITRATIVA | R80: -251780.79
H82: SALÁRIOS E ENCARGOS | R82: -154571.72
A83: 179 | D83: 4.1.1.01.0179 | I83: FINANCEIRO - PJ | R83: -13500
A84: 180 | D84: 4.1.1.01.0180 | I84: ADMINISTRACAO - PJ | R84: -36896.89
A85: 185 | D85: 4.1.1.01.0185 | I85: EDITORIAL - PJ | R85: -10525.29
A86: 186 | D86: 4.1.1.01.0186 | I86: LOGISTICA / EXPEDICAO - PJ | R86: -17022.5
A87: 187 | D87: 4.1.1.01.0187 | I87: DIRETORIA - PJ | R87: -24435.64
A88: 189 | D88: 4.1.1.02.0189 | I88: ADMINISTRACAO - CLT | R88: -12277.53
A89: 190 | D89: 4.1.1.02.0190 | I89: EXPEDICAO - CLT | R89: -5760.57
A90: 193 | D90: 4.1.1.02.0193 | I90: DIVERSOS | R90: -209.54
A91: 530 | D91: 4.1.1.02.0530 | I91: SALARIO DE FERIAS - ADMINISTRACAO | R91: -2240.18
A92: 531 | D92: 4.1.1.02.0531 | I92: 13 SALARIO - ADMINISTRACAO | R92: -730.45
A93: 195 | D93: 4.1.1.03.0195 | I93: INSS - ADMINISTRATIVO | R93: -4779
A94: 196 | D94: 4.1.1.03.0196 | I94: FGTS - ADMINISTRATIVO | R94: -1453.7
... A105: 203 | D105: 4.1.1.04.0203 | I105: VALE CESTA BASICA | R105: -1505
H106: ALUGUEL E CONDOMÍNIO | R106: -23498.33
A107: 229 | D107: 4.3.1.01.0229 | I107: ALUGUEIS | R107: -23498.33
H108: CONTABILIDADE | R108: -11331
A109: 214 | D109: 4.3.1.01.0214 | I109: SERVICOS CONTABEIS E AFINS | R109: -11331
H110: OUTRAS PRESTACAO DE SERVIÇO | R110: -11008
A111: 217 | D111: 4.3.1.01.0217 | I111: DESPESAS C/PRESTACAO DE SERVICOS - PJ | R111: -11008
H112: ENERGIA ELÉTRICA, ÁGUA E ESGOTO E INTERNET | R112: -4729.31
A113: 219 | D113: 4.3.1.01.0219 | I113: ENERGIA ELETRICA | R113: -3552.75
A114: 220 | D114: 4.3.1.01.0220 | I114: AGUA E ESGOTO | R114: -888.38
A115: 233 | D115: 4.3.1.01.0233 | I115: INTERNET | R115: -288.18
H116: SISTEMAS E FERRAMENTAS ADMINISTRATIVAS | R116: -31565.07
A117: 244 | D117: 4.3.1.01.0244 | I117: DESPESAS COM INFORMATICA / SISTEMAS / SOFTWARES | R117: -31565.07
H118: TARIFAS BANCÁRIAS | R118: -615.47
A119: 252 | D119: 4.3.1.03.0252 | I119: DESPESAS BANCARIAS | R119: -615.47
H120: OUTROS | R120: -14461.89
...

Sheet Relatorio
A1: Empresa: | D1: ASSOCIAÇÃO EDITORA PRESBITERIANA DE PINHEIROS | X1: Página: | Y1: 1
A2: C.N.P.J.: | D2: 40.804.477/0001-44
A4: DEMONSTRAÇÃO DO RESULTADO DO PERÍODO EM 2025
A6: Descrição | I6: 45658 | J6: 45689 | K6: 45717 | L6: 45748 | M6: 45778 | N6: 45809 | O6: 45839 | P6: 45870 | Q6: 45901 | R6: 45931 | S6: 45962 | T6: 45992 | V6: 46023 | W6: 46054 | Y6: 2026
A7: RECEITA COM VENDAS | I7: =SUMIF(Planilha1!$H$1:$H$110,A7,Planilha1!$R$1:$R$150) -> 495905.57 | J7: =SUMIF(Planilha2!$H$1:$H$110,A7,Planilha2!$R$1:$R$150) -> 418702.3 | K7: =SUMIF(Planilha3!$H$1:$H$110,A7,Planilha3!$R$1:$R$150) -> 467954.66 | L7: =SUMIF(Planilha4!$H$1:$H$110,A7,Planilha4!$R$1:$R$150) -> 388073.88 | M7: =SUMIF(Planilha5!$H$1:$H$110,A7,Planilha5!$R$1:$R$150) -> 503039.55 | N7: =SUMIF(Planilha6!$H$1:$H$110,A7,Planilha6!$R$1:$R$150) -> 347333.52 | O7: =SUMIF(Planilha7!$H$1:$H$110,A7,Planilha7!$R$1:$R$150) -> 316622.52 | P7: =SUMIF(Planilha8!$H$1:$H$110,A7,Planilha8!$R$1:$R$150) -> 393480.25 | Q7: =SUMIF(Planilha9!$H$1:$H$110,A7,Planilha9!$R$1:$R$150) -> 365887.99 | R7: =SUMIF(Planilha10!$H$1:$H$110,A7,Planilha10!$R$1:$R$150) -> 581307.37 | S7: =SUMIF(Planilha11!$H$1:$H$110,A7,Planilha11!$R$1:$R$150) -> 721066.96 | T7: =SUMIF(Planilha12!$H$1:$H$110,A7,Planilha12!$R$1:$R$150) -> 891397.91 | V7: =SUMIF(Planilha13!$H$1:$H$110,A7,Planilha13!$R$1:$R$150) -> 689636.36 | W7: =SUMIF(Planilha14!$H$1:$H$110,A7,Planilha14!$R$1:$R$150) -> 532921.71 | Y7: =SUMIF('2026'!$H$1:$H$110,A7,'2026'!$R$1:$R$150) -> 1222558.1 | Z7: =SUM(V7:W7)-Y7 -> 0
B8: ATACADO | I8: =SUMIF(Planilha1!$I$1:$I$150,B8,Planilha1!$R$1:RL$150) -> 254042.11 | J8: =SUMIF(Planilha2!$I$1:$I$150,B8,Planilha2!$R$1:RM$150) -> 164622.6 | K8: =SUMIF(Planilha3!$I$1:$I$150,B8,Planilha3!$R$1:RN$150) -> 193567.41 | L8: =SUMIF(Planilha4!$I$1:$I$150,B8,Planilha4!$R$1:RO$150) -> 132575.25 | M8: =SUMIF(Planilha5!$I$1:$I$150,B8,Planilha5!$R$1:RP$150) -> 219556.41 | N8: =SUMIF(Planilha6!$I$1:$I$150,B8,Planilha6!$R$1:RQ$150) -> 60852.57 | O8: =SUMIF(Planilha7!$I$1:$I$150,B8,Planilha7!$R$1:RR$150) -> 60934.28 | P8: =SUMIF(Planilha8!$I$1:$I$150,B8,Planilha8!$R$1:RS$150) -> 67772.31 | Q8: =SUMIF(Planilha9!$I$1:$I$150,B8,Planilha9!$R$1:RT$150) -> 119355.57 | R8: =SUMIF(Planilha10!$I$1:$I$150,B8,Planilha10!$R$1:RU$150) -> 103628.97 | S8: =SUMIF(Planilha11!$I$1:$I$150,B8,Planilha11!$R$1:RV$150) -> 81748.93 | T8: =SUMIF(Planilha12!$I$1:$I$150,B8,Planilha12!$R$1:RW$150) -> 302775.76 | V8: =SUMIF(Planilha13!$I$1:$I$150,B8,Planilha13!$R$1:RY$150) -> 296951.19 | W8: =SUMIF(Planilha14!$I$1:$I$150,B8,Planilha14!$R$1:RZ$150) -> 196602.12 | Y8: =SUMIF('2026'!$I$1:$I$150,B8,'2026'!$R$1:RQ$150) -> 493553.31 | Z8: =SUM(V8:W8)-Y8 -> 0
B9: ECOMMERCE | I9: =SUMIF(Planilha1!$I$1:$I$150,B9,Planilha1!$R$1:RL$150) -> 163266.31 | J9: =SUMIF(Planilha2!$I$1:$I$150,B9,Planilha2!$R$1:RM$150) -> 128055.93 | K9: =SUMIF(Planilha3!$I$1:$I$150,B9,Planilha3!$R$1:RN$150) -> 164134.17 | L9: =SUMIF(Planilha4!$I$1:$I$150,B9,Planilha4!$R$1:RO$150) -> 161518.87 | M9: =SUMIF(Planilha5!$I$1:$I$150,B9,Planilha5!$R$1:RP$150) -> 167517.93 | N9: =SUMIF(Planilha6!$I$1:$I$150,B9,Planilha6!$R$1:RQ$150) -> 173821.57 | O9: =SUMIF(Planilha7!$I$1:$I$150,B9,Planilha7!$R$1:RR$150) -> 158614.03 | P9: =SUMIF(Planilha8!$I$1:$I$150,B9,Planilha8!$R$1:RS$150) -> 183185.27 | Q9: =SUMIF(Planilha9!$I$1:$I$150,B9,Planilha9!$R$1:RT$150) -> 128905.32 | R9: =SUMIF(Planilha10!$I$1:$I$150,B9,Planilha10!$R$1:RU$150) -> 362077.95 | S9: =SUMIF(Planilha11!$I$1:$I$150,B9,Planilha11!$R$1:RV$150) -> 337371.61 | T9: =SUMIF(Planilha12!$I$1:$I$150,B9,Planilha12!$R$1:RW$150) -> 451807.46 | V9: =SUMIF(Planilha13!$I$1:$I$150,B9,Planilha13!$R$1:RY$150) -> 301545.85 | W9: =SUMIF(Planilha14!$I$1:$I$150,B9,Planilha14!$R$1:RZ$150) -> 211081.53 | Y9: =SUMIF('2026'!$I$1:$I$150,B9,'2026'!$R$1:RQ$150) -> 512627.38 | Z9: =SUM(V9:W9)-Y9 -> 0
B10: EVENTO | I10: =SUMIF(Planilha1!$I$1:$I$150,B10,Planilha1!$R$1:RL$150) -> 0 | J10: =SUMIF(Planilha2!$I$1:$I$150,B10,Planilha2!$R$1:RM$150) -> 47047.21 | K10: =SUMIF(Planilha3!$I$1:$I$150,B10,Planilha3!$R$1:RN$150) -> 20118.81 | L10: =SUMIF(Planilha4!$I$1:$I$150,B10,Planilha4!$R$1:RO$150) -> 1613.05 | M10: =SUMIF(Planilha5!$I$1:$I$150,B10,Planilha5!$R$1:RP$150) -> 2953.61 | N10: =SUMIF(Planilha6!$I$1:$I$150,B10,Planilha6!$R$1:RQ$150) -> 4466.5 | O10: =SUMIF(Planilha7!$I$1:$I$150,B10,Planilha7!$R$1:RR$150) -> 193.79 | P10: =SUMIF(Planilha8!$I$1:$I$150,B10,Planilha8!$R$1:RS$150) -> 5920.9 | Q10: =SUMIF(Planilha9!$I$1:$I$150,B10,Planilha9!$R$1:RT$150) -> 2022.62 | R10: =SUMIF(Planilha10!$I$1:$I$150,B10,Planilha10!$R$1:RU$150) -> 0 | S10: =SUMIF(Planilha11!$I$1:$I$150,B10,Planilha11!$R$1:RV$150) -> 139352.76 | T10: =SUMIF(Planilha12!$I$1:$I$150,B10,Planilha12!$R$1:RW$150) -> 0 | V10: =SUMIF(Planilha13!$I$1:$I$150,B10,Planilha13!$R$1:RY$150) -> 0 | W10: =SUMIF(Planilha14!$I$1:$I$150,B10,Planilha14!$R$1:RZ$150) -> 2312.7 | Y10: =SUMIF('2026'!$I$1:$I$150,B10,'2026'!$R$1:RQ$150) -> 2312.7 | Z10: =SUM(V10:W10)-Y10 -> 0
B11: LIVRARIA | I11: =SUMIF(Planilha1!$I$1:$I$150,B11,Planilha1!$R$1:RL$150) -> 78597.15 | J11: =SUMIF(Planilha2!$I$1:$I$150,B11,Planilha2!$R$1:RM$150) -> 78976.56 | K11: =SUMIF(Planilha3!$I$1:$I$150,B11,Planilha3!$R$1:RN$150) -> 90134.27 | L11: =SUMIF(Planilha4!$I$1:$I$150,B11,Planilha4!$R$1:RO$150) -> 92366.71 | M11: =SUMIF(Planilha5!$I$1:$I$150,B11,Planilha5!$R$1:RP$150) -> 113011.6 | N11: =SUMIF(Planilha6!$I$1:$I$150,B11,Planilha6!$R$1:RQ$150) -> 108192.88 | O11: =SUMIF(Planilha7!$I$1:$I$150,B11,Planilha7!$R$1:RR$150) -> 96573.67 | P11: =SUMIF(Planilha8!$I$1:$I$150,B11,Planilha8!$R$1:RS$150) -> 132362.67 | Q11: =SUMIF(Planilha9!$I$1:$I$150,B11,Planilha9!$R$1:RT$150) -> 108371.46 | R11: =SUMIF(Planilha10!$I$1:$I$150,B11,Planilha10!$R$1:RU$150) -> 114754.37 | S11: =SUMIF(Planilha11!$I$1:$I$150,B11,Planilha11!$R$1:RV$150) -> 159575.85 | T11: =SUMIF(Planilha12!$I$1:$I$150,B11,Planilha12!$R$1:RW$150) -> 135979.09 | V11: =SUMIF(Planilha13!$I$1:$I$150,B11,Planilha13!$R$1:RY$150) -> 90172.44 | W11: =SUMIF(Planilha14!$I$1:$I$150,B11,Planilha14!$R$1:RZ$150) -> 121460.56 | Y11: =SUMIF('2026'!$I$1:$I$150,B11,'2026'!$R$1:RQ$150) -> 211633 | Z11: =SUM(V11:W11)-Y11 -> 0
B12: SHOWROOM | I12: =SUMIF(Planilha1!$I$1:$I$150,B12,Planilha1!$R$1:RL$150) -> 0 | J12: =SUMIF(Planilha2!$I$1:$I$150,B12,Planilha2!$R$1:RM$150) -> 0 | K12: =SUMIF(Planilha3!$I$1:$I$150,B12,Planilha3!$R$1:RN$150) -> 0 | L12: =SUMIF(Planilha4!$I$1:$I$150,B12,Planilha4!$R$1:RO$150) -> 0 | M12: =SUMIF(Planilha5!$I$1:$I$150,B12,Planilha5!$R$1:RP$150) -> 0 | N12: =SUMIF(Planilha6!$I$1:$I$150,B12,Planilha6!$R$1:RQ$150) -> 0 | O12: =SUMIF(Planilha7!$I$1:$I$150,B12,Planilha7!$R$1:RR$150) -> 306.75 | P12: =SUMIF(Planilha8!$I$1:$I$150,B12,Planilha8!$R$1:RS$150) -> 4239.1 | Q12: =SUMIF(Planilha9!$I$1:$I$150,B12,Planilha9!$R$1:RT$150) -> 7233.02 | R12: =SUMIF(Planilha10!$I$1:$I$150,B12,Planilha10!$R$1:RU$150) -> 846.08 | S12: =SUMIF(Planilha11!$I$1:$I$150,B12,Planilha11!$R$1:RV$150) -> 3017.81 | T12: =SUMIF(Planilha12!$I$1:$I$150,B12,Planilha12!$R$1:RW$150) -> 835.6 | V12: =SUMIF(Planilha13!$I$1:$I$150,B12,Planilha13!$R$1:RY$150) -> 966.88 | W12: =SUMIF(Planilha14!$I$1:$I$150,B12,Planilha14!$R$1:RZ$150) -> 1464.8 | Y12: =SUMIF('2026'!$I$1:$I$150,B12,'2026'!$R$1:RQ$150) -> 2431.68 | Z12: =SUM(V12:W12)-Y12 -> 0
A13: MARKETPLACES | I13: =SUMIF(Planilha1!$H$1:$H$110,A13,Planilha1!$R$1:$R$150) -> 13298.19 | J13: =SUMIF(Planilha2!$H$1:$H$110,A13,Planilha2!$R$1:$R$150) -> 4630.01 | K13: =SUMIF(Planilha3!$H$1:$H$110,A13,Planilha3!$R$1:$R$150) -> 28379.02 | L13: =SUMIF(Planilha4!$H$1:$H$110,A13,Planilha4!$R$1:$R$150) -> 22410.2 | M13: =SUMIF(Planilha5!$H$1:$H$110,A13,Planilha5!$R$1:$R$150) -> 14548.79 | N13: =SUMIF(Planilha6!$H$1:$H$110,A13,Planilha6!$R$1:$R$150) -> 32617.49 | O13: =SUMIF(Planilha7!$H$1:$H$110,A13,Planilha7!$R$1:$R$150) -> 52521.49 | P13: =SUMIF(Planilha8!$H$1:$H$110,A13,Planilha8!$R$1:$R$150) -> 102348.89 | Q13: =SUMIF(Planilha9!$H$1:$H$110,A13,Planilha9!$R$1:$R$150) -> 76825.93 | R13: =SUMIF(Planilha10!$H$1:$H$110,A13,Planilha10!$R$1:$R$150) -> 66278.9 | S13: =SUMIF(Planilha11!$H$1:$H$110,A13,Planilha11!$R$1:$R$150) -> 97895.65 | T13: =SUMIF(Planilha12!$H$1:$H$110,A13,Planilha12!$R$1:$R$150) -> 217313.13 | V13: =SUMIF(Planilha13!$H$1:$H$110,A13,Planilha13!$R$1:$R$150) -> 191702.95 | W13: =SUMIF(Planilha14!$H$1:$H$110,A13,Planilha14!$R$1:$R$150) -> 115473.06 | Y13: =SUMIF('2026'!$H$1:$H$110,A13,'2026'!$R$1:$R$150) -> 307176.01 | Z13: =SUM(V13:W13)-Y13 -> 0
B14: AMAZON | I14: =SUMIF(Planilha1!$I$1:$I$150,B14,Planilha1!$R$1:RL$150) -> 11612.4 | J14: =SUMIF(Planilha2!$I$1:$I$150,B14,Planilha2!$R$1:RM$150) -> 1393.5 | K14: =SUMIF(Planilha3!$I$1:$I$150,B14,Planilha3!$R$1:RN$150) -> 22701.73 | L14: =SUMIF(Planilha4!$I$1:$I$150,B14,Planilha4!$R$1:RO$150) -> 19863 | M14: =SUMIF(Planilha5!$I$1:$I$150,B14,Planilha5!$R$1:RP$150) -> 11019.65 | N14: =SUMIF(Planilha6!$I$1:$I$150,B14,Planilha6!$R$1:RQ$150) -> 11271.66 | O14: =SUMIF(Planilha7!$I$1:$I$150,B14,Planilha7!$R$1:RR$150) -> 5295.83 | P14: =SUMIF(Planilha8!$I$1:$I$150,B14,Planilha8!$R$1:RS$150) -> 12708.58 | Q14: =SUMIF(Planilha9!$I$1:$I$150,B14,Planilha9!$R$1:RT$150) -> 14195.45 | R14: =SUMIF(Planilha10!$I$1:$I$150,B14,Planilha10!$R$1:RU$150) -> 23873.87 | S14: =SUMIF(Planilha11!$I$1:$I$150,B14,Planilha11!$R$1:RV$150) -> 43014.56 | T14: =SUMIF(Planilha12!$I$1:$I$150,B14,Planilha12!$R$1:RW$150) -> 62324.86 | V14: =SUMIF(Planilha13!$I$1:$I$150,B14,Planilha13!$R$1:RY$150) -> 74979.08 | W14: =SUMIF(Planilha14!$I$1:$I$150,B14,Planilha14!$R$1:RZ$150) -> 26276.33 | Y14: =SUMIF('2026'!$I$1:$I$150,B14,'2026'!$R$1:RQ$150) -> 101255.41 | Z14: =SUM(V14:W14)-Y14 -> 0
B15: AMAZON FULL | I15: =SUMIF(Planilha1!$I$1:$I$150,B15,Planilha1!$R$1:RL$150) -> 0 | J15: =SUMIF(Planilha2!$I$1:$I$150,B15,Planilha2!$R$1:RM$150) -> 0 | K15: =SUMIF(Planilha3!$I$1:$I$150,B15,Planilha3!$R$1:RN$150) -> 0 | L15: =SUMIF(Planilha4!$I$1:$I$150,B15,Planilha4!$R$1:RO$150) -> 0 | M15: =SUMIF(Planilha5!$I$1:$I$150,B15,Planilha5!$R$1:RP$150) -> 0 | N15: =SUMIF(Planilha6!$I$1:$I$150,B15,Planilha6!$R$1:RQ$150) -> 0 | O15: =SUMIF(Planilha7!$I$1:$I$150,B15,Planilha7!$R$1:RR$150) -> 0 | P15: =SUMIF(Planilha8!$I$1:$I$150,B15,Planilha8!$R$1:RS$150) -> 5694 | Q15: =SUMIF(Planilha9!$I$1:$I$150,B15,Planilha9!$R$1:RT$150) -> 3145.7 | R15: =SUMIF(Planilha10!$I$1:$I$150,B15,Planilha10!$R$1:RU$150) -> 3145.7 | S15: =SUMIF(Planilha11!$I$1:$I$150,B15,Planilha11!$R$1:RV$150) -> 1229.1 | T15: =SUMIF(Planilha12!$I$1:$I$150,B15,Planilha12!$R$1:RW$150) -> 2091 | V15: =SUMIF(Planilha13!$I$1:$I$150,B15,Planilha13!$R$1:RY$150) -> 5813.6 | W15: =SUMIF(Planilha14!$I$1:$I$150,B15,Planilha14!$R$1:RZ$150) -> 4352.9 | Y15: =SUMIF('2026'!$I$1:$I$150,B15,'2026'!$R$1:RQ$150) -> 10166.5 | Z15: =SUM(V15:W15)-Y15 -> 0
B16: MERCADO LIVRE | I16: =SUMIF(Planilha1!$I$1:$I$150,B16,Planilha1!$R$1:RL$150) -> 1685.79 | J16: =SUMIF(Planilha2!$I$1:$I$150,B16,Planilha2!$R$1:RM$150) -> 3236.51 | K16: =SUMIF(Planilha3!$I$1:$I$150,B16,Planilha3!$R$1:RN$150) -> 5677.29 | L16: =SUMIF(Planilha4!$I$1:$I$150,B16,Planilha4!$R$1:RO$150) -> 2547.2 | M16: =SUMIF(Planilha5!$I$1:$I$150,B16,Planilha5!$R$1:RP$150) -> 3529.14 | N16: =SUMIF(Planilha6!$I$1:$I$150,B16,Planilha6!$R$1:RQ$150) -> 18965.25 | O16: =SUMIF(Planilha7!$I$1:$I$150,B16,Planilha7!$R$1:RR$150) -> 26286.41 | P16: =SUMIF(Planilha8!$I$1:$I$150,B16,Planilha8!$R$1:RS$150) -> 56458.35 | Q16: =SUMIF(Planilha9!$I$1:$I$150,B16,Planilha9!$R$1:RT$150) -> 36501 | R16: =SUMIF(Planilha10!$I$1:$I$150,B16,Planilha10!$R$1:RU$150) -> 17237.34 | S16: =SUMIF(Planilha11!$I$1:$I$150,B16,Planilha11!$R$1:RV$150) -> 34575.46 | T16: =SUMIF(Planilha12!$I$1:$I$150,B16,Planilha12!$R$1:RW$150) -> 143877.78 | V16: =SUMIF(Planilha13!$I$1:$I$150,B16,Planilha13!$R$1:RY$150) -> 108716.92 | W16: =SUMIF(Planilha14!$I$1:$I$150,B16,Planilha14!$R$1:RZ$150) -> 83583.13 | Y16: =SUMIF('2026'!$I$1:$I$150,B16,'2026'!$R$1:RQ$150) -> 192300.05 | Z16: =SUM(V16:W16)-Y16 -> 0
B17: FULL ML | I17: =SUMIF(Planilha1!$I$1:$I$150,B17,Planilha1!$R$1:RL$150) -> 0 | J17: =SUMIF(Planilha2!$I$1:$I$150,B17,Planilha2!$R$1:RM$150) -> 0 | K17: =SUMIF(Planilha3!$I$1:$I$150,B17,Planilha3!$R$1:RN$150) -> 0 | L17: =SUMIF(Planilha4!$I$1:$I$150,B17,Planilha4!$R$1:RO$150) -> 0 | M17: =SUMIF(Planilha5!$I$1:$I$150,B17,Planilha5!$R$1:RP$150) -> 0 | N17: =SUMIF(Planilha6!$I$1:$I$150,B17,Planilha6!$R$1:RQ$150) -> 2281.66 | O17: =SUMIF(Planilha7!$I$1:$I$150,B17,Planilha7!$R$1:RR$150) -> 20939.25 | P17: =SUMIF(Planilha8!$I$1:$I$150,B17,Planilha8!$R$1:RS$150) -> 27487.96 | Q17: =SUMIF(Planilha9!$I$1:$I$150,B17,Planilha9!$R$1:RT$150) -> 22983.78 | R17: =SUMIF(Planilha10!$I$1:$I$150,B17,Planilha10!$R$1:RU$150) -> 22021.99 | S17: =SUMIF(Planilha11!$I$1:$I$150,B17,Planilha11!$R$1:RV$150) -> 19076.53 | T17: =SUMIF(Planilha12!$I$1:$I$150,B17,Planilha12!$R$1:RW$150) -> 9019.49 | V17: =SUMIF(Planilha13!$I$1:$I$150,B17,Planilha13!$R$1:RY$150) -> 2193.35 | W17: =SUMIF(Planilha14!$I$1:$I$150,B17,Planilha14!$R$1:RZ$150) -> 1260.7 | Y17: =SUMIF('2026'!$I$1:$I$150,B17,'2026'!$R$1:RQ$150) -> 3454.05 | Z17: =SUM(V17:W17)-Y17 -> 0
B18: TIKTOK | I18: =SUMIF(Planilha1!$I$1:$I$150,B18,Planilha1!$R$1:RL$150) -> 0 | J18: =SUMIF(Planilha2!$I$1:$I$150,B18,Planilha2!$R$1:RM$150) -> 0 | K18: =SUMIF(Planilha3!$I$1:$I$150,B18,Planilha3!$R$1:RN$150) -> 0 | L18: =SUMIF(Planilha4!$I$1:$I$150,B18,Planilha4!$R$1:RO$150) -> 0 | M18: =SUMIF(Planilha5!$I$1:$I$150,B18,Planilha5!$R$1:RP$150) -> 0 | N18: =SUMIF(Planilha6!$I$1:$I$150,B18,Planilha6!$R$1:RQ$150) -> 98.92 | O18: =SUMIF(Planilha7!$I$1:$I$150,B18,Planilha7!$R$1:RR$150) -> 0 | P18: =SUMIF(Planilha8!$I$1:$I$150,B18,Planilha8!$R$1:RS$150) -> 0 | Q18: =SUMIF(Planilha9!$I$1:$I$150,B18,Planilha9!$R$1:RT$150) -> 0 | R18: =SUMIF(Planilha10!$I$1:$I$150,B18,Planilha10!$R$1:RU$150) -> 0 | S18: =SUMIF(Planilha11!$I$1:$I$150,B18,Planilha11!$R$1:RV$150) -> 0 | T18: =SUMIF(Planilha12!$I$1:$I$150,B18,Planilha12!$R$1:RW$150) -> 0 | V18: =SUMIF(Planilha13!$I$1:$I$150,B18,Planilha13!$R$1:RY$150) -> 0 | W18: =SUMIF(Planilha14!$I$1:$I$150,B18,Planilha14!$R$1:RZ$150) -> 0 | Y18: =SUMIF('2026'!$I$1:$I$150,B18,'2026'!$R$1:RQ$150) -> 0 | Z18: =SUM(V18:W18)-Y18 -> 0
A19: TOTAL RECEITA BRUTA COM VENDAS | I19: =SUMIF(Planilha1!$H$1:$H$110,A19,Planilha1!$R$1:$R$150) -> 509203.76 | J19: =SUMIF(Planilha2!$H$1:$H$110,A19,Planilha2!$R$1:$R$150) -> 423332.31 | K19: =SUMIF(Planilha3!$H$1:$H$110,A19,Planilha3!$R$1:$R$150) -> 496333.68 | L19: =SUMIF(Planilha4!$H$1:$H$110,A19,Planilha4!$R$1:$R$150) -> 410484.08 | M19: =SUMIF(Planilha5!$H$1:$H$110,A19,Planilha5!$R$1:$R$150) -> 517588.34 | N19: =SUMIF(Planilha6!$H$1:$H$110,A19,Planilha6!$R$1:$R$150) -> 379951.01 | O19: =SUMIF(Planilha7!$H$1:$H$110,A19,Planilha7!$R$1:$R$150) -> 369144.01 | P19: =SUMIF(Planilha8!$H$1:$H$110,A19,Planilha8!$R$1:$R$150) -> 495829.14 | Q19: =SUMIF(Planilha9!$H$1:$H$110,A19,Planilha9!$R$1:$R$150) -> 442713.92 | R19: =SUMIF(Planilha10!$H$1:$H$110,A19,Planilha10!$R$1:$R$150) -> 647586.27 | S19: =SUMIF(Planilha11!$H$1:$H$110,A19,Planilha11!$R$1:$R$150) -> 818962.61 | T19: =SUMIF(Planilha12!$H$1:$H$110,A19,Planilha12!$R$1:$R$150) -> 1108711 | V19: =SUMIF(Planilha13!$H$1:$H$110,A19,Planilha13!$R$1:$R$150) -> 881339.31 | W19: =SUMIF(Planilha14!$H$1:$H$110,A19,Planilha14!$R$1:$R$150) -> 648394.77 | Y19: =SUMIF('2026'!$H$1:$H$110,A19,'2026'!$R$1:$R$150) -> 1529734.1 | Z19: =SUM(V19:W19)-Y19 -> 0
Z20: =SUM(V20:W20)-Y20 -> 0
A21: DEVOLUÇÃO E DESCONTO DE VENDAS | I21: =SUMIF(Planilha1!$H$1:$H$110,A21,Planilha1!$R$1:$R$150) -> -318.25 | J21: =SUMIF(Planilha2!$H$1:$H$110,A21,Planilha2!$R$1:$R$150) -> -743.82 | K21: =SUMIF(Planilha3!$H$1:$H$110,A21,Planilha3!$R$1:$R$150) -> -109.63 | L21: =SUMIF(Planilha4!$H$1:$H$110,A21,Planilha4!$R$1:$R$150) -> -967.46 | M21: =SUMIF(Planilha5!$H$1:$H$110,A21,Planilha5!$R$1:$R$150) -> -569.8 | N21: =SUMIF(Planilha6!$H$1:$H$110,A21,Planilha6!$R$1:$R$150) -> -1607.93 | O21: =SUMIF(Planilha7!$H$1:$H$110,A21,Planilha7!$R$1:$R$150) -> -3996.41 | P21: =SUMIF(Planilha8!$H$1:$H$110,A21,Planilha8!$R$1:$R$150) -> -4964.76 | Q21: =SUMIF(Planilha9!$H$1:$H$110,A21,Planilha9!$R$1:$R$150) -> -5299.1 | R21: =SUMIF(Planilha10!$H$1:$H$110,A21,Planilha10!$R$1:$R$150) -> -1467.16 | S21: =SUMIF(Planilha11!$H$1:$H$110,A21,Planilha11!$R$1:$R$150) -> -2839.49 | T21: =SUMIF(Planilha12!$H$1:$H$110,A21,Planilha12!$R$1:$R$150) -> -4693.04 | V21: =SUMIF(Planilha13!$H$1:$H$110,A21,Planilha13!$R$1:$R$150) -> -5995.25 | W21: =SUMIF(Planilha14!$H$1:$H$110,A21,Planilha14!$R$1:$R$150) -> -1321.6 | Y21: =SUMIF('2026'!$H$1:$H$110,A21,'2026'!$R$1:$R$150) -> -7316.85 | Z21: =SUM(V21:W21)-Y21 -> 0
B22: DEVOLUCAO DE VENDAS | I22: =SUMIF(Planilha1!$I$1:$I$150,B22,Planilha1!$R$1:RL$150) -> -296.45 | J22: =SUMIF(Planilha2!$I$1:$I$150,B22,Planilha2!$R$1:RM$150) -> -743.82 | K22: =SUMIF(Planilha3!$I$1:$I$150,B22,Planilha3!$R$1:RN$150) -> -109.63 | L22: =SUMIF(Planilha4!$I$1:$I$150,B22,Planilha4!$R$1:RO$150) -> -967.46 | M22: =SUMIF(Planilha5!$I$1:$I$150,B22,Planilha5!$R$1:RP$150) -> -569.8 | N22: =SUMIF(Planilha6!$I$1:$I$150,B22,Planilha6!$R$1:RQ$150) -> -1607.93 | O22: =SUMIF(Planilha7!$I$1:$I$150,B22,Planilha7!$R$1:RR$150) -> -3996.41 | P22: =SUMIF(Planilha8!$I$1:$I$150,B22,Planilha8!$R$1:RS$150) -> -4964.76 | Q22: =SUMIF(Planilha9!$I$1:$I$150,B22,Planilha9!$R$1:RT$150) -> -5299.1 | R22: =SUMIF(Planilha10!$I$1:$I$150,B22,Planilha10!$R$1:RU$150) -> -1467.16 | S22: =SUMIF(Planilha11!$I$1:$I$150,B22,Planilha11!$R$1:RV$150) -> -2839.49 | T22: =SUMIF(Planilha12!$I$1:$I$150,B22,Planilha12!$R$1:RW$150) -> -4693.04 | V22: =SUMIF(Planilha13!$I$1:$I$150,B22,Planilha13!$R$1:RY$150) -> -5995.25 | W22: =SUMIF(Planilha14!$I$1:$I$150,B22,Planilha14!$R$1:RZ$150) -> -1321.6 | Y22: =SUMIF('2026'!$I$1:$I$150,B22,'2026'!$R$1:RQ$150) -> -7316.85 | Z22: =SUM(V22:W22)-Y22 -> 0
B23: DESCONTO SOBRE VENDAS | I23: =SUMIF(Planilha1!$I$1:$I$150,B23,Planilha1!$R$1:RL$150) -> -21.8 | J23: =SUMIF(Planilha2!$I$1:$I$150,B23,Planilha2!$R$1:RM$150) -> 0 | K23: =SUMIF(Planilha3!$I$1:$I$150,B23,Planilha3!$R$1:RN$150) -> 0 | L23: =SUMIF(Planilha4!$I$1:$I$150,B23,Planilha4!$R$1:RO$150) -> 0 | M23: =SUMIF(Planilha5!$I$1:$I$150,B23,Planilha5!$R$1:RP$150) -> 0 | N23: =SUMIF(Planilha6!$I$1:$I$150,B23,Planilha6!$R$1:RQ$150) -> 0 | O23: =SUMIF(Planilha7!$I$1:$I$150,B23,Planilha7!$R$1:RR$150) -> 0 | P23: =SUMIF(Planilha8!$I$1:$I$150,B23,Planilha8!$R$1:RS$150) -> 0 | Q23: =SUMIF(Planilha9!$I$1:$I$150,B23,Planilha9!$R$1:RT$150) -> 0 | R23: =SUMIF(Planilha10!$I$1:$I$150,B23,Planilha10!$R$1:RU$150) -> 0 | S23: =SUMIF(Planilha11!$I$1:$I$150,B23,Planilha11!$R$1:RV$150) -> 0 | T23: =SUMIF(Planilha12!$I$1:$I$150,B23,Planilha12!$R$1:RW$150) -> 0 | V23: =SUMIF(Planilha13!$I$1:$I$150,B23,Planilha13!$R$1:RY$150) -> 0 | W23: =SUMIF(Planilha14!$I$1:$I$150,B23,Planilha14!$R$1:RZ$150) -> 0 | Y23: =SUMIF('2026'!$I$1:$I$150,B23,'2026'!$R$1:RQ$150) -> 0 | Z23: =SUM(V23:W23)-Y23 -> 0
A24: RECEITA LÍQUIDA DE VENDAS | I24: =SUMIF(Planilha1!$H$1:$H$110,A24,Planilha1!$R$1:$R$150) -> 508885.51 | J24: =SUMIF(Planilha2!$H$1:$H$110,A24,Planilha2!$R$1:$R$150) -> 422588.49 | K24: =SUMIF(Planilha3!$H$1:$H$110,A24,Planilha3!$R$1:$R$150) -> 496224.05 | L24: =SUMIF(Planilha4!$H$1:$H$110,A24,Planilha4!$R$1:$R$150) -> 409516.62 | M24: =SUMIF(Planilha5!$H$1:$H$110,A24,Planilha5!$R$1:$R$150) -> 517018.54 | N24: =SUMIF(Planilha6!$H$1:$H$110,A24,Planilha6!$R$1:$R$150) -> 378343.08 | O24: =SUMIF(Planilha7!$H$1:$H$110,A24,Planilha7!$R$1:$R$150) -> 365147.6 | P24: =SUMIF(Planilha8!$H$1:$H$110,A24,Planilha8!$R$1:$R$150) -> 490864.38 | Q24: =SUMIF(Planilha9!$H$1:$H$110,A24,Planilha9!$R$1:$R$150) -> 437414.82 | R24: =SUMIF(Planilha10!$H$1:$H$110,A24,Planilha10!$R$1:$R$150) -> 646119.11 | S24: =SUMIF(Planilha11!$H$1:$H$110,A24,Planilha11!$R$1:$R$150) -> 816123.12 | T24: =SUMIF(Planilha12!$H$1:$H$110,A24,Planilha12!$R$1:$R$150) -> 1104018 | V24: =SUMIF(Planilha13!$H$1:$H$110,A24,Planilha13!$R$1:$R$150) -> 875344.06 | W24: =SUMIF(Planilha14!$H$1:$H$110,A24,Planilha14!$R$1:$R$150) -> 647073.17 | Y24: =SUMIF('2026'!$H$1:$H$110,A24,'2026'!$R$1:$R$150) -> 1522417.2 | Z24: =SUM(V24:W24)-Y24 -> 0
Z25: =SUM(V25:W25)-Y25 -> 0
A26: FRETE COBRADO DOS CLIENTES | I26: =SUMIF(Planilha1!$H$1:$H$110,A26,Planilha1!$R$1:$R$150) -> 35417.32 | J26: =SUMIF(Planilha2!$H$1:$H$110,A26,Planilha2!$R$1:$R$150) -> 25291.83 | K26: =SUMIF(Planilha3!$H$1:$H$110,A26,Planilha3!$R$1:$R$150) -> 29999.19 | L26: =SUMIF(Planilha4!$H$1:$H$110,A26,Planilha4!$R$1:$R$150) -> 29685.64 | M26: =SUMIF(Planilha5!$H$1:$H$110,A26,Planilha5!$R$1:$R$150) -> 34698.87 | N26: =SUMIF(Planilha6!$H$1:$H$110,A26,Planilha6!$R$1:$R$150) -> 26661.5 | O26: =SUMIF(Planilha7!$H$1:$H$110,A26,Planilha7!$R$1:$R$150) -> 25319.27 | P26: =SUMIF(Planilha8!$H$1:$H$110,A26,Planilha8!$R$1:$R$150) -> 27185.91 | Q26: =SUMIF(Planilha9!$H$1:$H$110,A26,Planilha9!$R$1:$R$150) -> 20968.57 | R26: =SUMIF(Planilha10!$H$1:$H$110,A26,Planilha10!$R$1:$R$150) -> 34011.27 | S26: =SUMIF(Planilha11!$H$1:$H$110,A26,Planilha11!$R$1:$R$150) -> 41078.72 | T26: =SUMIF(Planilha12!$H$1:$H$110,A26,Planilha12!$R$1:$R$150) -> 70994.15 | V26: =SUMIF(Planilha13!$H$1:$H$110,A26,Planilha13!$R$1:$R$150) -> 57972.3 | W26: =SUMIF(Planilha14!$H$1:$H$110,A26,Planilha14!$R$1:$R$150) -> 43241.57 | Y26: =SUMIF('2026'!$H$1:$H$110,A26,'2026'!$R$1:$R$150) -> 101213.87 | Z26: =SUM(V26:W26)-Y26 -> 0
B27: FRETES COBRADOS DOS CLIENTES | I27: =SUMIF(Planilha1!$I$1:$I$150,B27,Planilha1!$R$1:RL$150) -> 35417.32 | J27: =SUMIF(Planilha2!$I$1:$I$150,B27,Planilha2!$R$1:RM$150) -> 25291.83 | K27: =SUMIF(Planilha3!$I$1:$I$150,B27,Planilha3!$R$1:RN$150) -> 29999.19 | L27: =SUMIF(Planilha4!$I$1:$I$150,B27,Planilha4!$R$1:RO$150) -> 29685.64 | M27: =SUMIF(Planilha5!$I$1:$I$150,B27,Planilha5!$R$1:RP$150) -> 34698.87 | N27: =SUMIF(Planilha6!$I$1:$I$150,B27,Planilha6!$R$1:RQ$150) -> 26661.5 | O27: =SUMIF(Planilha7!$I$1:$I$150,B27,Planilha7!$R$1:RR$150) -> 25319.27 | P27: =SUMIF(Planilha8!$I$1:$I$150,B27,Planilha8!$R$1:RS$150) -> 27185.91 | Q27: =SUMIF(Planilha9!$I$1:$I$150,B27,Planilha9!$R$1:RT$150) -> 20968.57 | R27: =SUMIF(Planilha10!$I$1:$I$150,B27,Planilha10!$R$1:RU$150) -> 34011.27 | S27: =SUMIF(Planilha11!$I$1:$I$150,B27,Planilha11!$R$1:RV$150) -> 41078.72 | T27: =SUMIF(Planilha12!$I$1:$I$150,B27,Planilha12!$R$1:RW$150) -> 70994.15 | V27: =SUMIF(Planilha13!$I$1:$I$150,B27,Planilha13!$R$1:RY$150) -> 57972.3 | W27: =SUMIF(Planilha14!$I$1:$I$150,B27,Planilha14!$R$1:RZ$150) -> 43241.57 | Y27: =SUMIF('2026'!$I$1:$I$150,B27,'2026'!$R$1:RQ$150) -> 101213.87 | Z27: =SUM(V27:W27)-Y27 -> 0
A28: RECEITA OPERACIONAL TOTAL | I28: =SUMIF(Planilha1!$H$1:$H$110,A28,Planilha1!$R$1:$R$150) -> 544302.83 | J28: =SUMIF(Planilha2!$H$1:$H$110,A28,Planilha2!$R$1:$R$150) -> 447880.32 | K28: =SUMIF(Planilha3!$H$1:$H$110,A28,Planilha3!$R$1:$R$150) -> 526223.24 | L28: =SUMIF(Planilha4!$H$1:$H$110,A28,Planilha4!$R$1:$R$150) -> 439202.26 | M28: =SUMIF(Planilha5!$H$1:$H$110,A28,Planilha5!$R$1:$R$150) -> 551717.41 | N28: =SUMIF(Planilha6!$H$1:$H$110,A28,Planilha6!$R$1:$R$150) -> 405004.58 | O28: =SUMIF(Planilha7!$H$1:$H$110,A28,Planilha7!$R$1:$R$150) -> 390466.87 | P28: =SUMIF(Planilha8!$H$1:$H$110,A28,Planilha8!$R$1:$R$150) -> 518050.29 | Q28: =SUMIF(Planilha9!$H$1:$H$110,A28,Planilha9!$R$1:$R$150) -> 458383.39 | R28: =SUMIF(Planilha10!$H$1:$H$110,A28,Planilha10!$R$1:$R$150) -> 680130.38 | S28: =SUMIF(Planilha11!$H$1:$H$110,A28,Planilha11!$R$1:$R$150) -> 857201.84 | T28: =SUMIF(Planilha12!$H$1:$H$110,A28,Planilha12!$R$1:$R$150) -> 1175012.1 | V28: =SUMIF(Planilha13!$H$1:$H$110,A28,Planilha13!$R$1:$R$150) -> 933316.36 | W28: =SUMIF(Planilha14!$H$1:$H$110,A28,Planilha14!$R$1:$R$150) -> 690314.74 | Y28: =SUMIF('2026'!$H$1:$H$110,A28,'2026'!$R$1:$R$150) -> 1623631.1 | Z28: =SUM(V28:W28)-Y28 -> 0
Z29: =SUM(V29:W29)-Y29 -> 0
A30: CUSTO DOS PRODUTOS VENDIDOS (CPV/CMV) | I30: =SUMIF(Planilha1!$H$1:$H$110,A30,Planilha1!$R$1:$R$150) -> -229501.55 | J30: =SUMIF(Planilha2!$H$1:$H$110,A30,Planilha2!$R$1:$R$150) -> -205378.48 | K30: =SUMIF(Planilha3!$H$1:$H$110,A30,Planilha3!$R$1:$R$150) -> -262495.89 | L30: =SUMIF(Planilha4!$H$1:$H$110,A30,Planilha4!$R$1:$R$150) -> -216442.65 | M30: =SUMIF(Planilha5!$H$1:$H$110,A30,Planilha5!$R$1:$R$150) -> -316722.03 | N30: =SUMIF(Planilha6!$H$1:$H$110,A30,Planilha6!$R$1:$R$150) -> -128709.05 | O30: =SUMIF(Planilha7!$H$1:$H$110,A30,Planilha7!$R$1:$R$150) -> -119343.78 | P30: =SUMIF(Planilha8!$H$1:$H$110,A30,Planilha8!$R$1:$R$150) -> -197655.91 | Q30: =SUMIF(Planilha9!$H$1:$H$110,A30,Planilha9!$R$1:$R$150) -> -116814.82 | R30: =SUMIF(Planilha10!$H$1:$H$110,A30,Planilha10!$R$1:$R$150) -> -149255.1 | S30: =SUMIF(Planilha11!$H$1:$H$110,A30,Planilha11!$R$1:$R$150) -> -295912.48 | T30: =SUMIF(Planilha12!$H$1:$H$110,A30,Planilha12!$R$1:$R$150) -> -418644.32 | V30: =SUMIF(Planilha13!$H$1:$H$110,A30,Planilha13!$R$1:$R$150) -> -323061.98 | W30: =SUMIF(Planilha14!$H$1:$H$110,A30,Planilha14!$R$1:$R$150) -> -268554.6 | Y30: =SUMIF('2026'!$H$1:$H$110,A30,'2026'!$R$1:$R$150) -> -591616.58 | Z30: =SUM(V30:W30)-Y30 -> 0
B31: CUSTO DAS MERCADORIAS VENDIDAS | I31: =SUMIF(Planilha1!$I$1:$I$150,B31,Planilha1!$R$1:RL$150) -> -118537 | J31: =SUMIF(Planilha2!$I$1:$I$150,B31,Planilha2!$R$1:RM$150) -> -142495.37 | K31: =SUMIF(Planilha3!$I$1:$I$150,B31,Planilha3!$R$1:RN$150) -> -202408.68 | L31: =SUMIF(Planilha4!$I$1:$I$150,B31,Planilha4!$R$1:RO$150) -> -171775.47 | M31: =SUMIF(Planilha5!$I$1:$I$150,B31,Planilha5!$R$1:RP$150) -> -216281.18 | N31: =SUMIF(Planilha6!$I$1:$I$150,B31,Planilha6!$R$1:RQ$150) -> -126681.55 | O31: =SUMIF(Planilha7!$I$1:$I$150,B31,Planilha7!$R$1:RR$150) -> -116012.28 | P31: =SUMIF(Planilha8!$I$1:$I$150,B31,Planilha8!$R$1:RS$150) -> -187451.29 | Q31: =SUMIF(Planilha9!$I$1:$I$150,B31,Planilha9!$R$1:RT$150) -> -103605.83 | R31: =SUMIF(Planilha10!$I$1:$I$150,B31,Planilha10!$R$1:RU$150) -> -137158.93 | S31: =SUMIF(Planilha11!$I$1:$I$150,B31,Planilha11!$R$1:RV$150) -> -252632.58 | T31: =SUMIF(Planilha12!$I$1:$I$150,B31,Planilha12!$R$1:RW$150) -> -315364.95 | V31: =SUMIF(Planilha13!$I$1:$I$150,B31,Planilha13!$R$1:RY$150) -> -224504.78 | W31: =SUMIF(Planilha14!$I$1:$I$150,B31,Planilha14!$R$1:RZ$150) -> -226388.73 | Y31: =SUMIF('2026'!$I$1:$I$150,B31,'2026'!$R$1:RQ$150) -> -450893.51 | Z31: =SUM(V31:W31)-Y31 -> 0
B32: DIREITOS AUTORAIS | I32: =SUMIF(Planilha1!$I$1:$I$150,B32,Planilha1!$R$1:RL$150) -> -39097.27 | J32: =SUMIF(Planilha2!$I$1:$I$150,B32,Planilha2!$R$1:RM$150) -> -22144.59 | K32: =SUMIF(Planilha3!$I$1:$I$150,B32,Planilha3!$R$1:RN$150) -> -21519.93 | L32: =SUMIF(Planilha4!$I$1:$I$150,B32,Planilha4!$R$1:RO$150) -> -15091.45 | M32: =SUMIF(Planilha5!$I$1:$I$150,B32,Planilha5!$R$1:RP$150) -> -20504.68 | N32: =SUMIF(Planilha6!$I$1:$I$150,B32,Planilha6!$R$1:RQ$150) -> -1895.08 | O32: =SUMIF(Planilha7!$I$1:$I$150,B32,Planilha7!$R$1:RR$150) -> -2867.37 | P32: =SUMIF(Planilha8!$I$1:$I$150,B32,Planilha8!$R$1:RS$150) -> -8035.08 | Q32: =SUMIF(Planilha9!$I$1:$I$150,B32,Planilha9!$R$1:RT$150) -> -13208.99 | R32: =SUMIF(Planilha10!$I$1:$I$150,B32,Planilha10!$R$1:RU$150) -> -9114.17 | S32: =SUMIF(Planilha11!$I$1:$I$150,B32,Planilha11!$R$1:RV$150) -> -43279.9 | T32: =SUMIF(Planilha12!$I$1:$I$150,B32,Planilha12!$R$1:RW$150) -> -73809.99 | V32: =SUMIF(Planilha13!$I$1:$I$150,B32,Planilha13!$R$1:RY$150) -> -55662.56 | W32: =SUMIF(Planilha14!$I$1:$I$150,B32,Planilha14!$R$1:RZ$150) -> -24922.51 | Y32: =SUMIF('2026'!$I$1:$I$150,B32,'2026'!$R$1:RQ$150) -> -80585.07 | Z32: =SUM(V32:W32)-Y32 -> 0
B33: MATERIAIS APLICADOS NA VENDA DE PRODUTOS | I33: =SUMIF(Planilha1!$I$1:$I$150,B33,Planilha1!$R$1:RL$150) -> -2271.61 | J33: =SUMIF(Planilha2!$I$1:$I$150,B33,Planilha2!$R$1:RM$150) -> -1716.78 | K33: =SUMIF(Planilha3!$I$1:$I$150,B33,Planilha3!$R$1:RN$150) -> -4910.46 | L33: =SUMIF(Planilha4!$I$1:$I$150,B33,Planilha4!$R$1:RO$150) -> -2405.33 | M33: =SUMIF(Planilha5!$I$1:$I$150,B33,Planilha5!$R$1:RP$150) -> -281.7 | N33: =SUMIF(Planilha6!$I$1:$I$150,B33,Planilha6!$R$1:RQ$150) -> 0 | O33: =SUMIF(Planilha7!$I$1:$I$150,B33,Planilha7!$R$1:RR$150) -> 0 | P33: =SUMIF(Planilha8!$I$1:$I$150,B33,Planilha8!$R$1:RS$150) -> -2169.54 | Q33: =SUMIF(Planilha9!$I$1:$I$150,B33,Planilha9!$R$1:RT$150) -> 0 | R33: =SUMIF(Planilha10!$I$1:$I$150,B33,Planilha10!$R$1:RU$150) -> -2982 | S33: =SUMIF(Planilha11!$I$1:$I$150,B33,Planilha11!$R$1:RV$150) -> 0 | T33: =SUMIF(Planilha12!$I$1:$I$150,B33,Planilha12!$R$1:RW$150) -> 0 | V33: =SUMIF(Planilha13!$I$1:$I$150,B33,Planilha13!$R$1:RY$150) -> 0 | W33: =SUMIF(Planilha14!$I$1:$I$150,B33,Planilha14!$R$1:RZ$150) -> 0 | Y33: =SUMIF('2026'!$I$1:$I$150,B33,'2026'!$R$1:RQ$150) -> 0 | Z33: =SUM(V33:W33)-Y33 -> 0
B34: ROYALTIES EDITORIAIS E OUTROS | I34: =SUMIF(Planilha1!$I$1:$I$150,B34,Planilha1!$R$1:RL$150) -> -69595.67 | J34: =SUMIF(Planilha2!$I$1:$I$150,B34,Planilha2!$R$1:RM$150) -> -39021.74 | K34: =SUMIF(Planilha3!$I$1:$I$150,B34,Planilha3!$R$1:RN$150) -> -33656.82 | L34: =SUMIF(Planilha4!$I$1:$I$150,B34,Planilha4!$R$1:RO$150) -> -27170.4 | M34: =SUMIF(Planilha5!$I$1:$I$150,B34,Planilha5!$R$1:RP$150) -> -79654.47 | N34: =SUMIF(Planilha6!$I$1:$I$150,B34,Planilha6!$R$1:RQ$150) -> -132.42 | O34: =SUMIF(Planilha7!$I$1:$I$150,B34,Planilha7!$R$1:RR$150) -> -464.13 | P34: =SUMIF(Planilha8!$I$1:$I$150,B34,Planilha8!$R$1:RS$150) -> 0 | Q34: =SUMIF(Planilha9!$I$1:$I$150,B34,Planilha9!$R$1:RT$150) -> 0 | R34: =SUMIF(Planilha10!$I$1:$I$150,B34,Planilha10!$R$1:RU$150) -> 0 | S34: =SUMIF(Planilha11!$I$1:$I$150,B34,Planilha11!$R$1:RV$150) -> 0 | T34: =SUMIF(Planilha12!$I$1:$I$150,B34,Planilha12!$R$1:RW$150) -> -29469.38 | V34: =SUMIF(Planilha13!$I$1:$I$150,B34,Planilha13!$R$1:RY$150) -> -42894.64 | W34: =SUMIF(Planilha14!$I$1:$I$150,B34,Planilha14!$R$1:RZ$150) -> -17243.36 | Y34: =SUMIF('2026'!$I$1:$I$150,B34,'2026'!$R$1:RQ$150) -> -60138 | Z34: =SUM(V34:W34)-Y34 -> 0
A35: TOTAL CUSTO DOS PRODUTOS VENDIDOS | I35: =SUMIF(Planilha1!$H$1:$H$110,A35,Planilha1!$R$1:$R$150) -> -229501.55 | J35: =SUMIF(Planilha2!$H$1:$H$110,A35,Planilha2!$R$1:$R$150) -> -205378.48 | K35: =SUMIF(Planilha3!$H$1:$H$110,A35,Planilha3!$R$1:$R$150) -> -262495.89 | L35: =SUMIF(Planilha4!$H$1:$H$110,A35,Planilha4!$R$1:$R$150) -> -216442.65 | M35: =SUMIF(Planilha5!$H$1:$H$110,A35,Planilha5!$R$1:$R$150) -> -316722.03 | N35: =SUMIF(Planilha6!$H$1:$H$110,A35,Planilha6!$R$1:$R$150) -> -128709.05 | O35: =SUMIF(Planilha7!$H$1:$H$110,A35,Planilha7!$R$1:$R$150) -> -119343.78 | P35: =SUMIF(Planilha8!$H$1:$H$110,A35,Planilha8!$R$1:$R$150) -> -197655.91 | Q35: =SUMIF(Planilha9!$H$1:$H$110,A35,Planilha9!$R$1:$R$150) -> -116814.82 | R35: =SUMIF(Planilha10!$H$1:$H$110,A35,Planilha10!$R$1:$R$150) -> -149255.1 | S35: =SUMIF(Planilha11!$H$1:$H$110,A35,Planilha11!$R$1:$R$150) -> -295912.48 | T35: =SUMIF(Planilha12!$H$1:$H$110,A35,Planilha12!$R$1:$R$150) -> -418644.32 | V35: =SUMIF(Planilha13!$H$1:$H$110,A35,Planilha13!$R$1:$R$150) -> -323061.98 | W35: =SUMIF(Planilha14!$H$1:$H$110,A35,Planilha14!$R$1:$R$150) -> -268554.6 | Y35: =SUMIF('2026'!$H$1:$H$110,A35,'2026'!$R$1:$R$150) -> -591616.58 | Z35: =SUM(V35:W35)-Y35 -> 0
Z36: =SUM(V36:W36)-Y36 -> 0
A37: RECEITAS FINANCEIRAS | I37: =SUMIF(Planilha1!$H$1:$H$110,A37,Planilha1!$R$1:$R$150) -> 0 | J37: =SUMIF(Planilha2!$H$1:$H$110,A37,Planilha2!$R$1:$R$150) -> 0 | K37: =SUMIF(Planilha3!$H$1:$H$110,A37,Planilha3!$R$1:$R$150) -> 0 | L37: =SUMIF(Planilha4!$H$1:$H$110,A37,Planilha4!$R$1:$R$150) -> 10.49 | M37: =SUMIF(Planilha5!$H$1:$H$110,A37,Planilha5!$R$1:$R$150) -> 0 | N37: =SUMIF(Planilha6!$H$1:$H$110,A37,Planilha6!$R$1:$R$150) -> 4.16 | O37: =SUMIF(Planilha7!$H$1:$H$110,A37,Planilha7!$R$1:$R$150) -> 0.76 | P37: =SUMIF(Planilha8!$H$1:$H$110,A37,Planilha8!$R$1:$R$150) -> 3.2 | Q37: =SUMIF(Planilha9!$H$1:$H$110,A37,Planilha9!$R$1:$R$150) -> 3.21 | R37: =SUMIF(Planilha10!$H$1:$H$110,A37,Planilha10!$R$1:$R$150) -> 0 | S37: =SUMIF(Planilha11!$H$1:$H$110,A37,Planilha11!$R$1:$R$150) -> 1.69 | T37: =SUMIF(Planilha12!$H$1:$H$110,A37,Planilha12!$R$1:$R$150) -> 5.05 | V37: =SUMIF(Planilha13!$H$1:$H$110,A37,Planilha13!$R$1:$R$150) -> 40.59 | W37: =SUMIF(Planilha14!$H$1:$H$110,A37,Planilha14!$R$1:$R$150) -> 12.69 | Y37: =SUMIF('2026'!$H$1:$H$110,A37,'2026'!$R$1:$R$150) -> 53.28 | Z37: =SUM(V37:W37)-Y37 -> 0
B38: FUNDOS DIVERSOS | I38: =SUMIF(Planilha1!$I$1:$I$150,A38,Planilha1!$R$1:RL$150) -> 0 | J38: =SUMIF(Planilha2!$I$1:$I$150,B38,Planilha2!$R$1:RM$150) -> 0 | K38: =SUMIF(Planilha3!$I$1:$I$150,B38,Planilha3!$R$1:RN$150) -> 0 | L38: =SUMIF(Planilha4!$I$1:$I$150,B38,Planilha4!$R$1:RO$150) -> 10.49 | M38: =SUMIF(Planilha5!$I$1:$I$150,B38,Planilha5!$R$1:RP$150) -> 0 | N38: =SUMIF(Planilha6!$I$1:$I$150,B38,Planilha6!$R$1:RQ$150) -> 4.16 | O38: =SUMIF(Planilha7!$I$1:$I$150,B38,Planilha7!$R$1:RR$150) -> 0.76 | P38: =SUMIF(Planilha8!$I$1:$I$150,B38,Planilha8!$R$1:RS$150) -> 3.2 | Q38: =SUMIF(Planilha9!$I$1:$I$150,B38,Planilha9!$R$1:RT$150) -> 3.21 | R38: =SUMIF(Planilha10!$I$1:$I$150,B38,Planilha10!$R$1:RU$150) -> 0 | S38: =SUMIF(Planilha11!$I$1:$I$150,B38,Planilha11!$R$1:RV$150) -> 1.69 | T38: =SUMIF(Planilha12!$I$1:$I$150,B38,Planilha12!$R$1:RW$150) -> 5.05 | V38: =SUMIF(Planilha13!$I$1:$I$150,B38,Planilha13!$R$1:RY$150) -> 40.59 | W38: =SUMIF(Planilha14!$I$1:$I$150,B38,Planilha14!$R$1:RZ$150) -> 12.69 | Y38: =SUMIF('2026'!$I$1:$I$150,B38,'2026'!$R$1:RQ$150) -> 53.28 | Z38: =SUM(V38:W38)-Y38 -> 0
A39: OUTRAS RECEITAS | I39: =SUMIF(Planilha1!$H$1:$H$110,A39,Planilha1!$R$1:$R$150) -> 0 | J39: =SUMIF(Planilha2!$H$1:$H$110,A39,Planilha2!$R$1:$R$150) -> 0 | K39: =SUMIF(Planilha3!$H$1:$H$110,A39,Planilha3!$R$1:$R$150) -> 0 | L39: =SUMIF(Planilha4!$H$1:$H$110,A39,Planilha4!$R$1:$R$150) -> 0 | M39: =SUMIF(Planilha5!$H$1:$H$110,A39,Planilha5!$R$1:$R$150) -> 0 | N39: =SUMIF(Planilha6!$H$1:$H$110,A39,Planilha6!$R$1:$R$150) -> 8.9 | O39: =SUMIF(Planilha7!$H$1:$H$110,A39,Planilha7!$R$1:$R$150) -> 78.94 | P39: =SUMIF(Planilha8!$H$1:$H$110,A39,Planilha8!$R$1:$R$150) -> 352.76 | Q39: =SUMIF(Planilha9!$H$1:$H$110,A39,Planilha9!$R$1:$R$150) -> 3834.2 | R39: =SUMIF(Planilha10!$H$1:$H$110,A39,Planilha10!$R$1:$R$150) -> 1552.28 | S39: =SUMIF(Planilha11!$H$1:$H$110,A39,Planilha11!$R$1:$R$150) -> 260.45 | T39: =SUMIF(Planilha12!$H$1:$H$110,A39,Planilha12!$R$1:$R$150) -> 646.12 | V39: =SUMIF(Planilha13!$H$1:$H$110,A39,Planilha13!$R$1:$R$150) -> 1231.9 | W39: =SUMIF(Planilha14!$H$1:$H$110,A39,Planilha14!$R$1:$R$150) -> 1831.47 | Y39: =SUMIF('2026'!$H$1:$H$110,A39,'2026'!$R$1:$R$150) -> 3063.37 | Z39: =SUM(V39:W39)-Y39 -> 0
B40: OUTRAS RECEITAS | I40: =SUMIF(Planilha1!$I$1:$I$150,A40,Planilha1!$R$1:RL$150) -> 0 | J40: =SUMIF(Planilha2!$I$1:$I$150,B40,Planilha2!$R$1:RM$150) -> 0 | K40: =SUMIF(Planilha3!$I$1:$I$150,B40,Planilha3!$R$1:RN$150) -> 0 | L40: =SUMIF(Planilha4!$I$1:$I$150,B40,Planilha4!$R$1:RO$150) -> 0 | M40: =SUMIF(Planilha5!$I$1:$I$150,B40,Planilha5!$R$1:RP$150) -> 0 | N40: =SUMIF(Planilha6!$I$1:$I$150,B40,Planilha6!$R$1:RQ$150) -> 8.9 | O40: =SUMIF(Planilha7!$I$1:$I$150,B40,Planilha7!$R$1:RR$150) -> 78.94 | P40: =SUMIF(Planilha8!$I$1:$I$150,B40,Planilha8!$R$1:RS$150) -> 352.76 | Q40: =SUMIF(Planilha9!$I$1:$I$150,B40,Planilha9!$R$1:RT$150) -> 3834.2 | R40: =SUMIF(Planilha10!$I$1:$I$150,B40,Planilha10!$R$1:RU$150) -> 1552.28 | S40: =SUMIF(Planilha11!$I$1:$I$150,B40,Planilha11!$R$1:RV$150) -> 260.45 | T40: =SUMIF(Planilha12!$I$1:$I$150,B40,Planilha12!$R$1:RW$150) -> 646.12 | V40: =SUMIF(Planilha13!$I$1:$I$150,B40,Planilha13!$R$1:RY$150) -> 1231.9 | W40: =SUMIF(Planilha14!$I$1:$I$150,B40,Planilha14!$R$1:RZ$150) -> 1831.47 | Y40: =SUMIF('2026'!$I$1:$I$150,B40,'2026'!$R$1:RQ$150) -> 3063.37 | Z40: =SUM(V40:W40)-Y40 -> 0
A41: LUCRO BRUTO | I41: =SUMIF(Planilha1!$H$1:$H$110,A41,Planilha1!$R$1:$R$150) -> 314801.28 | J41: =SUMIF(Planilha2!$H$1:$H$110,A41,Planilha2!$R$1:$R$150) -> 242501.84 | K41: =SUMIF(Planilha3!$H$1:$H$110,A41,Planilha3!$R$1:$R$150) -> 263727.35 | L41: =SUMIF(Planilha4!$H$1:$H$110,A41,Planilha4!$R$1:$R$150) -> 222770.1 | M41: =SUMIF(Planilha5!$H$1:$H$110,A41,Planilha5!$R$1:$R$150) -> 234995.38 | N41: =SUMIF(Planilha6!$H$1:$H$110,A41,Planilha6!$R$1:$R$150) -> 276308.59 | O41: =SUMIF(Planilha7!$H$1:$H$110,A41,Planilha7!$R$1:$R$150) -> 271202.79 | P41: =SUMIF(Planilha8!$H$1:$H$110,A41,Planilha8!$R$1:$R$150) -> 320750.34 | Q41: =SUMIF(Planilha9!$H$1:$H$110,A41,Planilha9!$R$1:$R$150) -> 345405.98 | R41: =SUMIF(Planilha10!$H$1:$H$110,A41,Planilha10!$R$1:$R$150) -> 532427.56 | S41: =SUMIF(Planilha11!$H$1:$H$110,A41,Planilha11!$R$1:$R$150) -> 561551.5 | T41: =SUMIF(Planilha12!$H$1:$H$110,A41,Planilha12!$R$1:$R$150) -> 757019 | V41: =SUMIF(Planilha13!$H$1:$H$110,A41,Planilha13!$R$1:$R$150) -> 611526.87 | W41: =SUMIF(Planilha14!$H$1:$H$110,A41,Planilha14!$R$1:$R$150) -> 423604.3 | Y41: =SUMIF('2026'!$H$1:$H$110,A41,'2026'!$R$1:$R$150) -> 1035131.2 | Z41: =SUM(V41:W41)-Y41 -> 0
Z42: =SUM(V42:W42)-Y42 -> 0
A43: DESPESAS VARIÁVEIS COMERCIAIS | I43: =SUMIF(Planilha1!$H$1:$H$110,A43,Planilha1!$R$1:$R$150) -> -45438.63 | J43: =SUMIF(Planilha2!$H$1:$H$110,A43,Planilha2!$R$1:$R$150) -> -37315.23 | K43: =SUMIF(Planilha3!$H$1:$H$110,A43,Planilha3!$R$1:$R$150) -> -38241.74 | L43: =SUMIF(Planilha4!$H$1:$H$110,A43,Planilha4!$R$1:$R$150) -> -36743.93 | M43: =SUMIF(Planilha5!$H$1:$H$110,A43,Planilha5!$R$1:$R$150) -> -46248.31 | N43: =SUMIF(Planilha6!$H$1:$H$110,A43,Planilha6!$R$1:$R$150) -> -33737.16 | O43: =SUMIF(Planilha7!$H$1:$H$110,A43,Planilha7!$R$1:$R$150) -> -29155.49 | P43: =SUMIF(Planilha8!$H$1:$H$110,A43,Planilha8!$R$1:$R$150) -> -23752.08 | Q43: =SUMIF(Planilha9!$H$1:$H$110,A43,Planilha9!$R$1:$R$150) -> -32588.96 | R43: =SUMIF(Planilha10!$H$1:$H$110,A43,Planilha10!$R$1:$R$150) -> -43020.04 | S43: =SUMIF(Planilha11!$H$1:$H$110,A43,Planilha11!$R$1:$R$150) -> -69590.53 | T43: =SUMIF(Planilha12!$H$1:$H$110,A43,Planilha12!$R$1:$R$150) -> -99850.61 | V43: =SUMIF(Planilha13!$H$1:$H$110,A43,Planilha13!$R$1:$R$150) -> -72234.57 | W43: =SUMIF(Planilha14!$H$1:$H$110,A43,Planilha14!$R$1:$R$150) -> -41897.45 | Y43: =SUMIF('2026'!$H$1:$H$110,A43,'2026'!$R$1:$R$150) -> -114132.02 | Z43: =SUM(V43:W43)-Y43 -> 0
B44: FRETES SOBRE MERCADORIAS | I44: =SUMIF(Planilha1!$I$1:$I$150,B44,Planilha1!$R$1:RL$150) -> -38368.67 | J44: =SUMIF(Planilha2!$I$1:$I$150,B44,Planilha2!$R$1:RM$150) -> -32396.03 | K44: =SUMIF(Planilha3!$I$1:$I$150,B44,Planilha3!$R$1:RN$150) -> -30266.43 | L44: =SUMIF(Planilha4!$I$1:$I$150,B44,Planilha4!$R$1:RO$150) -> -31117.68 | M44: =SUMIF(Planilha5!$I$1:$I$150,B44,Planilha5!$R$1:RP$150) -> -39597.87 | N44: =SUMIF(Planilha6!$I$1:$I$150,B44,Planilha6!$R$1:RQ$150) -> -27086.72 | O44: =SUMIF(Planilha7!$I$1:$I$150,B44,Planilha7!$R$1:RR$150) -> -25733.24 | P44: =SUMIF(Planilha8!$I$1:$I$150,B44,Planilha8!$R$1:RS$150) -> -22182.95 | Q44: =SUMIF(Planilha9!$I$1:$I$150,B44,Planilha9!$R$1:RT$150) -> -20189.25 | R44: =SUMIF(Planilha10!$I$1:$I$150,B44,Planilha10!$R$1:RU$150) -> -29566.35 | S44: =SUMIF(Planilha11!$I$1:$I$150,B44,Planilha11!$R$1:RV$150) -> -42892.46 | T44: =SUMIF(Planilha12!$I$1:$I$150,B44,Planilha12!$R$1:RW$150) -> -57419.4 | V44: =SUMIF(Planilha13!$I$1:$I$150,B44,Planilha13!$R$1:RY$150) -> -55960.11 | W44: =SUMIF(Planilha14!$I$1:$I$150,B44,Planilha14!$R$1:RZ$150) -> -37902.87 | Y44: =SUMIF('2026'!$I$1:$I$150,B44,'2026'!$R$1:RQ$150) -> -93862.98 | Z44: =SUM(V44:W44)-Y44 -> 0
B45: COMISSOES POR VENDA | I45: =SUMIF(Planilha1!$I$1:$I$150,B45,Planilha1!$R$1:RL$150) -> -5380.07 | J45: =SUMIF(Planilha2!$I$1:$I$150,B45,Planilha2!$R$1:RM$150) -> -4301.18 | K45: =SUMIF(Planilha3!$I$1:$I$150,B45,Planilha3!$R$1:RN$150) -> -4108.25 | L45: =SUMIF(Planilha4!$I$1:$I$150,B45,Planilha4!$R$1:RO$150) -> -2657.31 | M45: =SUMIF(Planilha5!$I$1:$I$150,B45,Planilha5!$R$1:RP$150) -> -3650.44 | N45: =SUMIF(Planilha6!$I$1:$I$150,B45,Planilha6!$R$1:RQ$150) -> -3650.44 | O45: =SUMIF(Planilha7!$I$1:$I$150,B45,Planilha7!$R$1:RR$150) -> -104.79 | P45: =SUMIF(Planilha8!$I$1:$I$150,B45,Planilha8!$R$1:RS$150) -> -219.13 | Q45: =SUMIF(Planilha9!$I$1:$I$150,B45,Planilha9!$R$1:RT$150) -> -569.13 | R45: =SUMIF(Planilha10!$I$1:$I$150,B45,Planilha10!$R$1:RU$150) -> -2093.42 | S45: =SUMIF(Planilha11!$I$1:$I$150,B45,Planilha11!$R$1:RV$150) -> -2570.34 | T45: =SUMIF(Planilha12!$I$1:$I$150,B45,Planilha12!$R$1:RW$150) -> -3885.76 | V45: =SUMIF(Planilha13!$I$1:$I$150,B45,Planilha13!$R$1:RY$150) -> -7925.23 | W45: =SUMIF(Planilha14!$I$1:$I$150,B45,Planilha14!$R$1:RZ$150) -> -1397.61 | Y45: =SUMIF('2026'!$I$1:$I$150,B45,'2026'!$R$1:RQ$150) -> -9322.84 | Z45: =SUM(V45:W45)-Y45 -> 0
B46: DESPESAS REPRESENTACAO COMERCIAL | I46: =SUMIF(Planilha1!$I$1:$I$150,B46,Planilha1!$R$1:RL$150) -> -690.89 | J46: =SUMIF(Planilha2!$I$1:$I$150,B46,Planilha2!$R$1:RM$150) -> -165.05 | K46: =SUMIF(Planilha3!$I$1:$I$150,B46,Planilha3!$R$1:RN$150) -> 0 | L46: =SUMIF(Planilha4!$I$1:$I$150,B46,Planilha4!$R$1:RO$150) -> -969 | M46: =SUMIF(Planilha5!$I$1:$I$150,B46,Planilha5!$R$1:RP$150) -> 0 | N46: =SUMIF(Planilha6!$I$1:$I$150,B46,Planilha6!$R$1:RQ$150) -> 0 | O46: =SUMIF(Planilha7!$I$1:$I$150,B46,Planilha7!$R$1:RR$150) -> 0 | P46: =SUMIF(Planilha8!$I$1:$I$150,B46,Planilha8!$R$1:RS$150) -> 0 | Q46: =SUMIF(Planilha9!$I$1:$I$150,B46,Planilha9!$R$1:RT$150) -> 0 | R46: =SUMIF(Planilha10!$I$1:$I$150,B46,Planilha10!$R$1:RU$150) -> 0 | S46: =SUMIF(Planilha11!$I$1:$I$150,B46,Planilha11!$R$1:RV$150) -> 0 | T46: =SUMIF(Planilha12!$I$1:$I$150,B46,Planilha12!$R$1:RW$150) -> 0 | V46: =SUMIF(Planilha13!$I$1:$I$150,B46,Planilha13!$R$1:RY$150) -> 0 | W46: =SUMIF(Planilha14!$I$1:$I$150,B46,Planilha14!$R$1:RZ$150) -> 0 | Y46: =SUMIF('2026'!$I$1:$I$150,B46,'2026'!$R$1:RQ$150) -> 0 | Z46: =SUM(V46:W46)-Y46 -> 0
B47: BONUS POR RESULTADO | I47: =SUMIF(Planilha1!$I$1:$I$150,B47,Planilha1!$R$1:RL$150) -> 0 | J47: =SUMIF(Planilha2!$I$1:$I$150,B47,Planilha2!$R$1:RM$150) -> 0 | K47: =SUMIF(Planilha3!$I$1:$I$150,B47,Planilha3!$R$1:RN$150) -> -3000 | L47: =SUMIF(Planilha4!$I$1:$I$150,B47,Planilha4!$R$1:RO$150) -> 0 | M47: =SUMIF(Planilha5!$I$1:$I$150,B47,Planilha5!$R$1:RP$150) -> -3000 | N47: =SUMIF(Planilha6!$I$1:$I$150,B47,Planilha6!$R$1:RQ$150) -> -3000 | O47: =SUMIF(Planilha7!$I$1:$I$150,B47,Planilha7!$R$1:RR$150) -> -750 | P47: =SUMIF(Planilha8!$I$1:$I$150,B47,Planilha8!$R$1:RS$150) -> -1350 | Q47: =SUMIF(Planilha9!$I$1:$I$150,B47,Planilha9!$R$1:RT$150) -> -7509.27 | R47: =SUMIF(Planilha10!$I$1:$I$150,B47,Planilha10!$R$1:RU$150) -> -7284.27 | S47: =SUMIF(Planilha11!$I$1:$I$150,B47,Planilha11!$R$1:RV$150) -> -16501.75 | T47: =SUMIF(Planilha12!$I$1:$I$150,B47,Planilha12!$R$1:RW$150) -> -5430.92 | V47: =SUMIF(Planilha13!$I$1:$I$150,B47,Planilha13!$R$1:RY$150) -> -450 | W47: =SUMIF(Planilha14!$I$1:$I$150,B47,Planilha14!$R$1:RZ$150) -> -450 | Y47: =SUMIF('2026'!$I$1:$I$150,B47,'2026'!$R$1:RQ$150) -> -900 | Z47: =SUM(V47:W47)-Y47 -> 0
B48: EMBALAGENS E MATERIAS GRAFICOS | I48: =SUMIF(Planilha1!$I$1:$I$150,B48,Planilha1!$R$1:RL$150) -> -999 | J48: =SUMIF(Planilha2!$I$1:$I$150,B48,Planilha2!$R$1:RM$150) -> -452.97 | K48: =SUMIF(Planilha3!$I$1:$I$150,B48,Planilha3!$R$1:RN$150) -> -867.06 | L48: =SUMIF(Planilha4!$I$1:$I$150,B48,Planilha4!$R$1:RO$150) -> -1999.94 | M48: =SUMIF(Planilha5!$I$1:$I$150,B48,Planilha5!$R$1:RP$150) -> 0 | N48: =SUMIF(Planilha6!$I$1:$I$150,B48,Planilha6!$R$1:RQ$150) -> 0 | O48: =SUMIF(Planilha7!$I$1:$I$150,B48,Planilha7!$R$1:RR$150) -> -2567.46 | P48: =SUMIF(Planilha8!$I$1:$I$150,B48,Planilha8!$R$1:RS$150) -> 0 | Q48: =SUMIF(Planilha9!$I$1:$I$150,B48,Planilha9!$R$1:RT$150) -> -4321.31 | R48: =SUMIF(Planilha10!$I$1:$I$150,B48,Planilha10!$R$1:RU$150) -> -4076 | S48: =SUMIF(Planilha11!$I$1:$I$150,B48,Planilha11!$R$1:RV$150) -> -7625.98 | T48: =SUMIF(Planilha12!$I$1:$I$150,B48,Planilha12!$R$1:RW$150) -> -33114.53 | V48: =SUMIF(Planilha13!$I$1:$I$150,B48,Planilha13!$R$1:RY$150) -> -7899.23 | W48: =SUMIF(Planilha14!$I$1:$I$150,B48,Planilha14!$R$1:RZ$150) -> -2146.97 | Y48: =SUMIF('2026'!$I$1:$I$150,B48,'2026'!$R$1:RQ$150) -> -10046.2 | Z48: =SUM(V48:W48)-Y48 -> 0
A49: TAXA DE CARTAO / GATEWAY | I49: =SUMIF(Planilha1!$H$1:$H$110,A49,Planilha1!$R$1:$R$150) -> -7467.97 | J49: =SUMIF(Planilha2!$H$1:$H$110,A49,Planilha2!$R$1:$R$150) -> -6388.04 | K49: =SUMIF(Planilha3!$H$1:$H$110,A49,Planilha3!$R$1:$R$150) -> -11904.13 | L49: =SUMIF(Planilha4!$H$1:$H$110,A49,Planilha4!$R$1:$R$150) -> -12710.26 | M49: =SUMIF(Planilha5!$H$1:$H$110,A49,Planilha5!$R$1:$R$150) -> -10745.85 | N49: =SUMIF(Planilha6!$H$1:$H$110,A49,Planilha6!$R$1:$R$150) -> -17952.99 | O49: =SUMIF(Planilha7!$H$1:$H$110,A49,Planilha7!$R$1:$R$150) -> -26613.38 | P49: =SUMIF(Planilha8!$H$1:$H$110,A49,Planilha8!$R$1:$R$150) -> -32006.59 | Q49: =SUMIF(Planilha9!$H$1:$H$110,A49,Planilha9!$R$1:$R$150) -> -23346.11 | R49: =SUMIF(Planilha10!$H$1:$H$110,A49,Planilha10!$R$1:$R$150) -> -20628.88 | S49: =SUMIF(Planilha11!$H$1:$H$110,A49,Planilha11!$R$1:$R$150) -> -37959.16 | T49: =SUMIF(Planilha12!$H$1:$H$110,A49,Planilha12!$R$1:$R$150) -> -82349.2 | V49: =SUMIF(Planilha13!$H$1:$H$110,A49,Planilha13!$R$1:$R$150) -> -80047.92 | W49: =SUMIF(Planilha14!$H$1:$H$110,A49,Planilha14!$R$1:$R$150) -> -47957.89 | Y49: =SUMIF('2026'!$H$1:$H$110,A49,'2026'!$R$1:$R$150) -> -128005.81 | Z49: =SUM(V49:W49)-Y49 -> 0
B50: DESPESAS PAGAR ME | I50: =SUMIF(Planilha1!$I$1:$I$150,B50,Planilha1!$R$1:RL$150) -> -14.41 | J50: =SUMIF(Planilha2!$I$1:$I$150,B50,Planilha2!$R$1:RM$150) -> -22.99 | K50: =SUMIF(Planilha3!$I$1:$I$150,B50,Planilha3!$R$1:RN$150) -> -36.25 | L50: =SUMIF(Planilha4!$I$1:$I$150,B50,Planilha4!$R$1:RO$150) -> -62.91 | M50: =SUMIF(Planilha5!$I$1:$I$150,B50,Planilha5!$R$1:RP$150) -> -114.26 | N50: =SUMIF(Planilha6!$I$1:$I$150,B50,Planilha6!$R$1:RQ$150) -> -23.94 | O50: =SUMIF(Planilha7!$I$1:$I$150,B50,Planilha7!$R$1:RR$150) -> -8.06 | P50: =SUMIF(Planilha8!$I$1:$I$150,B50,Planilha8!$R$1:RS$150) -> -18.34 | Q50: =SUMIF(Planilha9!$I$1:$I$150,B50,Planilha9!$R$1:RT$150) -> -18.54 | R50: =SUMIF(Planilha10!$I$1:$I$150,B50,Planilha10!$R$1:RU$150) -> -9485.26 | S50: =SUMIF(Planilha11!$I$1:$I$150,B50,Planilha11!$R$1:RV$150) -> -13576.69 | T50: =SUMIF(Planilha12!$I$1:$I$150,B50,Planilha12!$R$1:RW$150) -> -18860.63 | V50: =SUMIF(Planilha13!$I$1:$I$150,B50,Planilha13!$R$1:RY$150) -> -9629.75 | W50: =SUMIF(Planilha14!$I$1:$I$150,B50,Planilha14!$R$1:RZ$150) -> -7748.07 | Y50: =SUMIF('2026'!$I$1:$I$150,B50,'2026'!$R$1:RQ$150) -> -17377.82 | Z50: =SUM(V50:W50)-Y50 -> 0
B51: DESPESAS MERCADO PAGO.COM | I51: =SUMIF(Planilha1!$I$1:$I$150,B51,Planilha1!$R$1:RL$150) -> -127.84 | J51: =SUMIF(Planilha2!$I$1:$I$150,B51,Planilha2!$R$1:RM$150) -> -106.44 | K51: =SUMIF(Planilha3!$I$1:$I$150,B51,Planilha3!$R$1:RN$150) -> -120.19 | L51: =SUMIF(Planilha4!$I$1:$I$150,B51,Planilha4!$R$1:RO$150) -> -719.07 | M51: =SUMIF(Planilha5!$I$1:$I$150,B51,Planilha5!$R$1:RP$150) -> -1200.21 | N51: =SUMIF(Planilha6!$I$1:$I$150,B51,Planilha6!$R$1:RQ$150) -> -9031.48 | O51: =SUMIF(Planilha7!$I$1:$I$150,B51,Planilha7!$R$1:RR$150) -> -19449.37 | P51: =SUMIF(Planilha8!$I$1:$I$150,B51,Planilha8!$R$1:RS$150) -> -24004 | Q51: =SUMIF(Planilha9!$I$1:$I$150,B51,Planilha9!$R$1:RT$150) -> -14867.44 | R51: =SUMIF(Planilha10!$I$1:$I$150,B51,Planilha10!$R$1:RU$150) -> -10888.27 | S51: =SUMIF(Planilha11!$I$1:$I$150,B51,Planilha11!$R$1:RV$150) -> -22440.42 | T51: =SUMIF(Planilha12!$I$1:$I$150,B51,Planilha12!$R$1:RW$150) -> -53682.39 | V51: =SUMIF(Planilha13!$I$1:$I$150,B51,Planilha13!$R$1:RY$150) -> -45119.27 | W51: =SUMIF(Planilha14!$I$1:$I$150,B51,Planilha14!$R$1:RZ$150) -> -24656.73 | Y51: =SUMIF('2026'!$I$1:$I$150,B51,'2026'!$R$1:RQ$150) -> -69776 | Z51: =SUM(V51:W51)-Y51 -> 0
B52: DESPESAS AMAZON | I52: =SUMIF(Planilha1!$I$1:$I$150,B52,Planilha1!$R$1:RL$150) -> -192.64 | J52: =SUMIF(Planilha2!$I$1:$I$150,B52,Planilha2!$R$1:RM$150) -> -85.23 | K52: =SUMIF(Planilha3!$I$1:$I$150,B52,Planilha3!$R$1:RN$150) -> -3587.81 | L52: =SUMIF(Planilha4!$I$1:$I$150,B52,Planilha4!$R$1:RO$150) -> -1874.88 | M52: =SUMIF(Planilha5!$I$1:$I$150,B52,Planilha5!$R$1:RP$150) -> -104.59 | N52: =SUMIF(Planilha6!$I$1:$I$150,B52,Planilha6!$R$1:RQ$150) -> -822.32 | O52: =SUMIF(Planilha7!$I$1:$I$150,B52,Planilha7!$R$1:RR$150) -> -359.72 | P52: =SUMIF(Planilha8!$I$1:$I$150,B52,Planilha8!$R$1:RS$150) -> -331.66 | Q52: =SUMIF(Planilha9!$I$1:$I$150,B52,Planilha9!$R$1:RT$150) -> -331.66 | R52: =SUMIF(Planilha10!$I$1:$I$150,B52,Planilha10!$R$1:RU$150) -> -187.73 | S52: =SUMIF(Planilha11!$I$1:$I$150,B52,Planilha11!$R$1:RV$150) -> -149.29 | T52: =SUMIF(Planilha12!$I$1:$I$150,B52,Planilha12!$R$1:RW$150) -> -9742.64 | V52: =SUMIF(Planilha13!$I$1:$I$150,B52,Planilha13!$R$1:RY$150) -> -21745.48 | W52: =SUMIF(Planilha14!$I$1:$I$150,B52,Planilha14!$R$1:RZ$150) -> -10705.12 | Y52: =SUMIF('2026'!$I$1:$I$150,B52,'2026'!$R$1:RQ$150) -> -32450.6 | Z52: =SUM(V52:W52)-Y52 -> 0
B53: DESPESAS STONE | I53: =SUMIF(Planilha1!$I$1:$I$150,B53,Planilha1!$R$1:RL$150) -> -39.71 | J53: =SUMIF(Planilha2!$I$1:$I$150,B53,Planilha2!$R$1:RM$150) -> -70.31 | K53: =SUMIF(Planilha3!$I$1:$I$150,B53,Planilha3!$R$1:RN$150) -> -49.67 | L53: =SUMIF(Planilha4!$I$1:$I$150,B53,Planilha4!$R$1:RO$150) -> -70.3 | M53: =SUMIF(Planilha5!$I$1:$I$150,B53,Planilha5!$R$1:RP$150) -> -61.8 | N53: =SUMIF(Planilha6!$I$1:$I$150,B53,Planilha6!$R$1:RQ$150) -> -53.09 | O53: =SUMIF(Planilha7!$I$1:$I$150,B53,Planilha7!$R$1:RR$150) -> -60.02 | P53: =SUMIF(Planilha8!$I$1:$I$150,B53,Planilha8!$R$1:RS$150) -> -86.19 | Q53: =SUMIF(Planilha9!$I$1:$I$150,B53,Planilha9!$R$1:RT$150) -> -59.23 | R53: =SUMIF(Planilha10!$I$1:$I$150,B53,Planilha10!$R$1:RU$150) -> -67.62 | S53: =SUMIF(Planilha11!$I$1:$I$150,B53,Planilha11!$R$1:RV$150) -> -146.22 | T53: =SUMIF(Planilha12!$I$1:$I$150,B53,Planilha12!$R$1:RW$150) -> -63.54 | V53: =SUMIF(Planilha13!$I$1:$I$150,B53,Planilha13!$R$1:RY$150) -> -3553.42 | W53: =SUMIF(Planilha14!$I$1:$I$150,B53,Planilha14!$R$1:RZ$150) -> -4847.97 | Y53: =SUMIF('2026'!$I$1:$I$150,B53,'2026'!$R$1:RQ$150) -> -8401.39 | Z53: =SUM(V53:W53)-Y53 -> 0
B54: DESPESAS VINDI | I54: =SUMIF(Planilha1!$I$1:$I$150,B54,Planilha1!$R$1:RL$150) -> -7093.37 | J54: =SUMIF(Planilha2!$I$1:$I$150,B54,Planilha2!$R$1:RM$150) -> -6103.07 | K54: =SUMIF(Planilha3!$I$1:$I$150,B54,Planilha3!$R$1:RN$150) -> -8110.21 | L54: =SUMIF(Planilha4!$I$1:$I$150,B54,Planilha4!$R$1:RO$150) -> -9983.1 | M54: =SUMIF(Planilha5!$I$1:$I$150,B54,Planilha5!$R$1:RP$150) -> -9264.99 | N54: =SUMIF(Planilha6!$I$1:$I$150,B54,Planilha6!$R$1:RQ$150) -> -8022.16 | O54: =SUMIF(Planilha7!$I$1:$I$150,B54,Planilha7!$R$1:RR$150) -> -6736.21 | P54: =SUMIF(Planilha8!$I$1:$I$150,B54,Planilha8!$R$1:RS$150) -> -7566.4 | Q54: =SUMIF(Planilha9!$I$1:$I$150,B54,Planilha9!$R$1:RT$150) -> -8069.24 | R54: =SUMIF(Planilha10!$I$1:$I$150,B54,Planilha10!$R$1:RU$150) -> 0 | S54: =SUMIF(Planilha11!$I$1:$I$150,B54,Planilha11!$R$1:RV$150) -> -1646.54 | T54: =SUMIF(Planilha12!$I$1:$I$150,B54,Planilha12!$R$1:RW$150) -> 0 | V54: =SUMIF(Planilha13!$I$1:$I$150,B54,Planilha13!$R$1:RY$150) -> 0 | W54: =SUMIF(Planilha14!$I$1:$I$150,B54,Planilha14!$R$1:RZ$150) -> 0 | Y54: =SUMIF('2026'!$I$1:$I$150,B54,'2026'!$R$1:RQ$150) -> 0 | Z54: =SUM(V54:W54)-Y54 -> 0
A55: TOTAL DESPESAS VARIÁVEIS COMERCIAIS | I55: =SUMIF(Planilha1!$H$1:$H$110,A55,Planilha1!$R$1:$R$150) -> -52906.6 | J55: =SUMIF(Planilha2!$H$1:$H$110,A55,Planilha2!$R$1:$R$150) -> -43703.27 | K55: =SUMIF(Planilha3!$H$1:$H$110,A55,Planilha3!$R$1:$R$150) -> -50145.87 | L55: =SUMIF(Planilha4!$H$1:$H$110,A55,Planilha4!$R$1:$R$150) -> -49454.19 | M55: =SUMIF(Planilha5!$H$1:$H$110,A55,Planilha5!$R$1:$R$150) -> -56994.16 | N55: =SUMIF(Planilha6!$H$1:$H$110,A55,Planilha6!$R$1:$R$150) -> -51690.15 | O55: =SUMIF(Planilha7!$H$1:$H$110,A55,Planilha7!$R$1:$R$150) -> -55768.87 | P55: =SUMIF(Planilha8!$H$1:$H$110,A55,Planilha8!$R$1:$R$150) -> -55758.67 | Q55: =SUMIF(Planilha9!$H$1:$H$110,A55,Planilha9!$R$1:$R$150) -> -55935.07 | R55: =SUMIF(Planilha10!$H$1:$H$110,A55,Planilha10!$R$1:$R$150) -> -63648.92 | S55: =SUMIF(Planilha11!$H$1:$H$110,A55,Planilha11!$R$1:$R$150) -> -107549.69 | T55: =SUMIF(Planilha12!$H$1:$H$110,A55,Planilha12!$R$1:$R$150) -> -182199.81 | V55: =SUMIF(Planilha13!$H$1:$H$110,A55,Planilha13!$R$1:$R$150) -> -152282.49 | W55: =SUMIF(Planilha14!$H$1:$H$110,A55,Planilha14!$R$1:$R$150) -> -89855.34 | Y55: =SUMIF('2026'!$H$1:$H$110,A55,'2026'!$R$1:$R$150) -> -242137.83 | Z55: =SUM(V55:W55)-Y55 -> 0
Z56: =SUM(V56:W56)-Y56 -> 0
A57: Empresa: | D57: ASSOCIAÇÃO EDITORA PRESBITERIANA DE PINHEIROS | X57: Página: | Y57: =1+Y1 -> 2
A58: C.N.P.J.: | D58: 40.804.477/0001-44
A60: DEMONSTRAÇÃO DO RESULTADO DO PERÍODO EM 2025
A62: Descrição | I62: 45658 | J62: 45689 | K62: 45717 | L62: 45748 | M62: 45778 | N62: 45809 | O62: 45839 | P62: 45870 | Q62: 45901 | R62: 45931 | S62: 45962 | T62: 45992 | V62: 46023 | W62: 46054 | Y62: 2026
A63: MARGEM DE CONTRIBUIÇÃO | I63: =SUMIF(Planilha1!$H$1:$H$110,A63,Planilha1!$R$1:$R$150) -> 261894.68 | J63: =SUMIF(Planilha2!$H$1:$H$110,A63,Planilha2!$R$1:$R$150) -> 198798.57 | K63: =SUMIF(Planilha3!$H$1:$H$110,A63,Planilha3!$R$1:$R$150) -> 213581.48 | L63: =SUMIF(Planilha4!$H$1:$H$110,A63,Planilha4!$R$1:$R$150) -> 173315.91 | M63: =SUMIF(Planilha5!$H$1:$H$110,A63,Planilha5!$R$1:$R$150) -> 178001.22 | N63: =SUMIF(Planilha6!$H$1:$H$110,A63,Planilha6!$R$1:$R$150) -> 224618.44 | O63: =SUMIF(Planilha7!$H$1:$H$110,A63,Planilha7!$R$1:$R$150) -> 215433.92 | P63: =SUMIF(Planilha8!$H$1:$H$110,A63,Planilha8!$R$1:$R$150) -> 264991.67 | Q63: =SUMIF(Planilha9!$H$1:$H$110,A63,Planilha9!$R$1:$R$150) -> 289470.91 | R63: =SUMIF(Planilha10!$H$1:$H$110,A63,Planilha10!$R$1:$R$150) -> 468778.64 | S63: =SUMIF(Planilha11!$H$1:$H$110,A63,Planilha11!$R$1:$R$150) -> 454001.81 | T63: =SUMIF(Planilha12!$H$1:$H$110,A63,Planilha12!$R$1:$R$150) -> 574819.19 | V63: =SUMIF(Planilha13!$H$1:$H$110,A63,Planilha13!$R$1:$R$150) -> 459244.38 | W63: =SUMIF(Planilha14!$H$1:$H$110,A63,Planilha14!$R$1:$R$150) -> 333748.96 | Y63: =SUMIF('2026'!$H$1:$H$110,A63,'2026'!$R$1:$R$150) -> 792993.34 | Z63: =SUM(V63:W63)-Y63 -> 0
Z64: =SUM(V64:W64)-Y64 -> 0
A65: DESPESAS FIXAS OPERACIONAIS | I65: =SUMIF(Planilha1!$H$1:$H$110,A65,Planilha1!$R$1:$R$150) -> -73305.91 | J65: =SUMIF(Planilha2!$H$1:$H$110,A65,Planilha2!$R$1:$R$150) -> -90837.05 | K65: =SUMIF(Planilha3!$H$1:$H$110,A65,Planilha3!$R$1:$R$150) -> -82984.22 | L65: =SUMIF(Planilha4!$H$1:$H$110,A65,Planilha4!$R$1:$R$150) -> -97464.56 | M65: =SUMIF(Planilha5!$H$1:$H$110,A65,Planilha5!$R$1:$R$150) -> -83740.92 | N65: =SUMIF(Planilha6!$H$1:$H$110,A65,Planilha6!$R$1:$R$150) -> -88444.47 | O65: =SUMIF(Planilha7!$H$1:$H$110,A65,Planilha7!$R$1:$R$150) -> -82166.97 | P65: =SUMIF(Planilha8!$H$1:$H$110,A65,Planilha8!$R$1:$R$150) -> -110080.21 | Q65: =SUMIF(Planilha9!$H$1:$H$110,A65,Planilha9!$R$1:$R$150) -> -102457.77 | R65: =SUMIF(Planilha10!$H$1:$H$110,A65,Planilha10!$R$1:$R$150) -> -136596.67 | S65: =SUMIF(Planilha11!$H$1:$H$110,A65,Planilha11!$R$1:$R$150) -> -164181.19 | T65: =SUMIF(Planilha12!$H$1:$H$110,A65,Planilha12!$R$1:$R$150) -> -232783.36 | V65: =SUMIF(Planilha13!$H$1:$H$110,A65,Planilha13!$R$1:$R$150) -> -190557.32 | W65: =SUMIF(Planilha14!$H$1:$H$110,A65,Planilha14!$R$1:$R$150) -> -98463.87 | Y65: =SUMIF('2026'!$H$1:$H$110,A65,'2026'!$R$1:$R$150) -> -289021.19 | Z65: =SUM(V65:W65)-Y65 -> 0
Z66: =SUM(V66:W66)-Y66 -> 0
A67: DESPESA FIXA COMERCIAL | I67: =SUMIF(Planilha1!$H$1:$H$110,A67,Planilha1!$R$1:$R$150) -> -73305.91 | J67: =SUMIF(Planilha2!$H$1:$H$110,A67,Planilha2!$R$1:$R$150) -> -90837.05 | K67: =SUMIF(Planilha3!$H$1:$H$110,A67,Planilha3!$R$1:$R$150) -> -82984.22 | L67: =SUMIF(Planilha4!$H$1:$H$110,A67,Planilha4!$R$1:$R$150) -> -97464.56 | M67: =SUMIF(Planilha5!$H$1:$H$110,A67,Planilha5!$R$1:$R$150) -> -83740.92 | N67: =SUMIF(Planilha6!$H$1:$H$110,A67,Planilha6!$R$1:$R$150) -> -88444.47 | O67: =SUMIF(Planilha7!$H$1:$H$110,A67,Planilha7!$R$1:$R$150) -> -82166.97 | P67: =SUMIF(Planilha8!$H$1:$H$110,A67,Planilha8!$R$1:$R$150) -> -110080.21 | Q67: =SUMIF(Planilha9!$H$1:$H$110,A67,Planilha9!$R$1:$R$150) -> -102457.77 | R67: =SUMIF(Planilha10!$H$1:$H$110,A67,Planilha10!$R$1:$R$150) -> -136596.67 | S67: =SUMIF(Planilha11!$H$1:$H$110,A67,Planilha11!$R$1:$R$150) -> -164181.19 | T67: =SUMIF(Planilha12!$H$1:$H$110,A67,Planilha12!$R$1:$R$150) -> -232783.36 | V67: =SUMIF(Planilha13!$H$1:$H$110,A67,Planilha13!$R$1:$R$150) -> -190557.32 | W67: =SUMIF(Planilha14!$H$1:$H$110,A67,Planilha14!$R$1:$R$150) -> -98463.87 | Y67: =SUMIF('2026'!$H$1:$H$110,A67,'2026'!$R$1:$R$150) -> -289021.19 | Z67: =SUM(V67:W67)-Y67 -> 0
Z68: =SUM(V68:W68)-Y68 -> 0
A69: SALARIO FIXO DOS VENDEDORES | I69: =SUMIF(Planilha1!$H$1:$H$110,A69,Planilha1!$R$1:$R$150) -> -3214.9 | J69: =SUMIF(Planilha2!$H$1:$H$110,A69,Planilha2!$R$1:$R$150) -> -3214.9 | K69: =SUMIF(Planilha3!$H$1:$H$110,A69,Planilha3!$R$1:$R$150) -> -3214.9 | L69: =SUMIF(Planilha4!$H$1:$H$110,A69,Planilha4!$R$1:$R$150) -> -3214.9 | M69: =SUMIF(Planilha5!$H$1:$H$110,A69,Planilha5!$R$1:$R$150) -> -3214.9 | N69: =SUMIF(Planilha6!$H$1:$H$110,A69,Planilha6!$R$1:$R$150) -> -3214.9 | O69: =SUMIF(Planilha7!$H$1:$H$110,A69,Planilha7!$R$1:$R$150) -> -1951.3 | P69: =SUMIF(Planilha8!$H$1:$H$110,A69,Planilha8!$R$1:$R$150) -> -3000 | Q69: =SUMIF(Planilha9!$H$1:$H$110,A69,Planilha9!$R$1:$R$150) -> -3000 | R69: =SUMIF(Planilha10!$H$1:$H$110,A69,Planilha10!$R$1:$R$150) -> -3000 | S69: =SUMIF(Planilha11!$H$1:$H$110,A69,Planilha11!$R$1:$R$150) -> -3300 | T69: =SUMIF(Planilha12!$H$1:$H$110,A69,Planilha12!$R$1:$R$150) -> -3000 | V69: =SUMIF(Planilha13!$H$1:$H$110,A69,Planilha13!$R$1:$R$150) -> 0 | W69: =SUMIF(Planilha14!$H$1:$H$110,A69,Planilha14!$R$1:$R$150) -> -3000 | Y69: =SUMIF('2026'!$H$1:$H$110,A69,'2026'!$R$1:$R$150) -> -3000 | Z69: =SUM(V69:W69)-Y69 -> 0
B70: COMERCIAL - PJ | I70: =SUMIF(Planilha1!$I$1:$I$150,B70,Planilha1!$R$1:RL$150) -> -3214.9 | J70: =SUMIF(Planilha2!$I$1:$I$150,B70,Planilha2!$R$1:RM$150) -> -3214.9 | K70: =SUMIF(Planilha3!$I$1:$I$150,B70,Planilha3!$R$1:RN$150) -> -3214.9 | L70: =SUMIF(Planilha4!$I$1:$I$150,B70,Planilha4!$R$1:RO$150) -> -3214.9 | M70: =SUMIF(Planilha5!$I$1:$I$150,B70,Planilha5!$R$1:RP$150) -> -3214.9 | N70: =SUMIF(Planilha6!$I$1:$I$150,B70,Planilha6!$R$1:RQ$150) -> -3214.9 | O70: =SUMIF(Planilha7!$I$1:$I$150,B70,Planilha7!$R$1:RR$150) -> -1951.3 | P70: =SUMIF(Planilha8!$I$1:$I$150,B70,Planilha8!$R$1:RS$150) -> -3000 | Q70: =SUMIF(Planilha9!$I$1:$I$150,B70,Planilha9!$R$1:RT$150) -> -3000 | R70: =SUMIF(Planilha10!$I$1:$I$150,B70,Planilha10!$R$1:RU$150) -> -3000 | S70: =SUMIF(Planilha11!$I$1:$I$150,B70,Planilha11!$R$1:RV$150) -> -3300 | T70: =SUMIF(Planilha12!$I$1:$I$150,B70,Planilha12!$R$1:RW$150) -> -3000 | V70: =SUMIF(Planilha13!$I$1:$I$150,B70,Planilha13!$R$1:RY$150) -> 0 | W70: =SUMIF(Planilha14!$I$1:$I$150,B70,Planilha14!$R$1:RZ$150) -> -3000 | Y70: =SUMIF('2026'!$I$1:$I$150,B70,'2026'!$R$1:RQ$150) -> -3000 | Z70: =SUM(V70:W70)-Y70 -> 0
A71: EQUIPE DE MARKETING | I71: =SUMIF(Planilha1!$H$1:$H$110,A71,Planilha1!$R$1:$R$150) -> -20385.71 | J71: =SUMIF(Planilha2!$H$1:$H$110,A71,Planilha2!$R$1:$R$150) -> -23903.13 | K71: =SUMIF(Planilha3!$H$1:$H$110,A71,Planilha3!$R$1:$R$150) -> -20110 | L71: =SUMIF(Planilha4!$H$1:$H$110,A71,Planilha4!$R$1:$R$150) -> -28544.13 | M71: =SUMIF(Planilha5!$H$1:$H$110,A71,Planilha5!$R$1:$R$150) -> -25711.19 | N71: =SUMIF(Planilha6!$H$1:$H$110,A71,Planilha6!$R$1:$R$150) -> -17126.06 | O71: =SUMIF(Planilha7!$H$1:$H$110,A71,Planilha7!$R$1:$R$150) -> -18460.04 | P71: =SUMIF(Planilha8!$H$1:$H$110,A71,Planilha8!$R$1:$R$150) -> -19363.05 | Q71: =SUMIF(Planilha9!$H$1:$H$110,A71,Planilha9!$R$1:$R$150) -> -19513.05 | R71: =SUMIF(Planilha10!$H$1:$H$110,A71,Planilha10!$R$1:$R$150) -> -22554.72 | S71: =SUMIF(Planilha11!$H$1:$H$110,A71,Planilha11!$R$1:$R$150) -> -23907.55 | T71: =SUMIF(Planilha12!$H$1:$H$110,A71,Planilha12!$R$1:$R$150) -> -22308.05 | V71: =SUMIF(Planilha13!$H$1:$H$110,A71,Planilha13!$R$1:$R$150) -> -17289.13 | W71: =SUMIF(Planilha14!$H$1:$H$110,A71,Planilha14!$R$1:$R$150) -> -16818.05 | Y71: =SUMIF('2026'!$H$1:$H$110,A71,'2026'!$R$1:$R$150) -> -34107.18 | Z71: =SUM(V71:W71)-Y71 -> 0
B72: MARKETING - PJ | I72: =SUMIF(Planilha1!$I$1:$I$150,B72,Planilha1!$R$1:RL$150) -> -9430 | J72: =SUMIF(Planilha2!$I$1:$I$150,B72,Planilha2!$R$1:RM$150) -> -15915.33 | K72: =SUMIF(Planilha3!$I$1:$I$150,B72,Planilha3!$R$1:RN$150) -> -12910 | L72: =SUMIF(Planilha4!$I$1:$I$150,B72,Planilha4!$R$1:RO$150) -> -13250 | M72: =SUMIF(Planilha5!$I$1:$I$150,B72,Planilha5!$R$1:RP$150) -> -14410 | N72: =SUMIF(Planilha6!$I$1:$I$150,B72,Planilha6!$R$1:RQ$150) -> -12626.8 | O72: =SUMIF(Planilha7!$I$1:$I$150,B72,Planilha7!$R$1:RR$150) -> -12266.8 | P72: =SUMIF(Planilha8!$I$1:$I$150,B72,Planilha8!$R$1:RS$150) -> -12966.8 | Q72: =SUMIF(Planilha9!$I$1:$I$150,B72,Planilha9!$R$1:RT$150) -> -12806.8 | R72: =SUMIF(Planilha10!$I$1:$I$150,B72,Planilha10!$R$1:RU$150) -> -15913.47 | S72: =SUMIF(Planilha11!$I$1:$I$150,B72,Planilha11!$R$1:RV$150) -> -17756.8 | T72: =SUMIF(Planilha12!$I$1:$I$150,B72,Planilha12!$R$1:RW$150) -> -15666.8 | V72: =SUMIF(Planilha13!$I$1:$I$150,B72,Planilha13!$R$1:RY$150) -> -10666.8 | W72: =SUMIF(Planilha14!$I$1:$I$150,B72,Planilha14!$R$1:RZ$150) -> -10666.8 | Y72: =SUMIF('2026'!$I$1:$I$150,B72,'2026'!$R$1:RQ$150) -> -21333.6 | Z72: =SUM(V72:W72)-Y72 -> 0
B73: MARKETING - CLT | I73: =SUMIF(Planilha1!$I$1:$I$150,B73,Planilha1!$R$1:RL$150) -> -10955.71 | J73: =SUMIF(Planilha2!$I$1:$I$150,B73,Planilha2!$R$1:RM$150) -> -7987.8 | K73: =SUMIF(Planilha3!$I$1:$I$150,B73,Planilha3!$R$1:RN$150) -> -7200 | L73: =SUMIF(Planilha4!$I$1:$I$150,B73,Planilha4!$R$1:RO$150) -> -8961.13 | M73: =SUMIF(Planilha5!$I$1:$I$150,B73,Planilha5!$R$1:RP$150) -> -9698.29 | N73: =SUMIF(Planilha6!$I$1:$I$150,B73,Planilha6!$R$1:RQ$150) -> -8095.16 | O73: =SUMIF(Planilha7!$I$1:$I$150,B73,Planilha7!$R$1:RR$150) -> -4906.99 | P73: =SUMIF(Planilha8!$I$1:$I$150,B73,Planilha8!$R$1:RS$150) -> -5355 | Q73: =SUMIF(Planilha9!$I$1:$I$150,B73,Planilha9!$R$1:RT$150) -> -5910 | R73: =SUMIF(Planilha10!$I$1:$I$150,B73,Planilha10!$R$1:RU$150) -> -5355 | S73: =SUMIF(Planilha11!$I$1:$I$150,B73,Planilha11!$R$1:RV$150) -> -5355 | T73: =SUMIF(Planilha12!$I$1:$I$150,B73,Planilha12!$R$1:RW$150) -> -5355 | V73: =SUMIF(Planilha13!$I$1:$I$150,B73,Planilha13!$R$1:RY$150) -> -5568.06 | W73: =SUMIF(Planilha14!$I$1:$I$150,B73,Planilha14!$R$1:RZ$150) -> -5355 | Y73: =SUMIF('2026'!$I$1:$I$150,B73,'2026'!$R$1:RQ$150) -> -10923.06 | Z73: =SUM(V73:W73)-Y73 -> 0
B74: SALARIO DE FERIAS - MARKETING | I74: =SUMIF(Planilha1!$I$1:$I$150,B74,Planilha1!$R$1:RL$150) -> 0 | J74: =SUMIF(Planilha2!$I$1:$I$150,B74,Planilha2!$R$1:RM$150) -> 0 | K74: =SUMIF(Planilha3!$I$1:$I$150,B74,Planilha3!$R$1:RN$150) -> 0 | L74: =SUMIF(Planilha4!$I$1:$I$150,B74,Planilha4!$R$1:RO$150) -> -4983 | M74: =SUMIF(Planilha5!$I$1:$I$150,B74,Planilha5!$R$1:RP$150) -> -1089.15 | N74: =SUMIF(Planilha6!$I$1:$I$150,B74,Planilha6!$R$1:RQ$150) -> 4042.15 | O74: =SUMIF(Planilha7!$I$1:$I$150,B74,Planilha7!$R$1:RR$150) -> -840 | P74: =SUMIF(Planilha8!$I$1:$I$150,B74,Planilha8!$R$1:RS$150) -> -595 | Q74: =SUMIF(Planilha9!$I$1:$I$150,B74,Planilha9!$R$1:RT$150) -> -350 | R74: =SUMIF(Planilha10!$I$1:$I$150,B74,Planilha10!$R$1:RU$150) -> -840 | S74: =SUMIF(Planilha11!$I$1:$I$150,B74,Planilha11!$R$1:RV$150) -> -350 | T74: =SUMIF(Planilha12!$I$1:$I$150,B74,Planilha12!$R$1:RW$150) -> -840 | V74: =SUMIF(Planilha13!$I$1:$I$150,B74,Planilha13!$R$1:RY$150) -> -602.44 | W74: =SUMIF(Planilha14!$I$1:$I$150,B74,Planilha14!$R$1:RZ$150) -> -350 | Y74: =SUMIF('2026'!$I$1:$I$150,B74,'2026'!$R$1:RQ$150) -> -952.44 | Z74: =SUM(V74:W74)-Y74 -> 0
B75: 13 SALARIO - COMERCIAL | I75: =SUMIF(Planilha1!$I$1:$I$150,B75,Planilha1!$R$1:RL$150) -> 0 | J75: =SUMIF(Planilha2!$I$1:$I$150,B75,Planilha2!$R$1:RM$150) -> 0 | K75: =SUMIF(Planilha3!$I$1:$I$150,B75,Planilha3!$R$1:RN$150) -> 0 | L75: =SUMIF(Planilha4!$I$1:$I$150,B75,Planilha4!$R$1:RO$150) -> -1350 | M75: =SUMIF(Planilha5!$I$1:$I$150,B75,Planilha5!$R$1:RP$150) -> -513.75 | N75: =SUMIF(Planilha6!$I$1:$I$150,B75,Planilha6!$R$1:RQ$150) -> -446.25 | O75: =SUMIF(Planilha7!$I$1:$I$150,B75,Planilha7!$R$1:RR$150) -> -446.25 | P75: =SUMIF(Planilha8!$I$1:$I$150,B75,Planilha8!$R$1:RS$150) -> -446.25 | Q75: =SUMIF(Planilha9!$I$1:$I$150,B75,Planilha9!$R$1:RT$150) -> -446.25 | R75: =SUMIF(Planilha10!$I$1:$I$150,B75,Planilha10!$R$1:RU$150) -> -446.25 | S75: =SUMIF(Planilha11!$I$1:$I$150,B75,Planilha11!$R$1:RV$150) -> -445.75 | T75: =SUMIF(Planilha12!$I$1:$I$150,B75,Planilha12!$R$1:RW$150) -> -446.25 | V75: =SUMIF(Planilha13!$I$1:$I$150,B75,Planilha13!$R$1:RY$150) -> -451.83 | W75: =SUMIF(Planilha14!$I$1:$I$150,B75,Planilha14!$R$1:RZ$150) -> -446.25 | Y75: =SUMIF('2026'!$I$1:$I$150,B75,'2026'!$R$1:RQ$150) -> -898.08 | Z75: =SUM(V75:W75)-Y75 -> 0
A76: LIVRARIA | I76: =SUMIF(Planilha1!$H$1:$H$110,A76,Planilha1!$R$1:$R$150) -> -6985 | J76: =SUMIF(Planilha2!$H$1:$H$110,A76,Planilha2!$R$1:$R$150) -> -9700 | K76: =SUMIF(Planilha3!$H$1:$H$110,A76,Planilha3!$R$1:$R$150) -> -10520 | L76: =SUMIF(Planilha4!$H$1:$H$110,A76,Planilha4!$R$1:$R$150) -> -6320 | M76: =SUMIF(Planilha5!$H$1:$H$110,A76,Planilha5!$R$1:$R$150) -> -6830 | N76: =SUMIF(Planilha6!$H$1:$H$110,A76,Planilha6!$R$1:$R$150) -> -9887.76 | O76: =SUMIF(Planilha7!$H$1:$H$110,A76,Planilha7!$R$1:$R$150) -> -6270 | P76: =SUMIF(Planilha8!$H$1:$H$110,A76,Planilha8!$R$1:$R$150) -> -10570 | Q76: =SUMIF(Planilha9!$H$1:$H$110,A76,Planilha9!$R$1:$R$150) -> -7580 | R76: =SUMIF(Planilha10!$H$1:$H$110,A76,Planilha10!$R$1:$R$150) -> -6320 | S76: =SUMIF(Planilha11!$H$1:$H$110,A76,Planilha11!$R$1:$R$150) -> -11550 | T76: =SUMIF(Planilha12!$H$1:$H$110,A76,Planilha12!$R$1:$R$150) -> -7110 | V76: =SUMIF(Planilha13!$H$1:$H$110,A76,Planilha13!$R$1:$R$150) -> -8120 | W76: =SUMIF(Planilha14!$H$1:$H$110,A76,Planilha14!$R$1:$R$150) -> -8810 | Y76: =SUMIF('2026'!$H$1:$H$110,A76,'2026'!$R$1:$R$150) -> -16930 | Z76: =SUM(V76:W76)-Y76 -> 0
B77: LIVRARIA - PJ | I77: =SUMIF(Planilha1!$I$1:$I$150,B77,Planilha1!$R$1:RL$150) -> -6985 | J77: =SUMIF(Planilha2!$I$1:$I$150,B77,Planilha2!$R$1:RM$150) -> -9700 | K77: =SUMIF(Planilha3!$I$1:$I$150,B77,Planilha3!$R$1:RN$150) -> -10520 | L77: =SUMIF(Planilha4!$I$1:$I$150,B77,Planilha4!$R$1:RO$150) -> -6320 | M77: =SUMIF(Planilha5!$I$1:$I$150,B77,Planilha5!$R$1:RP$150) -> -6830 | N77: =SUMIF(Planilha6!$I$1:$I$150,B77,Planilha6!$R$1:RQ$150) -> -9887.76 | O77: =SUMIF(Planilha7!$I$1:$I$150,B77,Planilha7!$R$1:RR$150) -> -6270 | P77: =SUMIF(Planilha8!$I$1:$I$150,B77,Planilha8!$R$1:RS$150) -> -10570 | Q77: =SUMIF(Planilha9!$I$1:$I$150,B77,Planilha9!$R$1:RT$150) -> -7580 | R77: =SUMIF(Planilha10!$I$1:$I$150,B77,Planilha10!$R$1:RU$150) -> -6320 | S77: =SUMIF(Planilha11!$I$1:$I$150,B77,Planilha11!$R$1:RV$150) -> -11550 | T77: =SUMIF(Planilha12!$I$1:$I$150,B77,Planilha12!$R$1:RW$150) -> -7110 | V77: =SUMIF(Planilha13!$I$1:$I$150,B77,Planilha13!$R$1:RY$150) -> -8120 | W77: =SUMIF(Planilha14!$I$1:$I$150,B77,Planilha14!$R$1:RZ$150) -> -8810 | Y77: =SUMIF('2026'!$I$1:$I$150,B77,'2026'!$R$1:RQ$150) -> -16930 | Z77: =SUM(V77:W77)-Y77 -> 0
A78: ENCARGOS PREVIDENCIARIOS E SOCIAIS | I78: =SUMIF(Planilha1!$H$1:$H$110,A78,Planilha1!$R$1:$R$150) -> -5776.55 | J78: =SUMIF(Planilha2!$H$1:$H$110,A78,Planilha2!$R$1:$R$150) -> -3306.17 | K78: =SUMIF(Planilha3!$H$1:$H$110,A78,Planilha3!$R$1:$R$150) -> -3347.08 | L78: =SUMIF(Planilha4!$H$1:$H$110,A78,Planilha4!$R$1:$R$150) -> -6934.5 | M78: =SUMIF(Planilha5!$H$1:$H$110,A78,Planilha5!$R$1:$R$150) -> -2673.5 | N78: =SUMIF(Planilha6!$H$1:$H$110,A78,Planilha6!$R$1:$R$150) -> -852.12 | O78: =SUMIF(Planilha7!$H$1:$H$110,A78,Planilha7!$R$1:$R$150) -> -2451.69 | P78: =SUMIF(Planilha8!$H$1:$H$110,A78,Planilha8!$R$1:$R$150) -> -2256.52 | Q78: =SUMIF(Planilha9!$H$1:$H$110,A78,Planilha9!$R$1:$R$150) -> -2198.16 | R78: =SUMIF(Planilha10!$H$1:$H$110,A78,Planilha10!$R$1:$R$150) -> -3369.82 | S78: =SUMIF(Planilha11!$H$1:$H$110,A78,Planilha11!$R$1:$R$150) -> -3446.21 | T78: =SUMIF(Planilha12!$H$1:$H$110,A78,Planilha12!$R$1:$R$150) -> -2371.13 | V78: =SUMIF(Planilha13!$H$1:$H$110,A78,Planilha13!$R$1:$R$150) -> -2290.62 | W78: =SUMIF(Planilha14!$H$1:$H$110,A78,Planilha14!$R$1:$R$150) -> -2171.39 | Y78: =SUMIF('2026'!$H$1:$H$110,A78,'2026'!$R$1:$R$150) -> -4462.01 | Z78: =SUM(V78:W78)-Y78 -> 0
B79: INSS - COMERCIAL | I79: =SUMIF(Planilha1!$I$1:$I$150,B79,Planilha1!$R$1:RL$150) -> -3487.17 | J79: =SUMIF(Planilha2!$I$1:$I$150,B79,Planilha2!$R$1:RM$150) -> -1808.76 | K79: =SUMIF(Planilha3!$I$1:$I$150,B79,Planilha3!$R$1:RN$150) -> -1929.6 | L79: =SUMIF(Planilha4!$I$1:$I$150,B79,Planilha4!$R$1:RO$150) -> -2891.56 | M79: =SUMIF(Planilha5!$I$1:$I$150,B79,Planilha5!$R$1:RP$150) -> -1571.82 | N79: =SUMIF(Planilha6!$I$1:$I$150,B79,Planilha6!$R$1:RQ$150) -> -1601.59 | O79: =SUMIF(Planilha7!$I$1:$I$150,B79,Planilha7!$R$1:RR$150) -> -1490.62 | P79: =SUMIF(Planilha8!$I$1:$I$150,B79,Planilha8!$R$1:RS$150) -> -1435.14 | Q79: =SUMIF(Planilha9!$I$1:$I$150,B79,Planilha9!$R$1:RT$150) -> -1435.14 | R79: =SUMIF(Planilha10!$I$1:$I$150,B79,Planilha10!$R$1:RU$150) -> -2182.76 | S79: =SUMIF(Planilha11!$I$1:$I$150,B79,Planilha11!$R$1:RV$150) -> -2369.43 | T79: =SUMIF(Planilha12!$I$1:$I$150,B79,Planilha12!$R$1:RW$150) -> -1435.14 | V79: =SUMIF(Planilha13!$I$1:$I$150,B79,Planilha13!$R$1:RY$150) -> -1429.36 | W79: =SUMIF(Planilha14!$I$1:$I$150,B79,Planilha14!$R$1:RZ$150) -> -1408.37 | Y79: =SUMIF('2026'!$I$1:$I$150,B79,'2026'!$R$1:RQ$150) -> -2837.73 | Z79: =SUM(V79:W79)-Y79 -> 0
B80: FGTS - COMERCIAL | I80: =SUMIF(Planilha1!$I$1:$I$150,B80,Planilha1!$R$1:RL$150) -> -963.01 | J80: =SUMIF(Planilha2!$I$1:$I$150,B80,Planilha2!$R$1:RM$150) -> -539.92 | K80: =SUMIF(Planilha3!$I$1:$I$150,B80,Planilha3!$R$1:RN$150) -> -576 | L80: =SUMIF(Planilha4!$I$1:$I$150,B80,Planilha4!$R$1:RO$150) -> -644.91 | M80: =SUMIF(Planilha5!$I$1:$I$150,B80,Planilha5!$R$1:RP$150) -> -469.2 | N80: =SUMIF(Planilha6!$I$1:$I$150,B80,Planilha6!$R$1:RQ$150) -> -478.08 | O80: =SUMIF(Planilha7!$I$1:$I$150,B80,Planilha7!$R$1:RR$150) -> -444.96 | P80: =SUMIF(Planilha8!$I$1:$I$150,B80,Planilha8!$R$1:RS$150) -> -428.4 | Q80: =SUMIF(Planilha9!$I$1:$I$150,B80,Planilha9!$R$1:RT$150) -> -428.4 | R80: =SUMIF(Planilha10!$I$1:$I$150,B80,Planilha10!$R$1:RU$150) -> -651.56 | S80: =SUMIF(Planilha11!$I$1:$I$150,B80,Planilha11!$R$1:RV$150) -> -707.28 | T80: =SUMIF(Planilha12!$I$1:$I$150,B80,Planilha12!$R$1:RW$150) -> -428.4 | V80: =SUMIF(Planilha13!$I$1:$I$150,B80,Planilha13!$R$1:RY$150) -> -434.78 | W80: =SUMIF(Planilha14!$I$1:$I$150,B80,Planilha14!$R$1:RZ$150) -> -428.4 | Y80: =SUMIF('2026'!$I$1:$I$150,B80,'2026'!$R$1:RQ$150) -> -863.18 | Z80: =SUM(V80:W80)-Y80 -> 0
B81: PIS - COMERCIAL | I81: =SUMIF(Planilha1!$I$1:$I$150,B81,Planilha1!$R$1:RL$150) -> -120.37 | J81: =SUMIF(Planilha2!$I$1:$I$150,B81,Planilha2!$R$1:RM$150) -> -67.49 | K81: =SUMIF(Planilha3!$I$1:$I$150,B81,Planilha3!$R$1:RN$150) -> -72 | L81: =SUMIF(Planilha4!$I$1:$I$150,B81,Planilha4!$R$1:RO$150) -> -80.61 | M81: =SUMIF(Planilha5!$I$1:$I$150,B81,Planilha5!$R$1:RP$150) -> -58.65 | N81: =SUMIF(Planilha6!$I$1:$I$150,B81,Planilha6!$R$1:RQ$150) -> -59.76 | O81: =SUMIF(Planilha7!$I$1:$I$150,B81,Planilha7!$R$1:RR$150) -> -55.62 | P81: =SUMIF(Planilha8!$I$1:$I$150,B81,Planilha8!$R$1:RS$150) -> -53.55 | Q81: =SUMIF(Planilha9!$I$1:$I$150,B81,Planilha9!$R$1:RT$150) -> -53.55 | R81: =SUMIF(Planilha10!$I$1:$I$150,B81,Planilha10!$R$1:RU$150) -> -81.45 | S81: =SUMIF(Planilha11!$I$1:$I$150,B81,Planilha11!$R$1:RV$150) -> -88.41 | T81: =SUMIF(Planilha12!$I$1:$I$150,B81,Planilha12!$R$1:RW$150) -> -53.55 | V81: =SUMIF(Planilha13!$I$1:$I$150,B81,Planilha13!$R$1:RY$150) -> -54.35 | W81: =SUMIF(Planilha14!$I$1:$I$150,B81,Planilha14!$R$1:RZ$150) -> -53.55 | Y81: =SUMIF('2026'!$I$1:$I$150,B81,'2026'!$R$1:RQ$150) -> -107.9 | Z81: =SUM(V81:W81)-Y81 -> 0
B82: INSS FERIAS - COMERCIAL | I82: =SUMIF(Planilha1!$I$1:$I$150,B82,Planilha1!$R$1:RL$150) -> 0 | J82: =SUMIF(Planilha2!$I$1:$I$150,B82,Planilha2!$R$1:RM$150) -> 0 | K82: =SUMIF(Planilha3!$I$1:$I$150,B82,Planilha3!$R$1:RN$150) -> 0 | L82: =SUMIF(Planilha4!$I$1:$I$150,B82,Planilha4!$R$1:RO$150) -> -1335.46 | M82: =SUMIF(Planilha5!$I$1:$I$150,B82,Planilha5!$R$1:RP$150) -> -291.86 | N82: =SUMIF(Planilha6!$I$1:$I$150,B82,Planilha6!$R$1:RQ$150) -> 1083.28 | O82: =SUMIF(Planilha7!$I$1:$I$150,B82,Planilha7!$R$1:RR$150) -> -225.12 | P82: =SUMIF(Planilha8!$I$1:$I$150,B82,Planilha8!$R$1:RS$150) -> -142.15 | Q82: =SUMIF(Planilha9!$I$1:$I$150,B82,Planilha9!$R$1:RT$150) -> -92.05 | R82: =SUMIF(Planilha10!$I$1:$I$150,B82,Planilha10!$R$1:RU$150) -> -220.92 | S82: =SUMIF(Planilha11!$I$1:$I$150,B82,Planilha11!$R$1:RV$150) -> -92.05 | T82: =SUMIF(Planilha12!$I$1:$I$150,B82,Planilha12!$R$1:RW$150) -> -220.92 | V82: =SUMIF(Planilha13!$I$1:$I$150,B82,Planilha13!$R$1:RY$150) -> -158.42 | W82: =SUMIF(Planilha14!$I$1:$I$150,B82,Planilha14!$R$1:RZ$150) -> -92.05 | Y82: =SUMIF('2026'!$I$1:$I$150,B82,'2026'!$R$1:RQ$150) -> -250.47 | Z82: =SUM(V82:W82)-Y82 -> 0
B83: FGTS FERIAS - COMERCIAL | I83: =SUMIF(Planilha1!$I$1:$I$150,B83,Planilha1!$R$1:RL$150) -> 0 | J83: =SUMIF(Planilha2!$I$1:$I$150,B83,Planilha2!$R$1:RM$150) -> 0 | K83: =SUMIF(Planilha3!$I$1:$I$150,B83,Planilha3!$R$1:RN$150) -> 0 | L83: =SUMIF(Planilha4!$I$1:$I$150,B83,Planilha4!$R$1:RO$150) -> -398.63 | M83: =SUMIF(Planilha5!$I$1:$I$150,B83,Planilha5!$R$1:RP$150) -> -87.14 | N83: =SUMIF(Planilha6!$I$1:$I$150,B83,Planilha6!$R$1:RQ$150) -> 323.37 | O83: =SUMIF(Planilha7!$I$1:$I$150,B83,Planilha7!$R$1:RR$150) -> -67.2 | P83: =SUMIF(Planilha8!$I$1:$I$150,B83,Planilha8!$R$1:RS$150) -> -47.6 | Q83: =SUMIF(Planilha9!$I$1:$I$150,B83,Planilha9!$R$1:RT$150) -> -28 | R83: =SUMIF(Planilha10!$I$1:$I$150,B83,Planilha10!$R$1:RU$150) -> -67.2 | S83: =SUMIF(Planilha11!$I$1:$I$150,B83,Planilha11!$R$1:RV$150) -> -28 | T83: =SUMIF(Planilha12!$I$1:$I$150,B83,Planilha12!$R$1:RW$150) -> -67.2 | V83: =SUMIF(Planilha13!$I$1:$I$150,B83,Planilha13!$R$1:RY$150) -> -48.19 | W83: =SUMIF(Planilha14!$I$1:$I$150,B83,Planilha14!$R$1:RZ$150) -> -28 | Y83: =SUMIF('2026'!$I$1:$I$150,B83,'2026'!$R$1:RQ$150) -> -76.19 | Z83: =SUM(V83:W83)-Y83 -> 0
B84: PIS FERIAS - COMERCIAL | I84: =SUMIF(Planilha1!$I$1:$I$150,B84,Planilha1!$R$1:RL$150) -> 0 | J84: =SUMIF(Planilha2!$I$1:$I$150,B84,Planilha2!$R$1:RM$150) -> 0 | K84: =SUMIF(Planilha3!$I$1:$I$150,B84,Planilha3!$R$1:RN$150) -> 0 | L84: =SUMIF(Planilha4!$I$1:$I$150,B84,Planilha4!$R$1:RO$150) -> -49.83 | M84: =SUMIF(Planilha5!$I$1:$I$150,B84,Planilha5!$R$1:RP$150) -> -10.89 | N84: =SUMIF(Planilha6!$I$1:$I$150,B84,Planilha6!$R$1:RQ$150) -> 40.42 | O84: =SUMIF(Planilha7!$I$1:$I$150,B84,Planilha7!$R$1:RR$150) -> -8.4 | P84: =SUMIF(Planilha8!$I$1:$I$150,B84,Planilha8!$R$1:RS$150) -> -5.95 | Q84: =SUMIF(Planilha9!$I$1:$I$150,B84,Planilha9!$R$1:RT$150) -> -3.5 | R84: =SUMIF(Planilha10!$I$1:$I$150,B84,Planilha10!$R$1:RU$150) -> -8.4 | S84: =SUMIF(Planilha11!$I$1:$I$150,B84,Planilha11!$R$1:RV$150) -> -3.5 | T84: =SUMIF(Planilha12!$I$1:$I$150,B84,Planilha12!$R$1:RW$150) -> -8.4 | V84: =SUMIF(Planilha13!$I$1:$I$150,B84,Planilha13!$R$1:RY$150) -> -6.02 | W84: =SUMIF(Planilha14!$I$1:$I$150,B84,Planilha14!$R$1:RZ$150) -> -3.5 | Y84: =SUMIF('2026'!$I$1:$I$150,B84,'2026'!$R$1:RQ$150) -> -9.52 | Z84: =SUM(V84:W84)-Y84 -> 0
B85: INSS SOBRE 13 SALARIO - COMERCIAL | I85: =SUMIF(Planilha1!$I$1:$I$150,B85,Planilha1!$R$1:RL$150) -> 0 | J85: =SUMIF(Planilha2!$I$1:$I$150,B85,Planilha2!$R$1:RM$150) -> 0 | K85: =SUMIF(Planilha3!$I$1:$I$150,B85,Planilha3!$R$1:RN$150) -> 0 | L85: =SUMIF(Planilha4!$I$1:$I$150,B85,Planilha4!$R$1:RO$150) -> -361.8 | M85: =SUMIF(Planilha5!$I$1:$I$150,B85,Planilha5!$R$1:RP$150) -> -137.7 | N85: =SUMIF(Planilha6!$I$1:$I$150,B85,Planilha6!$R$1:RQ$150) -> -119.6 | O85: =SUMIF(Planilha7!$I$1:$I$150,B85,Planilha7!$R$1:RR$150) -> -119.6 | P85: =SUMIF(Planilha8!$I$1:$I$150,B85,Planilha8!$R$1:RS$150) -> -103.57 | Q85: =SUMIF(Planilha9!$I$1:$I$150,B85,Planilha9!$R$1:RT$150) -> -117.36 | R85: =SUMIF(Planilha10!$I$1:$I$150,B85,Planilha10!$R$1:RU$150) -> -117.37 | S85: =SUMIF(Planilha11!$I$1:$I$150,B85,Planilha11!$R$1:RV$150) -> -117.37 | T85: =SUMIF(Planilha12!$I$1:$I$150,B85,Planilha12!$R$1:RW$150) -> -117.36 | V85: =SUMIF(Planilha13!$I$1:$I$150,B85,Planilha13!$R$1:RY$150) -> -118.84 | W85: =SUMIF(Planilha14!$I$1:$I$150,B85,Planilha14!$R$1:RZ$150) -> -117.36 | Y85: =SUMIF('2026'!$I$1:$I$150,B85,'2026'!$R$1:RQ$150) -> -236.2 | Z85: =SUM(V85:W85)-Y85 -> 0
B86: FGTS SOBRE 13 SALARIO - COMERCIAL | I86: =SUMIF(Planilha1!$I$1:$I$150,B86,Planilha1!$R$1:RL$150) -> 0 | J86: =SUMIF(Planilha2!$I$1:$I$150,B86,Planilha2!$R$1:RM$150) -> 0 | K86: =SUMIF(Planilha3!$I$1:$I$150,B86,Planilha3!$R$1:RN$150) -> 0 | L86: =SUMIF(Planilha4!$I$1:$I$150,B86,Planilha4!$R$1:RO$150) -> -108 | M86: =SUMIF(Planilha5!$I$1:$I$150,B86,Planilha5!$R$1:RP$150) -> -41.1 | N86: =SUMIF(Planilha6!$I$1:$I$150,B86,Planilha6!$R$1:RQ$150) -> -35.7 | O86: =SUMIF(Planilha7!$I$1:$I$150,B86,Planilha7!$R$1:RR$150) -> -35.7 | P86: =SUMIF(Planilha8!$I$1:$I$150,B86,Planilha8!$R$1:RS$150) -> -35.7 | Q86: =SUMIF(Planilha9!$I$1:$I$150,B86,Planilha9!$R$1:RT$150) -> -35.7 | R86: =SUMIF(Planilha10!$I$1:$I$150,B86,Planilha10!$R$1:RU$150) -> -35.7 | S86: =SUMIF(Planilha11!$I$1:$I$150,B86,Planilha11!$R$1:RV$150) -> -35.7 | T86: =SUMIF(Planilha12!$I$1:$I$150,B86,Planilha12!$R$1:RW$150) -> -35.7 | V86: =SUMIF(Planilha13!$I$1:$I$150,B86,Planilha13!$R$1:RY$150) -> -36.14 | W86: =SUMIF(Planilha14!$I$1:$I$150,B86,Planilha14!$R$1:RZ$150) -> -35.7 | Y86: =SUMIF('2026'!$I$1:$I$150,B86,'2026'!$R$1:RQ$150) -> -71.84 | Z86: =SUM(V86:W86)-Y86 -> 0
B87: PIS SOBRE 13 SALARIO - COMERCIAL | I87: =SUMIF(Planilha1!$I$1:$I$150,B87,Planilha1!$R$1:RL$150) -> 0 | J87: =SUMIF(Planilha2!$I$1:$I$150,B87,Planilha2!$R$1:RM$150) -> 0 | K87: =SUMIF(Planilha3!$I$1:$I$150,B87,Planilha3!$R$1:RN$150) -> 0 | L87: =SUMIF(Planilha4!$I$1:$I$150,B87,Planilha4!$R$1:RO$150) -> -13.5 | M87: =SUMIF(Planilha5!$I$1:$I$150,B87,Planilha5!$R$1:RP$150) -> -5.14 | N87: =SUMIF(Planilha6!$I$1:$I$150,B87,Planilha6!$R$1:RQ$150) -> -4.46 | O87: =SUMIF(Planilha7!$I$1:$I$150,B87,Planilha7!$R$1:RR$150) -> -4.47 | P87: =SUMIF(Planilha8!$I$1:$I$150,B87,Planilha8!$R$1:RS$150) -> -4.46 | Q87: =SUMIF(Planilha9!$I$1:$I$150,B87,Planilha9!$R$1:RT$150) -> -4.46 | R87: =SUMIF(Planilha10!$I$1:$I$150,B87,Planilha10!$R$1:RU$150) -> -4.46 | S87: =SUMIF(Planilha11!$I$1:$I$150,B87,Planilha11!$R$1:RV$150) -> -4.47 | T87: =SUMIF(Planilha12!$I$1:$I$150,B87,Planilha12!$R$1:RW$150) -> -4.46 | V87: =SUMIF(Planilha13!$I$1:$I$150,B87,Planilha13!$R$1:RY$150) -> -4.52 | W87: =SUMIF(Planilha14!$I$1:$I$150,B87,Planilha14!$R$1:RZ$150) -> -4.46 | Y87: =SUMIF('2026'!$I$1:$I$150,B87,'2026'!$R$1:RQ$150) -> -8.98 | Z87: =SUM(V87:W87)-Y87 -> 0
B88: VALE TRANSPORTE - COMERCIAL | I88: =SUMIF(Planilha1!$I$1:$I$150,B88,Planilha1!$R$1:RL$150) -> -1206 | J88: =SUMIF(Planilha2!$I$1:$I$150,B88,Planilha2!$R$1:RM$150) -> -890 | K88: =SUMIF(Planilha3!$I$1:$I$150,B88,Planilha3!$R$1:RN$150) -> -769.48 | L88: =SUMIF(Planilha4!$I$1:$I$150,B88,Planilha4!$R$1:RO$150) -> -1050.2 | M88: =SUMIF(Planilha5!$I$1:$I$150,B88,Planilha5!$R$1:RP$150) -> 0 | N88: =SUMIF(Planilha6!$I$1:$I$150,B88,Planilha6!$R$1:RQ$150) -> 0 | O88: =SUMIF(Planilha7!$I$1:$I$150,B88,Planilha7!$R$1:RR$150) -> 0 | P88: =SUMIF(Planilha8!$I$1:$I$150,B88,Planilha8!$R$1:RS$150) -> 0 | Q88: =SUMIF(Planilha9!$I$1:$I$150,B88,Planilha9!$R$1:RT$150) -> 0 | R88: =SUMIF(Planilha10!$I$1:$I$150,B88,Planilha10!$R$1:RU$150) -> 0 | S88: =SUMIF(Planilha11!$I$1:$I$150,B88,Planilha11!$R$1:RV$150) -> 0 | T88: =SUMIF(Planilha12!$I$1:$I$150,B88,Planilha12!$R$1:RW$150) -> 0 | V88: =SUMIF(Planilha13!$I$1:$I$150,B88,Planilha13!$R$1:RY$150) -> 0 | W88: =SUMIF(Planilha14!$I$1:$I$150,B88,Planilha14!$R$1:RZ$150) -> 0 | Y88: =SUMIF('2026'!$I$1:$I$150,B88,'2026'!$R$1:RQ$150) -> 0 | Z88: =SUM(V88:W88)-Y88 -> 0
A89: SISTEMAS E FERRAMENTAS ADMINISTRATIVAS - COMERCIAL | I89: =SUMIF(Planilha1!$H$1:$H$110,A89,Planilha1!$R$1:$R$150) -> -3522.01 | J89: =SUMIF(Planilha2!$H$1:$H$110,A89,Planilha2!$R$1:$R$150) -> -7548.4 | K89: =SUMIF(Planilha3!$H$1:$H$110,A89,Planilha3!$R$1:$R$150) -> -7155.32 | L89: =SUMIF(Planilha4!$H$1:$H$110,A89,Planilha4!$R$1:$R$150) -> -10740.87 | M89: =SUMIF(Planilha5!$H$1:$H$110,A89,Planilha5!$R$1:$R$150) -> -4464.73 | N89: =SUMIF(Planilha6!$H$1:$H$110,A89,Planilha6!$R$1:$R$150) -> -7709.03 | O89: =SUMIF(Planilha7!$H$1:$H$110,A89,Planilha7!$R$1:$R$150) -> -3094.37 | P89: =SUMIF(Planilha8!$H$1:$H$110,A89,Planilha8!$R$1:$R$150) -> -6855.96 | Q89: =SUMIF(Planilha9!$H$1:$H$110,A89,Planilha9!$R$1:$R$150) -> -11826.89 | R89: =SUMIF(Planilha10!$H$1:$H$110,A89,Planilha10!$R$1:$R$150) -> -26498.07 | S89: =SUMIF(Planilha11!$H$1:$H$110,A89,Planilha11!$R$1:$R$150) -> -4963.09 | T89: =SUMIF(Planilha12!$H$1:$H$110,A89,Planilha12!$R$1:$R$150) -> -3250.79 | V89: =SUMIF(Planilha13!$H$1:$H$110,A89,Planilha13!$R$1:$R$150) -> -2765.23 | W89: =SUMIF(Planilha14!$H$1:$H$110,A89,Planilha14!$R$1:$R$150) -> -1625.71 | Y89: =SUMIF('2026'!$H$1:$H$110,A89,'2026'!$R$1:$R$150) -> -4390.94 | Z89: =SUM(V89:W89)-Y89 -> 0
B90: DESPESAS COM INFORMATICA / SISTEMAS / SOFTWARES - COMERCIAL | I90: =SUMIF(Planilha1!$I$1:$I$150,B90,Planilha1!$R$1:RL$150) -> -3522.01 | J90: =SUMIF(Planilha2!$I$1:$I$150,B90,Planilha2!$R$1:RM$150) -> -7548.4 | K90: =SUMIF(Planilha3!$I$1:$I$150,B90,Planilha3!$R$1:RN$150) -> -7155.32 | L90: =SUMIF(Planilha4!$I$1:$I$150,B90,Planilha4!$R$1:RO$150) -> -10740.87 | M90: =SUMIF(Planilha5!$I$1:$I$150,B90,Planilha5!$R$1:RP$150) -> -4464.73 | N90: =SUMIF(Planilha6!$I$1:$I$150,B90,Planilha6!$R$1:RQ$150) -> -7709.03 | O90: =SUMIF(Planilha7!$I$1:$I$150,B90,Planilha7!$R$1:RR$150) -> -3094.37 | P90: =SUMIF(Planilha8!$I$1:$I$150,B90,Planilha8!$R$1:RS$150) -> -6855.96 | Q90: =SUMIF(Planilha9!$I$1:$I$150,B90,Planilha9!$R$1:RT$150) -> -11826.89 | R90: =SUMIF(Planilha10!$I$1:$I$150,B90,Planilha10!$R$1:RU$150) -> -26498.07 | S90: =SUMIF(Planilha11!$I$1:$I$150,B90,Planilha11!$R$1:RV$150) -> -4963.09 | T90: =SUMIF(Planilha12!$I$1:$I$150,B90,Planilha12!$R$1:RW$150) -> -3250.79 | V90: =SUMIF(Planilha13!$I$1:$I$150,B90,Planilha13!$R$1:RY$150) -> -2765.23 | W90: =SUMIF(Planilha14!$I$1:$I$150,B90,Planilha14!$R$1:RZ$150) -> -1625.71 | Y90: =SUMIF('2026'!$I$1:$I$150,B90,'2026'!$R$1:RQ$150) -> -4390.94 | Z90: =SUM(V90:W90)-Y90 -> 0
A91: OUTROS - COMERCIAL | I91: =SUMIF(Planilha1!$H$1:$H$110,A91,Planilha1!$R$1:$R$150) -> -6307.63 | J91: =SUMIF(Planilha2!$H$1:$H$110,A91,Planilha2!$R$1:$R$150) -> -37.18 | K91: =SUMIF(Planilha3!$H$1:$H$110,A91,Planilha3!$R$1:$R$150) -> -3830.11 | L91: =SUMIF(Planilha4!$H$1:$H$110,A91,Planilha4!$R$1:$R$150) -> 0 | M91: =SUMIF(Planilha5!$H$1:$H$110,A91,Planilha5!$R$1:$R$150) -> 0 | N91: =SUMIF(Planilha6!$H$1:$H$110,A91,Planilha6!$R$1:$R$150) -> -26.8 | O91: =SUMIF(Planilha7!$H$1:$H$110,A91,Planilha7!$R$1:$R$150) -> -1218.93 | P91: =SUMIF(Planilha8!$H$1:$H$110,A91,Planilha8!$R$1:$R$150) -> -510.76 | Q91: =SUMIF(Planilha9!$H$1:$H$110,A91,Planilha9!$R$1:$R$150) -> -105.6 | R91: =SUMIF(Planilha10!$H$1:$H$110,A91,Planilha10!$R$1:$R$150) -> -15832.55 | S91: =SUMIF(Planilha11!$H$1:$H$110,A91,Planilha11!$R$1:$R$150) -> -44387.5 | T91: =SUMIF(Planilha12!$H$1:$H$110,A91,Planilha12!$R$1:$R$150) -> -65647.03 | V91: =SUMIF(Planilha13!$H$1:$H$110,A91,Planilha13!$R$1:$R$150) -> -11872.11 | W91: =SUMIF(Planilha14!$H$1:$H$110,A91,Planilha14!$R$1:$R$150) -> -8369.86 | Y91: =SUMIF('2026'!$H$1:$H$110,A91,'2026'!$R$1:$R$150) -> -20241.97 | Z91: =SUM(V91:W91)-Y91 -> 0
B92: VIAGEM, ESTADIA E PEDAGIO | I92: =SUMIF(Planilha1!$I$1:$I$150,B92,Planilha1!$R$1:RL$150) -> -6307.63 | J92: =SUMIF(Planilha2!$I$1:$I$150,B92,Planilha2!$R$1:RM$150) -> -37.18 | K92: =SUMIF(Planilha3!$I$1:$I$150,B92,Planilha3!$R$1:RN$150) -> -1157.42 | L92: =SUMIF(Planilha4!$I$1:$I$150,B92,Planilha4!$R$1:RO$150) -> 0 | M92: =SUMIF(Planilha5!$I$1:$I$150,B92,Planilha5!$R$1:RP$150) -> 0 | N92: =SUMIF(Planilha6!$I$1:$I$150,B92,Planilha6!$R$1:RQ$150) -> -26.8 | O92: =SUMIF(Planilha7!$I$1:$I$150,B92,Planilha7!$R$1:RR$150) -> -218.93 | P92: =SUMIF(Planilha8!$I$1:$I$150,B92,Planilha8!$R$1:RS$150) -> -215.41 | Q92: =SUMIF(Planilha9!$I$1:$I$150,B92,Planilha9!$R$1:RT$150) -> -55.6 | R92: =SUMIF(Planilha10!$I$1:$I$150,B92,Planilha10!$R$1:RU$150) -> -49.04 | S92: =SUMIF(Planilha11!$I$1:$I$150,B92,Planilha11!$R$1:RV$150) -> -45.54 | T92: =SUMIF(Planilha12!$I$1:$I$150,B92,Planilha12!$R$1:RW$150) -> -54.74 | V92: =SUMIF(Planilha13!$I$1:$I$150,B92,Planilha13!$R$1:RY$150) -> -64.74 | W92: =SUMIF(Planilha14!$I$1:$I$150,B92,Planilha14!$R$1:RZ$150) -> -34.74 | Y92: =SUMIF('2026'!$I$1:$I$150,B92,'2026'!$R$1:RQ$150) -> -99.48 | Z92: =SUM(V92:W92)-Y92 -> 0
B93: DESPESAS DE CUSTOS COM EVENTOS | I93: =SUMIF(Planilha1!$I$1:$I$150,B93,Planilha1!$R$1:RL$150) -> 0 | J93: =SUMIF(Planilha2!$I$1:$I$150,B93,Planilha2!$R$1:RM$150) -> 0 | K93: =SUMIF(Planilha3!$I$1:$I$150,B93,Planilha3!$R$1:RN$150) -> -2672.69 | L93: =SUMIF(Planilha4!$I$1:$I$150,B93,Planilha4!$R$1:RO$150) -> 0 | M93: =SUMIF(Planilha5!$I$1:$I$150,B93,Planilha5!$R$1:RP$150) -> 0 | N93: =SUMIF(Planilha6!$I$1:$I$150,B93,Planilha6!$R$1:RQ$150) -> 0 | O93: =SUMIF(Planilha7!$I$1:$I$150,B93,Planilha7!$R$1:RR$150) -> -1000 | P93: =SUMIF(Planilha8!$I$1:$I$150,B93,Planilha8!$R$1:RS$150) -> -295.35 | Q93: =SUMIF(Planilha9!$I$1:$I$150,B93,Planilha9!$R$1:RT$150) -> -50 | R93: =SUMIF(Planilha10!$I$1:$I$150,B93,Planilha10!$R$1:RU$150) -> -15783.51 | S93: =SUMIF(Planilha11!$I$1:$I$150,B93,Planilha11!$R$1:RV$150) -> -44341.96 | T93: =SUMIF(Planilha12!$I$1:$I$150,B93,Planilha12!$R$1:RW$150) -> -65592.29 | V93: =SUMIF(Planilha13!$I$1:$I$150,B93,Planilha13!$R$1:RY$150) -> -11807.37 | W93: =SUMIF(Planilha14!$I$1:$I$150,B93,Planilha14!$R$1:RZ$150) -> -8335.12 | Y93: =SUMIF('2026'!$I$1:$I$150,B93,'2026'!$R$1:RQ$150) -> -20142.49 | Z93: =SUM(V93:W93)-Y93 -> 0
A94: PUBLICIDADE | I94: =SUMIF(Planilha1!$H$1:$H$110,A94,Planilha1!$R$1:$R$150) -> -27114.11 | J94: =SUMIF(Planilha2!$H$1:$H$110,A94,Planilha2!$R$1:$R$150) -> -43127.27 | K94: =SUMIF(Planilha3!$H$1:$H$110,A94,Planilha3!$R$1:$R$150) -> -34806.81 | L94: =SUMIF(Planilha4!$H$1:$H$110,A94,Planilha4!$R$1:$R$150) -> -41710.16 | M94: =SUMIF(Planilha5!$H$1:$H$110,A94,Planilha5!$R$1:$R$150) -> -40846.6 | N94: =SUMIF(Planilha6!$H$1:$H$110,A94,Planilha6!$R$1:$R$150) -> -49627.8 | O94: =SUMIF(Planilha7!$H$1:$H$110,A94,Planilha7!$R$1:$R$150) -> -48720.64 | P94: =SUMIF(Planilha8!$H$1:$H$110,A94,Planilha8!$R$1:$R$150) -> -67523.92 | Q94: =SUMIF(Planilha9!$H$1:$H$110,A94,Planilha9!$R$1:$R$150) -> -58234.07 | R94: =SUMIF(Planilha10!$H$1:$H$110,A94,Planilha10!$R$1:$R$150) -> -59021.51 | S94: =SUMIF(Planilha11!$H$1:$H$110,A94,Planilha11!$R$1:$R$150) -> -72626.84 | T94: =SUMIF(Planilha12!$H$1:$H$110,A94,Planilha12!$R$1:$R$150) -> -129096.36 | V94: =SUMIF(Planilha13!$H$1:$H$110,A94,Planilha13!$R$1:$R$150) -> -148220.23 | W94: =SUMIF(Planilha14!$H$1:$H$110,A94,Planilha14!$R$1:$R$150) -> -57668.86 | Y94: =SUMIF('2026'!$H$1:$H$110,A94,'2026'!$R$1:$R$150) -> -205889.09 | Z94: =SUM(V94:W94)-Y94 -> 0
B95: PUBLICIDADE - TRAFEGO PAGO | I95: =SUMIF(Planilha1!$I$1:$I$150,B95,Planilha1!$R$1:RL$150) -> -25724.11 | J95: =SUMIF(Planilha2!$I$1:$I$150,B95,Planilha2!$R$1:RM$150) -> -41763.77 | K95: =SUMIF(Planilha3!$I$1:$I$150,B95,Planilha3!$R$1:RN$150) -> -32928.85 | L95: =SUMIF(Planilha4!$I$1:$I$150,B95,Planilha4!$R$1:RO$150) -> -39630.35 | M95: =SUMIF(Planilha5!$I$1:$I$150,B95,Planilha5!$R$1:RP$150) -> -38181.25 | N95: =SUMIF(Planilha6!$I$1:$I$150,B95,Planilha6!$R$1:RQ$150) -> -49627.8 | O95: =SUMIF(Planilha7!$I$1:$I$150,B95,Planilha7!$R$1:RR$150) -> -47548.8 | P95: =SUMIF(Planilha8!$I$1:$I$150,B95,Planilha8!$R$1:RS$150) -> -58078.98 | Q95: =SUMIF(Planilha9!$I$1:$I$150,B95,Planilha9!$R$1:RT$150) -> -52310.07 | R95: =SUMIF(Planilha10!$I$1:$I$150,B95,Planilha10!$R$1:RU$150) -> -55789.51 | S95: =SUMIF(Planilha11!$I$1:$I$150,B95,Planilha11!$R$1:RV$150) -> -68841.86 | T95: =SUMIF(Planilha12!$I$1:$I$150,B95,Planilha12!$R$1:RW$150) -> -126306.5 | V95: =SUMIF(Planilha13!$I$1:$I$150,B95,Planilha13!$R$1:RY$150) -> -98813.29 | W95: =SUMIF(Planilha14!$I$1:$I$150,B95,Planilha14!$R$1:RZ$150) -> -56239.25 | Y95: =SUMIF('2026'!$I$1:$I$150,B95,'2026'!$R$1:RQ$150) -> -155052.54 | Z95: =SUM(V95:W95)-Y95 -> 0
B96: DESPESAS COM MARKETING E PUBLICIDADE - | I96: =SUMIF(Planilha1!$I$1:$I$150,B96,Planilha1!$R$1:RL$150) -> -1390 | J96: =SUMIF(Planilha2!$I$1:$I$150,B96,Planilha2!$R$1:RM$150) -> -155 | K96: =SUMIF(Planilha3!$I$1:$I$150,B96,Planilha3!$R$1:RN$150) -> -664 | L96: =SUMIF(Planilha4!$I$1:$I$150,B96,Planilha4!$R$1:RO$150) -> -874.81 | M96: =SUMIF(Planilha5!$I$1:$I$150,B96,Planilha5!$R$1:RP$150) -> -2611.45 | N96: =SUMIF(Planilha6!$I$1:$I$150,B96,Planilha6!$R$1:RQ$150) -> 0 | O96: =SUMIF(Planilha7!$I$1:$I$150,B96,Planilha7!$R$1:RR$150) -> -1064.04 | P96: =SUMIF(Planilha8!$I$1:$I$150,B96,Planilha8!$R$1:RS$150) -> -9444.94 | Q96: =SUMIF(Planilha9!$I$1:$I$150,B96,Planilha9!$R$1:RT$150) -> -5924 | R96: =SUMIF(Planilha10!$I$1:$I$150,B96,Planilha10!$R$1:RU$150) -> -3232 | S96: =SUMIF(Planilha11!$I$1:$I$150,B96,Planilha11!$R$1:RV$150) -> -3784.98 | T96: =SUMIF(Planilha12!$I$1:$I$150,B96,Planilha12!$R$1:RW$150) -> -2789.86 | V96: =SUMIF(Planilha13!$I$1:$I$150,B96,Planilha13!$R$1:RY$150) -> -49406.94 | W96: =SUMIF(Planilha14!$I$1:$I$150,B96,Planilha14!$R$1:RZ$150) -> -1429.61 | Y96: =SUMIF('2026'!$I$1:$I$150,B96,'2026'!$R$1:RQ$150) -> -50836.55 | Z96: =SUM(V96:W96)-Y96 -> 0
B97: MARKETING E PUBLICIDADE - COMERCIAL | I97: =SUMIF(Planilha1!$I$1:$I$150,B97,Planilha1!$R$1:RL$150) -> 0 | J97: =SUMIF(Planilha2!$I$1:$I$150,B97,Planilha2!$R$1:RM$150) -> -1208.5 | K97: =SUMIF(Planilha3!$I$1:$I$150,B97,Planilha3!$R$1:RN$150) -> -1213.96 | L97: =SUMIF(Planilha4!$I$1:$I$150,B97,Planilha4!$R$1:RO$150) -> -1205 | M97: =SUMIF(Planilha5!$I$1:$I$150,B97,Planilha5!$R$1:RP$150) -> -53.9 | N97: =SUMIF(Planilha6!$I$1:$I$150,B97,Planilha6!$R$1:RQ$150) -> 0 | O97: =SUMIF(Planilha7!$I$1:$I$150,B97,Planilha7!$R$1:RR$150) -> -107.8 | P97: =SUMIF(Planilha8!$I$1:$I$150,B97,Planilha8!$R$1:RS$150) -> 0 | Q97: =SUMIF(Planilha9!$I$1:$I$150,B97,Planilha9!$R$1:RT$150) -> 0 | R97: =SUMIF(Planilha10!$I$1:$I$150,B97,Planilha10!$R$1:RU$150) -> 0 | S97: =SUMIF(Planilha11!$I$1:$I$150,B97,Planilha11!$R$1:RV$150) -> 0 | T97: =SUMIF(Planilha12!$I$1:$I$150,B97,Planilha12!$R$1:RW$150) -> 0 | V97: =SUMIF(Planilha13!$I$1:$I$150,B97,Planilha13!$R$1:RY$150) -> 0 | W97: =SUMIF(Planilha14!$I$1:$I$150,B97,Planilha14!$R$1:RZ$150) -> 0 | Y97: =SUMIF('2026'!$I$1:$I$150,B97,'2026'!$R$1:RQ$150) -> 0 | Z97: =SUM(V97:W97)-Y97 -> 0
A98: DESPESA FIXA ADMINITRATIVA | I98: =SUMIF(Planilha1!$H$1:$H$110,A98,Planilha1!$R$1:$R$150) -> -96068.02 | J98: =SUMIF(Planilha2!$H$1:$H$110,A98,Planilha2!$R$1:$R$150) -> -92790.32 | K98: =SUMIF(Planilha3!$H$1:$H$110,A98,Planilha3!$R$1:$R$150) -> -93267.69 | L98: =SUMIF(Planilha4!$H$1:$H$110,A98,Planilha4!$R$1:$R$150) -> -117707.2 | M98: =SUMIF(Planilha5!$H$1:$H$110,A98,Planilha5!$R$1:$R$150) -> -114758.28 | N98: =SUMIF(Planilha6!$H$1:$H$110,A98,Planilha6!$R$1:$R$150) -> -99594.14 | O98: =SUMIF(Planilha7!$H$1:$H$110,A98,Planilha7!$R$1:$R$150) -> -114685.31 | P98: =SUMIF(Planilha8!$H$1:$H$110,A98,Planilha8!$R$1:$R$150) -> -119785.41 | Q98: =SUMIF(Planilha9!$H$1:$H$110,A98,Planilha9!$R$1:$R$150) -> -100692.94 | R98: =SUMIF(Planilha10!$H$1:$H$110,A98,Planilha10!$R$1:$R$150) -> -113586.09 | S98: =SUMIF(Planilha11!$H$1:$H$110,A98,Planilha11!$R$1:$R$150) -> -115548.11 | T98: =SUMIF(Planilha12!$H$1:$H$110,A98,Planilha12!$R$1:$R$150) -> -172565.83 | V98: =SUMIF(Planilha13!$H$1:$H$110,A98,Planilha13!$R$1:$R$150) -> -132128.11 | W98: =SUMIF(Planilha14!$H$1:$H$110,A98,Planilha14!$R$1:$R$150) -> -119652.68 | Y98: =SUMIF('2026'!$H$1:$H$110,A98,'2026'!$R$1:$R$150) -> -251780.79 | Z98: =SUM(V98:W98)-Y98 -> 0
Z99: =SUM(V99:W99)-Y99 -> 0
A100: SALÁRIOS E ENCARGOS | I100: =SUMIF(Planilha1!$H$1:$H$110,A100,Planilha1!$R$1:$R$150) -> -57629.3 | J100: =SUMIF(Planilha2!$H$1:$H$110,A100,Planilha2!$R$1:$R$150) -> -58442.18 | K100: =SUMIF(Planilha3!$H$1:$H$110,A100,Planilha3!$R$1:$R$150) -> -59805.29 | L100: =SUMIF(Planilha4!$H$1:$H$110,A100,Planilha4!$R$1:$R$150) -> -78398.39 | M100: =SUMIF(Planilha5!$H$1:$H$110,A100,Planilha5!$R$1:$R$150) -> -77333.49 | N100: =SUMIF(Planilha6!$H$1:$H$110,A100,Planilha6!$R$1:$R$150) -> -63887.87 | O100: =SUMIF(Planilha7!$H$1:$H$110,A100,Planilha7!$R$1:$R$150) -> -68959.91 | P100: =SUMIF(Planilha8!$H$1:$H$110,A100,Planilha8!$R$1:$R$150) -> -68593.98 | Q100: =SUMIF(Planilha9!$H$1:$H$110,A100,Planilha9!$R$1:$R$150) -> -58966.48 | R100: =SUMIF(Planilha10!$H$1:$H$110,A100,Planilha10!$R$1:$R$150) -> -60162.76 | S100: =SUMIF(Planilha11!$H$1:$H$110,A100,Planilha11!$R$1:$R$150) -> -65289.27 | T100: =SUMIF(Planilha12!$H$1:$H$110,A100,Planilha12!$R$1:$R$150) -> -124354.32 | V100: =SUMIF(Planilha13!$H$1:$H$110,A100,Planilha13!$R$1:$R$150) -> -80976.13 | W100: =SUMIF(Planilha14!$H$1:$H$110,A100,Planilha14!$R$1:$R$150) -> -73595.59 | Y100: =SUMIF('2026'!$H$1:$H$110,A100,'2026'!$R$1:$R$150) -> -154571.72 | Z100: =SUM(V100:W100)-Y100 -> 0
B101: FINANCEIRO - PJ | I101: =SUMIF(Planilha1!$I$1:$I$150,B101,Planilha1!$R$1:RL$150) -> 0 | J101: =SUMIF(Planilha2!$I$1:$I$150,B101,Planilha2!$R$1:RM$150) -> 0 | K101: =SUMIF(Planilha3!$I$1:$I$150,B101,Planilha3!$R$1:RN$150) -> 0 | L101: =SUMIF(Planilha4!$I$1:$I$150,B101,Planilha4!$R$1:RO$150) -> 0 | M101: =SUMIF(Planilha5!$I$1:$I$150,B101,Planilha5!$R$1:RP$150) -> -3509.67 | N101: =SUMIF(Planilha6!$I$1:$I$150,B101,Planilha6!$R$1:RQ$150) -> -6750 | O101: =SUMIF(Planilha7!$I$1:$I$150,B101,Planilha7!$R$1:RR$150) -> -6750 | P101: =SUMIF(Planilha8!$I$1:$I$150,B101,Planilha8!$R$1:RS$150) -> -6750 | Q101: =SUMIF(Planilha9!$I$1:$I$150,B101,Planilha9!$R$1:RT$150) -> -6750 | R101: =SUMIF(Planilha10!$I$1:$I$150,B101,Planilha10!$R$1:RU$150) -> -6750 | S101: =SUMIF(Planilha11!$I$1:$I$150,B101,Planilha11!$R$1:RV$150) -> -7000 | T101: =SUMIF(Planilha12!$I$1:$I$150,B101,Planilha12!$R$1:RW$150) -> -6750 | V101: =SUMIF(Planilha13!$I$1:$I$150,B101,Planilha13!$R$1:RY$150) -> -6750 | W101: =SUMIF(Planilha14!$I$1:$I$150,B101,Planilha14!$R$1:RZ$150) -> -6750 | Y101: =SUMIF('2026'!$I$1:$I$150,B101,'2026'!$R$1:RQ$150) -> -13500 | Z101: =SUM(V101:W101)-Y101 -> 0
B102: ADMINISTRACAO - PJ | I102: =SUMIF(Planilha1!$I$1:$I$150,B102,Planilha1!$R$1:RL$150) -> -17401.46 | J102: =SUMIF(Planilha2!$I$1:$I$150,B102,Planilha2!$R$1:RM$150) -> -17401.46 | K102: =SUMIF(Planilha3!$I$1:$I$150,B102,Planilha3!$R$1:RN$150) -> -18271.54 | L102: =SUMIF(Planilha4!$I$1:$I$150,B102,Planilha4!$R$1:RO$150) -> -19141.62 | M102: =SUMIF(Planilha5!$I$1:$I$150,B102,Planilha5!$R$1:RP$150) -> -19141.62 | N102: =SUMIF(Planilha6!$I$1:$I$150,B102,Planilha6!$R$1:RQ$150) -> -19141.62 | O102: =SUMIF(Planilha7!$I$1:$I$150,B102,Planilha7!$R$1:RR$150) -> -19141.62 | P102: =SUMIF(Planilha8!$I$1:$I$150,B102,Planilha8!$R$1:RS$150) -> -19141.62 | Q102: =SUMIF(Planilha9!$I$1:$I$150,B102,Planilha9!$R$1:RT$150) -> -19141.62 | R102: =SUMIF(Planilha10!$I$1:$I$150,B102,Planilha10!$R$1:RU$150) -> -19141.62 | S102: =SUMIF(Planilha11!$I$1:$I$150,B102,Planilha11!$R$1:RV$150) -> -19141.62 | T102: =SUMIF(Planilha12!$I$1:$I$150,B102,Planilha12!$R$1:RW$150) -> -19141.62 | V102: =SUMIF(Planilha13!$I$1:$I$150,B102,Planilha13!$R$1:RY$150) -> -18435.91 | W102: =SUMIF(Planilha14!$I$1:$I$150,B102,Planilha14!$R$1:RZ$150) -> -18460.98 | Y102: =SUMIF('2026'!$I$1:$I$150,B102,'2026'!$R$1:RQ$150) -> -36896.89 | Z102: =SUM(V102:W102)-Y102 -> 0
B103: EDITORIAL - PJ | I103: =SUMIF(Planilha1!$I$1:$I$150,B103,Planilha1!$R$1:RL$150) -> 0 | J103: =SUMIF(Planilha2!$I$1:$I$150,B103,Planilha2!$R$1:RM$150) -> 0 | K103: =SUMIF(Planilha3!$I$1:$I$150,B103,Planilha3!$R$1:RN$150) -> 0 | L103: =SUMIF(Planilha4!$I$1:$I$150,B103,Planilha4!$R$1:RO$150) -> 0 | M103: =SUMIF(Planilha5!$I$1:$I$150,B103,Planilha5!$R$1:RP$150) -> 0 | N103: =SUMIF(Planilha6!$I$1:$I$150,B103,Planilha6!$R$1:RQ$150) -> 0 | O103: =SUMIF(Planilha7!$I$1:$I$150,B103,Planilha7!$R$1:RR$150) -> 0 | P103: =SUMIF(Planilha8!$I$1:$I$150,B103,Planilha8!$R$1:RS$150) -> 0 | Q103: =SUMIF(Planilha9!$I$1:$I$150,B103,Planilha9!$R$1:RT$150) -> 0 | R103: =SUMIF(Planilha10!$I$1:$I$150,B103,Planilha10!$R$1:RU$150) -> 0 | S103: =SUMIF(Planilha11!$I$1:$I$150,B103,Planilha11!$R$1:RV$150) -> 0 | T103: =SUMIF(Planilha12!$I$1:$I$150,B103,Planilha12!$R$1:RW$150) -> -4743 | V103: =SUMIF(Planilha13!$I$1:$I$150,B103,Planilha13!$R$1:RY$150) -> -8852.55 | W103: =SUMIF(Planilha14!$I$1:$I$150,B103,Planilha14!$R$1:RZ$150) -> -1672.74 | Y103: =SUMIF('2026'!$I$1:$I$150,B103,'2026'!$R$1:RQ$150) -> -10525.29 | Z103: =SUM(V103:W103)-Y103 -> 0
